Workbook

Sheet 1. Press Assumptions
A1: PRESS CAPITAL -- Fund I ASSUMPTIONS
A2: All blue cells are adjustable inputs. Black cells on gray are calculated.
A4: FUND PARAMETERS
A5: Fund Size ($) | B5: 150000000
A6: Number of Deals | B6: 5
A7: ARR per Deal ($) | B7: 25000000
A8: Entry Multiple (x ARR) | B8: =SUMPRODUCT('3. Deal Allocation'!B5:B9,'3. Deal Allocation'!C5:C9)/SUM('3. Deal Allocation'!B5:B9) -> 1.5762712
A9: Capital per Deal ($) | B9: 41666667 | E9: ARR x Entry Multiple (auto)
A10: Total Capital Deployed ($) | B10: 150000000 | E10: Deals x Capital per Deal (auto)
A11: Asset Deal % (50% rev haircut Y1) | B11: 0.25
A12: Share Deal % | B12: 0.75 | E12: 1 - Asset Deal %
A13: Leverage / Debt | B13: Zero | E13: No debt at fund or portfolio company level. All cash acquisitions.
A15: RETENTION & GROWTH
A16: Net Dollar Retention -- Base Case | B16: 0.85
A17: Net Dollar Retention -- Homerun | B17: 0.95
A18: Net Dollar Retention -- Looser | B18: 0.8 | E18: Conservative / stress test scenario
A19: NCA % -- Base Case | B19: 0
A20: NCA % -- Homerun | B20: 0.05
A21: Scenario Toggle (1=Base, 2=Homerun) | B21: 1 | E21: 1=Base, 2=Homerun, 3=Looser
A22: Active Retention Rate | B22: 0.85
A23: Active NCA Rate | B23: 0
A25: MARGIN MODEL
A26: Net Margin (flat, all years) | B26: 0.625 | E26: Used in flat-margin tabs (3a-3d). Set to 0 to use component costs.
A28: COST STRUCTURE
A29: All companies assumed breakeven at entry. Adjust per-deal entry margin on Tab 2.
A30: COGS | B30: 0.1 | E30: Ramps from 25% at close to 10% over 6 months
A31: Vendor Costs | B31: 0.05 | E31: Ramps from 10% at close to 5% over 6 months
A32: Corporate Allocation | B32: 0.06 | E32: Flat
A33: Legacy Headcount Expenses | B33: 0 | E33: Acquired company staff. 50% cut day 1, 90% by M6, 100% by M24. Rate derived from entry profit per deal.
A34: Salary Overhead Loading | B34: 0.3 | E34: On top of base salaries
A35: Bonus Pool Threshold | B35: 1 | C35: Set to 100% per GP -- no bonus pool. All margin upside flows to investors. | E35: Included in OpEx. Everything above 62.5% EBITDA margin goes to team.
A37: WATERFALL & DISTRIBUTION
A38: Phase 1: Return of Capital (x) | B38: 1 | E38: 100% to LPs until 1x returned
A39: Preferred Return (Annual) | B39: 0.1 | E39: 10% pref on unreturned capital
A40: Tier 2: LP Split % (1x-2x) | B40: 0.8 | E40: HoldCo gets 20%
A41: Tier 3: LP Split % (2x-3x) | B41: 0.8 | E41: HoldCo gets 25%
A42: Tier 4: LP Split % (above 3x) | B42: 0.8 | E42: HoldCo gets 30% -- perpetual
A43: Mgmt Fee Schedule | B43: 2% Y1 only | E43: 0% after Y1 once 3 deals deployed
A45: TIERED WATERFALL THRESHOLDS
A46: Tier | B46: Threshold (x) | C46: LP Split %
A47: Tier 1 | B47: 1x | C47: 1
A48: Tier 2 | B48: 2x | C48: 0.8
A49: Tier 3 | B49: 3x | C49: 0.75
A50: Tier 4 (above 3x) | C50: 0.7
A52: TEAM & COMPENSATION
A53: CEO Salary ($, base) | B53: 1000000
A54: COO Salary ($, base) | B54: 500000
A55: CFO Salary ($, base) | B55: 500000
A56: CPO Salary ($, base) | B56: 500000
A57: CTO Salary ($, base) | B57: 500000
A58: CRO Salary ($, base) | B58: 500000
A59: Team Steady State Headcount | B59: 20
A60: Direct Reports: 5 at $250K | B60: 250000 | E60: Senior operators (layered in with deals 1-3)
A61: Direct Reports: 9 at $125K | B61: 125000 | E61: Junior operators (layered in with deals 3-5)
A62: ARR Step Threshold ($) | B62: 100000000
A63: Step-Up Multiplier per Tier | B63: 1.5 | E63: 1.5x = 50% raise per tier; compounds across tiers
A65: DEPLOYMENT TIMING
A66: Fund Start Month (Global) | B66: 1
A67: Deal Closing Schedule (Global Month):
A68: OpCo 1 | B68: 4
A69: OpCo 2 | B69: 8
A70: OpCo 3 | B70: 12
A71: OpCo 4 | B71: 16
A72: OpCo 5 | B72: 20
A78: CAPITAL RECYCLING
A79: Recycling Enabled (1=Yes, 0=No) | B79: 1
A80: Recycle % of Pre-Waterfall NI | B80: 0.5 | E80: 100% during reinvestment period
A81: Reinvestment Period (months) | B81: 40 | C81: 50% recycling; window = M40 (2 yrs post full deployment); 120% deployment cap; done in practice M32. | E81: 3-year lockup; recycle stops after M36
A82: Number of Recycled Deals | B82: 1 | E82: OpCos 6-9, every 4 months
A83: Gross Capital, Recycled Deal ($) | B83: 36000000 | E83: ARR x Entry Multiple (auto)
A84: Total Recycled Capital ($) | B84: 36000000 | E84: 4 x $30M (auto)
A86: PER-DEAL ALLOCATION (Mixed Portfolio + Entry Margins)
A87: UW NDR = observed minus haircut. Profiles shown in col C.
A88: DEAL GRID (engine reads ARR / mult / close; UW NDR set per deal in engine) | B88: Outcome | C88: Profile | D88: ARR ($mm) | E88: Entry Mult | G88: UW NDR | H88: Real NDR | J88: Close M | K88: Close M (#)
A89: #1 | C89: OBS100/UW95 | D89: 25 | E89: 2 | G89: 1.05 | H89: 1 | J89: M4 | K89: 4
A90: #2 | C90: OBS95/UW90 | D90: 25 | E90: 1.5 | G90: 0.9 | H90: 0.85 | J90: M7 | K90: 8
A91: #3 | C91: OBS90/UW85 | D91: 25 | E91: 1.25 | G91: 0.92 | H91: 1 | J91: M10 | K91: 12
A92: #4 | C92: OBS90/UW85 | D92: 25 | E92: 1.25 | G92: 1.03 | H92: 0.8 | J92: M12 | K92: 16
A93: #5 | C93: OBS100/UW95 recycled | D93: 18 | E93: 2 | G93: 0.9 | H93: 0.8 | J93: M16 | K93: 32
A95: Recycled deal slot rows (96-99 unused)
A96: #6 | C96: UNUSED | D96: 0 | E96: 2 | G96: 1.05 | H96: 1 | J96: M24 | K96: 999
A97: #7 | C97: UNUSED | D97: 0 | E97: 2 | G97: 1.05 | H97: 1 | J97: M28 | K97: 999
A98: #8 | C98: UNUSED | D98: 0 | E98: 2 | G98: 0.9 | H98: 0.85 | J98: M32 | K98: 999
A99: #9 | C99: UNUSED | D99: 0 | E99: 2 | G99: 0.9 | H99: 0.8 | J99: M36 | K99: 999
A103: FTE per OpCo (legacy headcount at close) | B103: 140
A104: Loaded Cost per FTE ($) | B104: 200000
A106: Avg Tenure (years) | B106: 4 | E106: Drives severance weeks per person
A107: Weeks Severance per Year of Service | B107: 2 | E107: Lean policy
A108: Severance Cap (weeks) | B108: 12 | E108: Max weeks per individual
A109: Avg Severance Weeks per FTE (auto) | B109: 8 | E109: MIN(weeks_per_yr x tenure, cap)
A110: Avg Severance per FTE ($) (auto) | B110: 35000 | E110: Base salary basis
A111: Severance Split | B111: Per deal on Tab 2 | E111: Options: Seller (0%), 50/50 (50%), Press (100%). Set per deal in col M.
A112: Press Severance Cost per OpCo (auto) | B112: 0 | E112: Cash hit at close month
A114: TERMINAL VALUE (Exit Assumption)
A115: Exit Month -- n/a (permanent hold) | B115: 120 | E115: M120 = end of Year 10
A116: Terminal Value Multiple (x ARR) | B116: 0 | E116: Applied to ending ARR per OpCo at exit
A117: Include Exit in Waterfall (1=Yes, 0=No) | B117: 0 | E117: Toggle to add exit proceeds to Distributable NI
A129: MODEL HORIZON
A130: Total Months (P&L horizon) | B130: 180 | E130: 180 = 15 years (annual tabs), 120 = 10 years (monthly tabs)
A131: Monthly P&L Months | B131: 180 | E131: Tabs 3c/3d show this many months
...

Sheet 2. LP Economics
A1: LP ECONOMICS BY COMMITMENT SIZE (Fund I -- 50% Recycle)
A2: Live from _Engine_R50 (50% recycle). Returns identical across commitment sizes; cash scales linearly.
C5: $5M | F5: $10M | I5: $25M
A7: FUND PARTICIPATION
A8: Commitment | C8: 5 | F8: 10 | I8: 25
A9: Payback (months) | C9: TBD | F9: TBD | I9: TBD
A11: 10-YEAR RETURNS
A12: LP Net IRR (Staged) | C12: =_Engine_R50!$B$277 -> 0.17777176 | F12: =_Engine_R50!$B$277 -> 0.17777176 | I12: =_Engine_R50!$B$277 -> 0.17777176
A13: LP MOIC / DPI | C13: =_Engine_R50!$B$254 -> 2.3673409 | F13: =_Engine_R50!$B$254 -> 2.3673409 | I13: =_Engine_R50!$B$254 -> 2.3673409
A14: Cash Distributed | C14: =C13*C8 -> 11.836704 | F14: =F13*F8 -> 23.673409 | I14: =I13*I8 -> 59.183522
A16: 15-YEAR RETURNS
A17: LP Net IRR (Staged) | C17: =_Engine_R50!$B$276 -> 0.19472592 | F17: =_Engine_R50!$B$276 -> 0.19472592 | I17: =_Engine_R50!$B$276 -> 0.19472592
A18: LP MOIC / DPI | C18: =_Engine_R50!$B$252 -> 2.9981273 | F18: =_Engine_R50!$B$252 -> 2.9981273 | I18: =_Engine_R50!$B$252 -> 2.9981273
A19: Total Cash | C19: =C18*C8 -> 14.990636 | F19: =F18*F8 -> 29.981273 | I19: =I18*I8 -> 74.953182
A21: NOTE: returns above are identical across commitment sizes (the model has no LP class differentiation).
A22: See Tab 11 for NDR x Margin joint sensitivity. See Tab 20 for quarterly cash schedule.
B31: 0 | C31: 0 | D31: 0 | E31: 0 | F31: 0 | G31: 0 | H31: 0 | I31: 0 | J31: 0
D32: 0 | G32: 0 | J32: 0
D33: 0 | G33: 0 | J33: 0
B45: 0 | E45: 0 | H45: 0

Sheet 3. Deal Allocation
A1: PRESS CAPITAL -- DEAL ALLOCATION
A2: 4 initial deals ($100M ARR, blended 1.50x) + 1 recycled ($18M ARR @ 2.0x). Seller-paid severance nets price down.
A4: Deal | B4: ARR ($mm) | C4: Entry Mult | D4: Gross Price | E4: Sev Disc | F4: Net Price | G4: NDR | H4: Entry Profit | I4: Close Mo
A5: #1 | B5: ='1. Press Assumptions'!$D$89 -> 25 | C5: ='1. Press Assumptions'!$E$89 -> 2 | D5: =B5*C5 -> 50 | E5: =B5*0.1154*0.5 -> 1.4425 | F5: =D5-E5 -> 48.5575 | G5: 0.95 | H5: 0 | I5: ="M"&'1. Press Assumptions'!$K$89 -> M4
A6: #2 | B6: ='1. Press Assumptions'!$D$90 -> 25 | C6: ='1. Press Assumptions'!$E$90 -> 1.5 | D6: =B6*C6 -> 37.5 | E6: =B6*0.1154*0.5 -> 1.4425 | F6: =D6-E6 -> 36.0575 | G6: 0.9 | H6: 0 | I6: ="M"&'1. Press Assumptions'!$K$90 -> M8
A7: #3 | B7: ='1. Press Assumptions'!$D$91 -> 25 | C7: ='1. Press Assumptions'!$E$91 -> 1.25 | D7: =B7*C7 -> 31.25 | E7: =B7*0.1154*0.5 -> 1.4425 | F7: =D7-E7 -> 29.8075 | G7: 0.85 | H7: 0 | I7: ="M"&'1. Press Assumptions'!$K$91 -> M12
A8: #4 | B8: ='1. Press Assumptions'!$D$92 -> 25 | C8: ='1. Press Assumptions'!$E$92 -> 1.25 | D8: =B8*C8 -> 31.25 | E8: =B8*0.1154*0.5 -> 1.4425 | F8: =D8-E8 -> 29.8075 | G8: 0.85 | H8: 0 | I8: ="M"&'1. Press Assumptions'!$K$92 -> M16
A9: #5 (recycled) | B9: ='1. Press Assumptions'!$D$93 -> 18 | C9: ='1. Press Assumptions'!$E$93 -> 2 | D9: =B9*C9 -> 36 | E9: =B9*0.1154*0.5 -> 1.0386 | F9: =D9-E9 -> 34.9614 | G9: 0.95 | H9: 0 | I9: ="M"&'1. Press Assumptions'!$K$93 -> M32
A11: TOTAL | B11: =SUM(B5:B9) -> 118 | D11: =SUM(D5:D9) -> 186 | E11: =SUM(E5:E9) -> 6.8086 | F11: =SUM(F5:F9) -> 179.1914
A13: RECYCLED DEAL (50% retention through close; 120% deployment cap)
A14: Deal | B14: ARR ($mm) | C14: Entry Mult | D14: Gross Price | E14: Sev Disc | F14: Net Price | G14: NDR | H14: Entry Profit | I14: Close Mo
A15: #6 | B15: ='1. Press Assumptions'!$D$96 -> 0 | C15: ='1. Press Assumptions'!$E$96 -> 2 | D15: =B15*C15 -> 0 | E15: =B15*0.1154*0.5 -> 0 | F15: =D15-E15 -> 0 | G15: 0.95 | H15: 0 | I15: ="M"&'1. Press Assumptions'!$K$96 -> M999
A16: #7 | B16: ='1. Press Assumptions'!$D$97 -> 0 | C16: ='1. Press Assumptions'!$E$97 -> 2 | D16: =B16*C16 -> 0 | E16: =B16*0.1154*0.5 -> 0 | F16: =D16-E16 -> 0 | H16: 0 | I16: ="M"&'1. Press Assumptions'!$K$97 -> M999
A17: #8 | B17: ='1. Press Assumptions'!$D$98 -> 0 | C17: ='1. Press Assumptions'!$E$98 -> 2 | D17: =B17*C17 -> 0 | E17: =B17*0.1154*0.5 -> 0 | F17: =D17-E17 -> 0 | H17: 0 | I17: ="M"&'1. Press Assumptions'!$K$98 -> M999
A18: #9 | B18: ='1. Press Assumptions'!$D$99 -> 0 | C18: ='1. Press Assumptions'!$E$99 -> 2 | D18: =B18*C18 -> 0 | E18: =B18*0.1154*0.5 -> 0 | F18: =D18-E18 -> 0 | H18: 0 | I18: ="M"&'1. Press Assumptions'!$K$99 -> M999
A42: Green = premium (profitable + growing). Gold = par. Red = distress discount.

Sheet 4b. Annual P&L (Recycle)
A1: PRESS CAPITAL -- FUND I P&L | 50% RECYCLE x 36mo
A2: 8 deals @ $24M ARR. 50% retained M1-36.. LIVE from _Engine_R50.
A3: ($mm) | B3: Total | C3: Year 1 | D3: Year 2 | E3: Year 3 | F3: Year 4 | G3: Year 5 | H3: Year 6 | I3: Year 7 | J3: Year 8 | K3: Year 9 | L3: Year 10 | M3: Year 11 | N3: Year 12 | O3: Year 13 | P3: Year 14 | Q3: Year 15
A5: Revenue | B5: =SUM(C5:Q5) -> 888.49958 | C5: =_Engine_R50!B215 -> 30.752733 | D5: =_Engine_R50!B216 -> 86.999352 | E5: =_Engine_R50!B217 -> 90.334889 | F5: =_Engine_R50!B218 -> 90.934577 | G5: =_Engine_R50!B219 -> 82.060217 | H5: =_Engine_R50!B220 -> 74.232532 | I5: =_Engine_R50!B221 -> 67.313364 | J5: =_Engine_R50!B222 -> 61.183873 | K5: =_Engine_R50!B223 -> 55.741759 | L5: =_Engine_R50!B224 -> 50.898885 | M5: =_Engine_R50!B225 -> 46.579249 | N5: =_Engine_R50!B226 -> 42.717253 | O5: =_Engine_R50!B227 -> 39.25622 | P5: =_Engine_R50!B228 -> 36.147132 | Q5: =_Engine_R50!B229 -> 33.347546
A6: Cost of Goods Sold | B6: =SUM(C6:Q6) -> 88.849958 | C6: =_Engine_R50!C215 -> 3.0752733 | D6: =_Engine_R50!C216 -> 8.6999352 | E6: =_Engine_R50!C217 -> 9.0334889 | F6: =_Engine_R50!C218 -> 9.0934577 | G6: =_Engine_R50!C219 -> 8.2060217 | H6: =_Engine_R50!C220 -> 7.4232532 | I6: =_Engine_R50!C221 -> 6.7313364 | J6: =_Engine_R50!C222 -> 6.1183873 | K6: =_Engine_R50!C223 -> 5.5741759 | L6: =_Engine_R50!C224 -> 5.0898885 | M6: =_Engine_R50!C225 -> 4.6579249 | N6: =_Engine_R50!C226 -> 4.2717253 | O6: =_Engine_R50!C227 -> 3.925622 | P6: =_Engine_R50!C228 -> 3.6147132 | Q6: =_Engine_R50!C229 -> 3.3347546
A7: Gross Profit | B7: =SUM(C7:Q7) -> 799.64962 | C7: =C5-C6 -> 27.677459 | D7: =D5-D6 -> 78.299417 | E7: =E5-E6 -> 81.3014 | F7: =F5-F6 -> 81.841119 | G7: =G5-G6 -> 73.854195 | H7: =H5-H6 -> 66.809279 | I7: =I5-I6 -> 60.582027 | J7: =J5-J6 -> 55.065485 | ... Q7: =Q5-Q6 -> 30.012791
A9: Operating Expenses
A10: Vendor Costs | B10: =SUM(C10:Q10) -> 44.424979 | C10: =_Engine_R50!D215 -> 1.5376366 | D10: =_Engine_R50!D216 -> 4.3499676 | E10: =_Engine_R50!D217 -> 4.5167444 | F10: =_Engine_R50!D218 -> 4.5467289 | G10: =_Engine_R50!D219 -> 4.1030109 | H10: =_Engine_R50!D220 -> 3.7116266 | I10: =_Engine_R50!D221 -> 3.3656682 | J10: =_Engine_R50!D222 -> 3.0591936 | K10: =_Engine_R50!D223 -> 2.7870879 | L10: =_Engine_R50!D224 -> 2.5449442 | M10: =_Engine_R50!D225 -> 2.3289625 | N10: =_Engine_R50!D226 -> 2.1358626 | O10: =_Engine_R50!D227 -> 1.962811 | P10: =_Engine_R50!D228 -> 1.8073566 | Q10: =_Engine_R50!D229 -> 1.6673773
A11: Corporate Allocation | B11: =SUM(C11:Q11) -> 53.309975 | C11: =_Engine_R50!E215 -> 1.845164 | D11: =_Engine_R50!E216 -> 5.2199611 | E11: =_Engine_R50!E217 -> 5.4200933 | F11: =_Engine_R50!E218 -> 5.4560746 | G11: =_Engine_R50!E219 -> 4.923613 | H11: =_Engine_R50!E220 -> 4.4539519 | I11: =_Engine_R50!E221 -> 4.0388018 | J11: =_Engine_R50!E222 -> 3.6710324 | K11: =_Engine_R50!E223 -> 3.3445055 | L11: =_Engine_R50!E224 -> 3.0539331 | M11: =_Engine_R50!E225 -> 2.7947549 | N11: =_Engine_R50!E226 -> 2.5630352 | O11: =_Engine_R50!E227 -> 2.3553732 | P11: =_Engine_R50!E228 -> 2.1688279 | Q11: =_Engine_R50!E229 -> 2.0008528
A12: Team Compensation | B12: =SUM(C12:Q12) -> 110.33479 | C12: =_Engine_R50!F215 -> 3.4572699 | D12: =_Engine_R50!F216 -> 7.5965239 | E12: =_Engine_R50!F217 -> 7.637 | F12: =_Engine_R50!F218 -> 7.637 | G12: =_Engine_R50!F219 -> 7.637 | H12: =_Engine_R50!F220 -> 7.637 | I12: =_Engine_R50!F221 -> 7.637 | J12: =_Engine_R50!F222 -> 7.637 | K12: =_Engine_R50!F223 -> 7.637 | L12: =_Engine_R50!F224 -> 7.637 | M12: =_Engine_R50!F225 -> 7.637 | N12: =_Engine_R50!F226 -> 7.637 | O12: =_Engine_R50!F227 -> 7.637 | P12: =_Engine_R50!F228 -> 7.637 | Q12: =_Engine_R50!F229 -> 7.637
A13: Legacy Headcount Expenses | B13: =SUM(C13:Q13) -> 30.916667 | C13: =_Engine_R50!G215 -> 9.9555556 | D13: =_Engine_R50!G216 -> 12.392593 | E13: =_Engine_R50!G217 -> 6.312963 | F13: =_Engine_R50!G218 -> 1.9833333 | G13: =_Engine_R50!G219 -> 0.27222222 | H13: =_Engine_R50!G220 -> 0 | I13: =_Engine_R50!G221 -> 0 | J13: =_Engine_R50!G222 -> 0 | K13: =_Engine_R50!G223 -> 0 | L13: =_Engine_R50!G224 -> 0 | M13: =_Engine_R50!G225 -> 0 | N13: =_Engine_R50!G226 -> 0 | O13: =_Engine_R50!G227 -> 0 | P13: =_Engine_R50!G228 -> 0 | Q13: =_Engine_R50!G229 -> 0
A14: Bonus Pool | B14: =SUM(C14:Q14) -> 0 | C14: =_Engine_R50!H215 -> 0 | D14: =_Engine_R50!H216 -> 0 | E14: =_Engine_R50!H217 -> 0 | F14: =_Engine_R50!H218 -> 0 | G14: =_Engine_R50!H219 -> 0 | H14: =_Engine_R50!H220 -> 0 | I14: =_Engine_R50!H221 -> 0 | J14: =_Engine_R50!H222 -> 0 | K14: =_Engine_R50!H223 -> 0 | L14: =_Engine_R50!H224 -> 0 | M14: =_Engine_R50!H225 -> 0 | N14: =_Engine_R50!H226 -> 0 | O14: =_Engine_R50!H227 -> 0 | P14: =_Engine_R50!H228 -> 0 | Q14: =_Engine_R50!H229 -> 0
A15: Total Operating Expenses | B15: =SUM(C15:Q15) -> 238.98641 | C15: =C10+C11+C12+C13+C14 -> 16.795626 | D15: =D10+D11+D12+D13+D14 -> 29.559045 | E15: =E10+E11+E12+E13+E14 -> 23.886801 | F15: =F10+F11+F12+F13+F14 -> 19.623137 | G15: =G10+G11+G12+G13+G14 -> 16.935846 | H15: =H10+H11+H12+H13+H14 -> 15.802579 | I15: =I10+I11+I12+I13+I14 -> 15.04147 | J15: =J10+J11+J12+J13+J14 -> 14.367226 | ... Q15: =Q10+Q11+Q12+Q13+Q14 -> 11.30523
A17: EBITDA | B17: =SUM(C17:Q17) -> 560.66321 | C17: =_Engine_R50!I215 -> 10.881833 | D17: =_Engine_R50!I216 -> 48.740372 | E17: =_Engine_R50!I217 -> 57.414599 | F17: =_Engine_R50!I218 -> 62.217983 | G17: =_Engine_R50!I219 -> 56.918349 | H17: =_Engine_R50!I220 -> 51.0067 | I17: =_Engine_R50!I221 -> 45.540557 | J17: =_Engine_R50!I222 -> 40.698259 | K17: =_Engine_R50!I223 -> 36.398989 | L17: =_Engine_R50!I224 -> 32.573119 | M17: =_Engine_R50!I225 -> 29.160607 | N17: =_Engine_R50!I226 -> 26.10963 | O17: =_Engine_R50!I227 -> 23.375414 | P17: =_Engine_R50!I228 -> 20.919234 | Q17: =_Engine_R50!I229 -> 18.707561
A18: EBITDA Margin | B18: =B17/B5 -> 0.63102248 | C18: =IF(C5=0,0,C17/C5) -> 0.35384931 | D18: =IF(D5=0,0,D17/D5) -> 0.56023833 | E18: =IF(E5=0,0,E17/E5) -> 0.63557502 | F18: =IF(F5=0,0,F17/F5) -> 0.68420599 | G18: =IF(G5=0,0,G17/G5) -> 0.69361685 | H18: =IF(H5=0,0,H17/H5) -> 0.68712058 | I18: =IF(I5=0,0,I17/I5) -> 0.67654556 | J18: =IF(J5=0,0,J17/J5) -> 0.66517953 | ... Q18: =IF(Q5=0,0,Q17/Q5) -> 0.56098765
A20: Severance (Press 50%) | B20: =SUM(C20:Q20) -> 12.25 | C20: =_Engine_R50!J215 -> 7.35 | D20: =_Engine_R50!J216 -> 2.45 | E20: =_Engine_R50!J217 -> 2.45 | F20: =_Engine_R50!J218 -> 0 | G20: =_Engine_R50!J219 -> 0 | H20: =_Engine_R50!J220 -> 0 | I20: =_Engine_R50!J221 -> 0 | J20: =_Engine_R50!J222 -> 0 | K20: =_Engine_R50!J223 -> 0 | L20: =_Engine_R50!J224 -> 0 | M20: =_Engine_R50!J225 -> 0 | N20: =_Engine_R50!J226 -> 0 | O20: =_Engine_R50!J227 -> 0 | P20: =_Engine_R50!J228 -> 0 | Q20: =_Engine_R50!J229 -> 0
A21: Operating Income | B21: =B17-B20 -> 548.41321 | C21: =C17-C20 -> 3.5318334 | D21: =D17-D20 -> 46.290372 | E21: =E17-E20 -> 54.964599 | F21: =F17-F20 -> 62.217983 | G21: =G17-G20 -> 56.918349 | H21: =H17-H20 -> 51.0067 | I21: =I17-I20 -> 45.540557 | ... Q21: =Q17-Q20 -> 18.707561
A23: Management Fee | B23: =SUM(C23:Q23) -> 4.5 | C23: =_Engine_R50!K215 -> 3 | D23: =_Engine_R50!K216 -> 1.5 | E23: =_Engine_R50!K217 -> 0 | F23: =_Engine_R50!K218 -> 0 | G23: =_Engine_R50!K219 -> 0 | H23: =_Engine_R50!K220 -> 0 | I23: =_Engine_R50!K221 -> 0 | J23: =_Engine_R50!K222 -> 0 | K23: =_Engine_R50!K223 -> 0 | L23: =_Engine_R50!K224 -> 0 | M23: =_Engine_R50!K225 -> 0 | N23: =_Engine_R50!K226 -> 0 | O23: =_Engine_R50!K227 -> 0 | P23: =_Engine_R50!K228 -> 0 | Q23: =_Engine_R50!K229 -> 0
A24: Retained for Recycling (50%) | B24: =SUM(C24:Q24) -> 42.837043 | C24: =_Engine_R50!M215 -> 2.9830484 | D24: =_Engine_R50!M216 -> 22.395186 | E24: =_Engine_R50!M217 -> 17.458808 | F24: =_Engine_R50!M218 -> 0 | G24: =_Engine_R50!M219 -> 0 | H24: =_Engine_R50!M220 -> 0 | I24: =_Engine_R50!M221 -> 0 | J24: =_Engine_R50!M222 -> 0 | K24: =_Engine_R50!M223 -> 0 | L24: =_Engine_R50!M224 -> 0 | M24: =_Engine_R50!M225 -> 0 | N24: =_Engine_R50!M226 -> 0 | O24: =_Engine_R50!M227 -> 0 | P24: =_Engine_R50!M228 -> 0 | Q24: =_Engine_R50!M229 -> 0
A25: Distributable Cash | B25: =SUM(C25:Q25) -> 508.95181 | C25: =_Engine_R50!P215 -> -2.451215 | D25: =_Engine_R50!P216 -> 22.395186 | E25: =_Engine_R50!P217 -> 45.381434 | F25: =_Engine_R50!P218 -> 62.217983 | G25: =_Engine_R50!P219 -> 56.918349 | H25: =_Engine_R50!P220 -> 51.0067 | I25: =_Engine_R50!P221 -> 45.540557 | J25: =_Engine_R50!P222 -> 40.698259 | K25: =_Engine_R50!P223 -> 36.398989 | L25: =_Engine_R50!P224 -> 32.573119 | M25: =_Engine_R50!P225 -> 29.160607 | N25: =_Engine_R50!P226 -> 26.10963 | O25: =_Engine_R50!P227 -> 23.375414 | P25: =_Engine_R50!P228 -> 20.919234 | Q25: =_Engine_R50!P229 -> 18.707561
A26: Cumulative Distributable | B26: =Q26 -> 508.95181 | C26: =C25 -> -2.451215 | D26: =C26+D25 -> 19.943971 | E26: =D26+E25 -> 65.325405 | F26: =E26+F25 -> 127.54339 | G26: =F26+G25 -> 184.46174 | H26: =G26+H25 -> 235.46844 | I26: =H26+I25 -> 281.00899 | J26: =I26+J25 -> 321.70725 | K26: =J26+K25 -> 358.10624 | ... Q26: =P26+Q25 -> 508.95181

Sheet 4d. Monthly P&L (Recycle)
A1: MONTHLY P&L | 8 deals @ $24M ARR (LIVE)
A3: ($mm) | B3: M1 | C3: M2 | D3: M3 | E3: M4 | F3: M5 | G3: M6 | H3: M7 | I3: M8 | J3: M9 | K3: M10 | L3: M11 | M3: M12 | N3: M13 | O3: M14 | P3: M15 | Q3: M16 | R3: M17 | S3: M18 | T3: M19 | U3: M20 | V3: M21 | W3: M22 | X3: M23 | Y3: M24 | Z3: M25 | AA3: M26 | AB3: M27 | AC3: M28 | AD3: M29 | AE3: M30 | AF3: M31 | AG3: M32 | AH3: M33 | AI3: M34 | AJ3: M35 | AK3: M36 | AL3: M37 | AM3: M38 | AN3: M39 | AO3: M40 | AP3: M41 | AQ3: M42 | AR3: M43 | AS3: M44 | AT3: M45 | AU3: M46 | AV3: M47 | AW3: M48 | AX3: M49 | AY3: M50 | AZ3: M51 | BA3: M52 | BB3: M53 | BC3: M54 | BD3: M55 | BE3: M56 | BF3: M57 | BG3: M58 | BH3: M59 | BI3: M60 | BJ3: M61 | BK3: M62 | BL3: M63 | BM3: M64 | BN3: M65 | BO3: M66 | BP3: M67 | BQ3: M68 | BR3: M69 | BS3: M70 | BT3: M71 | BU3: M72 | BV3: M73 | BW3: M74 | BX3: M75 | BY3: M76 | BZ3: M77 | CA3: M78 | CB3: M79 | CC3: M80 | CD3: M81 | CE3: M82 | CF3: M83 | CG3: M84 | CH3: M85 | CI3: M86 | CJ3: M87 | CK3: M88 | CL3: M89 | CM3: M90 | CN3: M91 | CO3: M92 | CP3: M93 | CQ3: M94 | CR3: M95 | CS3: M96 | CT3: M97 | CU3: M98 | CV3: M99 | CW3: M100 | CX3: M101 | CY3: M102 | CZ3: M103 | DA3: M104 | DB3: M105 | DC3: M106 | DD3: M107 | DE3: M108 | DF3: M109 | DG3: M110 | DH3: M111 | DI3: M112 | DJ3: M113 | DK3: M114 | DL3: M115 | DM3: M116 | DN3: M117 | DO3: M118 | DP3: M119 | DQ3: M120 | DR3: M121 | DS3: M122 | DT3: M123 | DU3: M124 | DV3: M125 | DW3: M126 | DX3: M127 | DY3: M128 | DZ3: M129 | EA3: M130 | EB3: M131 | EC3: M132 | ED3: M133 | EE3: M134 | EF3: M135 | EG3: M136 | EH3: M137 | EI3: M138 | EJ3: M139 | EK3: M140 | EL3: M141 | EM3: M142 | EN3: M143 | EO3: M144 | EP3: M145 | EQ3: M146 | ER3: M147 | ES3: M148 | ET3: M149 | EU3: M150 | EV3: M151 | EW3: M152 | EX3: M153 | EY3: M154 | EZ3: M155 | FA3: M156 | FB3: M157 | FC3: M158 | FD3: M159 | FE3: M160 | FF3: M161 | FG3: M162 | FH3: M163 | FI3: M164 | FJ3: M165 | FK3: M166 | FL3: M167 | FM3: M168 | FN3: M169 | FO3: M170 | FP3: M171 | FQ3: M172 | FR3: M173 | FS3: M174 | FT3: M175 | FU3: M176 | FV3: M177 | FW3: M178 | FX3: M179 | FY3: M180
A5: Revenue by Deal
A6: Deal #1 | B6: =_Engine_R50!F31/12 -> 0 | C6: =_Engine_R50!F32/12 -> 0 | D6: =_Engine_R50!F33/12 -> 0 | E6: =_Engine_R50!F34/12 -> 2.0833333 | F6: =_Engine_R50!F35/12 -> 2.0744473 | G6: =_Engine_R50!F36/12 -> 2.0655991 | H6: =_Engine_R50!F37/12 -> 2.0567886 | I6: =_Engine_R50!F38/12 -> 2.0480158 | J6: =_Engine_R50!F39/12 -> 2.0392803 | K6: =_Engine_R50!F40/12 -> 2.0305822 | L6: =_Engine_R50!F41/12 -> 2.0219211 | M6: =_Engine_R50!F42/12 -> 2.0132969 | N6: =_Engine_R50!F43/12 -> 2.0047096 | O6: =_Engine_R50!F44/12 -> 1.9961589 | P6: =_Engine_R50!F45/12 -> 1.9876446 | Q6: =_Engine_R50!F46/12 -> 1.9791667 | R6: =_Engine_R50!F47/12 -> 1.9707249 | S6: =_Engine_R50!F48/12 -> 1.9623191 | T6: =_Engine_R50!F49/12 -> 1.9539492 | U6: =_Engine_R50!F50/12 -> 1.945615 | V6: =_Engine_R50!F51/12 -> 1.9373163 | W6: =_Engine_R50!F52/12 -> 1.929053 | X6: =_Engine_R50!F53/12 -> 1.920825 | Y6: =_Engine_R50!F54/12 -> 1.9126321 | Z6: =_Engine_R50!F55/12 -> 1.9044741 | AA6: =_Engine_R50!F56/12 -> 1.8963509 | AB6: =_Engine_R50!F57/12 -> 1.8882624 | AC6: =_Engine_R50!F58/12 -> 1.8802083 | AD6: =_Engine_R50!F59/12 -> 1.8721886 | AE6: =_Engine_R50!F60/12 -> 1.8642032 | AF6: =_Engine_R50!F61/12 -> 1.8562517 | AG6: =_Engine_R50!F62/12 -> 1.8483342 | AH6: =_Engine_R50!F63/12 -> 1.8404505 | AI6: =_Engine_R50!F64/12 -> 1.8326004 | AJ6: =_Engine_R50!F65/12 -> 1.8247838 | AK6: =_Engine_R50!F66/12 -> 1.8170005 | AL6: =_Engine_R50!F67/12 -> 1.8092504 | AM6: =_Engine_R50!F68/12 -> 1.8015334 | AN6: =_Engine_R50!F69/12 -> 1.7938493 | AO6: =_Engine_R50!F70/12 -> 1.7861979 | AP6: =_Engine_R50!F71/12 -> 1.7785792 | AQ6: =_Engine_R50!F72/12 -> 1.770993 | AR6: =_Engine_R50!F73/12 -> 1.7634392 | AS6: =_Engine_R50!F74/12 -> 1.7559175 | AT6: =_Engine_R50!F75/12 -> 1.748428 | AU6: =_Engine_R50!F76/12 -> 1.7409704 | AV6: =_Engine_R50!F77/12 -> 1.7335446 | AW6: =_Engine_R50!F78/12 -> 1.7261505 | AX6: =_Engine_R50!F79/12 -> 1.7187879 | AY6: =_Engine_R50!F80/12 -> 1.7114567 | AZ6: =_Engine_R50!F81/12 -> 1.7041568 | BA6: =_Engine_R50!F82/12 -> 1.696888 | BB6: =_Engine_R50!F83/12 -> 1.6896503 | BC6: =_Engine_R50!F84/12 -> 1.6824434 | BD6: =_Engine_R50!F85/12 -> 1.6752672 | BE6: =_Engine_R50!F86/12 -> 1.6681216 | BF6: =_Engine_R50!F87/12 -> 1.6610066 | BG6: =_Engine_R50!F88/12 -> 1.6539219 | BH6: =_Engine_R50!F89/12 -> 1.6468674 | BI6: =_Engine_R50!F90/12 -> 1.6398429 | BJ6: =_Engine_R50!F91/12 -> 1.6328485 | BK6: =_Engine_R50!F92/12 -> 1.6258839 | BL6: =_Engine_R50!F93/12 -> 1.618949 | BM6: =_Engine_R50!F94/12 -> 1.6120436 | BN6: =_Engine_R50!F95/12 -> 1.6051677 | BO6: =_Engine_R50!F96/12 -> 1.5983212 | BP6: =_Engine_R50!F97/12 -> 1.5915038 | BQ6: =_Engine_R50!F98/12 -> 1.5847156 | BR6: =_Engine_R50!F99/12 -> 1.5779563 | BS6: =_Engine_R50!F100/12 -> 1.5712258 | BT6: =_Engine_R50!F101/12 -> 1.564524 | BU6: =_Engine_R50!F102/12 -> 1.5578508 | BV6: =_Engine_R50!F103/12 -> 1.5512061 | BW6: =_Engine_R50!F104/12 -> 1.5445897 | BX6: =_Engine_R50!F105/12 -> 1.5380015 | BY6: =_Engine_R50!F106/12 -> 1.5314414 | BZ6: =_Engine_R50!F107/12 -> 1.5249094 | CA6: =_Engine_R50!F108/12 -> 1.5184051 | CB6: =_Engine_R50!F109/12 -> 1.5119286 | CC6: =_Engine_R50!F110/12 -> 1.5054798 | CD6: =_Engine_R50!F111/12 -> 1.4990584 | CE6: =_Engine_R50!F112/12 -> 1.4926645 | CF6: =_Engine_R50!F113/12 -> 1.4862978 | CG6: =_Engine_R50!F114/12 -> 1.4799583 | CH6: =_Engine_R50!F115/12 -> 1.4736458 | CI6: =_Engine_R50!F116/12 -> 1.4673602 | CJ6: =_Engine_R50!F117/12 -> 1.4611014 | CK6: =_Engine_R50!F118/12 -> 1.4548694 | CL6: =_Engine_R50!F119/12 -> 1.4486639 | CM6: =_Engine_R50!F120/12 -> 1.4424849 | CN6: =_Engine_R50!F121/12 -> 1.4363322 | CO6: =_Engine_R50!F122/12 -> 1.4302058 | CP6: =_Engine_R50!F123/12 -> 1.4241055 | CQ6: =_Engine_R50!F124/12 -> 1.4180313 | CR6: =_Engine_R50!F125/12 -> 1.4119829 | CS6: =_Engine_R50!F126/12 -> 1.4059603 | CT6: =_Engine_R50!F127/12 -> 1.3999635 | CU6: =_Engine_R50!F128/12 -> 1.3939922 | CV6: =_Engine_R50!F129/12 -> 1.3880464 | CW6: =_Engine_R50!F130/12 -> 1.3821259 | CX6: =_Engine_R50!F131/12 -> 1.3762307 | CY6: =_Engine_R50!F132/12 -> 1.3703606 | CZ6: =_Engine_R50!F133/12 -> 1.3645156 | DA6: =_Engine_R50!F134/12 -> 1.3586955 | DB6: =_Engine_R50!F135/12 -> 1.3529002 | DC6: =_Engine_R50!F136/12 -> 1.3471297 | DD6: =_Engine_R50!F137/12 -> 1.3413838 | DE6: =_Engine_R50!F138/12 -> 1.3356623 | DF6: =_Engine_R50!F139/12 -> 1.3299653 | DG6: =_Engine_R50!F140/12 -> 1.3242926 | DH6: =_Engine_R50!F141/12 -> 1.318644 | DI6: =_Engine_R50!F142/12 -> 1.3130196 | DJ6: =_Engine_R50!F143/12 -> 1.3074192 | DK6: =_Engine_R50!F144/12 -> 1.3018426 | DL6: =_Engine_R50!F145/12 -> 1.2962898 | DM6: =_Engine_R50!F146/12 -> 1.2907607 | DN6: =_Engine_R50!F147/12 -> 1.2852552 | DO6: =_Engine_R50!F148/12 -> 1.2797732 | DP6: =_Engine_R50!F149/12 -> 1.2743146 | DQ6: =_Engine_R50!F150/12 -> 1.2688792 | DR6: =_Engine_R50!F151/12 -> 1.263467 | DS6: =_Engine_R50!F152/12 -> 1.2580779 | DT6: =_Engine_R50!F153/12 -> 1.2527118 | DU6: =_Engine_R50!F154/12 -> 1.2473686 | DV6: =_Engine_R50!F155/12 -> 1.2420482 | DW6: =_Engine_R50!F156/12 -> 1.2367505 | DX6: =_Engine_R50!F157/12 -> 1.2314753 | DY6: =_Engine_R50!F158/12 -> 1.2262227 | DZ6: =_Engine_R50!F159/12 -> 1.2209925 | EA6: =_Engine_R50!F160/12 -> 1.2157845 | EB6: =_Engine_R50!F161/12 -> 1.2105988 | EC6: =_Engine_R50!F162/12 -> 1.2054352 | ED6: =_Engine_R50!F163/12 -> 1.2002937 | EE6: =_Engine_R50!F164/12 -> 1.195174 | EF6: =_Engine_R50!F165/12 -> 1.1900762 | EG6: =_Engine_R50!F166/12 -> 1.1850002 | EH6: =_Engine_R50!F167/12 -> 1.1799458 | EI6: =_Engine_R50!F168/12 -> 1.1749129 | EJ6: =_Engine_R50!F169/12 -> 1.1699016 | EK6: =_Engine_R50!F170/12 -> 1.1649116 | EL6: =_Engine_R50!F171/12 -> 1.1599428 | EM6: =_Engine_R50!F172/12 -> 1.1549953 | EN6: =_Engine_R50!F173/12 -> 1.1500689 | EO6: =_Engine_R50!F174/12 -> 1.1451635 | EP6: =_Engine_R50!F175/12 -> 1.140279 | EQ6: =_Engine_R50!F176/12 -> 1.1354153 | ER6: =_Engine_R50!F177/12 -> 1.1305724 | ES6: =_Engine_R50!F178/12 -> 1.1257502 | ET6: =_Engine_R50!F179/12 -> 1.1209485 | EU6: =_Engine_R50!F180/12 -> 1.1161673 | EV6: =_Engine_R50!F181/12 -> 1.1114065 | EW6: =_Engine_R50!F182/12 -> 1.106666 | EX6: =_Engine_R50!F183/12 -> 1.1019457 | EY6: =_Engine_R50!F184/12 -> 1.0972456 | EZ6: =_Engine_R50!F185/12 -> 1.0925654 | FA6: =_Engine_R50!F186/12 -> 1.0879053 | FB6: =_Engine_R50!F187/12 -> 1.083265 | FC6: =_Engine_R50!F188/12 -> 1.0786446 | FD6: =_Engine_R50!F189/12 -> 1.0740438 | FE6: =_Engine_R50!F190/12 -> 1.0694627 | FF6: =_Engine_R50!F191/12 -> 1.0649011 | FG6: =_Engine_R50!F192/12 -> 1.0603589 | FH6: =_Engine_R50!F193/12 -> 1.0558362 | FI6: =_Engine_R50!F194/12 -> 1.0513327 | FJ6: =_Engine_R50!F195/12 -> 1.0468484 | FK6: =_Engine_R50!F196/12 -> 1.0423833 | FL6: =_Engine_R50!F197/12 -> 1.0379372 | FM6: =_Engine_R50!F198/12 -> 1.03351 | FN6: =_Engine_R50!F199/12 -> 1.0291018 | FO6: =_Engine_R50!F200/12 -> 1.0247123 | FP6: =_Engine_R50!F201/12 -> 1.0203416 | FQ6: =_Engine_R50!F202/12 -> 1.0159895 | FR6: =_Engine_R50!F203/12 -> 1.011656 | FS6: =_Engine_R50!F204/12 -> 1.007341 | FT6: =_Engine_R50!F205/12 -> 1.0030444 | FU6: =_Engine_R50!F206/12 -> 0.99876605 | FV6: =_Engine_R50!F207/12 -> 0.994506 | FW6: =_Engine_R50!F208/12 -> 0.99026411 | FX6: =_Engine_R50!F209/12 -> 0.98604032 | FY6: =_Engine_R50!F210/12 -> 0.98183454
A7: Deal #2 | B7: =_Engine_R50!G31/12 -> 0 | C7: =_Engine_R50!G32/12 -> 0 | D7: =_Engine_R50!G33/12 -> 0 | E7: =_Engine_R50!G34/12 -> 0 | F7: =_Engine_R50!G35/12 -> 0 | G7: =_Engine_R50!G36/12 -> 0 | H7: =_Engine_R50!G37/12 -> 0 | I7: =_Engine_R50!G38/12 -> 2.0833333 | J7: =_Engine_R50!G39/12 -> 2.0651216 | K7: =_Engine_R50!G40/12 -> 2.0470692 | L7: =_Engine_R50!G41/12 -> 2.0291745 | M7: =_Engine_R50!G42/12 -> 2.0114362 | N7: =_Engine_R50!G43/12 -> 1.993853 | O7: =_Engine_R50!G44/12 -> 1.9764235 | P7: =_Engine_R50!G45/12 -> 1.9591464 | Q7: =_Engine_R50!G46/12 -> 1.9420203 | R7: =_Engine_R50!G47/12 -> 1.9250439 | S7: =_Engine_R50!G48/12 -> 1.9082159 | T7: =_Engine_R50!G49/12 -> 1.8915351 | U7: =_Engine_R50!G50/12 -> 1.875 | V7: =_Engine_R50!G51/12 -> 1.8586095 | W7: =_Engine_R50!G52/12 -> 1.8423622 | X7: =_Engine_R50!G53/12 -> 1.826257 | Y7: =_Engine_R50!G54/12 -> 1.8102926 | Z7: =_Engine_R50!G55/12 -> 1.7944677 | AA7: =_Engine_R50!G56/12 -> 1.7787812 | AB7: =_Engine_R50!G57/12 -> 1.7632318 | AC7: =_Engine_R50!G58/12 -> 1.7478183 | AD7: =_Engine_R50!G59/12 -> 1.7325395 | AE7: =_Engine_R50!G60/12 -> 1.7173944 | AF7: =_Engine_R50!G61/12 -> 1.7023816 | AG7: =_Engine_R50!G62/12 -> 1.6875 | AH7: =_Engine_R50!G63/12 -> 1.6727485 | AI7: =_Engine_R50!G64/12 -> 1.658126 | AJ7: =_Engine_R50!G65/12 -> 1.6436313 | AK7: =_Engine_R50!G66/12 -> 1.6292633 | AL7: =_Engine_R50!G67/12 -> 1.615021 | AM7: =_Engine_R50!G68/12 -> 1.6009031 | AN7: =_Engine_R50!G69/12 -> 1.5869086 | AO7: =_Engine_R50!G70/12 -> 1.5730365 | AP7: =_Engine_R50!G71/12 -> 1.5592856 | AQ7: =_Engine_R50!G72/12 -> 1.5456549 | AR7: =_Engine_R50!G73/12 -> 1.5321434 | AS7: =_Engine_R50!G74/12 -> 1.51875 | AT7: =_Engine_R50!G75/12 -> 1.5054737 | AU7: =_Engine_R50!G76/12 -> 1.4923134 | AV7: =_Engine_R50!G77/12 -> 1.4792682 | AW7: =_Engine_R50!G78/12 -> 1.466337 | AX7: =_Engine_R50!G79/12 -> 1.4535189 | AY7: =_Engine_R50!G80/12 -> 1.4408128 | AZ7: =_Engine_R50!G81/12 -> 1.4282177 | BA7: =_Engine_R50!G82/12 -> 1.4157328 | BB7: =_Engine_R50!G83/12 -> 1.403357 | BC7: =_Engine_R50!G84/12 -> 1.3910894 | BD7: =_Engine_R50!G85/12 -> 1.3789291 | BE7: =_Engine_R50!G86/12 -> 1.366875 | BF7: =_Engine_R50!G87/12 -> 1.3549263 | BG7: =_Engine_R50!G88/12 -> 1.3430821 | BH7: =_Engine_R50!G89/12 -> 1.3313414 | BI7: =_Engine_R50!G90/12 -> 1.3197033 | BJ7: =_Engine_R50!G91/12 -> 1.308167 | BK7: =_Engine_R50!G92/12 -> 1.2967315 | BL7: =_Engine_R50!G93/12 -> 1.285396 | BM7: =_Engine_R50!G94/12 -> 1.2741595 | BN7: =_Engine_R50!G95/12 -> 1.2630213 | BO7: =_Engine_R50!G96/12 -> 1.2519805 | BP7: =_Engine_R50!G97/12 -> 1.2410362 | BQ7: =_Engine_R50!G98/12 -> 1.2301875 | BR7: =_Engine_R50!G99/12 -> 1.2194337 | BS7: =_Engine_R50!G100/12 -> 1.2087739 | BT7: =_Engine_R50!G101/12 -> 1.1982072 | BU7: =_Engine_R50!G102/12 -> 1.187733 | BV7: =_Engine_R50!G103/12 -> 1.1773503 | BW7: =_Engine_R50!G104/12 -> 1.1670583 | BX7: =_Engine_R50!G105/12 -> 1.1568564 | BY7: =_Engine_R50!G106/12 -> 1.1467436 | BZ7: =_Engine_R50!G107/12 -> 1.1367192 | CA7: =_Engine_R50!G108/12 -> 1.1267824 | CB7: =_Engine_R50!G109/12 -> 1.1169325 | CC7: =_Engine_R50!G110/12 -> 1.1071688 | CD7: =_Engine_R50!G111/12 -> 1.0974903 | CE7: =_Engine_R50!G112/12 -> 1.0878965 | CF7: =_Engine_R50!G113/12 -> 1.0783865 | CG7: =_Engine_R50!G114/12 -> 1.0689597 | CH7: =_Engine_R50!G115/12 -> 1.0596152 | CI7: =_Engine_R50!G116/12 -> 1.0503525 | CJ7: =_Engine_R50!G117/12 -> 1.0411707 | CK7: =_Engine_R50!G118/12 -> 1.0320692 | CL7: =_Engine_R50!G119/12 -> 1.0230473 | CM7: =_Engine_R50!G120/12 -> 1.0141042 | CN7: =_Engine_R50!G121/12 -> 1.0052393 | CO7: =_Engine_R50!G122/12 -> 0.99645187 | CP7: =_Engine_R50!G123/12 -> 0.98774128 | CQ7: =_Engine_R50!G124/12 -> 0.97910683 | CR7: =_Engine_R50!G125/12 -> 0.97054786 | CS7: =_Engine_R50!G126/12 -> 0.96206371 | CT7: =_Engine_R50!G127/12 -> 0.95365372 | CU7: =_Engine_R50!G128/12 -> 0.94531725 | CV7: =_Engine_R50!G129/12 -> 0.93705366 | CW7: =_Engine_R50!G130/12 -> 0.9288623 | CX7: =_Engine_R50!G131/12 -> 0.92074254 | CY7: =_Engine_R50!G132/12 -> 0.91269377 | CZ7: =_Engine_R50!G133/12 -> 0.90471536 | DA7: =_Engine_R50!G134/12 -> 0.89680669 | DB7: =_Engine_R50!G135/12 -> 0.88896715 | DC7: =_Engine_R50!G136/12 -> 0.88119615 | DD7: =_Engine_R50!G137/12 -> 0.87349307 | DE7: =_Engine_R50!G138/12 -> 0.86585734 | DF7: =_Engine_R50!G139/12 -> 0.85828835 | DG7: =_Engine_R50!G140/12 -> 0.85078553 | DH7: =_Engine_R50!G141/12 -> 0.84334829 | DI7: =_Engine_R50!G142/12 -> 0.83597607 | DJ7: =_Engine_R50!G143/12 -> 0.82866829 | DK7: =_Engine_R50!G144/12 -> 0.82142439 | DL7: =_Engine_R50!G145/12 -> 0.81424382 | DM7: =_Engine_R50!G146/12 -> 0.80712602 | DN7: =_Engine_R50!G147/12 -> 0.80007044 | DO7: =_Engine_R50!G148/12 -> 0.79307653 | DP7: =_Engine_R50!G149/12 -> 0.78614377 | DQ7: =_Engine_R50!G150/12 -> 0.7792716 | DR7: =_Engine_R50!G151/12 -> 0.77245951 | DS7: =_Engine_R50!G152/12 -> 0.76570697 | DT7: =_Engine_R50!G153/12 -> 0.75901346 | DU7: =_Engine_R50!G154/12 -> 0.75237846 | DV7: =_Engine_R50!G155/12 -> 0.74580146 | DW7: =_Engine_R50!G156/12 -> 0.73928195 | DX7: =_Engine_R50!G157/12 -> 0.73281944 | DY7: =_Engine_R50!G158/12 -> 0.72641342 | DZ7: =_Engine_R50!G159/12 -> 0.72006339 | EA7: =_Engine_R50!G160/12 -> 0.71376888 | EB7: =_Engine_R50!G161/12 -> 0.70752939 | EC7: =_Engine_R50!G162/12 -> 0.70134444 | ED7: =_Engine_R50!G163/12 -> 0.69521356 | EE7: =_Engine_R50!G164/12 -> 0.68913628 | EF7: =_Engine_R50!G165/12 -> 0.68311211 | EG7: =_Engine_R50!G166/12 -> 0.67714061 | EH7: =_Engine_R50!G167/12 -> 0.67122131 | EI7: =_Engine_R50!G168/12 -> 0.66535376 | EJ7: =_Engine_R50!G169/12 -> 0.6595375 | EK7: =_Engine_R50!G170/12 -> 0.65377208 | EL7: =_Engine_R50!G171/12 -> 0.64805705 | EM7: =_Engine_R50!G172/12 -> 0.64239199 | EN7: =_Engine_R50!G173/12 -> 0.63677645 | EO7: =_Engine_R50!G174/12 -> 0.63121 | EP7: =_Engine_R50!G175/12 -> 0.62569221 | EQ7: =_Engine_R50!G176/12 -> 0.62022265 | ER7: =_Engine_R50!G177/12 -> 0.6148009 | ES7: =_Engine_R50!G178/12 -> 0.60942655 | ET7: =_Engine_R50!G179/12 -> 0.60409918 | EU7: =_Engine_R50!G180/12 -> 0.59881838 | EV7: =_Engine_R50!G181/12 -> 0.59358375 | EW7: =_Engine_R50!G182/12 -> 0.58839487 | EX7: =_Engine_R50!G183/12 -> 0.58325135 | EY7: =_Engine_R50!G184/12 -> 0.57815279 | EZ7: =_Engine_R50!G185/12 -> 0.57309881 | FA7: =_Engine_R50!G186/12 -> 0.568089 | FB7: =_Engine_R50!G187/12 -> 0.56312299 | FC7: =_Engine_R50!G188/12 -> 0.55820038 | FD7: =_Engine_R50!G189/12 -> 0.55332081 | FE7: =_Engine_R50!G190/12 -> 0.5484839 | FF7: =_Engine_R50!G191/12 -> 0.54368926 | FG7: =_Engine_R50!G192/12 -> 0.53893654 | FH7: =_Engine_R50!G193/12 -> 0.53422537 | FI7: =_Engine_R50!G194/12 -> 0.52955538 | FJ7: =_Engine_R50!G195/12 -> 0.52492621 | FK7: =_Engine_R50!G196/12 -> 0.52033751 | FL7: =_Engine_R50!G197/12 -> 0.51578892 | FM7: =_Engine_R50!G198/12 -> 0.5112801 | FN7: =_Engine_R50!G199/12 -> 0.50681069 | FO7: =_Engine_R50!G200/12 -> 0.50238035 | FP7: =_Engine_R50!G201/12 -> 0.49798873 | FQ7: =_Engine_R50!G202/12 -> 0.49363551 | FR7: =_Engine_R50!G203/12 -> 0.48932034 | FS7: =_Engine_R50!G204/12 -> 0.48504289 | FT7: =_Engine_R50!G205/12 -> 0.48080283 | FU7: =_Engine_R50!G206/12 -> 0.47659984 | FV7: =_Engine_R50!G207/12 -> 0.47243359 | FW7: =_Engine_R50!G208/12 -> 0.46830376 | FX7: =_Engine_R50!G209/12 -> 0.46421003 | FY7: =_Engine_R50!G210/12 -> 0.46015209
A8: Deal #3 | B8: =_Engine_R50!H31/12 -> 0 | C8: =_Engine_R50!H32/12 -> 0 | D8: =_Engine_R50!H33/12 -> 0 | E8: =_Engine_R50!H34/12 -> 0 | F8: =_Engine_R50!H35/12 -> 0 | G8: =_Engine_R50!H36/12 -> 0 | H8: =_Engine_R50!H37/12 -> 0 | I8: =_Engine_R50!H38/12 -> 0 | J8: =_Engine_R50!H39/12 -> 0 | K8: =_Engine_R50!H40/12 -> 0 | L8: =_Engine_R50!H41/12 -> 0 | M8: =_Engine_R50!H42/12 -> 2.0833333 | N8: =_Engine_R50!H43/12 -> 2.0553084 | O8: =_Engine_R50!H44/12 -> 2.0276605 | P8: =_Engine_R50!H45/12 -> 2.0003846 | Q8: =_Engine_R50!H46/12 -> 1.9734755 | R8: =_Engine_R50!H47/12 -> 1.9469284 | S8: =_Engine_R50!H48/12 -> 1.9207384 | T8: =_Engine_R50!H49/12 -> 1.8949008 | U8: =_Engine_R50!H50/12 -> 1.8694107 | V8: =_Engine_R50!H51/12 -> 1.8442634 | W8: =_Engine_R50!H52/12 -> 1.8194545 | X8: =_Engine_R50!H53/12 -> 1.7949793 | Y8: =_Engine_R50!H54/12 -> 1.7708333 | Z8: =_Engine_R50!H55/12 -> 1.7470122 | AA8: =_Engine_R50!H56/12 -> 1.7235115 | AB8: =_Engine_R50!H57/12 -> 1.7003269 | AC8: =_Engine_R50!H58/12 -> 1.6774542 | AD8: =_Engine_R50!H59/12 -> 1.6548891 | AE8: =_Engine_R50!H60/12 -> 1.6326277 | AF8: =_Engine_R50!H61/12 -> 1.6106656 | AG8: =_Engine_R50!H62/12 -> 1.5889991 | AH8: =_Engine_R50!H63/12 -> 1.5676239 | AI8: =_Engine_R50!H64/12 -> 1.5465363 | AJ8: =_Engine_R50!H65/12 -> 1.5257324 | AK8: =_Engine_R50!H66/12 -> 1.5052083 | AL8: =_Engine_R50!H67/12 -> 1.4849604 | AM8: =_Engine_R50!H68/12 -> 1.4649847 | AN8: =_Engine_R50!H69/12 -> 1.4452778 | AO8: =_Engine_R50!H70/12 -> 1.425836 | AP8: =_Engine_R50!H71/12 -> 1.4066558 | AQ8: =_Engine_R50!H72/12 -> 1.3877335 | AR8: =_Engine_R50!H73/12 -> 1.3690658 | AS8: =_Engine_R50!H74/12 -> 1.3506492 | AT8: =_Engine_R50!H75/12 -> 1.3324803 | AU8: =_Engine_R50!H76/12 -> 1.3145559 | AV8: =_Engine_R50!H77/12 -> 1.2968725 | AW8: =_Engine_R50!H78/12 -> 1.2794271 | AX8: =_Engine_R50!H79/12 -> 1.2622163 | AY8: =_Engine_R50!H80/12 -> 1.245237 | AZ8: =_Engine_R50!H81/12 -> 1.2284862 | BA8: =_Engine_R50!H82/12 -> 1.2119606 | BB8: =_Engine_R50!H83/12 -> 1.1956574 | BC8: =_Engine_R50!H84/12 -> 1.1795735 | BD8: =_Engine_R50!H85/12 -> 1.1637059 | BE8: =_Engine_R50!H86/12 -> 1.1480518 | BF8: =_Engine_R50!H87/12 -> 1.1326083 | BG8: =_Engine_R50!H88/12 -> 1.1173725 | BH8: =_Engine_R50!H89/12 -> 1.1023417 | BI8: =_Engine_R50!H90/12 -> 1.087513 | BJ8: =_Engine_R50!H91/12 -> 1.0728839 | BK8: =_Engine_R50!H92/12 -> 1.0584515 | BL8: =_Engine_R50!H93/12 -> 1.0442132 | BM8: =_Engine_R50!H94/12 -> 1.0301665 | BN8: =_Engine_R50!H95/12 -> 1.0163088 | BO8: =_Engine_R50!H96/12 -> 1.0026375 | BP8: =_Engine_R50!H97/12 -> 0.98915004 | BQ8: =_Engine_R50!H98/12 -> 0.97584404 | BR8: =_Engine_R50!H99/12 -> 0.96271704 | BS8: =_Engine_R50!H100/12 -> 0.94976662 | BT8: =_Engine_R50!H101/12 -> 0.93699041 | BU8: =_Engine_R50!H102/12 -> 0.92438607 | BV8: =_Engine_R50!H103/12 -> 0.91195128 | BW8: =_Engine_R50!H104/12 -> 0.89968376 | BX8: =_Engine_R50!H105/12 -> 0.88758126 | BY8: =_Engine_R50!H106/12 -> 0.87564156 | BZ8: =_Engine_R50!H107/12 -> 0.86386248 | CA8: =_Engine_R50!H108/12 -> 0.85224184 | CB8: =_Engine_R50!H109/12 -> 0.84077753 | CC8: =_Engine_R50!H110/12 -> 0.82946744 | CD8: =_Engine_R50!H111/12 -> 0.81830949 | CE8: =_Engine_R50!H112/12 -> 0.80730163 | CF8: =_Engine_R50!H113/12 -> 0.79644185 | CG8: =_Engine_R50!H114/12 -> 0.78572816 | CH8: =_Engine_R50!H115/12 -> 0.77515858 | CI8: =_Engine_R50!H116/12 -> 0.76473119 | CJ8: =_Engine_R50!H117/12 -> 0.75444407 | CK8: =_Engine_R50!H118/12 -> 0.74429533 | CL8: =_Engine_R50!H119/12 -> 0.73428311 | CM8: =_Engine_R50!H120/12 -> 0.72440557 | CN8: =_Engine_R50!H121/12 -> 0.7146609 | CO8: =_Engine_R50!H122/12 -> 0.70504732 | CP8: =_Engine_R50!H123/12 -> 0.69556306 | CQ8: =_Engine_R50!H124/12 -> 0.68620639 | CR8: =_Engine_R50!H125/12 -> 0.67697557 | CS8: =_Engine_R50!H126/12 -> 0.66786893 | CT8: =_Engine_R50!H127/12 -> 0.6588848 | CU8: =_Engine_R50!H128/12 -> 0.65002151 | CV8: =_Engine_R50!H129/12 -> 0.64127746 | CW8: =_Engine_R50!H130/12 -> 0.63265103 | CX8: =_Engine_R50!H131/12 -> 0.62414064 | CY8: =_Engine_R50!H132/12 -> 0.61574473 | CZ8: =_Engine_R50!H133/12 -> 0.60746177 | DA8: =_Engine_R50!H134/12 -> 0.59929022 | DB8: =_Engine_R50!H135/12 -> 0.5912286 | DC8: =_Engine_R50!H136/12 -> 0.58327543 | DD8: =_Engine_R50!H137/12 -> 0.57542924 | DE8: =_Engine_R50!H138/12 -> 0.56768859 | DF8: =_Engine_R50!H139/12 -> 0.56005208 | DG8: =_Engine_R50!H140/12 -> 0.55251829 | DH8: =_Engine_R50!H141/12 -> 0.54508584 | DI8: =_Engine_R50!H142/12 -> 0.53775337 | DJ8: =_Engine_R50!H143/12 -> 0.53051954 | DK8: =_Engine_R50!H144/12 -> 0.52338302 | DL8: =_Engine_R50!H145/12 -> 0.5163425 | DM8: =_Engine_R50!H146/12 -> 0.50939669 | DN8: =_Engine_R50!H147/12 -> 0.50254431 | DO8: =_Engine_R50!H148/12 -> 0.49578411 | DP8: =_Engine_R50!H149/12 -> 0.48911485 | DQ8: =_Engine_R50!H150/12 -> 0.4825353 | DR8: =_Engine_R50!H151/12 -> 0.47604427 | DS8: =_Engine_R50!H152/12 -> 0.46964054 | DT8: =_Engine_R50!H153/12 -> 0.46332296 | DU8: =_Engine_R50!H154/12 -> 0.45709037 | DV8: =_Engine_R50!H155/12 -> 0.45094161 | DW8: =_Engine_R50!H156/12 -> 0.44487557 | DX8: =_Engine_R50!H157/12 -> 0.43889113 | DY8: =_Engine_R50!H158/12 -> 0.43298719 | DZ8: =_Engine_R50!H159/12 -> 0.42716267 | EA8: =_Engine_R50!H160/12 -> 0.4214165 | EB8: =_Engine_R50!H161/12 -> 0.41574762 | EC8: =_Engine_R50!H162/12 -> 0.41015501 | ED8: =_Engine_R50!H163/12 -> 0.40463763 | EE8: =_Engine_R50!H164/12 -> 0.39919446 | EF8: =_Engine_R50!H165/12 -> 0.39382452 | EG8: =_Engine_R50!H166/12 -> 0.38852681 | EH8: =_Engine_R50!H167/12 -> 0.38330037 | EI8: =_Engine_R50!H168/12 -> 0.37814423 | EJ8: =_Engine_R50!H169/12 -> 0.37305746 | EK8: =_Engine_R50!H170/12 -> 0.36803911 | EL8: =_Engine_R50!H171/12 -> 0.36308827 | EM8: =_Engine_R50!H172/12 -> 0.35820402 | EN8: =_Engine_R50!H173/12 -> 0.35338548 | EO8: =_Engine_R50!H174/12 -> 0.34863176 | EP8: =_Engine_R50!H175/12 -> 0.34394198 | EQ8: =_Engine_R50!H176/12 -> 0.33931529 | ER8: =_Engine_R50!H177/12 -> 0.33475084 | ES8: =_Engine_R50!H178/12 -> 0.33024779 | ET8: =_Engine_R50!H179/12 -> 0.32580531 | EU8: =_Engine_R50!H180/12 -> 0.3214226 | EV8: =_Engine_R50!H181/12 -> 0.31709884 | EW8: =_Engine_R50!H182/12 -> 0.31283324 | EX8: =_Engine_R50!H183/12 -> 0.30862503 | EY8: =_Engine_R50!H184/12 -> 0.30447342 | EZ8: =_Engine_R50!H185/12 -> 0.30037766 | FA8: =_Engine_R50!H186/12 -> 0.29633699 | FB8: =_Engine_R50!H187/12 -> 0.29235068 | FC8: =_Engine_R50!H188/12 -> 0.288418 | FD8: =_Engine_R50!H189/12 -> 0.28453821 | FE8: =_Engine_R50!H190/12 -> 0.28071062 | FF8: =_Engine_R50!H191/12 -> 0.27693452 | FG8: =_Engine_R50!H192/12 -> 0.27320921 | FH8: =_Engine_R50!H193/12 -> 0.26953401 | FI8: =_Engine_R50!H194/12 -> 0.26590826 | FJ8: =_Engine_R50!H195/12 -> 0.26233127 | FK8: =_Engine_R50!H196/12 -> 0.25880241 | FL8: =_Engine_R50!H197/12 -> 0.25532101 | FM8: =_Engine_R50!H198/12 -> 0.25188644 | FN8: =_Engine_R50!H199/12 -> 0.24849808 | FO8: =_Engine_R50!H200/12 -> 0.2451553 | FP8: =_Engine_R50!H201/12 -> 0.24185748 | FQ8: =_Engine_R50!H202/12 -> 0.23860403 | FR8: =_Engine_R50!H203/12 -> 0.23539434 | FS8: =_Engine_R50!H204/12 -> 0.23222783 | FT8: =_Engine_R50!H205/12 -> 0.22910391 | FU8: =_Engine_R50!H206/12 -> 0.22602202 | FV8: =_Engine_R50!H207/12 -> 0.22298158 | FW8: =_Engine_R50!H208/12 -> 0.21998204 | FX8: =_Engine_R50!H209/12 -> 0.21702286 | FY8: =_Engine_R50!H210/12 -> 0.21410348
A9: Deal #4 | B9: =_Engine_R50!I31/12 -> 0 | C9: =_Engine_R50!I32/12 -> 0 | D9: =_Engine_R50!I33/12 -> 0 | E9: =_Engine_R50!I34/12 -> 0 | F9: =_Engine_R50!I35/12 -> 0 | G9: =_Engine_R50!I36/12 -> 0 | H9: =_Engine_R50!I37/12 -> 0 | I9: =_Engine_R50!I38/12 -> 0 | J9: =_Engine_R50!I39/12 -> 0 | K9: =_Engine_R50!I40/12 -> 0 | L9: =_Engine_R50!I41/12 -> 0 | M9: =_Engine_R50!I42/12 -> 0 | N9: =_Engine_R50!I43/12 -> 0 | O9: =_Engine_R50!I44/12 -> 0 | P9: =_Engine_R50!I45/12 -> 0 | Q9: =_Engine_R50!I46/12 -> 2.0833333 | R9: =_Engine_R50!I47/12 -> 2.0553084 | S9: =_Engine_R50!I48/12 -> 2.0276605 | T9: =_Engine_R50!I49/12 -> 2.0003846 | U9: =_Engine_R50!I50/12 -> 1.9734755 | V9: =_Engine_R50!I51/12 -> 1.9469284 | W9: =_Engine_R50!I52/12 -> 1.9207384 | X9: =_Engine_R50!I53/12 -> 1.8949008 | Y9: =_Engine_R50!I54/12 -> 1.8694107 | Z9: =_Engine_R50!I55/12 -> 1.8442634 | AA9: =_Engine_R50!I56/12 -> 1.8194545 | AB9: =_Engine_R50!I57/12 -> 1.7949793 | AC9: =_Engine_R50!I58/12 -> 1.7708333 | AD9: =_Engine_R50!I59/12 -> 1.7470122 | AE9: =_Engine_R50!I60/12 -> 1.7235115 | AF9: =_Engine_R50!I61/12 -> 1.7003269 | AG9: =_Engine_R50!I62/12 -> 1.6774542 | AH9: =_Engine_R50!I63/12 -> 1.6548891 | AI9: =_Engine_R50!I64/12 -> 1.6326277 | AJ9: =_Engine_R50!I65/12 -> 1.6106656 | AK9: =_Engine_R50!I66/12 -> 1.5889991 | AL9: =_Engine_R50!I67/12 -> 1.5676239 | AM9: =_Engine_R50!I68/12 -> 1.5465363 | AN9: =_Engine_R50!I69/12 -> 1.5257324 | AO9: =_Engine_R50!I70/12 -> 1.5052083 | AP9: =_Engine_R50!I71/12 -> 1.4849604 | AQ9: =_Engine_R50!I72/12 -> 1.4649847 | AR9: =_Engine_R50!I73/12 -> 1.4452778 | AS9: =_Engine_R50!I74/12 -> 1.425836 | AT9: =_Engine_R50!I75/12 -> 1.4066558 | AU9: =_Engine_R50!I76/12 -> 1.3877335 | AV9: =_Engine_R50!I77/12 -> 1.3690658 | AW9: =_Engine_R50!I78/12 -> 1.3506492 | AX9: =_Engine_R50!I79/12 -> 1.3324803 | AY9: =_Engine_R50!I80/12 -> 1.3145559 | AZ9: =_Engine_R50!I81/12 -> 1.2968725 | BA9: =_Engine_R50!I82/12 -> 1.2794271 | BB9: =_Engine_R50!I83/12 -> 1.2622163 | BC9: =_Engine_R50!I84/12 -> 1.245237 | BD9: =_Engine_R50!I85/12 -> 1.2284862 | BE9: =_Engine_R50!I86/12 -> 1.2119606 | BF9: =_Engine_R50!I87/12 -> 1.1956574 | BG9: =_Engine_R50!I88/12 -> 1.1795735 | BH9: =_Engine_R50!I89/12 -> 1.1637059 | BI9: =_Engine_R50!I90/12 -> 1.1480518 | BJ9: =_Engine_R50!I91/12 -> 1.1326083 | BK9: =_Engine_R50!I92/12 -> 1.1173725 | BL9: =_Engine_R50!I93/12 -> 1.1023417 | BM9: =_Engine_R50!I94/12 -> 1.087513 | BN9: =_Engine_R50!I95/12 -> 1.0728839 | BO9: =_Engine_R50!I96/12 -> 1.0584515 | BP9: =_Engine_R50!I97/12 -> 1.0442132 | BQ9: =_Engine_R50!I98/12 -> 1.0301665 | BR9: =_Engine_R50!I99/12 -> 1.0163088 | BS9: =_Engine_R50!I100/12 -> 1.0026375 | BT9: =_Engine_R50!I101/12 -> 0.98915004 | BU9: =_Engine_R50!I102/12 -> 0.97584404 | BV9: =_Engine_R50!I103/12 -> 0.96271704 | BW9: =_Engine_R50!I104/12 -> 0.94976662 | BX9: =_Engine_R50!I105/12 -> 0.93699041 | BY9: =_Engine_R50!I106/12 -> 0.92438607 | BZ9: =_Engine_R50!I107/12 -> 0.91195128 | CA9: =_Engine_R50!I108/12 -> 0.89968376 | CB9: =_Engine_R50!I109/12 -> 0.88758126 | CC9: =_Engine_R50!I110/12 -> 0.87564156 | CD9: =_Engine_R50!I111/12 -> 0.86386248 | CE9: =_Engine_R50!I112/12 -> 0.85224184 | CF9: =_Engine_R50!I113/12 -> 0.84077753 | CG9: =_Engine_R50!I114/12 -> 0.82946744 | CH9: =_Engine_R50!I115/12 -> 0.81830949 | CI9: =_Engine_R50!I116/12 -> 0.80730163 | CJ9: =_Engine_R50!I117/12 -> 0.79644185 | CK9: =_Engine_R50!I118/12 -> 0.78572816 | CL9: =_Engine_R50!I119/12 -> 0.77515858 | CM9: =_Engine_R50!I120/12 -> 0.76473119 | CN9: =_Engine_R50!I121/12 -> 0.75444407 | CO9: =_Engine_R50!I122/12 -> 0.74429533 | CP9: =_Engine_R50!I123/12 -> 0.73428311 | CQ9: =_Engine_R50!I124/12 -> 0.72440557 | CR9: =_Engine_R50!I125/12 -> 0.7146609 | CS9: =_Engine_R50!I126/12 -> 0.70504732 | CT9: =_Engine_R50!I127/12 -> 0.69556306 | CU9: =_Engine_R50!I128/12 -> 0.68620639 | CV9: =_Engine_R50!I129/12 -> 0.67697557 | CW9: =_Engine_R50!I130/12 -> 0.66786893 | CX9: =_Engine_R50!I131/12 -> 0.6588848 | CY9: =_Engine_R50!I132/12 -> 0.65002151 | CZ9: =_Engine_R50!I133/12 -> 0.64127746 | DA9: =_Engine_R50!I134/12 -> 0.63265103 | DB9: =_Engine_R50!I135/12 -> 0.62414064 | DC9: =_Engine_R50!I136/12 -> 0.61574473 | DD9: =_Engine_R50!I137/12 -> 0.60746177 | DE9: =_Engine_R50!I138/12 -> 0.59929022 | DF9: =_Engine_R50!I139/12 -> 0.5912286 | DG9: =_Engine_R50!I140/12 -> 0.58327543 | DH9: =_Engine_R50!I141/12 -> 0.57542924 | DI9: =_Engine_R50!I142/12 -> 0.56768859 | DJ9: =_Engine_R50!I143/12 -> 0.56005208 | DK9: =_Engine_R50!I144/12 -> 0.55251829 | DL9: =_Engine_R50!I145/12 -> 0.54508584 | DM9: =_Engine_R50!I146/12 -> 0.53775337 | DN9: =_Engine_R50!I147/12 -> 0.53051954 | DO9: =_Engine_R50!I148/12 -> 0.52338302 | DP9: =_Engine_R50!I149/12 -> 0.5163425 | DQ9: =_Engine_R50!I150/12 -> 0.50939669 | DR9: =_Engine_R50!I151/12 -> 0.50254431 | DS9: =_Engine_R50!I152/12 -> 0.49578411 | DT9: =_Engine_R50!I153/12 -> 0.48911485 | DU9: =_Engine_R50!I154/12 -> 0.4825353 | DV9: =_Engine_R50!I155/12 -> 0.47604427 | DW9: =_Engine_R50!I156/12 -> 0.46964054 | DX9: =_Engine_R50!I157/12 -> 0.46332296 | DY9: =_Engine_R50!I158/12 -> 0.45709037 | DZ9: =_Engine_R50!I159/12 -> 0.45094161 | EA9: =_Engine_R50!I160/12 -> 0.44487557 | EB9: =_Engine_R50!I161/12 -> 0.43889113 | EC9: =_Engine_R50!I162/12 -> 0.43298719 | ED9: =_Engine_R50!I163/12 -> 0.42716267 | EE9: =_Engine_R50!I164/12 -> 0.4214165 | EF9: =_Engine_R50!I165/12 -> 0.41574762 | EG9: =_Engine_R50!I166/12 -> 0.41015501 | EH9: =_Engine_R50!I167/12 -> 0.40463763 | EI9: =_Engine_R50!I168/12 -> 0.39919446 | EJ9: =_Engine_R50!I169/12 -> 0.39382452 | EK9: =_Engine_R50!I170/12 -> 0.38852681 | EL9: =_Engine_R50!I171/12 -> 0.38330037 | EM9: =_Engine_R50!I172/12 -> 0.37814423 | EN9: =_Engine_R50!I173/12 -> 0.37305746 | EO9: =_Engine_R50!I174/12 -> 0.36803911 | EP9: =_Engine_R50!I175/12 -> 0.36308827 | EQ9: =_Engine_R50!I176/12 -> 0.35820402 | ER9: =_Engine_R50!I177/12 -> 0.35338548 | ES9: =_Engine_R50!I178/12 -> 0.34863176 | ET9: =_Engine_R50!I179/12 -> 0.34394198 | EU9: =_Engine_R50!I180/12 -> 0.33931529 | EV9: =_Engine_R50!I181/12 -> 0.33475084 | EW9: =_Engine_R50!I182/12 -> 0.33024779 | EX9: =_Engine_R50!I183/12 -> 0.32580531 | EY9: =_Engine_R50!I184/12 -> 0.3214226 | EZ9: =_Engine_R50!I185/12 -> 0.31709884 | FA9: =_Engine_R50!I186/12 -> 0.31283324 | FB9: =_Engine_R50!I187/12 -> 0.30862503 | FC9: =_Engine_R50!I188/12 -> 0.30447342 | FD9: =_Engine_R50!I189/12 -> 0.30037766 | FE9: =_Engine_R50!I190/12 -> 0.29633699 | FF9: =_Engine_R50!I191/12 -> 0.29235068 | FG9: =_Engine_R50!I192/12 -> 0.288418 | FH9: =_Engine_R50!I193/12 -> 0.28453821 | FI9: =_Engine_R50!I194/12 -> 0.28071062 | FJ9: =_Engine_R50!I195/12 -> 0.27693452 | FK9: =_Engine_R50!I196/12 -> 0.27320921 | FL9: =_Engine_R50!I197/12 -> 0.26953401 | FM9: =_Engine_R50!I198/12 -> 0.26590826 | FN9: =_Engine_R50!I199/12 -> 0.26233127 | FO9: =_Engine_R50!I200/12 -> 0.25880241 | FP9: =_Engine_R50!I201/12 -> 0.25532101 | FQ9: =_Engine_R50!I202/12 -> 0.25188644 | FR9: =_Engine_R50!I203/12 -> 0.24849808 | FS9: =_Engine_R50!I204/12 -> 0.2451553 | FT9: =_Engine_R50!I205/12 -> 0.24185748 | FU9: =_Engine_R50!I206/12 -> 0.23860403 | FV9: =_Engine_R50!I207/12 -> 0.23539434 | FW9: =_Engine_R50!I208/12 -> 0.23222783 | FX9: =_Engine_R50!I209/12 -> 0.22910391 | FY9: =_Engine_R50!I210/12 -> 0.22602202
A10: Deal #5 | B10: =_Engine_R50!J31/12 -> 0 | C10: =_Engine_R50!J32/12 -> 0 | D10: =_Engine_R50!J33/12 -> 0 | E10: =_Engine_R50!J34/12 -> 0 | F10: =_Engine_R50!J35/12 -> 0 | G10: =_Engine_R50!J36/12 -> 0 | H10: =_Engine_R50!J37/12 -> 0 | I10: =_Engine_R50!J38/12 -> 0 | J10: =_Engine_R50!J39/12 -> 0 | K10: =_Engine_R50!J40/12 -> 0 | L10: =_Engine_R50!J41/12 -> 0 | M10: =_Engine_R50!J42/12 -> 0 | N10: =_Engine_R50!J43/12 -> 0 | O10: =_Engine_R50!J44/12 -> 0 | P10: =_Engine_R50!J45/12 -> 0 | Q10: =_Engine_R50!J46/12 -> 0 | R10: =_Engine_R50!J47/12 -> 0 | S10: =_Engine_R50!J48/12 -> 0 | T10: =_Engine_R50!J49/12 -> 0 | U10: =_Engine_R50!J50/12 -> 0 | V10: =_Engine_R50!J51/12 -> 0 | W10: =_Engine_R50!J52/12 -> 0 | X10: =_Engine_R50!J53/12 -> 0 | Y10: =_Engine_R50!J54/12 -> 0 | Z10: =_Engine_R50!J55/12 -> 0 | AA10: =_Engine_R50!J56/12 -> 0 | AB10: =_Engine_R50!J57/12 -> 0 | AC10: =_Engine_R50!J58/12 -> 0 | AD10: =_Engine_R50!J59/12 -> 0 | AE10: =_Engine_R50!J60/12 -> 0 | AF10: =_Engine_R50!J61/12 -> 0 | AG10: =_Engine_R50!J62/12 -> 1.5 | AH10: =_Engine_R50!J63/12 -> 1.493602 | AI10: =_Engine_R50!J64/12 -> 1.4872313 | AJ10: =_Engine_R50!J65/12 -> 1.4808878 | AK10: =_Engine_R50!J66/12 -> 1.4745714 | AL10: =_Engine_R50!J67/12 -> 1.4682818 | AM10: =_Engine_R50!J68/12 -> 1.4620192 | AN10: =_Engine_R50!J69/12 -> 1.4557832 | AO10: =_Engine_R50!J70/12 -> 1.4495738 | AP10: =_Engine_R50!J71/12 -> 1.4433909 | AQ10: =_Engine_R50!J72/12 -> 1.4372344 | AR10: =_Engine_R50!J73/12 -> 1.4311041 | AS10: =_Engine_R50!J74/12 -> 1.425 | AT10: =_Engine_R50!J75/12 -> 1.4189219 | AU10: =_Engine_R50!J76/12 -> 1.4128698 | AV10: =_Engine_R50!J77/12 -> 1.4068434 | AW10: =_Engine_R50!J78/12 -> 1.4008428 | AX10: =_Engine_R50!J79/12 -> 1.3948677 | AY10: =_Engine_R50!J80/12 -> 1.3889182 | AZ10: =_Engine_R50!J81/12 -> 1.382994 | BA10: =_Engine_R50!J82/12 -> 1.3770951 | BB10: =_Engine_R50!J83/12 -> 1.3712214 | BC10: =_Engine_R50!J84/12 -> 1.3653727 | BD10: =_Engine_R50!J85/12 -> 1.3595489 | BE10: =_Engine_R50!J86/12 -> 1.35375 | BF10: =_Engine_R50!J87/12 -> 1.3479758 | BG10: =_Engine_R50!J88/12 -> 1.3422263 | BH10: =_Engine_R50!J89/12 -> 1.3365013 | BI10: =_Engine_R50!J90/12 -> 1.3308007 | BJ10: =_Engine_R50!J91/12 -> 1.3251244 | BK10: =_Engine_R50!J92/12 -> 1.3194723 | BL10: =_Engine_R50!J93/12 -> 1.3138443 | BM10: =_Engine_R50!J94/12 -> 1.3082403 | BN10: =_Engine_R50!J95/12 -> 1.3026603 | BO10: =_Engine_R50!J96/12 -> 1.297104 | BP10: =_Engine_R50!J97/12 -> 1.2915715 | BQ10: =_Engine_R50!J98/12 -> 1.2860625 | BR10: =_Engine_R50!J99/12 -> 1.280577 | BS10: =_Engine_R50!J100/12 -> 1.275115 | BT10: =_Engine_R50!J101/12 -> 1.2696762 | BU10: =_Engine_R50!J102/12 -> 1.2642606 | BV10: =_Engine_R50!J103/12 -> 1.2588681 | BW10: =_Engine_R50!J104/12 -> 1.2534987 | BX10: =_Engine_R50!J105/12 -> 1.2481521 | BY10: =_Engine_R50!J106/12 -> 1.2428283 | BZ10: =_Engine_R50!J107/12 -> 1.2375273 | CA10: =_Engine_R50!J108/12 -> 1.2322488 | CB10: =_Engine_R50!J109/12 -> 1.2269929 | CC10: =_Engine_R50!J110/12 -> 1.2217594 | CD10: =_Engine_R50!J111/12 -> 1.2165482 | CE10: =_Engine_R50!J112/12 -> 1.2113592 | CF10: =_Engine_R50!J113/12 -> 1.2061924 | CG10: =_Engine_R50!J114/12 -> 1.2010476 | CH10: =_Engine_R50!J115/12 -> 1.1959247 | CI10: =_Engine_R50!J116/12 -> 1.1908237 | CJ10: =_Engine_R50!J117/12 -> 1.1857445 | CK10: =_Engine_R50!J118/12 -> 1.1806869 | CL10: =_Engine_R50!J119/12 -> 1.1756509 | CM10: =_Engine_R50!J120/12 -> 1.1706364 | CN10: =_Engine_R50!J121/12 -> 1.1656432 | CO10: =_Engine_R50!J122/12 -> 1.1606714 | CP10: =_Engine_R50!J123/12 -> 1.1557208 | CQ10: =_Engine_R50!J124/12 -> 1.1507913 | CR10: =_Engine_R50!J125/12 -> 1.1458828 | CS10: =_Engine_R50!J126/12 -> 1.1409952 | CT10: =_Engine_R50!J127/12 -> 1.1361285 | CU10: =_Engine_R50!J128/12 -> 1.1312825 | CV10: =_Engine_R50!J129/12 -> 1.1264573 | CW10: =_Engine_R50!J130/12 -> 1.1216526 | CX10: =_Engine_R50!J131/12 -> 1.1168684 | CY10: =_Engine_R50!J132/12 -> 1.1121046 | CZ10: =_Engine_R50!J133/12 -> 1.1073611 | DA10: =_Engine_R50!J134/12 -> 1.1026378 | DB10: =_Engine_R50!J135/12 -> 1.0979347 | DC10: =_Engine_R50!J136/12 -> 1.0932517 | DD10: =_Engine_R50!J137/12 -> 1.0885886 | DE10: =_Engine_R50!J138/12 -> 1.0839454 | DF10: =_Engine_R50!J139/12 -> 1.0793221 | DG10: =_Engine_R50!J140/12 -> 1.0747184 | DH10: =_Engine_R50!J141/12 -> 1.0701344 | DI10: =_Engine_R50!J142/12 -> 1.0655699 | DJ10: =_Engine_R50!J143/12 -> 1.0610249 | DK10: =_Engine_R50!J144/12 -> 1.0564993 | DL10: =_Engine_R50!J145/12 -> 1.051993 | DM10: =_Engine_R50!J146/12 -> 1.0475059 | DN10: =_Engine_R50!J147/12 -> 1.043038 | DO10: =_Engine_R50!J148/12 -> 1.0385891 | DP10: =_Engine_R50!J149/12 -> 1.0341592 | DQ10: =_Engine_R50!J150/12 -> 1.0297482 | DR10: =_Engine_R50!J151/12 -> 1.025356 | DS10: =_Engine_R50!J152/12 -> 1.0209825 | DT10: =_Engine_R50!J153/12 -> 1.0166277 | DU10: =_Engine_R50!J154/12 -> 1.0122914 | DV10: =_Engine_R50!J155/12 -> 1.0079737 | DW10: =_Engine_R50!J156/12 -> 1.0036744 | DX10: =_Engine_R50!J157/12 -> 0.99939338 | DY10: =_Engine_R50!J158/12 -> 0.99513065 | DZ10: =_Engine_R50!J159/12 -> 0.9908861 | EA10: =_Engine_R50!J160/12 -> 0.98665965 | EB10: =_Engine_R50!J161/12 -> 0.98245123 | EC10: =_Engine_R50!J162/12 -> 0.97826077 | ED10: =_Engine_R50!J163/12 -> 0.97408817 | EE10: =_Engine_R50!J164/12 -> 0.96993338 | EF10: =_Engine_R50!J165/12 -> 0.9657963 | EG10: =_Engine_R50!J166/12 -> 0.96167687 | EH10: =_Engine_R50!J167/12 -> 0.95757501 | EI10: =_Engine_R50!J168/12 -> 0.95349065 | EJ10: =_Engine_R50!J169/12 -> 0.94942371 | EK10: =_Engine_R50!J170/12 -> 0.94537411 | EL10: =_Engine_R50!J171/12 -> 0.94134179 | EM10: =_Engine_R50!J172/12 -> 0.93732667 | EN10: =_Engine_R50!J173/12 -> 0.93332867 | EO10: =_Engine_R50!J174/12 -> 0.92934773 | EP10: =_Engine_R50!J175/12 -> 0.92538376 | EQ10: =_Engine_R50!J176/12 -> 0.92143671 | ER10: =_Engine_R50!J177/12 -> 0.91750649 | ES10: =_Engine_R50!J178/12 -> 0.91359303 | ET10: =_Engine_R50!J179/12 -> 0.90969626 | EU10: =_Engine_R50!J180/12 -> 0.90581612 | EV10: =_Engine_R50!J181/12 -> 0.90195252 | EW10: =_Engine_R50!J182/12 -> 0.89810541 | EX10: =_Engine_R50!J183/12 -> 0.8942747 | EY10: =_Engine_R50!J184/12 -> 0.89046034 | EZ10: =_Engine_R50!J185/12 -> 0.88666224 | FA10: =_Engine_R50!J186/12 -> 0.88288034 | FB10: =_Engine_R50!J187/12 -> 0.87911458 | FC10: =_Engine_R50!J188/12 -> 0.87536487 | FD10: =_Engine_R50!J189/12 -> 0.87163116 | FE10: =_Engine_R50!J190/12 -> 0.86791338 | FF10: =_Engine_R50!J191/12 -> 0.86421145 | FG10: =_Engine_R50!J192/12 -> 0.86052531 | FH10: =_Engine_R50!J193/12 -> 0.8568549 | FI10: =_Engine_R50!J194/12 -> 0.85320014 | FJ10: =_Engine_R50!J195/12 -> 0.84956097 | FK10: =_Engine_R50!J196/12 -> 0.84593732 | FL10: =_Engine_R50!J197/12 -> 0.84232913 | FM10: =_Engine_R50!J198/12 -> 0.83873632 | FN10: =_Engine_R50!J199/12 -> 0.83515885 | FO10: =_Engine_R50!J200/12 -> 0.83159663 | FP10: =_Engine_R50!J201/12 -> 0.8280496 | FQ10: =_Engine_R50!J202/12 -> 0.82451771 | FR10: =_Engine_R50!J203/12 -> 0.82100088 | FS10: =_Engine_R50!J204/12 -> 0.81749905 | FT10: =_Engine_R50!J205/12 -> 0.81401215 | FU10: =_Engine_R50!J206/12 -> 0.81054013 | FV10: =_Engine_R50!J207/12 -> 0.80708292 | FW10: =_Engine_R50!J208/12 -> 0.80364045 | FX10: =_Engine_R50!J209/12 -> 0.80021267 | FY10: =_Engine_R50!J210/12 -> 0.79679951
A11: Deal #6 | B11: =_Engine_R50!K31/12 -> 0 | C11: =_Engine_R50!K32/12 -> 0 | D11: =_Engine_R50!K33/12 -> 0 | E11: =_Engine_R50!K34/12 -> 0 | F11: =_Engine_R50!K35/12 -> 0 | G11: =_Engine_R50!K36/12 -> 0 | H11: =_Engine_R50!K37/12 -> 0 | I11: =_Engine_R50!K38/12 -> 0 | J11: =_Engine_R50!K39/12 -> 0 | K11: =_Engine_R50!K40/12 -> 0 | L11: =_Engine_R50!K41/12 -> 0 | M11: =_Engine_R50!K42/12 -> 0 | N11: =_Engine_R50!K43/12 -> 0 | O11: =_Engine_R50!K44/12 -> 0 | P11: =_Engine_R50!K45/12 -> 0 | Q11: =_Engine_R50!K46/12 -> 0 | R11: =_Engine_R50!K47/12 -> 0 | S11: =_Engine_R50!K48/12 -> 0 | T11: =_Engine_R50!K49/12 -> 0 | U11: =_Engine_R50!K50/12 -> 0 | V11: =_Engine_R50!K51/12 -> 0 | W11: =_Engine_R50!K52/12 -> 0 | X11: =_Engine_R50!K53/12 -> 0 | Y11: =_Engine_R50!K54/12 -> 0 | Z11: =_Engine_R50!K55/12 -> 0 | AA11: =_Engine_R50!K56/12 -> 0 | AB11: =_Engine_R50!K57/12 -> 0 | AC11: =_Engine_R50!K58/12 -> 0 | AD11: =_Engine_R50!K59/12 -> 0 | AE11: =_Engine_R50!K60/12 -> 0 | AF11: =_Engine_R50!K61/12 -> 0 | AG11: =_Engine_R50!K62/12 -> 0 | AH11: =_Engine_R50!K63/12 -> 0 | AI11: =_Engine_R50!K64/12 -> 0 | AJ11: =_Engine_R50!K65/12 -> 0 | AK11: =_Engine_R50!K66/12 -> 0 | AL11: =_Engine_R50!K67/12 -> 0 | AM11: =_Engine_R50!K68/12 -> 0 | AN11: =_Engine_R50!K69/12 -> 0 | AO11: =_Engine_R50!K70/12 -> 0 | AP11: =_Engine_R50!K71/12 -> 0 | AQ11: =_Engine_R50!K72/12 -> 0 | AR11: =_Engine_R50!K73/12 -> 0 | AS11: =_Engine_R50!K74/12 -> 0 | AT11: =_Engine_R50!K75/12 -> 0 | AU11: =_Engine_R50!K76/12 -> 0 | AV11: =_Engine_R50!K77/12 -> 0 | AW11: =_Engine_R50!K78/12 -> 0 | AX11: =_Engine_R50!K79/12 -> 0 | AY11: =_Engine_R50!K80/12 -> 0 | AZ11: =_Engine_R50!K81/12 -> 0 | BA11: =_Engine_R50!K82/12 -> 0 | BB11: =_Engine_R50!K83/12 -> 0 | BC11: =_Engine_R50!K84/12 -> 0 | BD11: =_Engine_R50!K85/12 -> 0 | BE11: =_Engine_R50!K86/12 -> 0 | BF11: =_Engine_R50!K87/12 -> 0 | BG11: =_Engine_R50!K88/12 -> 0 | BH11: =_Engine_R50!K89/12 -> 0 | BI11: =_Engine_R50!K90/12 -> 0 | BJ11: =_Engine_R50!K91/12 -> 0 | BK11: =_Engine_R50!K92/12 -> 0 | BL11: =_Engine_R50!K93/12 -> 0 | BM11: =_Engine_R50!K94/12 -> 0 | BN11: =_Engine_R50!K95/12 -> 0 | BO11: =_Engine_R50!K96/12 -> 0 | BP11: =_Engine_R50!K97/12 -> 0 | BQ11: =_Engine_R50!K98/12 -> 0 | BR11: =_Engine_R50!K99/12 -> 0 | BS11: =_Engine_R50!K100/12 -> 0 | BT11: =_Engine_R50!K101/12 -> 0 | BU11: =_Engine_R50!K102/12 -> 0 | BV11: =_Engine_R50!K103/12 -> 0 | BW11: =_Engine_R50!K104/12 -> 0 | BX11: =_Engine_R50!K105/12 -> 0 | BY11: =_Engine_R50!K106/12 -> 0 | BZ11: =_Engine_R50!K107/12 -> 0 | CA11: =_Engine_R50!K108/12 -> 0 | CB11: =_Engine_R50!K109/12 -> 0 | CC11: =_Engine_R50!K110/12 -> 0 | CD11: =_Engine_R50!K111/12 -> 0 | CE11: =_Engine_R50!K112/12 -> 0 | CF11: =_Engine_R50!K113/12 -> 0 | CG11: =_Engine_R50!K114/12 -> 0 | CH11: =_Engine_R50!K115/12 -> 0 | CI11: =_Engine_R50!K116/12 -> 0 | CJ11: =_Engine_R50!K117/12 -> 0 | CK11: =_Engine_R50!K118/12 -> 0 | CL11: =_Engine_R50!K119/12 -> 0 | CM11: =_Engine_R50!K120/12 -> 0 | CN11: =_Engine_R50!K121/12 -> 0 | CO11: =_Engine_R50!K122/12 -> 0 | CP11: =_Engine_R50!K123/12 -> 0 | CQ11: =_Engine_R50!K124/12 -> 0 | CR11: =_Engine_R50!K125/12 -> 0 | CS11: =_Engine_R50!K126/12 -> 0 | CT11: =_Engine_R50!K127/12 -> 0 | CU11: =_Engine_R50!K128/12 -> 0 | CV11: =_Engine_R50!K129/12 -> 0 | CW11: =_Engine_R50!K130/12 -> 0 | CX11: =_Engine_R50!K131/12 -> 0 | CY11: =_Engine_R50!K132/12 -> 0 | CZ11: =_Engine_R50!K133/12 -> 0 | DA11: =_Engine_R50!K134/12 -> 0 | DB11: =_Engine_R50!K135/12 -> 0 | DC11: =_Engine_R50!K136/12 -> 0 | DD11: =_Engine_R50!K137/12 -> 0 | DE11: =_Engine_R50!K138/12 -> 0 | DF11: =_Engine_R50!K139/12 -> 0 | DG11: =_Engine_R50!K140/12 -> 0 | DH11: =_Engine_R50!K141/12 -> 0 | DI11: =_Engine_R50!K142/12 -> 0 | DJ11: =_Engine_R50!K143/12 -> 0 | DK11: =_Engine_R50!K144/12 -> 0 | DL11: =_Engine_R50!K145/12 -> 0 | DM11: =_Engine_R50!K146/12 -> 0 | DN11: =_Engine_R50!K147/12 -> 0 | DO11: =_Engine_R50!K148/12 -> 0 | DP11: =_Engine_R50!K149/12 -> 0 | DQ11: =_Engine_R50!K150/12 -> 0 | DR11: =_Engine_R50!K151/12 -> 0 | DS11: =_Engine_R50!K152/12 -> 0 | DT11: =_Engine_R50!K153/12 -> 0 | DU11: =_Engine_R50!K154/12 -> 0 | DV11: =_Engine_R50!K155/12 -> 0 | DW11: =_Engine_R50!K156/12 -> 0 | DX11: =_Engine_R50!K157/12 -> 0 | DY11: =_Engine_R50!K158/12 -> 0 | DZ11: =_Engine_R50!K159/12 -> 0 | EA11: =_Engine_R50!K160/12 -> 0 | EB11: =_Engine_R50!K161/12 -> 0 | EC11: =_Engine_R50!K162/12 -> 0 | ED11: =_Engine_R50!K163/12 -> 0 | EE11: =_Engine_R50!K164/12 -> 0 | EF11: =_Engine_R50!K165/12 -> 0 | EG11: =_Engine_R50!K166/12 -> 0 | EH11: =_Engine_R50!K167/12 -> 0 | EI11: =_Engine_R50!K168/12 -> 0 | EJ11: =_Engine_R50!K169/12 -> 0 | EK11: =_Engine_R50!K170/12 -> 0 | EL11: =_Engine_R50!K171/12 -> 0 | EM11: =_Engine_R50!K172/12 -> 0 | EN11: =_Engine_R50!K173/12 -> 0 | EO11: =_Engine_R50!K174/12 -> 0 | EP11: =_Engine_R50!K175/12 -> 0 | EQ11: =_Engine_R50!K176/12 -> 0 | ER11: =_Engine_R50!K177/12 -> 0 | ES11: =_Engine_R50!K178/12 -> 0 | ET11: =_Engine_R50!K179/12 -> 0 | EU11: =_Engine_R50!K180/12 -> 0 | EV11: =_Engine_R50!K181/12 -> 0 | EW11: =_Engine_R50!K182/12 -> 0 | EX11: =_Engine_R50!K183/12 -> 0 | EY11: =_Engine_R50!K184/12 -> 0 | EZ11: =_Engine_R50!K185/12 -> 0 | FA11: =_Engine_R50!K186/12 -> 0 | FB11: =_Engine_R50!K187/12 -> 0 | FC11: =_Engine_R50!K188/12 -> 0 | FD11: =_Engine_R50!K189/12 -> 0 | FE11: =_Engine_R50!K190/12 -> 0 | FF11: =_Engine_R50!K191/12 -> 0 | FG11: =_Engine_R50!K192/12 -> 0 | FH11: =_Engine_R50!K193/12 -> 0 | FI11: =_Engine_R50!K194/12 -> 0 | FJ11: =_Engine_R50!K195/12 -> 0 | FK11: =_Engine_R50!K196/12 -> 0 | FL11: =_Engine_R50!K197/12 -> 0 | FM11: =_Engine_R50!K198/12 -> 0 | FN11: =_Engine_R50!K199/12 -> 0 | FO11: =_Engine_R50!K200/12 -> 0 | FP11: =_Engine_R50!K201/12 -> 0 | FQ11: =_Engine_R50!K202/12 -> 0 | FR11: =_Engine_R50!K203/12 -> 0 | FS11: =_Engine_R50!K204/12 -> 0 | FT11: =_Engine_R50!K205/12 -> 0 | FU11: =_Engine_R50!K206/12 -> 0 | FV11: =_Engine_R50!K207/12 -> 0 | FW11: =_Engine_R50!K208/12 -> 0 | FX11: =_Engine_R50!K209/12 -> 0 | FY11: =_Engine_R50!K210/12 -> 0
A12: Deal #7 | B12: =_Engine_R50!L31/12 -> 0 | C12: =_Engine_R50!L32/12 -> 0 | D12: =_Engine_R50!L33/12 -> 0 | E12: =_Engine_R50!L34/12 -> 0 | F12: =_Engine_R50!L35/12 -> 0 | G12: =_Engine_R50!L36/12 -> 0 | H12: =_Engine_R50!L37/12 -> 0 | I12: =_Engine_R50!L38/12 -> 0 | J12: =_Engine_R50!L39/12 -> 0 | K12: =_Engine_R50!L40/12 -> 0 | L12: =_Engine_R50!L41/12 -> 0 | M12: =_Engine_R50!L42/12 -> 0 | N12: =_Engine_R50!L43/12 -> 0 | O12: =_Engine_R50!L44/12 -> 0 | P12: =_Engine_R50!L45/12 -> 0 | Q12: =_Engine_R50!L46/12 -> 0 | R12: =_Engine_R50!L47/12 -> 0 | S12: =_Engine_R50!L48/12 -> 0 | T12: =_Engine_R50!L49/12 -> 0 | U12: =_Engine_R50!L50/12 -> 0 | V12: =_Engine_R50!L51/12 -> 0 | W12: =_Engine_R50!L52/12 -> 0 | X12: =_Engine_R50!L53/12 -> 0 | Y12: =_Engine_R50!L54/12 -> 0 | Z12: =_Engine_R50!L55/12 -> 0 | AA12: =_Engine_R50!L56/12 -> 0 | AB12: =_Engine_R50!L57/12 -> 0 | AC12: =_Engine_R50!L58/12 -> 0 | AD12: =_Engine_R50!L59/12 -> 0 | AE12: =_Engine_R50!L60/12 -> 0 | AF12: =_Engine_R50!L61/12 -> 0 | AG12: =_Engine_R50!L62/12 -> 0 | AH12: =_Engine_R50!L63/12 -> 0 | AI12: =_Engine_R50!L64/12 -> 0 | AJ12: =_Engine_R50!L65/12 -> 0 | AK12: =_Engine_R50!L66/12 -> 0 | AL12: =_Engine_R50!L67/12 -> 0 | AM12: =_Engine_R50!L68/12 -> 0 | AN12: =_Engine_R50!L69/12 -> 0 | AO12: =_Engine_R50!L70/12 -> 0 | AP12: =_Engine_R50!L71/12 -> 0 | AQ12: =_Engine_R50!L72/12 -> 0 | AR12: =_Engine_R50!L73/12 -> 0 | AS12: =_Engine_R50!L74/12 -> 0 | AT12: =_Engine_R50!L75/12 -> 0 | AU12: =_Engine_R50!L76/12 -> 0 | AV12: =_Engine_R50!L77/12 -> 0 | AW12: =_Engine_R50!L78/12 -> 0 | AX12: =_Engine_R50!L79/12 -> 0 | AY12: =_Engine_R50!L80/12 -> 0 | AZ12: =_Engine_R50!L81/12 -> 0 | BA12: =_Engine_R50!L82/12 -> 0 | BB12: =_Engine_R50!L83/12 -> 0 | BC12: =_Engine_R50!L84/12 -> 0 | BD12: =_Engine_R50!L85/12 -> 0 | BE12: =_Engine_R50!L86/12 -> 0 | BF12: =_Engine_R50!L87/12 -> 0 | BG12: =_Engine_R50!L88/12 -> 0 | BH12: =_Engine_R50!L89/12 -> 0 | BI12: =_Engine_R50!L90/12 -> 0 | BJ12: =_Engine_R50!L91/12 -> 0 | BK12: =_Engine_R50!L92/12 -> 0 | BL12: =_Engine_R50!L93/12 -> 0 | BM12: =_Engine_R50!L94/12 -> 0 | BN12: =_Engine_R50!L95/12 -> 0 | BO12: =_Engine_R50!L96/12 -> 0 | BP12: =_Engine_R50!L97/12 -> 0 | BQ12: =_Engine_R50!L98/12 -> 0 | BR12: =_Engine_R50!L99/12 -> 0 | BS12: =_Engine_R50!L100/12 -> 0 | BT12: =_Engine_R50!L101/12 -> 0 | BU12: =_Engine_R50!L102/12 -> 0 | BV12: =_Engine_R50!L103/12 -> 0 | BW12: =_Engine_R50!L104/12 -> 0 | BX12: =_Engine_R50!L105/12 -> 0 | BY12: =_Engine_R50!L106/12 -> 0 | BZ12: =_Engine_R50!L107/12 -> 0 | CA12: =_Engine_R50!L108/12 -> 0 | CB12: =_Engine_R50!L109/12 -> 0 | CC12: =_Engine_R50!L110/12 -> 0 | CD12: =_Engine_R50!L111/12 -> 0 | CE12: =_Engine_R50!L112/12 -> 0 | CF12: =_Engine_R50!L113/12 -> 0 | CG12: =_Engine_R50!L114/12 -> 0 | CH12: =_Engine_R50!L115/12 -> 0 | CI12: =_Engine_R50!L116/12 -> 0 | CJ12: =_Engine_R50!L117/12 -> 0 | CK12: =_Engine_R50!L118/12 -> 0 | CL12: =_Engine_R50!L119/12 -> 0 | CM12: =_Engine_R50!L120/12 -> 0 | CN12: =_Engine_R50!L121/12 -> 0 | CO12: =_Engine_R50!L122/12 -> 0 | CP12: =_Engine_R50!L123/12 -> 0 | CQ12: =_Engine_R50!L124/12 -> 0 | CR12: =_Engine_R50!L125/12 -> 0 | CS12: =_Engine_R50!L126/12 -> 0 | CT12: =_Engine_R50!L127/12 -> 0 | CU12: =_Engine_R50!L128/12 -> 0 | CV12: =_Engine_R50!L129/12 -> 0 | CW12: =_Engine_R50!L130/12 -> 0 | CX12: =_Engine_R50!L131/12 -> 0 | CY12: =_Engine_R50!L132/12 -> 0 | CZ12: =_Engine_R50!L133/12 -> 0 | DA12: =_Engine_R50!L134/12 -> 0 | DB12: =_Engine_R50!L135/12 -> 0 | DC12: =_Engine_R50!L136/12 -> 0 | DD12: =_Engine_R50!L137/12 -> 0 | DE12: =_Engine_R50!L138/12 -> 0 | DF12: =_Engine_R50!L139/12 -> 0 | DG12: =_Engine_R50!L140/12 -> 0 | DH12: =_Engine_R50!L141/12 -> 0 | DI12: =_Engine_R50!L142/12 -> 0 | DJ12: =_Engine_R50!L143/12 -> 0 | DK12: =_Engine_R50!L144/12 -> 0 | DL12: =_Engine_R50!L145/12 -> 0 | DM12: =_Engine_R50!L146/12 -> 0 | DN12: =_Engine_R50!L147/12 -> 0 | DO12: =_Engine_R50!L148/12 -> 0 | DP12: =_Engine_R50!L149/12 -> 0 | DQ12: =_Engine_R50!L150/12 -> 0 | DR12: =_Engine_R50!L151/12 -> 0 | DS12: =_Engine_R50!L152/12 -> 0 | DT12: =_Engine_R50!L153/12 -> 0 | DU12: =_Engine_R50!L154/12 -> 0 | DV12: =_Engine_R50!L155/12 -> 0 | DW12: =_Engine_R50!L156/12 -> 0 | DX12: =_Engine_R50!L157/12 -> 0 | DY12: =_Engine_R50!L158/12 -> 0 | DZ12: =_Engine_R50!L159/12 -> 0 | EA12: =_Engine_R50!L160/12 -> 0 | EB12: =_Engine_R50!L161/12 -> 0 | EC12: =_Engine_R50!L162/12 -> 0 | ED12: =_Engine_R50!L163/12 -> 0 | EE12: =_Engine_R50!L164/12 -> 0 | EF12: =_Engine_R50!L165/12 -> 0 | EG12: =_Engine_R50!L166/12 -> 0 | EH12: =_Engine_R50!L167/12 -> 0 | EI12: =_Engine_R50!L168/12 -> 0 | EJ12: =_Engine_R50!L169/12 -> 0 | EK12: =_Engine_R50!L170/12 -> 0 | EL12: =_Engine_R50!L171/12 -> 0 | EM12: =_Engine_R50!L172/12 -> 0 | EN12: =_Engine_R50!L173/12 -> 0 | EO12: =_Engine_R50!L174/12 -> 0 | EP12: =_Engine_R50!L175/12 -> 0 | EQ12: =_Engine_R50!L176/12 -> 0 | ER12: =_Engine_R50!L177/12 -> 0 | ES12: =_Engine_R50!L178/12 -> 0 | ET12: =_Engine_R50!L179/12 -> 0 | EU12: =_Engine_R50!L180/12 -> 0 | EV12: =_Engine_R50!L181/12 -> 0 | EW12: =_Engine_R50!L182/12 -> 0 | EX12: =_Engine_R50!L183/12 -> 0 | EY12: =_Engine_R50!L184/12 -> 0 | EZ12: =_Engine_R50!L185/12 -> 0 | FA12: =_Engine_R50!L186/12 -> 0 | FB12: =_Engine_R50!L187/12 -> 0 | FC12: =_Engine_R50!L188/12 -> 0 | FD12: =_Engine_R50!L189/12 -> 0 | FE12: =_Engine_R50!L190/12 -> 0 | FF12: =_Engine_R50!L191/12 -> 0 | FG12: =_Engine_R50!L192/12 -> 0 | FH12: =_Engine_R50!L193/12 -> 0 | FI12: =_Engine_R50!L194/12 -> 0 | FJ12: =_Engine_R50!L195/12 -> 0 | FK12: =_Engine_R50!L196/12 -> 0 | FL12: =_Engine_R50!L197/12 -> 0 | FM12: =_Engine_R50!L198/12 -> 0 | FN12: =_Engine_R50!L199/12 -> 0 | FO12: =_Engine_R50!L200/12 -> 0 | FP12: =_Engine_R50!L201/12 -> 0 | FQ12: =_Engine_R50!L202/12 -> 0 | FR12: =_Engine_R50!L203/12 -> 0 | FS12: =_Engine_R50!L204/12 -> 0 | FT12: =_Engine_R50!L205/12 -> 0 | FU12: =_Engine_R50!L206/12 -> 0 | FV12: =_Engine_R50!L207/12 -> 0 | FW12: =_Engine_R50!L208/12 -> 0 | FX12: =_Engine_R50!L209/12 -> 0 | FY12: =_Engine_R50!L210/12 -> 0
A13: Deal #8 | B13: =_Engine_R50!P31 -> 0 | C13: =_Engine_R50!P32 -> 0 | D13: =_Engine_R50!P33 -> 0 | E13: =_Engine_R50!P34 -> 2.0833333 | F13: =_Engine_R50!P35 -> 2.0744473 | G13: =_Engine_R50!P36 -> 2.0655991 | H13: =_Engine_R50!P37 -> 2.0567886 | I13: =_Engine_R50!P38 -> 4.1313491 | J13: =_Engine_R50!P39 -> 4.104402 | K13: =_Engine_R50!P40 -> 4.0776513 | L13: =_Engine_R50!P41 -> 4.0510955 | M13: =_Engine_R50!P42 -> 6.1080665 | N13: =_Engine_R50!P43 -> 6.0538711 | O13: =_Engine_R50!P44 -> 6.0002429 | P13: =_Engine_R50!P45 -> 5.9471756 | Q13: =_Engine_R50!P46 -> 7.9779958 | R13: =_Engine_R50!P47 -> 7.8980057 | S13: =_Engine_R50!P48 -> 7.818934 | T13: =_Engine_R50!P49 -> 7.7407696 | U13: =_Engine_R50!P50 -> 7.6635011 | V13: =_Engine_R50!P51 -> 7.5871176 | W13: =_Engine_R50!P52 -> 7.5116082 | X13: =_Engine_R50!P53 -> 7.4369621 | Y13: =_Engine_R50!P54 -> 7.3631687 | Z13: =_Engine_R50!P55 -> 7.2902174 | AA13: =_Engine_R50!P56 -> 7.2180981 | AB13: =_Engine_R50!P57 -> 7.1468003 | AC13: =_Engine_R50!P58 -> 7.0763141 | AD13: =_Engine_R50!P59 -> 7.0066295 | AE13: =_Engine_R50!P60 -> 6.9377366 | AF13: =_Engine_R50!P61 -> 6.8696258 | AG13: =_Engine_R50!P62 -> 8.3022875 | AH13: =_Engine_R50!P63 -> 8.2293141 | AI13: =_Engine_R50!P64 -> 8.1571217 | AJ13: =_Engine_R50!P65 -> 8.085701 | AK13: =_Engine_R50!P66 -> 8.0150426 | AL13: =_Engine_R50!P67 -> 7.9451375 | AM13: =_Engine_R50!P68 -> 7.8759767 | AN13: =_Engine_R50!P69 -> 7.8075513 | AO13: =_Engine_R50!P70 -> 7.7398525 | AP13: =_Engine_R50!P71 -> 7.6728718 | AQ13: =_Engine_R50!P72 -> 7.6066006 | AR13: =_Engine_R50!P73 -> 7.5410303 | AS13: =_Engine_R50!P74 -> 7.4761528 | AT13: =_Engine_R50!P75 -> 7.4119597 | AU13: =_Engine_R50!P76 -> 7.3484429 | AV13: =_Engine_R50!P77 -> 7.2855945 | AW13: =_Engine_R50!P78 -> 7.2234065 | AX13: =_Engine_R50!P79 -> 7.1618711 | AY13: =_Engine_R50!P80 -> 7.1009806 | AZ13: =_Engine_R50!P81 -> 7.0407273 | BA13: =_Engine_R50!P82 -> 6.9811037 | BB13: =_Engine_R50!P83 -> 6.9221023 | BC13: =_Engine_R50!P84 -> 6.863716 | BD13: =_Engine_R50!P85 -> 6.8059373 | BE13: =_Engine_R50!P86 -> 6.7487591 | BF13: =_Engine_R50!P87 -> 6.6921744 | BG13: =_Engine_R50!P88 -> 6.6361762 | BH13: =_Engine_R50!P89 -> 6.5807576 | BI13: =_Engine_R50!P90 -> 6.5259117 | BJ13: =_Engine_R50!P91 -> 6.471632 | BK13: =_Engine_R50!P92 -> 6.4179116 | BL13: =_Engine_R50!P93 -> 6.3647441 | BM13: =_Engine_R50!P94 -> 6.3121231 | BN13: =_Engine_R50!P95 -> 6.260042 | BO13: =_Engine_R50!P96 -> 6.2084946 | BP13: =_Engine_R50!P97 -> 6.1574747 | BQ13: =_Engine_R50!P98 -> 6.1069762 | BR13: =_Engine_R50!P99 -> 6.0569928 | BS13: =_Engine_R50!P100 -> 6.0075187 | BT13: =_Engine_R50!P101 -> 5.9585479 | BU13: =_Engine_R50!P102 -> 5.9100745 | BV13: =_Engine_R50!P103 -> 5.8620928 | BW13: =_Engine_R50!P104 -> 5.8145971 | BX13: =_Engine_R50!P105 -> 5.7675816 | BY13: =_Engine_R50!P106 -> 5.721041 | BZ13: =_Engine_R50!P107 -> 5.6749696 | CA13: =_Engine_R50!P108 -> 5.629362 | CB13: =_Engine_R50!P109 -> 5.5842129 | CC13: =_Engine_R50!P110 -> 5.5395169 | CD13: =_Engine_R50!P111 -> 5.4952689 | CE13: =_Engine_R50!P112 -> 5.4514636 | CF13: =_Engine_R50!P113 -> 5.4080961 | CG13: =_Engine_R50!P114 -> 5.3651611 | CH13: =_Engine_R50!P115 -> 5.3226538 | CI13: =_Engine_R50!P116 -> 5.2805692 | CJ13: =_Engine_R50!P117 -> 5.2389026 | CK13: =_Engine_R50!P118 -> 5.197649 | CL13: =_Engine_R50!P119 -> 5.1568038 | CM13: =_Engine_R50!P120 -> 5.1163622 | CN13: =_Engine_R50!P121 -> 5.0763197 | CO13: =_Engine_R50!P122 -> 5.0366717 | CP13: =_Engine_R50!P123 -> 4.9974137 | CQ13: =_Engine_R50!P124 -> 4.9585413 | CR13: =_Engine_R50!P125 -> 4.92005 | CS13: =_Engine_R50!P126 -> 4.8819355 | CT13: =_Engine_R50!P127 -> 4.8441936 | CU13: =_Engine_R50!P128 -> 4.8068199 | CV13: =_Engine_R50!P129 -> 4.7698103 | CW13: =_Engine_R50!P130 -> 4.7331607 | CX13: =_Engine_R50!P131 -> 4.696867 | CY13: =_Engine_R50!P132 -> 4.6609252 | CZ13: =_Engine_R50!P133 -> 4.6253313 | DA13: =_Engine_R50!P134 -> 4.5900813 | DB13: =_Engine_R50!P135 -> 4.5551714 | DC13: =_Engine_R50!P136 -> 4.5205977 | DD13: =_Engine_R50!P137 -> 4.4863565 | DE13: =_Engine_R50!P138 -> 4.4524439 | DF13: =_Engine_R50!P139 -> 4.4188564 | DG13: =_Engine_R50!P140 -> 4.3855902 | DH13: =_Engine_R50!P141 -> 4.3526418 | DI13: =_Engine_R50!P142 -> 4.3200076 | DJ13: =_Engine_R50!P143 -> 4.287684 | DK13: =_Engine_R50!P144 -> 4.2556676 | DL13: =_Engine_R50!P145 -> 4.223955 | DM13: =_Engine_R50!P146 -> 4.1925428 | DN13: =_Engine_R50!P147 -> 4.1614275 | DO13: =_Engine_R50!P148 -> 4.130606 | DP13: =_Engine_R50!P149 -> 4.1000749 | DQ13: =_Engine_R50!P150 -> 4.069831 | DR13: =_Engine_R50!P151 -> 4.0398711 | DS13: =_Engine_R50!P152 -> 4.0101921 | DT13: =_Engine_R50!P153 -> 3.9807908 | DU13: =_Engine_R50!P154 -> 3.9516642 | DV13: =_Engine_R50!P155 -> 3.9228092 | DW13: =_Engine_R50!P156 -> 3.8942229 | DX13: =_Engine_R50!P157 -> 3.8659022 | DY13: =_Engine_R50!P158 -> 3.8378443 | DZ13: =_Engine_R50!P159 -> 3.8100462 | EA13: =_Engine_R50!P160 -> 3.7825051 | EB13: =_Engine_R50!P161 -> 3.7552182 | EC13: =_Engine_R50!P162 -> 3.7281827 | ED13: =_Engine_R50!P163 -> 3.7013957 | EE13: =_Engine_R50!P164 -> 3.6748547 | EF13: =_Engine_R50!P165 -> 3.6485568 | EG13: =_Engine_R50!P166 -> 3.6224995 | EH13: =_Engine_R50!P167 -> 3.5966801 | EI13: =_Engine_R50!P168 -> 3.571096 | EJ13: =_Engine_R50!P169 -> 3.5457447 | EK13: =_Engine_R50!P170 -> 3.5206237 | EL13: =_Engine_R50!P171 -> 3.4957303 | EM13: =_Engine_R50!P172 -> 3.4710622 | EN13: =_Engine_R50!P173 -> 3.446617 | EO13: =_Engine_R50!P174 -> 3.4223921 | EP13: =_Engine_R50!P175 -> 3.3983852 | EQ13: =_Engine_R50!P176 -> 3.374594 | ER13: =_Engine_R50!P177 -> 3.3510161 | ES13: =_Engine_R50!P178 -> 3.3276493 | ET13: =_Engine_R50!P179 -> 3.3044912 | EU13: =_Engine_R50!P180 -> 3.2815397 | EV13: =_Engine_R50!P181 -> 3.2587924 | EW13: =_Engine_R50!P182 -> 3.2362473 | EX13: =_Engine_R50!P183 -> 3.2139021 | EY13: =_Engine_R50!P184 -> 3.1917547 | EZ13: =_Engine_R50!P185 -> 3.169803 | FA13: =_Engine_R50!P186 -> 3.1480449 | FB13: =_Engine_R50!P187 -> 3.1264783 | FC13: =_Engine_R50!P188 -> 3.1051012 | FD13: =_Engine_R50!P189 -> 3.0839117 | FE13: =_Engine_R50!P190 -> 3.0629076 | FF13: =_Engine_R50!P191 -> 3.042087 | FG13: =_Engine_R50!P192 -> 3.021448 | FH13: =_Engine_R50!P193 -> 3.0009887 | FI13: =_Engine_R50!P194 -> 2.9807071 | FJ13: =_Engine_R50!P195 -> 2.9606014 | FK13: =_Engine_R50!P196 -> 2.9406697 | FL13: =_Engine_R50!P197 -> 2.9209103 | FM13: =_Engine_R50!P198 -> 2.9013212 | FN13: =_Engine_R50!P199 -> 2.8819007 | FO13: =_Engine_R50!P200 -> 2.862647 | FP13: =_Engine_R50!P201 -> 2.8435584 | FQ13: =_Engine_R50!P202 -> 2.8246332 | FR13: =_Engine_R50!P203 -> 2.8058697 | FS13: =_Engine_R50!P204 -> 2.787266 | FT13: =_Engine_R50!P205 -> 2.7688207 | FU13: =_Engine_R50!P206 -> 2.7505321 | FV13: =_Engine_R50!P207 -> 2.7323984 | FW13: =_Engine_R50!P208 -> 2.7144182 | FX13: =_Engine_R50!P209 -> 2.6965898 | FY13: =_Engine_R50!P210 -> 2.6789116
B14: =_Engine_R50!Q31 -> 0 | C14: =_Engine_R50!Q32 -> 0 | D14: =_Engine_R50!Q33 -> 0 | E14: =_Engine_R50!Q34 -> 0.20833333 | F14: =_Engine_R50!Q35 -> 0.20744473 | G14: =_Engine_R50!Q36 -> 0.20655991 | H14: =_Engine_R50!Q37 -> 0.20567886 | I14: =_Engine_R50!Q38 -> 0.41313491 | J14: =_Engine_R50!Q39 -> 0.4104402 | K14: =_Engine_R50!Q40 -> 0.40776513 | L14: =_Engine_R50!Q41 -> 0.40510955 | M14: =_Engine_R50!Q42 -> 0.61080665 | N14: =_Engine_R50!Q43 -> 0.60538711 | O14: =_Engine_R50!Q44 -> 0.60002429 | P14: =_Engine_R50!Q45 -> 0.59471756 | Q14: =_Engine_R50!Q46 -> 0.79779958 | R14: =_Engine_R50!Q47 -> 0.78980057 | S14: =_Engine_R50!Q48 -> 0.7818934 | T14: =_Engine_R50!Q49 -> 0.77407696 | U14: =_Engine_R50!Q50 -> 0.76635011 | V14: =_Engine_R50!Q51 -> 0.75871176 | W14: =_Engine_R50!Q52 -> 0.75116082 | X14: =_Engine_R50!Q53 -> 0.74369621 | Y14: =_Engine_R50!Q54 -> 0.73631687 | Z14: =_Engine_R50!Q55 -> 0.72902174 | AA14: =_Engine_R50!Q56 -> 0.72180981 | AB14: =_Engine_R50!Q57 -> 0.71468003 | AC14: =_Engine_R50!Q58 -> 0.70763141 | AD14: =_Engine_R50!Q59 -> 0.70066295 | AE14: =_Engine_R50!Q60 -> 0.69377366 | AF14: =_Engine_R50!Q61 -> 0.68696258 | AG14: =_Engine_R50!Q62 -> 0.83022875 | AH14: =_Engine_R50!Q63 -> 0.82293141 | AI14: =_Engine_R50!Q64 -> 0.81571217 | AJ14: =_Engine_R50!Q65 -> 0.8085701 | AK14: =_Engine_R50!Q66 -> 0.80150426 | AL14: =_Engine_R50!Q67 -> 0.79451375 | AM14: =_Engine_R50!Q68 -> 0.78759767 | AN14: =_Engine_R50!Q69 -> 0.78075513 | AO14: =_Engine_R50!Q70 -> 0.77398525 | AP14: =_Engine_R50!Q71 -> 0.76728718 | AQ14: =_Engine_R50!Q72 -> 0.76066006 | AR14: =_Engine_R50!Q73 -> 0.75410303 | AS14: =_Engine_R50!Q74 -> 0.74761528 | AT14: =_Engine_R50!Q75 -> 0.74119597 | AU14: =_Engine_R50!Q76 -> 0.73484429 | AV14: =_Engine_R50!Q77 -> 0.72855945 | AW14: =_Engine_R50!Q78 -> 0.72234065 | AX14: =_Engine_R50!Q79 -> 0.71618711 | AY14: =_Engine_R50!Q80 -> 0.71009806 | AZ14: =_Engine_R50!Q81 -> 0.70407273 | BA14: =_Engine_R50!Q82 -> 0.69811037 | BB14: =_Engine_R50!Q83 -> 0.69221023 | BC14: =_Engine_R50!Q84 -> 0.6863716 | BD14: =_Engine_R50!Q85 -> 0.68059373 | BE14: =_Engine_R50!Q86 -> 0.67487591 | BF14: =_Engine_R50!Q87 -> 0.66921744 | BG14: =_Engine_R50!Q88 -> 0.66361762 | BH14: =_Engine_R50!Q89 -> 0.65807576 | BI14: =_Engine_R50!Q90 -> 0.65259117 | BJ14: =_Engine_R50!Q91 -> 0.6471632 | BK14: =_Engine_R50!Q92 -> 0.64179116 | BL14: =_Engine_R50!Q93 -> 0.63647441 | BM14: =_Engine_R50!Q94 -> 0.63121231 | BN14: =_Engine_R50!Q95 -> 0.6260042 | BO14: =_Engine_R50!Q96 -> 0.62084946 | BP14: =_Engine_R50!Q97 -> 0.61574747 | BQ14: =_Engine_R50!Q98 -> 0.61069762 | BR14: =_Engine_R50!Q99 -> 0.60569928 | BS14: =_Engine_R50!Q100 -> 0.60075187 | BT14: =_Engine_R50!Q101 -> 0.59585479 | BU14: =_Engine_R50!Q102 -> 0.59100745 | BV14: =_Engine_R50!Q103 -> 0.58620928 | BW14: =_Engine_R50!Q104 -> 0.58145971 | BX14: =_Engine_R50!Q105 -> 0.57675816 | BY14: =_Engine_R50!Q106 -> 0.5721041 | BZ14: =_Engine_R50!Q107 -> 0.56749696 | CA14: =_Engine_R50!Q108 -> 0.5629362 | CB14: =_Engine_R50!Q109 -> 0.55842129 | CC14: =_Engine_R50!Q110 -> 0.55395169 | CD14: =_Engine_R50!Q111 -> 0.54952689 | CE14: =_Engine_R50!Q112 -> 0.54514636 | CF14: =_Engine_R50!Q113 -> 0.54080961 | CG14: =_Engine_R50!Q114 -> 0.53651611 | CH14: =_Engine_R50!Q115 -> 0.53226538 | CI14: =_Engine_R50!Q116 -> 0.52805692 | CJ14: =_Engine_R50!Q117 -> 0.52389026 | CK14: =_Engine_R50!Q118 -> 0.5197649 | CL14: =_Engine_R50!Q119 -> 0.51568038 | CM14: =_Engine_R50!Q120 -> 0.51163622 | CN14: =_Engine_R50!Q121 -> 0.50763197 | CO14: =_Engine_R50!Q122 -> 0.50366717 | CP14: =_Engine_R50!Q123 -> 0.49974137 | CQ14: =_Engine_R50!Q124 -> 0.49585413 | CR14: =_Engine_R50!Q125 -> 0.492005 | CS14: =_Engine_R50!Q126 -> 0.48819355 | CT14: =_Engine_R50!Q127 -> 0.48441936 | CU14: =_Engine_R50!Q128 -> 0.48068199 | CV14: =_Engine_R50!Q129 -> 0.47698103 | CW14: =_Engine_R50!Q130 -> 0.47331607 | CX14: =_Engine_R50!Q131 -> 0.4696867 | CY14: =_Engine_R50!Q132 -> 0.46609252 | CZ14: =_Engine_R50!Q133 -> 0.46253313 | DA14: =_Engine_R50!Q134 -> 0.45900813 | DB14: =_Engine_R50!Q135 -> 0.45551714 | DC14: =_Engine_R50!Q136 -> 0.45205977 | DD14: =_Engine_R50!Q137 -> 0.44863565 | DE14: =_Engine_R50!Q138 -> 0.44524439 | DF14: =_Engine_R50!Q139 -> 0.44188564 | DG14: =_Engine_R50!Q140 -> 0.43855902 | DH14: =_Engine_R50!Q141 -> 0.43526418 | DI14: =_Engine_R50!Q142 -> 0.43200076 | DJ14: =_Engine_R50!Q143 -> 0.4287684 | DK14: =_Engine_R50!Q144 -> 0.42556676 | DL14: =_Engine_R50!Q145 -> 0.4223955 | DM14: =_Engine_R50!Q146 -> 0.41925428 | DN14: =_Engine_R50!Q147 -> 0.41614275 | DO14: =_Engine_R50!Q148 -> 0.4130606 | DP14: =_Engine_R50!Q149 -> 0.41000749 | DQ14: =_Engine_R50!Q150 -> 0.4069831 | DR14: =_Engine_R50!Q151 -> 0.40398711 | DS14: =_Engine_R50!Q152 -> 0.40101921 | DT14: =_Engine_R50!Q153 -> 0.39807908 | DU14: =_Engine_R50!Q154 -> 0.39516642 | DV14: =_Engine_R50!Q155 -> 0.39228092 | DW14: =_Engine_R50!Q156 -> 0.38942229 | DX14: =_Engine_R50!Q157 -> 0.38659022 | DY14: =_Engine_R50!Q158 -> 0.38378443 | DZ14: =_Engine_R50!Q159 -> 0.38100462 | EA14: =_Engine_R50!Q160 -> 0.37825051 | EB14: =_Engine_R50!Q161 -> 0.37552182 | EC14: =_Engine_R50!Q162 -> 0.37281827 | ED14: =_Engine_R50!Q163 -> 0.37013957 | EE14: =_Engine_R50!Q164 -> 0.36748547 | EF14: =_Engine_R50!Q165 -> 0.36485568 | EG14: =_Engine_R50!Q166 -> 0.36224995 | EH14: =_Engine_R50!Q167 -> 0.35966801 | EI14: =_Engine_R50!Q168 -> 0.3571096 | EJ14: =_Engine_R50!Q169 -> 0.35457447 | EK14: =_Engine_R50!Q170 -> 0.35206237 | EL14: =_Engine_R50!Q171 -> 0.34957303 | EM14: =_Engine_R50!Q172 -> 0.34710622 | EN14: =_Engine_R50!Q173 -> 0.3446617 | EO14: =_Engine_R50!Q174 -> 0.34223921 | EP14: =_Engine_R50!Q175 -> 0.33983852 | EQ14: =_Engine_R50!Q176 -> 0.3374594 | ER14: =_Engine_R50!Q177 -> 0.33510161 | ES14: =_Engine_R50!Q178 -> 0.33276493 | ET14: =_Engine_R50!Q179 -> 0.33044912 | EU14: =_Engine_R50!Q180 -> 0.32815397 | EV14: =_Engine_R50!Q181 -> 0.32587924 | EW14: =_Engine_R50!Q182 -> 0.32362473 | EX14: =_Engine_R50!Q183 -> 0.32139021 | EY14: =_Engine_R50!Q184 -> 0.31917547 | EZ14: =_Engine_R50!Q185 -> 0.3169803 | FA14: =_Engine_R50!Q186 -> 0.31480449 | FB14: =_Engine_R50!Q187 -> 0.31264783 | FC14: =_Engine_R50!Q188 -> 0.31051012 | FD14: =_Engine_R50!Q189 -> 0.30839117 | FE14: =_Engine_R50!Q190 -> 0.30629076 | FF14: =_Engine_R50!Q191 -> 0.3042087 | FG14: =_Engine_R50!Q192 -> 0.3021448 | FH14: =_Engine_R50!Q193 -> 0.30009887 | FI14: =_Engine_R50!Q194 -> 0.29807071 | FJ14: =_Engine_R50!Q195 -> 0.29606014 | FK14: =_Engine_R50!Q196 -> 0.29406697 | FL14: =_Engine_R50!Q197 -> 0.29209103 | FM14: =_Engine_R50!Q198 -> 0.29013212 | FN14: =_Engine_R50!Q199 -> 0.28819007 | FO14: =_Engine_R50!Q200 -> 0.2862647 | FP14: =_Engine_R50!Q201 -> 0.28435584 | FQ14: =_Engine_R50!Q202 -> 0.28246332 | FR14: =_Engine_R50!Q203 -> 0.28058697 | FS14: =_Engine_R50!Q204 -> 0.2787266 | FT14: =_Engine_R50!Q205 -> 0.27688207 | FU14: =_Engine_R50!Q206 -> 0.27505321 | FV14: =_Engine_R50!Q207 -> 0.27323984 | FW14: =_Engine_R50!Q208 -> 0.27144182 | FX14: =_Engine_R50!Q209 -> 0.26965898 | FY14: =_Engine_R50!Q210 -> 0.26789116
A15: Portfolio P&L | B15: =B13-B14 -> 0 | C15: =C13-C14 -> 0 | D15: =D13-D14 -> 0 | E15: =E13-E14 -> 1.875 | F15: =F13-F14 -> 1.8670025 | G15: =G13-G14 -> 1.8590392 | H15: =H13-H14 -> 1.8511098 | I15: =I13-I14 -> 3.7182142 | ... FY15: =FY13-FY14 -> 2.4110205
A16: Revenue | B16: 0 | C16: 0 | D16: 0 | E16: 2.1333 | F16: 2.1046 | G16: 2.0763 | H16: 4.3151 | I16: 4.257 | J16: 4.1997 | K16: 6.6516 | L16: 6.5621 | M16: 8.6405 | N16: 8.5243 | O16: 8.4096 | P16: 8.2965 | Q16: 10.3015 | R16: 10.163 | S16: 10.0263 | T16: 9.8914 | U16: 9.7583 | V16: 9.6271 | W16: 9.4976 | X16: 9.3698 | Y16: 11.2438 | Z16: 11.0925 | AA16: 10.9433 | AB16: 10.7961 | AC16: 10.6508 | AD16: 10.5076 | AE16: 12.3662 | AF16: 12.1999 | AG16: 12.0358 | AH16: 11.8739 | AI16: 11.7141 | AJ16: 11.5566 | AK16: 13.4011 | AL16: 13.2208 | AM16: 13.043 | AN16: 12.8675 | AO16: 12.6944 | AP16: 12.5237 | AQ16: 12.3552 | AR16: 12.189 | AS16: 12.025 | AT16: 11.8633 | AU16: 11.7037 | AV16: 11.5463 | AW16: 11.3909 | AX16: 11.2377 | AY16: 11.0865 | AZ16: 10.9374 | BA16: 10.7903 | BB16: 10.6451 | BC16: 10.5019 | BD16: 10.3606 | BE16: 10.2213 | BF16: 10.0838 | BG16: 9.9481 | BH16: 9.8143 | BI16: 9.6823 | BJ16: 9.552 | BK16: 9.4236 | BL16: 9.2968 | BM16: 9.1717 | BN16: 9.0484 | BO16: 8.9266 | BP16: 8.8066 | BQ16: 8.6881 | BR16: 8.5712 | BS16: 8.4559 | BT16: 8.3422 | BU16: 8.2299 | BV16: 8.1192 | BW16: 8.01 | BX16: 7.9023 | BY16: 7.796 | BZ16: 7.6911 | CA16: 7.5876 | CB16: 7.4856 | CC16: 7.3849 | CD16: 7.2855 | CE16: 7.1875 | CF16: 7.0908 | CG16: 6.9955 | CH16: 6.9014 | CI16: 6.8085 | CJ16: 6.7169 | CK16: 6.6266 | CL16: 6.5374 | CM16: 6.4495 | CN16: 6.3627 | CO16: 6.2771 | CP16: 6.1927 | CQ16: 6.1094 | CR16: 6.0272 | CS16: 5.9461 | CT16: 5.8662 | CU16: 5.7872 | CV16: 5.7094 | CW16: 5.6326 | CX16: 5.5568 | CY16: 5.4821 | CZ16: 5.4083 | DA16: 5.3356 | DB16: 5.2638 | DC16: 5.193 | DD16: 5.1231 | DE16: 5.0542 | DF16: 4.9862 | DG16: 4.9192 | DH16: 4.853 | DI16: 4.7877 | DJ16: 4.7233 | DK16: 4.6598 | DL16: 4.5971 | DM16: 4.5352 | DN16: 4.4742 | DO16: 4.414 | DP16: 4.3547 | DQ16: 4.2961 | DR16: 4.2383 | DS16: 4.1813 | DT16: 4.125 | DU16: 4.0695 | DV16: 4.0148 | DW16: 3.9608 | DX16: 3.9075 | DY16: 3.855 | DZ16: 3.8031 | EA16: 3.7519 | EB16: 3.7015 | EC16: 3.6517 | ED16: 3.6025 | EE16: 3.5541 | EF16: 3.5063 | EG16: 3.4591 | EH16: 3.4126 | EI16: 3.3667 | EJ16: 3.3214 | EK16: 3.2767 | EL16: 3.2326 | EM16: 3.1891 | EN16: 3.1462 | EO16: 3.1039 | EP16: 3.0622 | EQ16: 3.021 | ER16: 2.9803 | ES16: 2.9402 | ET16: 2.9007 | EU16: 2.8617 | EV16: 2.8232 | EW16: 2.7852 | EX16: 2.7477 | EY16: 2.7108 | EZ16: 2.6743 | FA16: 2.6383 | FB16: 2.6028 | FC16: 2.5678 | FD16: 2.5333 | FE16: 2.4992 | FF16: 2.4656 | FG16: 2.4324 | FH16: 2.3997 | FI16: 2.3674 | FJ16: 2.3356 | FK16: 2.3042 | FL16: 2.2732 | FM16: 2.2426 | FN16: 2.2124 | FO16: 2.1827 | FP16: 2.1533 | FQ16: 2.1243 | FR16: 2.0958 | FS16: 2.0676 | FT16: 2.0397 | FU16: 2.0123 | FV16: 1.9852 | FW16: 1.9585 | FX16: 1.9322 | FY16: 1.9062
A17: Cost of Goods Sold | B17: =_Engine_R50!R31 -> 0 | C17: =_Engine_R50!R32 -> 0 | D17: =_Engine_R50!R33 -> 0 | E17: =_Engine_R50!R34 -> 0.10416667 | F17: =_Engine_R50!R35 -> 0.10372236 | G17: =_Engine_R50!R36 -> 0.10327995 | H17: =_Engine_R50!R37 -> 0.10283943 | I17: =_Engine_R50!R38 -> 0.20656746 | J17: =_Engine_R50!R39 -> 0.2052201 | K17: =_Engine_R50!R40 -> 0.20388257 | L17: =_Engine_R50!R41 -> 0.20255478 | M17: =_Engine_R50!R42 -> 0.30540332 | N17: =_Engine_R50!R43 -> 0.30269355 | O17: =_Engine_R50!R44 -> 0.30001215 | P17: =_Engine_R50!R45 -> 0.29735878 | Q17: =_Engine_R50!R46 -> 0.39889979 | R17: =_Engine_R50!R47 -> 0.39490028 | S17: =_Engine_R50!R48 -> 0.3909467 | T17: =_Engine_R50!R49 -> 0.38703848 | U17: =_Engine_R50!R50 -> 0.38317506 | V17: =_Engine_R50!R51 -> 0.37935588 | W17: =_Engine_R50!R52 -> 0.37558041 | X17: =_Engine_R50!R53 -> 0.37184811 | Y17: =_Engine_R50!R54 -> 0.36815843 | Z17: =_Engine_R50!R55 -> 0.36451087 | AA17: =_Engine_R50!R56 -> 0.3609049 | AB17: =_Engine_R50!R57 -> 0.35734002 | AC17: =_Engine_R50!R58 -> 0.35381571 | AD17: =_Engine_R50!R59 -> 0.35033148 | AE17: =_Engine_R50!R60 -> 0.34688683 | AF17: =_Engine_R50!R61 -> 0.34348129 | AG17: =_Engine_R50!R62 -> 0.41511437 | AH17: =_Engine_R50!R63 -> 0.41146571 | AI17: =_Engine_R50!R64 -> 0.40785609 | AJ17: =_Engine_R50!R65 -> 0.40428505 | AK17: =_Engine_R50!R66 -> 0.40075213 | AL17: =_Engine_R50!R67 -> 0.39725687 | AM17: =_Engine_R50!R68 -> 0.39379883 | AN17: =_Engine_R50!R69 -> 0.39037756 | AO17: =_Engine_R50!R70 -> 0.38699263 | AP17: =_Engine_R50!R71 -> 0.38364359 | AQ17: =_Engine_R50!R72 -> 0.38033003 | AR17: =_Engine_R50!R73 -> 0.37705152 | AS17: =_Engine_R50!R74 -> 0.37380764 | AT17: =_Engine_R50!R75 -> 0.37059798 | AU17: =_Engine_R50!R76 -> 0.36742215 | AV17: =_Engine_R50!R77 -> 0.36427973 | AW17: =_Engine_R50!R78 -> 0.36117033 | AX17: =_Engine_R50!R79 -> 0.35809356 | AY17: =_Engine_R50!R80 -> 0.35504903 | AZ17: =_Engine_R50!R81 -> 0.35203636 | BA17: =_Engine_R50!R82 -> 0.34905518 | BB17: =_Engine_R50!R83 -> 0.34610512 | BC17: =_Engine_R50!R84 -> 0.3431858 | BD17: =_Engine_R50!R85 -> 0.34029686 | BE17: =_Engine_R50!R86 -> 0.33743796 | BF17: =_Engine_R50!R87 -> 0.33460872 | BG17: =_Engine_R50!R88 -> 0.33180881 | BH17: =_Engine_R50!R89 -> 0.32903788 | BI17: =_Engine_R50!R90 -> 0.32629559 | BJ17: =_Engine_R50!R91 -> 0.3235816 | BK17: =_Engine_R50!R92 -> 0.32089558 | BL17: =_Engine_R50!R93 -> 0.31823721 | BM17: =_Engine_R50!R94 -> 0.31560615 | BN17: =_Engine_R50!R95 -> 0.3130021 | BO17: =_Engine_R50!R96 -> 0.31042473 | BP17: =_Engine_R50!R97 -> 0.30787374 | BQ17: =_Engine_R50!R98 -> 0.30534881 | BR17: =_Engine_R50!R99 -> 0.30284964 | BS17: =_Engine_R50!R100 -> 0.30037593 | BT17: =_Engine_R50!R101 -> 0.29792739 | BU17: =_Engine_R50!R102 -> 0.29550372 | BV17: =_Engine_R50!R103 -> 0.29310464 | BW17: =_Engine_R50!R104 -> 0.29072985 | BX17: =_Engine_R50!R105 -> 0.28837908 | BY17: =_Engine_R50!R106 -> 0.28605205 | BZ17: =_Engine_R50!R107 -> 0.28374848 | CA17: =_Engine_R50!R108 -> 0.2814681 | CB17: =_Engine_R50!R109 -> 0.27921064 | CC17: =_Engine_R50!R110 -> 0.27697585 | CD17: =_Engine_R50!R111 -> 0.27476344 | CE17: =_Engine_R50!R112 -> 0.27257318 | CF17: =_Engine_R50!R113 -> 0.2704048 | CG17: =_Engine_R50!R114 -> 0.26825806 | CH17: =_Engine_R50!R115 -> 0.26613269 | CI17: =_Engine_R50!R116 -> 0.26402846 | CJ17: =_Engine_R50!R117 -> 0.26194513 | CK17: =_Engine_R50!R118 -> 0.25988245 | CL17: =_Engine_R50!R119 -> 0.25784019 | CM17: =_Engine_R50!R120 -> 0.25581811 | CN17: =_Engine_R50!R121 -> 0.25381599 | CO17: =_Engine_R50!R122 -> 0.25183359 | CP17: =_Engine_R50!R123 -> 0.24987069 | CQ17: =_Engine_R50!R124 -> 0.24792706 | CR17: =_Engine_R50!R125 -> 0.2460025 | CS17: =_Engine_R50!R126 -> 0.24409678 | CT17: =_Engine_R50!R127 -> 0.24220968 | CU17: =_Engine_R50!R128 -> 0.24034099 | CV17: =_Engine_R50!R129 -> 0.23849052 | CW17: =_Engine_R50!R130 -> 0.23665804 | CX17: =_Engine_R50!R131 -> 0.23484335 | CY17: =_Engine_R50!R132 -> 0.23304626 | CZ17: =_Engine_R50!R133 -> 0.23126656 | DA17: =_Engine_R50!R134 -> 0.22950406 | DB17: =_Engine_R50!R135 -> 0.22775857 | DC17: =_Engine_R50!R136 -> 0.22602988 | DD17: =_Engine_R50!R137 -> 0.22431782 | DE17: =_Engine_R50!R138 -> 0.2226222 | DF17: =_Engine_R50!R139 -> 0.22094282 | DG17: =_Engine_R50!R140 -> 0.21927951 | DH17: =_Engine_R50!R141 -> 0.21763209 | DI17: =_Engine_R50!R142 -> 0.21600038 | DJ17: =_Engine_R50!R143 -> 0.2143842 | DK17: =_Engine_R50!R144 -> 0.21278338 | DL17: =_Engine_R50!R145 -> 0.21119775 | DM17: =_Engine_R50!R146 -> 0.20962714 | DN17: =_Engine_R50!R147 -> 0.20807138 | DO17: =_Engine_R50!R148 -> 0.2065303 | DP17: =_Engine_R50!R149 -> 0.20500374 | DQ17: =_Engine_R50!R150 -> 0.20349155 | DR17: =_Engine_R50!R151 -> 0.20199355 | DS17: =_Engine_R50!R152 -> 0.2005096 | DT17: =_Engine_R50!R153 -> 0.19903954 | DU17: =_Engine_R50!R154 -> 0.19758321 | DV17: =_Engine_R50!R155 -> 0.19614046 | DW17: =_Engine_R50!R156 -> 0.19471115 | DX17: =_Engine_R50!R157 -> 0.19329511 | DY17: =_Engine_R50!R158 -> 0.19189222 | DZ17: =_Engine_R50!R159 -> 0.19050231 | EA17: =_Engine_R50!R160 -> 0.18912526 | EB17: =_Engine_R50!R161 -> 0.18776091 | EC17: =_Engine_R50!R162 -> 0.18640913 | ED17: =_Engine_R50!R163 -> 0.18506979 | EE17: =_Engine_R50!R164 -> 0.18374273 | EF17: =_Engine_R50!R165 -> 0.18242784 | EG17: =_Engine_R50!R166 -> 0.18112498 | EH17: =_Engine_R50!R167 -> 0.17983401 | EI17: =_Engine_R50!R168 -> 0.1785548 | EJ17: =_Engine_R50!R169 -> 0.17728724 | EK17: =_Engine_R50!R170 -> 0.17603118 | EL17: =_Engine_R50!R171 -> 0.17478652 | EM17: =_Engine_R50!R172 -> 0.17355311 | EN17: =_Engine_R50!R173 -> 0.17233085 | EO17: =_Engine_R50!R174 -> 0.1711196 | EP17: =_Engine_R50!R175 -> 0.16991926 | EQ17: =_Engine_R50!R176 -> 0.1687297 | ER17: =_Engine_R50!R177 -> 0.16755081 | ES17: =_Engine_R50!R178 -> 0.16638247 | ET17: =_Engine_R50!R179 -> 0.16522456 | EU17: =_Engine_R50!R180 -> 0.16407698 | EV17: =_Engine_R50!R181 -> 0.16293962 | EW17: =_Engine_R50!R182 -> 0.16181236 | EX17: =_Engine_R50!R183 -> 0.1606951 | EY17: =_Engine_R50!R184 -> 0.15958773 | EZ17: =_Engine_R50!R185 -> 0.15849015 | FA17: =_Engine_R50!R186 -> 0.15740224 | FB17: =_Engine_R50!R187 -> 0.15632392 | FC17: =_Engine_R50!R188 -> 0.15525506 | FD17: =_Engine_R50!R189 -> 0.15419558 | FE17: =_Engine_R50!R190 -> 0.15314538 | FF17: =_Engine_R50!R191 -> 0.15210435 | FG17: =_Engine_R50!R192 -> 0.1510724 | FH17: =_Engine_R50!R193 -> 0.15004943 | FI17: =_Engine_R50!R194 -> 0.14903535 | FJ17: =_Engine_R50!R195 -> 0.14803007 | FK17: =_Engine_R50!R196 -> 0.14703349 | FL17: =_Engine_R50!R197 -> 0.14604551 | FM17: =_Engine_R50!R198 -> 0.14506606 | FN17: =_Engine_R50!R199 -> 0.14409503 | FO17: =_Engine_R50!R200 -> 0.14313235 | FP17: =_Engine_R50!R201 -> 0.14217792 | FQ17: =_Engine_R50!R202 -> 0.14123166 | FR17: =_Engine_R50!R203 -> 0.14029348 | FS17: =_Engine_R50!R204 -> 0.1393633 | FT17: =_Engine_R50!R205 -> 0.13844104 | FU17: =_Engine_R50!R206 -> 0.1375266 | FV17: =_Engine_R50!R207 -> 0.13661992 | FW17: =_Engine_R50!R208 -> 0.13572091 | FX17: =_Engine_R50!R209 -> 0.13482949 | FY17: =_Engine_R50!R210 -> 0.13394558
A18: Gross Profit | B18: =_Engine_R50!S31 -> 0 | C18: =_Engine_R50!S32 -> 0 | D18: =_Engine_R50!S33 -> 0 | E18: =_Engine_R50!S34 -> 0.125 | F18: =_Engine_R50!S35 -> 0.12446684 | G18: =_Engine_R50!S36 -> 0.12393594 | H18: =_Engine_R50!S37 -> 0.12340732 | I18: =_Engine_R50!S38 -> 0.24788095 | J18: =_Engine_R50!S39 -> 0.24626412 | K18: =_Engine_R50!S40 -> 0.24465908 | L18: =_Engine_R50!S41 -> 0.24306573 | M18: =_Engine_R50!S42 -> 0.36648399 | N18: =_Engine_R50!S43 -> 0.36323226 | O18: =_Engine_R50!S44 -> 0.36001458 | P18: =_Engine_R50!S45 -> 0.35683053 | Q18: =_Engine_R50!S46 -> 0.47867975 | R18: =_Engine_R50!S47 -> 0.47388034 | S18: =_Engine_R50!S48 -> 0.46913604 | T18: =_Engine_R50!S49 -> 0.46444618 | U18: =_Engine_R50!S50 -> 0.45981007 | V18: =_Engine_R50!S51 -> 0.45522706 | W18: =_Engine_R50!S52 -> 0.45069649 | X18: =_Engine_R50!S53 -> 0.44621773 | Y18: =_Engine_R50!S54 -> 0.44179012 | Z18: =_Engine_R50!S55 -> 0.43741305 | AA18: =_Engine_R50!S56 -> 0.43308588 | AB18: =_Engine_R50!S57 -> 0.42880802 | AC18: =_Engine_R50!S58 -> 0.42457885 | AD18: =_Engine_R50!S59 -> 0.42039777 | AE18: =_Engine_R50!S60 -> 0.4162642 | AF18: =_Engine_R50!S61 -> 0.41217755 | AG18: =_Engine_R50!S62 -> 0.49813725 | AH18: =_Engine_R50!S63 -> 0.49375885 | AI18: =_Engine_R50!S64 -> 0.4894273 | AJ18: =_Engine_R50!S65 -> 0.48514206 | AK18: =_Engine_R50!S66 -> 0.48090255 | AL18: =_Engine_R50!S67 -> 0.47670825 | AM18: =_Engine_R50!S68 -> 0.4725586 | AN18: =_Engine_R50!S69 -> 0.46845308 | AO18: =_Engine_R50!S70 -> 0.46439115 | AP18: =_Engine_R50!S71 -> 0.46037231 | AQ18: =_Engine_R50!S72 -> 0.45639603 | AR18: =_Engine_R50!S73 -> 0.45246182 | AS18: =_Engine_R50!S74 -> 0.44856917 | AT18: =_Engine_R50!S75 -> 0.44471758 | AU18: =_Engine_R50!S76 -> 0.44090658 | AV18: =_Engine_R50!S77 -> 0.43713567 | AW18: =_Engine_R50!S78 -> 0.43340439 | AX18: =_Engine_R50!S79 -> 0.42971227 | AY18: =_Engine_R50!S80 -> 0.42605883 | AZ18: =_Engine_R50!S81 -> 0.42244364 | BA18: =_Engine_R50!S82 -> 0.41886622 | BB18: =_Engine_R50!S83 -> 0.41532614 | BC18: =_Engine_R50!S84 -> 0.41182296 | BD18: =_Engine_R50!S85 -> 0.40835624 | BE18: =_Engine_R50!S86 -> 0.40492555 | BF18: =_Engine_R50!S87 -> 0.40153046 | BG18: =_Engine_R50!S88 -> 0.39817057 | BH18: =_Engine_R50!S89 -> 0.39484545 | BI18: =_Engine_R50!S90 -> 0.3915547 | BJ18: =_Engine_R50!S91 -> 0.38829792 | BK18: =_Engine_R50!S92 -> 0.3850747 | BL18: =_Engine_R50!S93 -> 0.38188465 | BM18: =_Engine_R50!S94 -> 0.37872738 | BN18: =_Engine_R50!S95 -> 0.37560252 | BO18: =_Engine_R50!S96 -> 0.37250968 | BP18: =_Engine_R50!S97 -> 0.36944848 | BQ18: =_Engine_R50!S98 -> 0.36641857 | BR18: =_Engine_R50!S99 -> 0.36341957 | BS18: =_Engine_R50!S100 -> 0.36045112 | BT18: =_Engine_R50!S101 -> 0.35751287 | BU18: =_Engine_R50!S102 -> 0.35460447 | BV18: =_Engine_R50!S103 -> 0.35172557 | BW18: =_Engine_R50!S104 -> 0.34887582 | BX18: =_Engine_R50!S105 -> 0.3460549 | BY18: =_Engine_R50!S106 -> 0.34326246 | BZ18: =_Engine_R50!S107 -> 0.34049817 | CA18: =_Engine_R50!S108 -> 0.33776172 | CB18: =_Engine_R50!S109 -> 0.33505277 | CC18: =_Engine_R50!S110 -> 0.33237101 | CD18: =_Engine_R50!S111 -> 0.32971613 | CE18: =_Engine_R50!S112 -> 0.32708782 | CF18: =_Engine_R50!S113 -> 0.32448576 | CG18: =_Engine_R50!S114 -> 0.32190967 | CH18: =_Engine_R50!S115 -> 0.31935923 | CI18: =_Engine_R50!S116 -> 0.31683415 | CJ18: =_Engine_R50!S117 -> 0.31433415 | CK18: =_Engine_R50!S118 -> 0.31185894 | CL18: =_Engine_R50!S119 -> 0.30940823 | CM18: =_Engine_R50!S120 -> 0.30698173 | CN18: =_Engine_R50!S121 -> 0.30457918 | CO18: =_Engine_R50!S122 -> 0.3022003 | CP18: =_Engine_R50!S123 -> 0.29984482 | CQ18: =_Engine_R50!S124 -> 0.29751248 | CR18: =_Engine_R50!S125 -> 0.295203 | CS18: =_Engine_R50!S126 -> 0.29291613 | CT18: =_Engine_R50!S127 -> 0.29065161 | CU18: =_Engine_R50!S128 -> 0.28840919 | CV18: =_Engine_R50!S129 -> 0.28618862 | CW18: =_Engine_R50!S130 -> 0.28398964 | CX18: =_Engine_R50!S131 -> 0.28181202 | CY18: =_Engine_R50!S132 -> 0.27965551 | CZ18: =_Engine_R50!S133 -> 0.27751988 | DA18: =_Engine_R50!S134 -> 0.27540488 | DB18: =_Engine_R50!S135 -> 0.27331028 | DC18: =_Engine_R50!S136 -> 0.27123586 | DD18: =_Engine_R50!S137 -> 0.26918139 | DE18: =_Engine_R50!S138 -> 0.26714664 | DF18: =_Engine_R50!S139 -> 0.26513138 | DG18: =_Engine_R50!S140 -> 0.26313541 | DH18: =_Engine_R50!S141 -> 0.26115851 | DI18: =_Engine_R50!S142 -> 0.25920045 | DJ18: =_Engine_R50!S143 -> 0.25726104 | DK18: =_Engine_R50!S144 -> 0.25534006 | DL18: =_Engine_R50!S145 -> 0.2534373 | DM18: =_Engine_R50!S146 -> 0.25155257 | DN18: =_Engine_R50!S147 -> 0.24968565 | DO18: =_Engine_R50!S148 -> 0.24783636 | DP18: =_Engine_R50!S149 -> 0.24600449 | DQ18: =_Engine_R50!S150 -> 0.24418986 | DR18: =_Engine_R50!S151 -> 0.24239227 | DS18: =_Engine_R50!S152 -> 0.24061152 | DT18: =_Engine_R50!S153 -> 0.23884745 | DU18: =_Engine_R50!S154 -> 0.23709985 | DV18: =_Engine_R50!S155 -> 0.23536855 | DW18: =_Engine_R50!S156 -> 0.23365337 | DX18: =_Engine_R50!S157 -> 0.23195413 | DY18: =_Engine_R50!S158 -> 0.23027066 | DZ18: =_Engine_R50!S159 -> 0.22860277 | EA18: =_Engine_R50!S160 -> 0.22695031 | EB18: =_Engine_R50!S161 -> 0.22531309 | EC18: =_Engine_R50!S162 -> 0.22369096 | ED18: =_Engine_R50!S163 -> 0.22208374 | EE18: =_Engine_R50!S164 -> 0.22049128 | EF18: =_Engine_R50!S165 -> 0.21891341 | EG18: =_Engine_R50!S166 -> 0.21734997 | EH18: =_Engine_R50!S167 -> 0.21580081 | EI18: =_Engine_R50!S168 -> 0.21426576 | EJ18: =_Engine_R50!S169 -> 0.21274468 | EK18: =_Engine_R50!S170 -> 0.21123742 | EL18: =_Engine_R50!S171 -> 0.20974382 | EM18: =_Engine_R50!S172 -> 0.20826373 | EN18: =_Engine_R50!S173 -> 0.20679702 | EO18: =_Engine_R50!S174 -> 0.20534352 | EP18: =_Engine_R50!S175 -> 0.20390311 | EQ18: =_Engine_R50!S176 -> 0.20247564 | ER18: =_Engine_R50!S177 -> 0.20106097 | ES18: =_Engine_R50!S178 -> 0.19965896 | ET18: =_Engine_R50!S179 -> 0.19826947 | EU18: =_Engine_R50!S180 -> 0.19689238 | EV18: =_Engine_R50!S181 -> 0.19552755 | EW18: =_Engine_R50!S182 -> 0.19417484 | EX18: =_Engine_R50!S183 -> 0.19283413 | EY18: =_Engine_R50!S184 -> 0.19150528 | EZ18: =_Engine_R50!S185 -> 0.19018818 | FA18: =_Engine_R50!S186 -> 0.18888269 | FB18: =_Engine_R50!S187 -> 0.1875887 | FC18: =_Engine_R50!S188 -> 0.18630607 | FD18: =_Engine_R50!S189 -> 0.1850347 | FE18: =_Engine_R50!S190 -> 0.18377445 | FF18: =_Engine_R50!S191 -> 0.18252522 | FG18: =_Engine_R50!S192 -> 0.18128688 | FH18: =_Engine_R50!S193 -> 0.18005932 | FI18: =_Engine_R50!S194 -> 0.17884242 | FJ18: =_Engine_R50!S195 -> 0.17763608 | FK18: =_Engine_R50!S196 -> 0.17644018 | FL18: =_Engine_R50!S197 -> 0.17525462 | FM18: =_Engine_R50!S198 -> 0.17407927 | FN18: =_Engine_R50!S199 -> 0.17291404 | FO18: =_Engine_R50!S200 -> 0.17175882 | FP18: =_Engine_R50!S201 -> 0.17061351 | FQ18: =_Engine_R50!S202 -> 0.16947799 | FR18: =_Engine_R50!S203 -> 0.16835218 | FS18: =_Engine_R50!S204 -> 0.16723596 | FT18: =_Engine_R50!S205 -> 0.16612924 | FU18: =_Engine_R50!S206 -> 0.16503192 | FV18: =_Engine_R50!S207 -> 0.16394391 | FW18: =_Engine_R50!S208 -> 0.16286509 | FX18: =_Engine_R50!S209 -> 0.16179539 | FY18: =_Engine_R50!S210 -> 0.1607347
B19: =_Engine_R50!D31 -> 0.28810582 | C19: =_Engine_R50!D32 -> 0.28810582 | D19: =_Engine_R50!D33 -> 0.28810582 | E19: =_Engine_R50!D34 -> 0.28810582 | F19: =_Engine_R50!D35 -> 0.28810582 | G19: =_Engine_R50!D36 -> 0.28810582 | H19: =_Engine_R50!D37 -> 0.28810582 | I19: =_Engine_R50!D38 -> 0.28810582 | J19: =_Engine_R50!D39 -> 0.28810582 | K19: =_Engine_R50!D40 -> 0.28810582 | L19: =_Engine_R50!D41 -> 0.28810582 | M19: =_Engine_R50!D42 -> 0.28810582 | N19: =_Engine_R50!D43 -> 0.63304366 | O19: =_Engine_R50!D44 -> 0.63304366 | P19: =_Engine_R50!D45 -> 0.63304366 | Q19: =_Engine_R50!D46 -> 0.63304366 | R19: =_Engine_R50!D47 -> 0.63304366 | S19: =_Engine_R50!D48 -> 0.63304366 | T19: =_Engine_R50!D49 -> 0.63304366 | U19: =_Engine_R50!D50 -> 0.63304366 | V19: =_Engine_R50!D51 -> 0.63304366 | W19: =_Engine_R50!D52 -> 0.63304366 | X19: =_Engine_R50!D53 -> 0.63304366 | Y19: =_Engine_R50!D54 -> 0.63304366 | Z19: =_Engine_R50!D55 -> 0.63641667 | AA19: =_Engine_R50!D56 -> 0.63641667 | AB19: =_Engine_R50!D57 -> 0.63641667 | AC19: =_Engine_R50!D58 -> 0.63641667 | AD19: =_Engine_R50!D59 -> 0.63641667 | AE19: =_Engine_R50!D60 -> 0.63641667 | AF19: =_Engine_R50!D61 -> 0.63641667 | AG19: =_Engine_R50!D62 -> 0.63641667 | AH19: =_Engine_R50!D63 -> 0.63641667 | AI19: =_Engine_R50!D64 -> 0.63641667 | AJ19: =_Engine_R50!D65 -> 0.63641667 | AK19: =_Engine_R50!D66 -> 0.63641667 | AL19: =_Engine_R50!D67 -> 0.63641667 | AM19: =_Engine_R50!D68 -> 0.63641667 | AN19: =_Engine_R50!D69 -> 0.63641667 | AO19: =_Engine_R50!D70 -> 0.63641667 | AP19: =_Engine_R50!D71 -> 0.63641667 | AQ19: =_Engine_R50!D72 -> 0.63641667 | AR19: =_Engine_R50!D73 -> 0.63641667 | AS19: =_Engine_R50!D74 -> 0.63641667 | AT19: =_Engine_R50!D75 -> 0.63641667 | AU19: =_Engine_R50!D76 -> 0.63641667 | AV19: =_Engine_R50!D77 -> 0.63641667 | AW19: =_Engine_R50!D78 -> 0.63641667 | AX19: =_Engine_R50!D79 -> 0.63641667 | AY19: =_Engine_R50!D80 -> 0.63641667 | AZ19: =_Engine_R50!D81 -> 0.63641667 | BA19: =_Engine_R50!D82 -> 0.63641667 | BB19: =_Engine_R50!D83 -> 0.63641667 | BC19: =_Engine_R50!D84 -> 0.63641667 | BD19: =_Engine_R50!D85 -> 0.63641667 | BE19: =_Engine_R50!D86 -> 0.63641667 | BF19: =_Engine_R50!D87 -> 0.63641667 | BG19: =_Engine_R50!D88 -> 0.63641667 | BH19: =_Engine_R50!D89 -> 0.63641667 | BI19: =_Engine_R50!D90 -> 0.63641667 | BJ19: =_Engine_R50!D91 -> 0.63641667 | BK19: =_Engine_R50!D92 -> 0.63641667 | BL19: =_Engine_R50!D93 -> 0.63641667 | BM19: =_Engine_R50!D94 -> 0.63641667 | BN19: =_Engine_R50!D95 -> 0.63641667 | BO19: =_Engine_R50!D96 -> 0.63641667 | BP19: =_Engine_R50!D97 -> 0.63641667 | BQ19: =_Engine_R50!D98 -> 0.63641667 | BR19: =_Engine_R50!D99 -> 0.63641667 | BS19: =_Engine_R50!D100 -> 0.63641667 | BT19: =_Engine_R50!D101 -> 0.63641667 | BU19: =_Engine_R50!D102 -> 0.63641667 | BV19: =_Engine_R50!D103 -> 0.63641667 | BW19: =_Engine_R50!D104 -> 0.63641667 | BX19: =_Engine_R50!D105 -> 0.63641667 | BY19: =_Engine_R50!D106 -> 0.63641667 | BZ19: =_Engine_R50!D107 -> 0.63641667 | CA19: =_Engine_R50!D108 -> 0.63641667 | CB19: =_Engine_R50!D109 -> 0.63641667 | CC19: =_Engine_R50!D110 -> 0.63641667 | CD19: =_Engine_R50!D111 -> 0.63641667 | CE19: =_Engine_R50!D112 -> 0.63641667 | CF19: =_Engine_R50!D113 -> 0.63641667 | CG19: =_Engine_R50!D114 -> 0.63641667 | CH19: =_Engine_R50!D115 -> 0.63641667 | CI19: =_Engine_R50!D116 -> 0.63641667 | CJ19: =_Engine_R50!D117 -> 0.63641667 | CK19: =_Engine_R50!D118 -> 0.63641667 | CL19: =_Engine_R50!D119 -> 0.63641667 | CM19: =_Engine_R50!D120 -> 0.63641667 | CN19: =_Engine_R50!D121 -> 0.63641667 | CO19: =_Engine_R50!D122 -> 0.63641667 | CP19: =_Engine_R50!D123 -> 0.63641667 | CQ19: =_Engine_R50!D124 -> 0.63641667 | CR19: =_Engine_R50!D125 -> 0.63641667 | CS19: =_Engine_R50!D126 -> 0.63641667 | CT19: =_Engine_R50!D127 -> 0.63641667 | CU19: =_Engine_R50!D128 -> 0.63641667 | CV19: =_Engine_R50!D129 -> 0.63641667 | CW19: =_Engine_R50!D130 -> 0.63641667 | CX19: =_Engine_R50!D131 -> 0.63641667 | CY19: =_Engine_R50!D132 -> 0.63641667 | CZ19: =_Engine_R50!D133 -> 0.63641667 | DA19: =_Engine_R50!D134 -> 0.63641667 | DB19: =_Engine_R50!D135 -> 0.63641667 | DC19: =_Engine_R50!D136 -> 0.63641667 | DD19: =_Engine_R50!D137 -> 0.63641667 | DE19: =_Engine_R50!D138 -> 0.63641667 | DF19: =_Engine_R50!D139 -> 0.63641667 | DG19: =_Engine_R50!D140 -> 0.63641667 | DH19: =_Engine_R50!D141 -> 0.63641667 | DI19: =_Engine_R50!D142 -> 0.63641667 | DJ19: =_Engine_R50!D143 -> 0.63641667 | DK19: =_Engine_R50!D144 -> 0.63641667 | DL19: =_Engine_R50!D145 -> 0.63641667 | DM19: =_Engine_R50!D146 -> 0.63641667 | DN19: =_Engine_R50!D147 -> 0.63641667 | DO19: =_Engine_R50!D148 -> 0.63641667 | DP19: =_Engine_R50!D149 -> 0.63641667 | DQ19: =_Engine_R50!D150 -> 0.63641667 | DR19: =_Engine_R50!D151 -> 0.63641667 | DS19: =_Engine_R50!D152 -> 0.63641667 | DT19: =_Engine_R50!D153 -> 0.63641667 | DU19: =_Engine_R50!D154 -> 0.63641667 | DV19: =_Engine_R50!D155 -> 0.63641667 | DW19: =_Engine_R50!D156 -> 0.63641667 | DX19: =_Engine_R50!D157 -> 0.63641667 | DY19: =_Engine_R50!D158 -> 0.63641667 | DZ19: =_Engine_R50!D159 -> 0.63641667 | EA19: =_Engine_R50!D160 -> 0.63641667 | EB19: =_Engine_R50!D161 -> 0.63641667 | EC19: =_Engine_R50!D162 -> 0.63641667 | ED19: =_Engine_R50!D163 -> 0.63641667 | EE19: =_Engine_R50!D164 -> 0.63641667 | EF19: =_Engine_R50!D165 -> 0.63641667 | EG19: =_Engine_R50!D166 -> 0.63641667 | EH19: =_Engine_R50!D167 -> 0.63641667 | EI19: =_Engine_R50!D168 -> 0.63641667 | EJ19: =_Engine_R50!D169 -> 0.63641667 | EK19: =_Engine_R50!D170 -> 0.63641667 | EL19: =_Engine_R50!D171 -> 0.63641667 | EM19: =_Engine_R50!D172 -> 0.63641667 | EN19: =_Engine_R50!D173 -> 0.63641667 | EO19: =_Engine_R50!D174 -> 0.63641667 | EP19: =_Engine_R50!D175 -> 0.63641667 | EQ19: =_Engine_R50!D176 -> 0.63641667 | ER19: =_Engine_R50!D177 -> 0.63641667 | ES19: =_Engine_R50!D178 -> 0.63641667 | ET19: =_Engine_R50!D179 -> 0.63641667 | EU19: =_Engine_R50!D180 -> 0.63641667 | EV19: =_Engine_R50!D181 -> 0.63641667 | EW19: =_Engine_R50!D182 -> 0.63641667 | EX19: =_Engine_R50!D183 -> 0.63641667 | EY19: =_Engine_R50!D184 -> 0.63641667 | EZ19: =_Engine_R50!D185 -> 0.63641667 | FA19: =_Engine_R50!D186 -> 0.63641667 | FB19: =_Engine_R50!D187 -> 0.63641667 | FC19: =_Engine_R50!D188 -> 0.63641667 | FD19: =_Engine_R50!D189 -> 0.63641667 | FE19: =_Engine_R50!D190 -> 0.63641667 | FF19: =_Engine_R50!D191 -> 0.63641667 | FG19: =_Engine_R50!D192 -> 0.63641667 | FH19: =_Engine_R50!D193 -> 0.63641667 | FI19: =_Engine_R50!D194 -> 0.63641667 | FJ19: =_Engine_R50!D195 -> 0.63641667 | FK19: =_Engine_R50!D196 -> 0.63641667 | FL19: =_Engine_R50!D197 -> 0.63641667 | FM19: =_Engine_R50!D198 -> 0.63641667 | FN19: =_Engine_R50!D199 -> 0.63641667 | FO19: =_Engine_R50!D200 -> 0.63641667 | FP19: =_Engine_R50!D201 -> 0.63641667 | FQ19: =_Engine_R50!D202 -> 0.63641667 | FR19: =_Engine_R50!D203 -> 0.63641667 | FS19: =_Engine_R50!D204 -> 0.63641667 | FT19: =_Engine_R50!D205 -> 0.63641667 | FU19: =_Engine_R50!D206 -> 0.63641667 | FV19: =_Engine_R50!D207 -> 0.63641667 | FW19: =_Engine_R50!D208 -> 0.63641667 | FX19: =_Engine_R50!D209 -> 0.63641667 | FY19: =_Engine_R50!D210 -> 0.63641667
A20: Vendor Costs | B20: =_Engine_R50!E31 -> 0 | C20: =_Engine_R50!E32 -> 0 | D20: =_Engine_R50!E33 -> 0 | E20: =_Engine_R50!E34 -> 1.1666667 | F20: =_Engine_R50!E35 -> 0.98 | G20: =_Engine_R50!E36 -> 0.79333333 | H20: =_Engine_R50!E37 -> 0.60666667 | I20: =_Engine_R50!E38 -> 1.5866667 | J20: =_Engine_R50!E39 -> 1.2133333 | K20: =_Engine_R50!E40 -> 1.0137037 | L20: =_Engine_R50!E41 -> 0.81407407 | M20: =_Engine_R50!E42 -> 1.7811111 | N20: =_Engine_R50!E43 -> 1.3948148 | O20: =_Engine_R50!E44 -> 1.1822222 | P20: =_Engine_R50!E45 -> 0.96962963 | Q20: =_Engine_R50!E46 -> 1.9237037 | R20: =_Engine_R50!E47 -> 1.5244444 | S20: =_Engine_R50!E48 -> 1.2988889 | T20: =_Engine_R50!E49 -> 1.0733333 | U20: =_Engine_R50!E50 -> 0.84777778 | V20: =_Engine_R50!E51 -> 0.62222222 | W20: =_Engine_R50!E52 -> 0.57037037 | X20: =_Engine_R50!E53 -> 0.51851852 | Y20: =_Engine_R50!E54 -> 0.46666667 | Z20: =_Engine_R50!E55 -> 0.41481481 | AA20: =_Engine_R50!E56 -> 0.36296296 | AB20: =_Engine_R50!E57 -> 0.31111111 | AC20: =_Engine_R50!E58 -> 0.27222222 | AD20: =_Engine_R50!E59 -> 0.23333333 | AE20: =_Engine_R50!E60 -> 0.19444444 | AF20: =_Engine_R50!E61 -> 0.15555556 | AG20: =_Engine_R50!E62 -> 1.2962963 | AH20: =_Engine_R50!E63 -> 1.0837037 | AI20: =_Engine_R50!E64 -> 0.87111111 | AJ20: =_Engine_R50!E65 -> 0.65851852 | AK20: =_Engine_R50!E66 -> 0.45888889 | AL20: =_Engine_R50!E67 -> 0.25925926 | AM20: =_Engine_R50!E68 -> 0.23333333 | AN20: =_Engine_R50!E69 -> 0.20740741 | AO20: =_Engine_R50!E70 -> 0.19444444 | AP20: =_Engine_R50!E71 -> 0.18148148 | AQ20: =_Engine_R50!E72 -> 0.16851852 | AR20: =_Engine_R50!E73 -> 0.15555556 | AS20: =_Engine_R50!E74 -> 0.14259259 | AT20: =_Engine_R50!E75 -> 0.12962963 | AU20: =_Engine_R50!E76 -> 0.11666667 | AV20: =_Engine_R50!E77 -> 0.1037037 | AW20: =_Engine_R50!E78 -> 0.090740741 | AX20: =_Engine_R50!E79 -> 0.077777778 | AY20: =_Engine_R50!E80 -> 0.064814815 | AZ20: =_Engine_R50!E81 -> 0.051851852 | BA20: =_Engine_R50!E82 -> 0.038888889 | BB20: =_Engine_R50!E83 -> 0.025925926 | BC20: =_Engine_R50!E84 -> 0.012962963 | BD20: =_Engine_R50!E85 -> 0 | BE20: =_Engine_R50!E86 -> 0 | BF20: =_Engine_R50!E87 -> 0 | BG20: =_Engine_R50!E88 -> 0 | BH20: =_Engine_R50!E89 -> 0 | BI20: =_Engine_R50!E90 -> 0 | BJ20: =_Engine_R50!E91 -> 0 | BK20: =_Engine_R50!E92 -> 0 | BL20: =_Engine_R50!E93 -> 0 | BM20: =_Engine_R50!E94 -> 0 | BN20: =_Engine_R50!E95 -> 0 | BO20: =_Engine_R50!E96 -> 0 | BP20: =_Engine_R50!E97 -> 0 | BQ20: =_Engine_R50!E98 -> 0 | BR20: =_Engine_R50!E99 -> 0 | BS20: =_Engine_R50!E100 -> 0 | BT20: =_Engine_R50!E101 -> 0 | BU20: =_Engine_R50!E102 -> 0 | BV20: =_Engine_R50!E103 -> 0 | BW20: =_Engine_R50!E104 -> 0 | BX20: =_Engine_R50!E105 -> 0 | BY20: =_Engine_R50!E106 -> 0 | BZ20: =_Engine_R50!E107 -> 0 | CA20: =_Engine_R50!E108 -> 0 | CB20: =_Engine_R50!E109 -> 0 | CC20: =_Engine_R50!E110 -> 0 | CD20: =_Engine_R50!E111 -> 0 | CE20: =_Engine_R50!E112 -> 0 | CF20: =_Engine_R50!E113 -> 0 | CG20: =_Engine_R50!E114 -> 0 | CH20: =_Engine_R50!E115 -> 0 | CI20: =_Engine_R50!E116 -> 0 | CJ20: =_Engine_R50!E117 -> 0 | CK20: =_Engine_R50!E118 -> 0 | CL20: =_Engine_R50!E119 -> 0 | CM20: =_Engine_R50!E120 -> 0 | CN20: =_Engine_R50!E121 -> 0 | CO20: =_Engine_R50!E122 -> 0 | CP20: =_Engine_R50!E123 -> 0 | CQ20: =_Engine_R50!E124 -> 0 | CR20: =_Engine_R50!E125 -> 0 | CS20: =_Engine_R50!E126 -> 0 | CT20: =_Engine_R50!E127 -> 0 | CU20: =_Engine_R50!E128 -> 0 | CV20: =_Engine_R50!E129 -> 0 | CW20: =_Engine_R50!E130 -> 0 | CX20: =_Engine_R50!E131 -> 0 | CY20: =_Engine_R50!E132 -> 0 | CZ20: =_Engine_R50!E133 -> 0 | DA20: =_Engine_R50!E134 -> 0 | DB20: =_Engine_R50!E135 -> 0 | DC20: =_Engine_R50!E136 -> 0 | DD20: =_Engine_R50!E137 -> 0 | DE20: =_Engine_R50!E138 -> 0 | DF20: =_Engine_R50!E139 -> 0 | DG20: =_Engine_R50!E140 -> 0 | DH20: =_Engine_R50!E141 -> 0 | DI20: =_Engine_R50!E142 -> 0 | DJ20: =_Engine_R50!E143 -> 0 | DK20: =_Engine_R50!E144 -> 0 | DL20: =_Engine_R50!E145 -> 0 | DM20: =_Engine_R50!E146 -> 0 | DN20: =_Engine_R50!E147 -> 0 | DO20: =_Engine_R50!E148 -> 0 | DP20: =_Engine_R50!E149 -> 0 | DQ20: =_Engine_R50!E150 -> 0 | DR20: =_Engine_R50!E151 -> 0 | DS20: =_Engine_R50!E152 -> 0 | DT20: =_Engine_R50!E153 -> 0 | DU20: =_Engine_R50!E154 -> 0 | DV20: =_Engine_R50!E155 -> 0 | DW20: =_Engine_R50!E156 -> 0 | DX20: =_Engine_R50!E157 -> 0 | DY20: =_Engine_R50!E158 -> 0 | DZ20: =_Engine_R50!E159 -> 0 | EA20: =_Engine_R50!E160 -> 0 | EB20: =_Engine_R50!E161 -> 0 | EC20: =_Engine_R50!E162 -> 0 | ED20: =_Engine_R50!E163 -> 0 | EE20: =_Engine_R50!E164 -> 0 | EF20: =_Engine_R50!E165 -> 0 | EG20: =_Engine_R50!E166 -> 0 | EH20: =_Engine_R50!E167 -> 0 | EI20: =_Engine_R50!E168 -> 0 | EJ20: =_Engine_R50!E169 -> 0 | EK20: =_Engine_R50!E170 -> 0 | EL20: =_Engine_R50!E171 -> 0 | EM20: =_Engine_R50!E172 -> 0 | EN20: =_Engine_R50!E173 -> 0 | EO20: =_Engine_R50!E174 -> 0 | EP20: =_Engine_R50!E175 -> 0 | EQ20: =_Engine_R50!E176 -> 0 | ER20: =_Engine_R50!E177 -> 0 | ES20: =_Engine_R50!E178 -> 0 | ET20: =_Engine_R50!E179 -> 0 | EU20: =_Engine_R50!E180 -> 0 | EV20: =_Engine_R50!E181 -> 0 | EW20: =_Engine_R50!E182 -> 0 | EX20: =_Engine_R50!E183 -> 0 | EY20: =_Engine_R50!E184 -> 0 | EZ20: =_Engine_R50!E185 -> 0 | FA20: =_Engine_R50!E186 -> 0 | FB20: =_Engine_R50!E187 -> 0 | FC20: =_Engine_R50!E188 -> 0 | FD20: =_Engine_R50!E189 -> 0 | FE20: =_Engine_R50!E190 -> 0 | FF20: =_Engine_R50!E191 -> 0 | FG20: =_Engine_R50!E192 -> 0 | FH20: =_Engine_R50!E193 -> 0 | FI20: =_Engine_R50!E194 -> 0 | FJ20: =_Engine_R50!E195 -> 0 | FK20: =_Engine_R50!E196 -> 0 | FL20: =_Engine_R50!E197 -> 0 | FM20: =_Engine_R50!E198 -> 0 | FN20: =_Engine_R50!E199 -> 0 | FO20: =_Engine_R50!E200 -> 0 | FP20: =_Engine_R50!E201 -> 0 | FQ20: =_Engine_R50!E202 -> 0 | FR20: =_Engine_R50!E203 -> 0 | FS20: =_Engine_R50!E204 -> 0 | FT20: =_Engine_R50!E205 -> 0 | FU20: =_Engine_R50!E206 -> 0 | FV20: =_Engine_R50!E207 -> 0 | FW20: =_Engine_R50!E208 -> 0 | FX20: =_Engine_R50!E209 -> 0 | FY20: =_Engine_R50!E210 -> 0
A21: Corporate Allocation | B21: =_Engine_R50!U31 -> 0 | C21: =_Engine_R50!U32 -> 0 | D21: =_Engine_R50!U33 -> 0 | E21: =_Engine_R50!U34 -> 0 | F21: =_Engine_R50!U35 -> 0 | G21: =_Engine_R50!U36 -> 0 | H21: =_Engine_R50!U37 -> 0 | I21: =_Engine_R50!U38 -> 0 | J21: =_Engine_R50!U39 -> 0 | K21: =_Engine_R50!U40 -> 0 | L21: =_Engine_R50!U41 -> 0 | M21: =_Engine_R50!U42 -> 0 | N21: =_Engine_R50!U43 -> 0 | O21: =_Engine_R50!U44 -> 0 | P21: =_Engine_R50!U45 -> 0 | Q21: =_Engine_R50!U46 -> 0 | R21: =_Engine_R50!U47 -> 0 | S21: =_Engine_R50!U48 -> 0 | T21: =_Engine_R50!U49 -> 0 | U21: =_Engine_R50!U50 -> 0 | V21: =_Engine_R50!U51 -> 0 | W21: =_Engine_R50!U52 -> 0 | X21: =_Engine_R50!U53 -> 0 | Y21: =_Engine_R50!U54 -> 0 | Z21: =_Engine_R50!U55 -> 0 | AA21: =_Engine_R50!U56 -> 0 | AB21: =_Engine_R50!U57 -> 0 | AC21: =_Engine_R50!U58 -> 0 | AD21: =_Engine_R50!U59 -> 0 | AE21: =_Engine_R50!U60 -> 0 | AF21: =_Engine_R50!U61 -> 0 | AG21: =_Engine_R50!U62 -> 0 | AH21: =_Engine_R50!U63 -> 0 | AI21: =_Engine_R50!U64 -> 0 | AJ21: =_Engine_R50!U65 -> 0 | AK21: =_Engine_R50!U66 -> 0 | AL21: =_Engine_R50!U67 -> 0 | AM21: =_Engine_R50!U68 -> 0 | AN21: =_Engine_R50!U69 -> 0 | AO21: =_Engine_R50!U70 -> 0 | AP21: =_Engine_R50!U71 -> 0 | AQ21: =_Engine_R50!U72 -> 0 | AR21: =_Engine_R50!U73 -> 0 | AS21: =_Engine_R50!U74 -> 0 | AT21: =_Engine_R50!U75 -> 0 | AU21: =_Engine_R50!U76 -> 0 | AV21: =_Engine_R50!U77 -> 0 | AW21: =_Engine_R50!U78 -> 0 | AX21: =_Engine_R50!U79 -> 0 | AY21: =_Engine_R50!U80 -> 0 | AZ21: =_Engine_R50!U81 -> 0 | BA21: =_Engine_R50!U82 -> 0 | BB21: =_Engine_R50!U83 -> 0 | BC21: =_Engine_R50!U84 -> 0 | BD21: =_Engine_R50!U85 -> 0 | BE21: =_Engine_R50!U86 -> 0 | BF21: =_Engine_R50!U87 -> 0 | BG21: =_Engine_R50!U88 -> 0 | BH21: =_Engine_R50!U89 -> 0 | BI21: =_Engine_R50!U90 -> 0 | BJ21: =_Engine_R50!U91 -> 0 | BK21: =_Engine_R50!U92 -> 0 | BL21: =_Engine_R50!U93 -> 0 | BM21: =_Engine_R50!U94 -> 0 | BN21: =_Engine_R50!U95 -> 0 | BO21: =_Engine_R50!U96 -> 0 | BP21: =_Engine_R50!U97 -> 0 | BQ21: =_Engine_R50!U98 -> 0 | BR21: =_Engine_R50!U99 -> 0 | BS21: =_Engine_R50!U100 -> 0 | BT21: =_Engine_R50!U101 -> 0 | BU21: =_Engine_R50!U102 -> 0 | BV21: =_Engine_R50!U103 -> 0 | BW21: =_Engine_R50!U104 -> 0 | BX21: =_Engine_R50!U105 -> 0 | BY21: =_Engine_R50!U106 -> 0 | BZ21: =_Engine_R50!U107 -> 0 | CA21: =_Engine_R50!U108 -> 0 | CB21: =_Engine_R50!U109 -> 0 | CC21: =_Engine_R50!U110 -> 0 | CD21: =_Engine_R50!U111 -> 0 | CE21: =_Engine_R50!U112 -> 0 | CF21: =_Engine_R50!U113 -> 0 | CG21: =_Engine_R50!U114 -> 0 | CH21: =_Engine_R50!U115 -> 0 | CI21: =_Engine_R50!U116 -> 0 | CJ21: =_Engine_R50!U117 -> 0 | CK21: =_Engine_R50!U118 -> 0 | CL21: =_Engine_R50!U119 -> 0 | CM21: =_Engine_R50!U120 -> 0 | CN21: =_Engine_R50!U121 -> 0 | CO21: =_Engine_R50!U122 -> 0 | CP21: =_Engine_R50!U123 -> 0 | CQ21: =_Engine_R50!U124 -> 0 | CR21: =_Engine_R50!U125 -> 0 | CS21: =_Engine_R50!U126 -> 0 | CT21: =_Engine_R50!U127 -> 0 | CU21: =_Engine_R50!U128 -> 0 | CV21: =_Engine_R50!U129 -> 0 | CW21: =_Engine_R50!U130 -> 0 | CX21: =_Engine_R50!U131 -> 0 | CY21: =_Engine_R50!U132 -> 0 | CZ21: =_Engine_R50!U133 -> 0 | DA21: =_Engine_R50!U134 -> 0 | DB21: =_Engine_R50!U135 -> 0 | DC21: =_Engine_R50!U136 -> 0 | DD21: =_Engine_R50!U137 -> 0 | DE21: =_Engine_R50!U138 -> 0 | DF21: =_Engine_R50!U139 -> 0 | DG21: =_Engine_R50!U140 -> 0 | DH21: =_Engine_R50!U141 -> 0 | DI21: =_Engine_R50!U142 -> 0 | DJ21: =_Engine_R50!U143 -> 0 | DK21: =_Engine_R50!U144 -> 0 | DL21: =_Engine_R50!U145 -> 0 | DM21: =_Engine_R50!U146 -> 0 | DN21: =_Engine_R50!U147 -> 0 | DO21: =_Engine_R50!U148 -> 0 | DP21: =_Engine_R50!U149 -> 0 | DQ21: =_Engine_R50!U150 -> 0 | DR21: =_Engine_R50!U151 -> 0 | DS21: =_Engine_R50!U152 -> 0 | DT21: =_Engine_R50!U153 -> 0 | DU21: =_Engine_R50!U154 -> 0 | DV21: =_Engine_R50!U155 -> 0 | DW21: =_Engine_R50!U156 -> 0 | DX21: =_Engine_R50!U157 -> 0 | DY21: =_Engine_R50!U158 -> 0 | DZ21: =_Engine_R50!U159 -> 0 | EA21: =_Engine_R50!U160 -> 0 | EB21: =_Engine_R50!U161 -> 0 | EC21: =_Engine_R50!U162 -> 0 | ED21: =_Engine_R50!U163 -> 0 | EE21: =_Engine_R50!U164 -> 0 | EF21: =_Engine_R50!U165 -> 0 | EG21: =_Engine_R50!U166 -> 0 | EH21: =_Engine_R50!U167 -> 0 | EI21: =_Engine_R50!U168 -> 0 | EJ21: =_Engine_R50!U169 -> 0 | EK21: =_Engine_R50!U170 -> 0 | EL21: =_Engine_R50!U171 -> 0 | EM21: =_Engine_R50!U172 -> 0 | EN21: =_Engine_R50!U173 -> 0 | EO21: =_Engine_R50!U174 -> 0 | EP21: =_Engine_R50!U175 -> 0 | EQ21: =_Engine_R50!U176 -> 0 | ER21: =_Engine_R50!U177 -> 0 | ES21: =_Engine_R50!U178 -> 0 | ET21: =_Engine_R50!U179 -> 0 | EU21: =_Engine_R50!U180 -> 0 | EV21: =_Engine_R50!U181 -> 0 | EW21: =_Engine_R50!U182 -> 0 | EX21: =_Engine_R50!U183 -> 0 | EY21: =_Engine_R50!U184 -> 0 | EZ21: =_Engine_R50!U185 -> 0 | FA21: =_Engine_R50!U186 -> 0 | FB21: =_Engine_R50!U187 -> 0 | FC21: =_Engine_R50!U188 -> 0 | FD21: =_Engine_R50!U189 -> 0 | FE21: =_Engine_R50!U190 -> 0 | FF21: =_Engine_R50!U191 -> 0 | FG21: =_Engine_R50!U192 -> 0 | FH21: =_Engine_R50!U193 -> 0 | FI21: =_Engine_R50!U194 -> 0 | FJ21: =_Engine_R50!U195 -> 0 | FK21: =_Engine_R50!U196 -> 0 | FL21: =_Engine_R50!U197 -> 0 | FM21: =_Engine_R50!U198 -> 0 | FN21: =_Engine_R50!U199 -> 0 | FO21: =_Engine_R50!U200 -> 0 | FP21: =_Engine_R50!U201 -> 0 | FQ21: =_Engine_R50!U202 -> 0 | FR21: =_Engine_R50!U203 -> 0 | FS21: =_Engine_R50!U204 -> 0 | FT21: =_Engine_R50!U205 -> 0 | FU21: =_Engine_R50!U206 -> 0 | FV21: =_Engine_R50!U207 -> 0 | FW21: =_Engine_R50!U208 -> 0 | FX21: =_Engine_R50!U209 -> 0 | FY21: =_Engine_R50!U210 -> 0
A22: Team Compensation | B22: =B17+B18+B19+B20+B21+B14 -> 0.28810582 | C22: =C17+C18+C19+C20+C21+C14 -> 0.28810582 | D22: =D17+D18+D19+D20+D21+D14 -> 0.28810582 | E22: =E17+E18+E19+E20+E21+E14 -> 1.8922725 | F22: =F17+F18+F19+F20+F21+F14 -> 1.7037397 | G22: =G17+G18+G19+G20+G21+G14 -> 1.515215 | H22: =H17+H18+H19+H20+H21+H14 -> 1.3266981 | I22: =I17+I18+I19+I20+I21+I14 -> 2.7423558 | ... FY22: =FY17+FY18+FY19+FY20+FY21+FY14 -> 1.1989881
A23: Legacy Headcount Expenses | B23: 0 | C23: 0 | D23: 0 | E23: 1.2587 | F23: 1.0927 | G23: 0.9309 | H23: 2.1106 | I23: 1.7807 | J23: 1.4592 | K23: 2.626 | L23: 2.21 | M23: 3.083 | N23: 2.5195 | O23: 2.06 | P23: 1.6124 | Q23: 2.4254 | R23: 1.9842 | S23: 1.5545 | T23: 1.2214 | U23: 0.9492 | V23: 0.6842 | W23: 0.4261 | X23: 0.3161 | Y23: 1.3889 | Z23: 1.179 | AA23: 0.9744 | AB23: 0.7751 | AC23: 0.581 | AD23: 0.4408 | AE23: 1.4842 | AF23: 1.2745 | AG23: 1.0701 | AH23: 0.871 | AI23: 0.6771 | AJ23: 0.4882 | AK23: 1.4842 | AL23: 1.2745 | AM23: 1.0701 | AN23: 0.871 | AO23: 0.6771 | AP23: 0.4882 | AQ23: 0.3042 | AR23: 0.2501 | AS23: 0.1974 | AT23: 0.1461 | AU23: 0.0961 | AV23: 0.0474 | AW23: 0 | AX23: 0 | AY23: 0 | AZ23: 0 | BA23: 0 | BB23: 0 | BC23: 0 | BD23: 0 | BE23: 0 | BF23: 0 | BG23: 0 | BH23: 0 | BI23: 0 | BJ23: 0 | BK23: 0 | BL23: 0 | BM23: 0 | BN23: 0 | BO23: 0 | BP23: 0 | BQ23: 0 | BR23: 0 | BS23: 0 | BT23: 0 | BU23: 0 | BV23: 0 | BW23: 0 | BX23: 0 | BY23: 0 | BZ23: 0 | CA23: 0 | CB23: 0 | CC23: 0 | CD23: 0 | CE23: 0 | CF23: 0 | CG23: 0 | CH23: 0 | CI23: 0 | CJ23: 0 | CK23: 0 | CL23: 0 | CM23: 0 | CN23: 0 | CO23: 0 | CP23: 0 | CQ23: 0 | CR23: 0 | CS23: 0 | CT23: 0 | CU23: 0 | CV23: 0 | CW23: 0 | CX23: 0 | CY23: 0 | CZ23: 0 | DA23: 0 | DB23: 0 | DC23: 0 | DD23: 0 | DE23: 0 | DF23: 0 | DG23: 0 | DH23: 0 | DI23: 0 | DJ23: 0 | DK23: 0 | DL23: 0 | DM23: 0 | DN23: 0 | DO23: 0 | DP23: 0 | DQ23: 0 | DR23: 0 | DS23: 0 | DT23: 0 | DU23: 0 | DV23: 0 | DW23: 0 | DX23: 0 | DY23: 0 | DZ23: 0 | EA23: 0 | EB23: 0 | EC23: 0 | ED23: 0 | EE23: 0 | EF23: 0 | EG23: 0 | EH23: 0 | EI23: 0 | EJ23: 0 | EK23: 0 | EL23: 0 | EM23: 0 | EN23: 0 | EO23: 0 | EP23: 0 | EQ23: 0 | ER23: 0 | ES23: 0 | ET23: 0 | EU23: 0 | EV23: 0 | EW23: 0 | EX23: 0 | EY23: 0 | EZ23: 0 | FA23: 0 | FB23: 0 | FC23: 0 | FD23: 0 | FE23: 0 | FF23: 0 | FG23: 0 | FH23: 0 | FI23: 0 | FJ23: 0 | FK23: 0 | FL23: 0 | FM23: 0 | FN23: 0 | FO23: 0 | FP23: 0 | FQ23: 0 | FR23: 0 | FS23: 0 | FT23: 0 | FU23: 0 | FV23: 0 | FW23: 0 | FX23: 0 | FY23: 0
A24: Bonus Pool | B24: =_Engine_R50!V31 -> -0.28810582 | C24: =_Engine_R50!V32 -> -0.28810582 | D24: =_Engine_R50!V33 -> -0.28810582 | E24: =_Engine_R50!V34 -> 0.19106084 | F24: =_Engine_R50!V35 -> 0.3707075 | G24: =_Engine_R50!V36 -> 0.55038411 | H24: =_Engine_R50!V37 -> 0.73009053 | I24: =_Engine_R50!V38 -> 1.3889933 | J24: =_Engine_R50!V39 -> 1.7410384 | K24: =_Engine_R50!V40 -> 1.919535 | L24: =_Engine_R50!V41 -> 2.0981856 | M24: =_Engine_R50!V42 -> 2.7561556 | N24: =_Engine_R50!V43 -> 2.7546997 | O24: =_Engine_R50!V44 -> 2.924926 | P24: =_Engine_R50!V45 -> 3.0955954 | Q24: =_Engine_R50!V46 -> 3.7458693 | R24: =_Engine_R50!V47 -> 4.0819364 | S24: =_Engine_R50!V48 -> 4.2450253 | T24: =_Engine_R50!V49 -> 4.408831 | U24: =_Engine_R50!V50 -> 4.5733445 | V24: =_Engine_R50!V51 -> 4.7385571 | W24: =_Engine_R50!V52 -> 4.7307565 | X24: =_Engine_R50!V53 -> 4.7236379 | Y24: =_Engine_R50!V54 -> 4.7171929 | Z24: =_Engine_R50!V55 -> 4.7080403 | AA24: =_Engine_R50!V56 -> 4.7029178 | AB24: =_Engine_R50!V57 -> 4.6984445 | AC24: =_Engine_R50!V58 -> 4.6816493 | AD24: =_Engine_R50!V59 -> 4.6654873 | AE24: =_Engine_R50!V60 -> 4.6499508 | AF24: =_Engine_R50!V61 -> 4.6350322 | AG24: =_Engine_R50!V62 -> 4.6260941 | AH24: =_Engine_R50!V63 -> 4.7810378 | AI24: =_Engine_R50!V64 -> 4.9365984 | AJ24: =_Engine_R50!V65 -> 5.0927686 | AK24: =_Engine_R50!V66 -> 5.2365781 | AL24: =_Engine_R50!V67 -> 5.3809827 | AM24: =_Engine_R50!V68 -> 5.3522716 | AN24: =_Engine_R50!V69 -> 5.3241414 | AO24: =_Engine_R50!V70 -> 5.2836224 | AP24: =_Engine_R50!V71 -> 5.2436706 | AQ24: =_Engine_R50!V72 -> 5.2042793 | AR24: =_Engine_R50!V73 -> 5.1654417 | AS24: =_Engine_R50!V74 -> 5.1271514 | AT24: =_Engine_R50!V75 -> 5.0894019 | AU24: =_Engine_R50!V76 -> 5.0521866 | AV24: =_Engine_R50!V77 -> 5.0154993 | AW24: =_Engine_R50!V78 -> 4.9793338 | AX24: =_Engine_R50!V79 -> 4.9436837 | AY24: =_Engine_R50!V80 -> 4.9085432 | AZ24: =_Engine_R50!V81 -> 4.873906 | BA24: =_Engine_R50!V82 -> 4.8397663 | BB24: =_Engine_R50!V83 -> 4.8061183 | BC24: =_Engine_R50!V84 -> 4.772956 | BD24: =_Engine_R50!V85 -> 4.7402738 | BE24: =_Engine_R50!V86 -> 4.695103 | BF24: =_Engine_R50!V87 -> 4.6504011 | BG24: =_Engine_R50!V88 -> 4.6061625 | BH24: =_Engine_R50!V89 -> 4.5623818 | BI24: =_Engine_R50!V90 -> 4.5190536 | BJ24: =_Engine_R50!V91 -> 4.4761726 | BK24: =_Engine_R50!V92 -> 4.4337335 | BL24: =_Engine_R50!V93 -> 4.3917312 | BM24: =_Engine_R50!V94 -> 4.3501606 | BN24: =_Engine_R50!V95 -> 4.3090165 | BO24: =_Engine_R50!V96 -> 4.2682941 | BP24: =_Engine_R50!V97 -> 4.2279884 | BQ24: =_Engine_R50!V98 -> 4.1880945 | BR24: =_Engine_R50!V99 -> 4.1486076 | BS24: =_Engine_R50!V100 -> 4.1095231 | BT24: =_Engine_R50!V101 -> 4.0708361 | BU24: =_Engine_R50!V102 -> 4.0325422 | BV24: =_Engine_R50!V103 -> 3.9946366 | BW24: =_Engine_R50!V104 -> 3.957115 | BX24: =_Engine_R50!V105 -> 3.9199728 | BY24: =_Engine_R50!V106 -> 3.8832057 | BZ24: =_Engine_R50!V107 -> 3.8468093 | CA24: =_Engine_R50!V108 -> 3.8107793 | CB24: =_Engine_R50!V109 -> 3.7751115 | CC24: =_Engine_R50!V110 -> 3.7398017 | CD24: =_Engine_R50!V111 -> 3.7048458 | CE24: =_Engine_R50!V112 -> 3.6702396 | CF24: =_Engine_R50!V113 -> 3.6359792 | CG24: =_Engine_R50!V114 -> 3.6020606 | CH24: =_Engine_R50!V115 -> 3.5684798 | CI24: =_Engine_R50!V116 -> 3.535233 | CJ24: =_Engine_R50!V117 -> 3.5023164 | CK24: =_Engine_R50!V118 -> 3.469726 | CL24: =_Engine_R50!V119 -> 3.4374583 | CM24: =_Engine_R50!V120 -> 3.4055095 | CN24: =_Engine_R50!V121 -> 3.3738759 | CO24: =_Engine_R50!V122 -> 3.342554 | CP24: =_Engine_R50!V123 -> 3.3115402 | CQ24: =_Engine_R50!V124 -> 3.280831 | CR24: =_Engine_R50!V125 -> 3.2504228 | CS24: =_Engine_R50!V126 -> 3.2203124 | CT24: =_Engine_R50!V127 -> 3.1904962 | CU24: =_Engine_R50!V128 -> 3.160971 | CV24: =_Engine_R50!V129 -> 3.1317335 | CW24: =_Engine_R50!V130 -> 3.1027803 | CX24: =_Engine_R50!V131 -> 3.0741083 | CY24: =_Engine_R50!V132 -> 3.0457142 | CZ24: =_Engine_R50!V133 -> 3.017595 | DA24: =_Engine_R50!V134 -> 2.9897475 | DB24: =_Engine_R50!V135 -> 2.9621687 | DC24: =_Engine_R50!V136 -> 2.9348555 | DD24: =_Engine_R50!V137 -> 2.9078049 | DE24: =_Engine_R50!V138 -> 2.881014 | DF24: =_Engine_R50!V139 -> 2.8544799 | DG24: =_Engine_R50!V140 -> 2.8281996 | DH24: =_Engine_R50!V141 -> 2.8021704 | DI24: =_Engine_R50!V142 -> 2.7763893 | DJ24: =_Engine_R50!V143 -> 2.7508537 | DK24: =_Engine_R50!V144 -> 2.7255608 | DL24: =_Engine_R50!V145 -> 2.7005078 | DM24: =_Engine_R50!V146 -> 2.6756921 | DN24: =_Engine_R50!V147 -> 2.6511111 | DO24: =_Engine_R50!V148 -> 2.6267621 | DP24: =_Engine_R50!V149 -> 2.6026425 | DQ24: =_Engine_R50!V150 -> 2.5787498 | DR24: =_Engine_R50!V151 -> 2.5550815 | DS24: =_Engine_R50!V152 -> 2.5316351 | DT24: =_Engine_R50!V153 -> 2.5084081 | DU24: =_Engine_R50!V154 -> 2.4853981 | DV24: =_Engine_R50!V155 -> 2.4626026 | DW24: =_Engine_R50!V156 -> 2.4400194 | DX24: =_Engine_R50!V157 -> 2.4176461 | DY24: =_Engine_R50!V158 -> 2.3954803 | DZ24: =_Engine_R50!V159 -> 2.3735199 | EA24: =_Engine_R50!V160 -> 2.3517624 | EB24: =_Engine_R50!V161 -> 2.3302057 | EC24: =_Engine_R50!V162 -> 2.3088476 | ED24: =_Engine_R50!V163 -> 2.2876859 | EE24: =_Engine_R50!V164 -> 2.2667185 | EF24: =_Engine_R50!V165 -> 2.2459432 | EG24: =_Engine_R50!V166 -> 2.2253579 | EH24: =_Engine_R50!V167 -> 2.2049606 | EI24: =_Engine_R50!V168 -> 2.1847492 | EJ24: =_Engine_R50!V169 -> 2.1647217 | EK24: =_Engine_R50!V170 -> 2.144876 | EL24: =_Engine_R50!V171 -> 2.1252103 | EM24: =_Engine_R50!V172 -> 2.1057225 | EN24: =_Engine_R50!V173 -> 2.0864107 | EO24: =_Engine_R50!V174 -> 2.0672731 | EP24: =_Engine_R50!V175 -> 2.0483077 | EQ24: =_Engine_R50!V176 -> 2.0295126 | ER24: =_Engine_R50!V177 -> 2.0108861 | ES24: =_Engine_R50!V178 -> 1.9924263 | ET24: =_Engine_R50!V179 -> 1.9741314 | EU24: =_Engine_R50!V180 -> 1.9559997 | EV24: =_Engine_R50!V181 -> 1.9380294 | EW24: =_Engine_R50!V182 -> 1.9202187 | EX24: =_Engine_R50!V183 -> 1.902566 | EY24: =_Engine_R50!V184 -> 1.8850695 | EZ24: =_Engine_R50!V185 -> 1.8677277 | FA24: =_Engine_R50!V186 -> 1.8505388 | FB24: =_Engine_R50!V187 -> 1.8335012 | FC24: =_Engine_R50!V188 -> 1.8166133 | FD24: =_Engine_R50!V189 -> 1.7998735 | FE24: =_Engine_R50!V190 -> 1.7832803 | FF24: =_Engine_R50!V191 -> 1.7668321 | FG24: =_Engine_R50!V192 -> 1.7505273 | FH24: =_Engine_R50!V193 -> 1.7343644 | FI24: =_Engine_R50!V194 -> 1.7183419 | FJ24: =_Engine_R50!V195 -> 1.7024584 | FK24: =_Engine_R50!V196 -> 1.6867124 | FL24: =_Engine_R50!V197 -> 1.6711024 | FM24: =_Engine_R50!V198 -> 1.6556271 | FN24: =_Engine_R50!V199 -> 1.6402849 | FO24: =_Engine_R50!V200 -> 1.6250745 | FP24: =_Engine_R50!V201 -> 1.6099945 | FQ24: =_Engine_R50!V202 -> 1.5950436 | FR24: =_Engine_R50!V203 -> 1.5802204 | FS24: =_Engine_R50!V204 -> 1.5655235 | FT24: =_Engine_R50!V205 -> 1.5509517 | FU24: =_Engine_R50!V206 -> 1.5365037 | FV24: =_Engine_R50!V207 -> 1.5221781 | FW24: =_Engine_R50!V208 -> 1.5079737 | FX24: =_Engine_R50!V209 -> 1.4938893 | FY24: =_Engine_R50!V210 -> 1.4799235
A25: Total Operating Expenses | B25: =_Engine_R50!W31 -> 0 | C25: =_Engine_R50!W32 -> 0 | D25: =_Engine_R50!W33 -> 0 | E25: =_Engine_R50!W34 -> 2.45 | F25: =_Engine_R50!W35 -> 0 | G25: =_Engine_R50!W36 -> 0 | H25: =_Engine_R50!W37 -> 0 | I25: =_Engine_R50!W38 -> 2.45 | J25: =_Engine_R50!W39 -> 0 | K25: =_Engine_R50!W40 -> 0 | L25: =_Engine_R50!W41 -> 0 | M25: =_Engine_R50!W42 -> 2.45 | N25: =_Engine_R50!W43 -> 0 | O25: =_Engine_R50!W44 -> 0 | P25: =_Engine_R50!W45 -> 0 | Q25: =_Engine_R50!W46 -> 2.45 | R25: =_Engine_R50!W47 -> 0 | S25: =_Engine_R50!W48 -> 0 | T25: =_Engine_R50!W49 -> 0 | U25: =_Engine_R50!W50 -> 0 | V25: =_Engine_R50!W51 -> 0 | W25: =_Engine_R50!W52 -> 0 | X25: =_Engine_R50!W53 -> 0 | Y25: =_Engine_R50!W54 -> 0 | Z25: =_Engine_R50!W55 -> 0 | AA25: =_Engine_R50!W56 -> 0 | AB25: =_Engine_R50!W57 -> 0 | AC25: =_Engine_R50!W58 -> 0 | AD25: =_Engine_R50!W59 -> 0 | AE25: =_Engine_R50!W60 -> 0 | AF25: =_Engine_R50!W61 -> 0 | AG25: =_Engine_R50!W62 -> 2.45 | AH25: =_Engine_R50!W63 -> 0 | AI25: =_Engine_R50!W64 -> 0 | AJ25: =_Engine_R50!W65 -> 0 | AK25: =_Engine_R50!W66 -> 0 | AL25: =_Engine_R50!W67 -> 0 | AM25: =_Engine_R50!W68 -> 0 | AN25: =_Engine_R50!W69 -> 0 | AO25: =_Engine_R50!W70 -> 0 | AP25: =_Engine_R50!W71 -> 0 | AQ25: =_Engine_R50!W72 -> 0 | AR25: =_Engine_R50!W73 -> 0 | AS25: =_Engine_R50!W74 -> 0 | AT25: =_Engine_R50!W75 -> 0 | AU25: =_Engine_R50!W76 -> 0 | AV25: =_Engine_R50!W77 -> 0 | AW25: =_Engine_R50!W78 -> 0 | AX25: =_Engine_R50!W79 -> 0 | AY25: =_Engine_R50!W80 -> 0 | AZ25: =_Engine_R50!W81 -> 0 | BA25: =_Engine_R50!W82 -> 0 | BB25: =_Engine_R50!W83 -> 0 | BC25: =_Engine_R50!W84 -> 0 | BD25: =_Engine_R50!W85 -> 0 | BE25: =_Engine_R50!W86 -> 0 | BF25: =_Engine_R50!W87 -> 0 | BG25: =_Engine_R50!W88 -> 0 | BH25: =_Engine_R50!W89 -> 0 | BI25: =_Engine_R50!W90 -> 0 | BJ25: =_Engine_R50!W91 -> 0 | BK25: =_Engine_R50!W92 -> 0 | BL25: =_Engine_R50!W93 -> 0 | BM25: =_Engine_R50!W94 -> 0 | BN25: =_Engine_R50!W95 -> 0 | BO25: =_Engine_R50!W96 -> 0 | BP25: =_Engine_R50!W97 -> 0 | BQ25: =_Engine_R50!W98 -> 0 | BR25: =_Engine_R50!W99 -> 0 | BS25: =_Engine_R50!W100 -> 0 | BT25: =_Engine_R50!W101 -> 0 | BU25: =_Engine_R50!W102 -> 0 | BV25: =_Engine_R50!W103 -> 0 | BW25: =_Engine_R50!W104 -> 0 | BX25: =_Engine_R50!W105 -> 0 | BY25: =_Engine_R50!W106 -> 0 | BZ25: =_Engine_R50!W107 -> 0 | CA25: =_Engine_R50!W108 -> 0 | CB25: =_Engine_R50!W109 -> 0 | CC25: =_Engine_R50!W110 -> 0 | CD25: =_Engine_R50!W111 -> 0 | CE25: =_Engine_R50!W112 -> 0 | CF25: =_Engine_R50!W113 -> 0 | CG25: =_Engine_R50!W114 -> 0 | CH25: =_Engine_R50!W115 -> 0 | CI25: =_Engine_R50!W116 -> 0 | CJ25: =_Engine_R50!W117 -> 0 | CK25: =_Engine_R50!W118 -> 0 | CL25: =_Engine_R50!W119 -> 0 | CM25: =_Engine_R50!W120 -> 0 | CN25: =_Engine_R50!W121 -> 0 | CO25: =_Engine_R50!W122 -> 0 | CP25: =_Engine_R50!W123 -> 0 | CQ25: =_Engine_R50!W124 -> 0 | CR25: =_Engine_R50!W125 -> 0 | CS25: =_Engine_R50!W126 -> 0 | CT25: =_Engine_R50!W127 -> 0 | CU25: =_Engine_R50!W128 -> 0 | CV25: =_Engine_R50!W129 -> 0 | CW25: =_Engine_R50!W130 -> 0 | CX25: =_Engine_R50!W131 -> 0 | CY25: =_Engine_R50!W132 -> 0 | CZ25: =_Engine_R50!W133 -> 0 | DA25: =_Engine_R50!W134 -> 0 | DB25: =_Engine_R50!W135 -> 0 | DC25: =_Engine_R50!W136 -> 0 | DD25: =_Engine_R50!W137 -> 0 | DE25: =_Engine_R50!W138 -> 0 | DF25: =_Engine_R50!W139 -> 0 | DG25: =_Engine_R50!W140 -> 0 | DH25: =_Engine_R50!W141 -> 0 | DI25: =_Engine_R50!W142 -> 0 | DJ25: =_Engine_R50!W143 -> 0 | DK25: =_Engine_R50!W144 -> 0 | DL25: =_Engine_R50!W145 -> 0 | DM25: =_Engine_R50!W146 -> 0 | DN25: =_Engine_R50!W147 -> 0 | DO25: =_Engine_R50!W148 -> 0 | DP25: =_Engine_R50!W149 -> 0 | DQ25: =_Engine_R50!W150 -> 0 | DR25: =_Engine_R50!W151 -> 0 | DS25: =_Engine_R50!W152 -> 0 | DT25: =_Engine_R50!W153 -> 0 | DU25: =_Engine_R50!W154 -> 0 | DV25: =_Engine_R50!W155 -> 0 | DW25: =_Engine_R50!W156 -> 0 | DX25: =_Engine_R50!W157 -> 0 | DY25: =_Engine_R50!W158 -> 0 | DZ25: =_Engine_R50!W159 -> 0 | EA25: =_Engine_R50!W160 -> 0 | EB25: =_Engine_R50!W161 -> 0 | EC25: =_Engine_R50!W162 -> 0 | ED25: =_Engine_R50!W163 -> 0 | EE25: =_Engine_R50!W164 -> 0 | EF25: =_Engine_R50!W165 -> 0 | EG25: =_Engine_R50!W166 -> 0 | EH25: =_Engine_R50!W167 -> 0 | EI25: =_Engine_R50!W168 -> 0 | EJ25: =_Engine_R50!W169 -> 0 | EK25: =_Engine_R50!W170 -> 0 | EL25: =_Engine_R50!W171 -> 0 | EM25: =_Engine_R50!W172 -> 0 | EN25: =_Engine_R50!W173 -> 0 | EO25: =_Engine_R50!W174 -> 0 | EP25: =_Engine_R50!W175 -> 0 | EQ25: =_Engine_R50!W176 -> 0 | ER25: =_Engine_R50!W177 -> 0 | ES25: =_Engine_R50!W178 -> 0 | ET25: =_Engine_R50!W179 -> 0 | EU25: =_Engine_R50!W180 -> 0 | EV25: =_Engine_R50!W181 -> 0 | EW25: =_Engine_R50!W182 -> 0 | EX25: =_Engine_R50!W183 -> 0 | EY25: =_Engine_R50!W184 -> 0 | EZ25: =_Engine_R50!W185 -> 0 | FA25: =_Engine_R50!W186 -> 0 | FB25: =_Engine_R50!W187 -> 0 | FC25: =_Engine_R50!W188 -> 0 | FD25: =_Engine_R50!W189 -> 0 | FE25: =_Engine_R50!W190 -> 0 | FF25: =_Engine_R50!W191 -> 0 | FG25: =_Engine_R50!W192 -> 0 | FH25: =_Engine_R50!W193 -> 0 | FI25: =_Engine_R50!W194 -> 0 | FJ25: =_Engine_R50!W195 -> 0 | FK25: =_Engine_R50!W196 -> 0 | FL25: =_Engine_R50!W197 -> 0 | FM25: =_Engine_R50!W198 -> 0 | FN25: =_Engine_R50!W199 -> 0 | FO25: =_Engine_R50!W200 -> 0 | FP25: =_Engine_R50!W201 -> 0 | FQ25: =_Engine_R50!W202 -> 0 | FR25: =_Engine_R50!W203 -> 0 | FS25: =_Engine_R50!W204 -> 0 | FT25: =_Engine_R50!W205 -> 0 | FU25: =_Engine_R50!W206 -> 0 | FV25: =_Engine_R50!W207 -> 0 | FW25: =_Engine_R50!W208 -> 0 | FX25: =_Engine_R50!W209 -> 0 | FY25: =_Engine_R50!W210 -> 0
B26: =B24-B25 -> -0.28810582 | C26: =C24-C25 -> -0.28810582 | D26: =D24-D25 -> -0.28810582 | E26: =E24-E25 -> -2.2589392 | F26: =F24-F25 -> 0.3707075 | G26: =G24-G25 -> 0.55038411 | H26: =H24-H25 -> 0.73009053 | I26: =I24-I25 -> -1.0610067 | ... FY26: =FY24-FY25 -> 1.4799235
A27: EBITDA | B27: -0.0813 | C27: -0.0813 | D27: -0.0813 | E27: -0.3385 | F27: -0.1193 | G27: 0.094 | H27: -0.389 | I27: 0.5333 | J27: 0.9563 | K27: 1.3136 | L27: 1.8227 | M27: 2.2907 | N27: 2.6832 | O27: 3.2096 | P27: 3.7212 | Q27: 4.198 | R27: 4.6743 | S27: 5.1369 | T27: 5.4349 | U27: 5.6715 | V27: 5.9006 | W27: 6.1223 | X27: 6.1314 | Y27: 6.1389 | Z27: 6.3006 | AA27: 6.4566 | AB27: 6.6071 | AC27: 6.7522 | AD27: 6.8432 | AE27: 6.9304 | AF27: 7.0799 | AG27: 7.2239 | AH27: 7.3626 | AI27: 7.4961 | AJ27: 7.6245 | AK27: 7.7479 | AL27: 7.8864 | AM27: 8.0196 | AN27: 8.1476 | AO27: 8.2706 | AP27: 8.3885 | AQ27: 8.5017 | AR27: 8.4245 | AS27: 8.3477 | AT27: 8.2712 | AU27: 8.1952 | AV27: 8.1195 | AW27: 1.5668 | AX27: 7.9231 | AY27: 7.8037 | AZ27: 7.6859 | BA27: 7.5696 | BB27: 7.455 | BC27: 7.3418 | BD27: 7.2302 | BE27: 7.1201 | BF27: 7.0115 | BG27: 6.9043 | BH27: 6.7986 | BI27: -2.5255 | BJ27: 6.5914 | BK27: 6.4899 | BL27: 6.3898 | BM27: 6.291 | BN27: 6.1935 | BO27: 6.0974 | BP27: 6.0025 | BQ27: 5.9089 | BR27: 5.8166 | BS27: 5.7255 | BT27: 5.6356 | BU27: -0.5714 | BV27: 5.4595 | BW27: 5.3732 | BX27: 5.2881 | BY27: 5.2041 | BZ27: 5.1213 | CA27: 5.0395 | CB27: 4.9589 | CC27: 4.8794 | CD27: 4.8009 | CE27: 4.7235 | CF27: 4.6471 | CG27: 1.0895 | CH27: 4.4974 | CI27: 4.424 | CJ27: 4.3517 | CK27: 4.2803 | CL27: 4.2099 | CM27: 4.1404 | CN27: 4.0719 | CO27: 4.0043 | CP27: 3.9375 | CQ27: 3.8717 | CR27: 3.8068 | CS27: 2.5013 | CT27: 3.6796 | CU27: 3.6172 | CV27: 3.5557 | CW27: 3.4951 | CX27: 3.4352 | CY27: 3.3761 | CZ27: 3.3179 | DA27: 3.2604 | DB27: 3.2037 | DC27: 3.1478 | DD27: 3.0926 | DE27: 3.0381 | DF27: 2.9844 | DG27: 2.9314 | DH27: 2.8792 | DI27: 2.8276 | DJ27: 2.7767 | DK27: 2.7265 | DL27: 2.677 | DM27: 2.6281 | DN27: 2.58 | DO27: 2.5324 | DP27: 2.4855 | DQ27: 2.4392 | DR27: 2.3936 | DS27: 2.3485 | DT27: 2.3041 | DU27: 2.2603 | DV27: 2.217 | DW27: 2.1743 | DX27: 2.1322 | DY27: 2.0907 | DZ27: 2.0498 | EA27: 2.0093 | EB27: 1.9695 | EC27: 1.9301 | ED27: 1.8913 | EE27: 1.853 | EF27: 1.8153 | EG27: 1.778 | EH27: 1.7413 | EI27: 1.705 | EJ27: 1.6692 | EK27: 1.6339 | EL27: 1.5991 | EM27: 1.5647 | EN27: 1.5308 | EO27: 1.4974 | EP27: 1.4644 | EQ27: 1.4319 | ER27: 1.3998 | ES27: 1.3681 | ET27: 1.3369 | EU27: 1.306 | EV27: 1.2756 | EW27: 1.2456 | EX27: 1.216 | EY27: 1.1868 | EZ27: 1.158 | FA27: 1.1296 | FB27: 1.1016 | FC27: 1.0739 | FD27: 1.0466 | FE27: 1.0197 | FF27: 0.9931 | FG27: 0.9669 | FH27: 0.9411 | FI27: 0.9156 | FJ27: 0.8904 | FK27: 0.8656 | FL27: 0.8411 | FM27: 0.817 | FN27: 0.7931 | FO27: 0.7696 | FP27: 0.7464 | FQ27: 0.7235 | FR27: 0.701 | FS27: 0.6787 | FT27: 0.6567 | FU27: 0.635 | FV27: 0.6137 | FW27: 0.5926 | FX27: 0.5717 | FY27: 0.5512
A28: Severance (Press 50%) | B28: =_Engine_R50!C31 -> 0.25 | C28: =_Engine_R50!C32 -> 0.25 | D28: =_Engine_R50!C33 -> 0.25 | E28: =_Engine_R50!C34 -> 0.25 | F28: =_Engine_R50!C35 -> 0.25 | G28: =_Engine_R50!C36 -> 0.25 | H28: =_Engine_R50!C37 -> 0.25 | I28: =_Engine_R50!C38 -> 0.25 | J28: =_Engine_R50!C39 -> 0.25 | K28: =_Engine_R50!C40 -> 0.25 | L28: =_Engine_R50!C41 -> 0.25 | M28: =_Engine_R50!C42 -> 0.25 | N28: =_Engine_R50!C43 -> 0.25 | O28: =_Engine_R50!C44 -> 0.25 | P28: =_Engine_R50!C45 -> 0.25 | Q28: =_Engine_R50!C46 -> 0.25 | R28: =_Engine_R50!C47 -> 0.25 | S28: =_Engine_R50!C48 -> 0.25 | T28: =_Engine_R50!C49 -> 0 | U28: =_Engine_R50!C50 -> 0 | V28: =_Engine_R50!C51 -> 0 | W28: =_Engine_R50!C52 -> 0 | X28: =_Engine_R50!C53 -> 0 | Y28: =_Engine_R50!C54 -> 0 | Z28: =_Engine_R50!C55 -> 0 | AA28: =_Engine_R50!C56 -> 0 | AB28: =_Engine_R50!C57 -> 0 | AC28: =_Engine_R50!C58 -> 0 | AD28: =_Engine_R50!C59 -> 0 | AE28: =_Engine_R50!C60 -> 0 | AF28: =_Engine_R50!C61 -> 0 | AG28: =_Engine_R50!C62 -> 0 | AH28: =_Engine_R50!C63 -> 0 | AI28: =_Engine_R50!C64 -> 0 | AJ28: =_Engine_R50!C65 -> 0 | AK28: =_Engine_R50!C66 -> 0 | AL28: =_Engine_R50!C67 -> 0 | AM28: =_Engine_R50!C68 -> 0 | AN28: =_Engine_R50!C69 -> 0 | AO28: =_Engine_R50!C70 -> 0 | AP28: =_Engine_R50!C71 -> 0 | AQ28: =_Engine_R50!C72 -> 0 | AR28: =_Engine_R50!C73 -> 0 | AS28: =_Engine_R50!C74 -> 0 | AT28: =_Engine_R50!C75 -> 0 | AU28: =_Engine_R50!C76 -> 0 | AV28: =_Engine_R50!C77 -> 0 | AW28: =_Engine_R50!C78 -> 0 | AX28: =_Engine_R50!C79 -> 0 | AY28: =_Engine_R50!C80 -> 0 | AZ28: =_Engine_R50!C81 -> 0 | BA28: =_Engine_R50!C82 -> 0 | BB28: =_Engine_R50!C83 -> 0 | BC28: =_Engine_R50!C84 -> 0 | BD28: =_Engine_R50!C85 -> 0 | BE28: =_Engine_R50!C86 -> 0 | BF28: =_Engine_R50!C87 -> 0 | BG28: =_Engine_R50!C88 -> 0 | BH28: =_Engine_R50!C89 -> 0 | BI28: =_Engine_R50!C90 -> 0 | BJ28: =_Engine_R50!C91 -> 0 | BK28: =_Engine_R50!C92 -> 0 | BL28: =_Engine_R50!C93 -> 0 | BM28: =_Engine_R50!C94 -> 0 | BN28: =_Engine_R50!C95 -> 0 | BO28: =_Engine_R50!C96 -> 0 | BP28: =_Engine_R50!C97 -> 0 | BQ28: =_Engine_R50!C98 -> 0 | BR28: =_Engine_R50!C99 -> 0 | BS28: =_Engine_R50!C100 -> 0 | BT28: =_Engine_R50!C101 -> 0 | BU28: =_Engine_R50!C102 -> 0 | BV28: =_Engine_R50!C103 -> 0 | BW28: =_Engine_R50!C104 -> 0 | BX28: =_Engine_R50!C105 -> 0 | BY28: =_Engine_R50!C106 -> 0 | BZ28: =_Engine_R50!C107 -> 0 | CA28: =_Engine_R50!C108 -> 0 | CB28: =_Engine_R50!C109 -> 0 | CC28: =_Engine_R50!C110 -> 0 | CD28: =_Engine_R50!C111 -> 0 | CE28: =_Engine_R50!C112 -> 0 | CF28: =_Engine_R50!C113 -> 0 | CG28: =_Engine_R50!C114 -> 0 | CH28: =_Engine_R50!C115 -> 0 | CI28: =_Engine_R50!C116 -> 0 | CJ28: =_Engine_R50!C117 -> 0 | CK28: =_Engine_R50!C118 -> 0 | CL28: =_Engine_R50!C119 -> 0 | CM28: =_Engine_R50!C120 -> 0 | CN28: =_Engine_R50!C121 -> 0 | CO28: =_Engine_R50!C122 -> 0 | CP28: =_Engine_R50!C123 -> 0 | CQ28: =_Engine_R50!C124 -> 0 | CR28: =_Engine_R50!C125 -> 0 | CS28: =_Engine_R50!C126 -> 0 | CT28: =_Engine_R50!C127 -> 0 | CU28: =_Engine_R50!C128 -> 0 | CV28: =_Engine_R50!C129 -> 0 | CW28: =_Engine_R50!C130 -> 0 | CX28: =_Engine_R50!C131 -> 0 | CY28: =_Engine_R50!C132 -> 0 | CZ28: =_Engine_R50!C133 -> 0 | DA28: =_Engine_R50!C134 -> 0 | DB28: =_Engine_R50!C135 -> 0 | DC28: =_Engine_R50!C136 -> 0 | DD28: =_Engine_R50!C137 -> 0 | DE28: =_Engine_R50!C138 -> 0 | DF28: =_Engine_R50!C139 -> 0 | DG28: =_Engine_R50!C140 -> 0 | DH28: =_Engine_R50!C141 -> 0 | DI28: =_Engine_R50!C142 -> 0 | DJ28: =_Engine_R50!C143 -> 0 | DK28: =_Engine_R50!C144 -> 0 | DL28: =_Engine_R50!C145 -> 0 | DM28: =_Engine_R50!C146 -> 0 | DN28: =_Engine_R50!C147 -> 0 | DO28: =_Engine_R50!C148 -> 0 | DP28: =_Engine_R50!C149 -> 0 | DQ28: =_Engine_R50!C150 -> 0 | DR28: =_Engine_R50!C151 -> 0 | DS28: =_Engine_R50!C152 -> 0 | DT28: =_Engine_R50!C153 -> 0 | DU28: =_Engine_R50!C154 -> 0 | DV28: =_Engine_R50!C155 -> 0 | DW28: =_Engine_R50!C156 -> 0 | DX28: =_Engine_R50!C157 -> 0 | DY28: =_Engine_R50!C158 -> 0 | DZ28: =_Engine_R50!C159 -> 0 | EA28: =_Engine_R50!C160 -> 0 | EB28: =_Engine_R50!C161 -> 0 | EC28: =_Engine_R50!C162 -> 0 | ED28: =_Engine_R50!C163 -> 0 | EE28: =_Engine_R50!C164 -> 0 | EF28: =_Engine_R50!C165 -> 0 | EG28: =_Engine_R50!C166 -> 0 | EH28: =_Engine_R50!C167 -> 0 | EI28: =_Engine_R50!C168 -> 0 | EJ28: =_Engine_R50!C169 -> 0 | EK28: =_Engine_R50!C170 -> 0 | EL28: =_Engine_R50!C171 -> 0 | EM28: =_Engine_R50!C172 -> 0 | EN28: =_Engine_R50!C173 -> 0 | EO28: =_Engine_R50!C174 -> 0 | EP28: =_Engine_R50!C175 -> 0 | EQ28: =_Engine_R50!C176 -> 0 | ER28: =_Engine_R50!C177 -> 0 | ES28: =_Engine_R50!C178 -> 0 | ET28: =_Engine_R50!C179 -> 0 | EU28: =_Engine_R50!C180 -> 0 | EV28: =_Engine_R50!C181 -> 0 | EW28: =_Engine_R50!C182 -> 0 | EX28: =_Engine_R50!C183 -> 0 | EY28: =_Engine_R50!C184 -> 0 | EZ28: =_Engine_R50!C185 -> 0 | FA28: =_Engine_R50!C186 -> 0 | FB28: =_Engine_R50!C187 -> 0 | FC28: =_Engine_R50!C188 -> 0 | FD28: =_Engine_R50!C189 -> 0 | FE28: =_Engine_R50!C190 -> 0 | FF28: =_Engine_R50!C191 -> 0 | FG28: =_Engine_R50!C192 -> 0 | FH28: =_Engine_R50!C193 -> 0 | FI28: =_Engine_R50!C194 -> 0 | FJ28: =_Engine_R50!C195 -> 0 | FK28: =_Engine_R50!C196 -> 0 | FL28: =_Engine_R50!C197 -> 0 | FM28: =_Engine_R50!C198 -> 0 | FN28: =_Engine_R50!C199 -> 0 | FO28: =_Engine_R50!C200 -> 0 | FP28: =_Engine_R50!C201 -> 0 | FQ28: =_Engine_R50!C202 -> 0 | FR28: =_Engine_R50!C203 -> 0 | FS28: =_Engine_R50!C204 -> 0 | FT28: =_Engine_R50!C205 -> 0 | FU28: =_Engine_R50!C206 -> 0 | FV28: =_Engine_R50!C207 -> 0 | FW28: =_Engine_R50!C208 -> 0 | FX28: =_Engine_R50!C209 -> 0 | FY28: =_Engine_R50!C210 -> 0
A29: Operating Income | B29: =_Engine_R50!Z31 -> -0.53810583 | C29: =_Engine_R50!Z32 -> -0.53810583 | D29: =_Engine_R50!Z33 -> -0.53810583 | E29: =_Engine_R50!Z34 -> -2.5089392 | F29: =_Engine_R50!Z35 -> 0.060353752 | G29: =_Engine_R50!Z36 -> 0.15019205 | H29: =_Engine_R50!Z37 -> 0.24004527 | I29: =_Engine_R50!Z38 -> -1.3110067 | J29: =_Engine_R50!Z39 -> 0.7455192 | K29: =_Engine_R50!Z40 -> 0.8347675 | L29: =_Engine_R50!Z41 -> 0.92409279 | M29: =_Engine_R50!Z42 -> 0.028077795 | N29: =_Engine_R50!Z43 -> 1.2523498 | O29: =_Engine_R50!Z44 -> 1.337463 | P29: =_Engine_R50!Z45 -> 1.4227977 | Q29: =_Engine_R50!Z46 -> 0.52293466 | R29: =_Engine_R50!Z47 -> 1.9159682 | S29: =_Engine_R50!Z48 -> 1.9975127 | T29: =_Engine_R50!Z49 -> 2.2044155 | U29: =_Engine_R50!Z50 -> 2.2866722 | V29: =_Engine_R50!Z51 -> 2.3692785 | W29: =_Engine_R50!Z52 -> 2.3653782 | X29: =_Engine_R50!Z53 -> 2.3618189 | Y29: =_Engine_R50!Z54 -> 2.3585965 | Z29: =_Engine_R50!Z55 -> 2.3540201 | AA29: =_Engine_R50!Z56 -> 2.3514589 | AB29: =_Engine_R50!Z57 -> 2.3492222 | AC29: =_Engine_R50!Z58 -> 2.3408246 | AD29: =_Engine_R50!Z59 -> 2.3327437 | AE29: =_Engine_R50!Z60 -> 2.3249754 | AF29: =_Engine_R50!Z61 -> 2.3175161 | AG29: =_Engine_R50!Z62 -> 1.0880471 | AH29: =_Engine_R50!Z63 -> 12.65668 | AI29: =_Engine_R50!Z64 -> 4.9365984 | AJ29: =_Engine_R50!Z65 -> 5.0927686 | AK29: =_Engine_R50!Z66 -> 5.2365781 | AL29: =_Engine_R50!Z67 -> 5.3809827 | AM29: =_Engine_R50!Z68 -> 5.3522716 | AN29: =_Engine_R50!Z69 -> 5.3241414 | AO29: =_Engine_R50!Z70 -> 5.2836224 | AP29: =_Engine_R50!Z71 -> 5.2436706 | AQ29: =_Engine_R50!Z72 -> 5.2042793 | AR29: =_Engine_R50!Z73 -> 5.1654417 | AS29: =_Engine_R50!Z74 -> 5.1271514 | AT29: =_Engine_R50!Z75 -> 5.0894019 | AU29: =_Engine_R50!Z76 -> 5.0521866 | AV29: =_Engine_R50!Z77 -> 5.0154993 | AW29: =_Engine_R50!Z78 -> 4.9793338 | AX29: =_Engine_R50!Z79 -> 4.9436837 | AY29: =_Engine_R50!Z80 -> 4.9085432 | AZ29: =_Engine_R50!Z81 -> 4.873906 | BA29: =_Engine_R50!Z82 -> 4.8397663 | BB29: =_Engine_R50!Z83 -> 4.8061183 | BC29: =_Engine_R50!Z84 -> 4.772956 | BD29: =_Engine_R50!Z85 -> 4.7402738 | BE29: =_Engine_R50!Z86 -> 4.695103 | BF29: =_Engine_R50!Z87 -> 4.6504011 | BG29: =_Engine_R50!Z88 -> 4.6061625 | BH29: =_Engine_R50!Z89 -> 4.5623818 | BI29: =_Engine_R50!Z90 -> 4.5190536 | BJ29: =_Engine_R50!Z91 -> 4.4761726 | BK29: =_Engine_R50!Z92 -> 4.4337335 | BL29: =_Engine_R50!Z93 -> 4.3917312 | BM29: =_Engine_R50!Z94 -> 4.3501606 | BN29: =_Engine_R50!Z95 -> 4.3090165 | BO29: =_Engine_R50!Z96 -> 4.2682941 | BP29: =_Engine_R50!Z97 -> 4.2279884 | BQ29: =_Engine_R50!Z98 -> 4.1880945 | BR29: =_Engine_R50!Z99 -> 4.1486076 | BS29: =_Engine_R50!Z100 -> 4.1095231 | BT29: =_Engine_R50!Z101 -> 4.0708361 | BU29: =_Engine_R50!Z102 -> 4.0325422 | BV29: =_Engine_R50!Z103 -> 3.9946366 | BW29: =_Engine_R50!Z104 -> 3.957115 | BX29: =_Engine_R50!Z105 -> 3.9199728 | BY29: =_Engine_R50!Z106 -> 3.8832057 | BZ29: =_Engine_R50!Z107 -> 3.8468093 | CA29: =_Engine_R50!Z108 -> 3.8107793 | CB29: =_Engine_R50!Z109 -> 3.7751115 | CC29: =_Engine_R50!Z110 -> 3.7398017 | CD29: =_Engine_R50!Z111 -> 3.7048458 | CE29: =_Engine_R50!Z112 -> 3.6702396 | CF29: =_Engine_R50!Z113 -> 3.6359792 | CG29: =_Engine_R50!Z114 -> 3.6020606 | CH29: =_Engine_R50!Z115 -> 3.5684798 | CI29: =_Engine_R50!Z116 -> 3.535233 | CJ29: =_Engine_R50!Z117 -> 3.5023164 | CK29: =_Engine_R50!Z118 -> 3.469726 | CL29: =_Engine_R50!Z119 -> 3.4374583 | CM29: =_Engine_R50!Z120 -> 3.4055095 | CN29: =_Engine_R50!Z121 -> 3.3738759 | CO29: =_Engine_R50!Z122 -> 3.342554 | CP29: =_Engine_R50!Z123 -> 3.3115402 | CQ29: =_Engine_R50!Z124 -> 3.280831 | CR29: =_Engine_R50!Z125 -> 3.2504228 | CS29: =_Engine_R50!Z126 -> 3.2203124 | CT29: =_Engine_R50!Z127 -> 3.1904962 | CU29: =_Engine_R50!Z128 -> 3.160971 | CV29: =_Engine_R50!Z129 -> 3.1317335 | CW29: =_Engine_R50!Z130 -> 3.1027803 | CX29: =_Engine_R50!Z131 -> 3.0741083 | CY29: =_Engine_R50!Z132 -> 3.0457142 | CZ29: =_Engine_R50!Z133 -> 3.017595 | DA29: =_Engine_R50!Z134 -> 2.9897475 | DB29: =_Engine_R50!Z135 -> 2.9621687 | DC29: =_Engine_R50!Z136 -> 2.9348555 | DD29: =_Engine_R50!Z137 -> 2.9078049 | DE29: =_Engine_R50!Z138 -> 2.881014 | DF29: =_Engine_R50!Z139 -> 2.8544799 | DG29: =_Engine_R50!Z140 -> 2.8281996 | DH29: =_Engine_R50!Z141 -> 2.8021704 | DI29: =_Engine_R50!Z142 -> 2.7763893 | DJ29: =_Engine_R50!Z143 -> 2.7508537 | DK29: =_Engine_R50!Z144 -> 2.7255608 | DL29: =_Engine_R50!Z145 -> 2.7005078 | DM29: =_Engine_R50!Z146 -> 2.6756921 | DN29: =_Engine_R50!Z147 -> 2.6511111 | DO29: =_Engine_R50!Z148 -> 2.6267621 | DP29: =_Engine_R50!Z149 -> 2.6026425 | DQ29: =_Engine_R50!Z150 -> 2.5787498 | DR29: =_Engine_R50!Z151 -> 2.5550815 | DS29: =_Engine_R50!Z152 -> 2.5316351 | DT29: =_Engine_R50!Z153 -> 2.5084081 | DU29: =_Engine_R50!Z154 -> 2.4853981 | DV29: =_Engine_R50!Z155 -> 2.4626026 | DW29: =_Engine_R50!Z156 -> 2.4400194 | DX29: =_Engine_R50!Z157 -> 2.4176461 | DY29: =_Engine_R50!Z158 -> 2.3954803 | DZ29: =_Engine_R50!Z159 -> 2.3735199 | EA29: =_Engine_R50!Z160 -> 2.3517624 | EB29: =_Engine_R50!Z161 -> 2.3302057 | EC29: =_Engine_R50!Z162 -> 2.3088476 | ED29: =_Engine_R50!Z163 -> 2.2876859 | EE29: =_Engine_R50!Z164 -> 2.2667185 | EF29: =_Engine_R50!Z165 -> 2.2459432 | EG29: =_Engine_R50!Z166 -> 2.2253579 | EH29: =_Engine_R50!Z167 -> 2.2049606 | EI29: =_Engine_R50!Z168 -> 2.1847492 | EJ29: =_Engine_R50!Z169 -> 2.1647217 | EK29: =_Engine_R50!Z170 -> 2.144876 | EL29: =_Engine_R50!Z171 -> 2.1252103 | EM29: =_Engine_R50!Z172 -> 2.1057225 | EN29: =_Engine_R50!Z173 -> 2.0864107 | EO29: =_Engine_R50!Z174 -> 2.0672731 | EP29: =_Engine_R50!Z175 -> 2.0483077 | EQ29: =_Engine_R50!Z176 -> 2.0295126 | ER29: =_Engine_R50!Z177 -> 2.0108861 | ES29: =_Engine_R50!Z178 -> 1.9924263 | ET29: =_Engine_R50!Z179 -> 1.9741314 | EU29: =_Engine_R50!Z180 -> 1.9559997 | EV29: =_Engine_R50!Z181 -> 1.9380294 | EW29: =_Engine_R50!Z182 -> 1.9202187 | EX29: =_Engine_R50!Z183 -> 1.902566 | EY29: =_Engine_R50!Z184 -> 1.8850695 | EZ29: =_Engine_R50!Z185 -> 1.8677277 | FA29: =_Engine_R50!Z186 -> 1.8505388 | FB29: =_Engine_R50!Z187 -> 1.8335012 | FC29: =_Engine_R50!Z188 -> 1.8166133 | FD29: =_Engine_R50!Z189 -> 1.7998735 | FE29: =_Engine_R50!Z190 -> 1.7832803 | FF29: =_Engine_R50!Z191 -> 1.7668321 | FG29: =_Engine_R50!Z192 -> 1.7505273 | FH29: =_Engine_R50!Z193 -> 1.7343644 | FI29: =_Engine_R50!Z194 -> 1.7183419 | FJ29: =_Engine_R50!Z195 -> 1.7024584 | FK29: =_Engine_R50!Z196 -> 1.6867124 | FL29: =_Engine_R50!Z197 -> 1.6711024 | FM29: =_Engine_R50!Z198 -> 1.6556271 | FN29: =_Engine_R50!Z199 -> 1.6402849 | FO29: =_Engine_R50!Z200 -> 1.6250745 | FP29: =_Engine_R50!Z201 -> 1.6099945 | FQ29: =_Engine_R50!Z202 -> 1.5950436 | FR29: =_Engine_R50!Z203 -> 1.5802204 | FS29: =_Engine_R50!Z204 -> 1.5655235 | FT29: =_Engine_R50!Z205 -> 1.5509517 | FU29: =_Engine_R50!Z206 -> 1.5365037 | FV29: =_Engine_R50!Z207 -> 1.5221781 | FW29: =_Engine_R50!Z208 -> 1.5079737 | FX29: =_Engine_R50!Z209 -> 1.4938893 | FY29: =_Engine_R50!Z210 -> 1.4799235
A31: Management Fee | B31: 0.25 | C31: 0.25 | D31: 0.25 | E31: 0.25 | F31: 0.25 | G31: 0.25 | H31: 0.25 | I31: 0.25 | J31: 0.25 | K31: 0.25 | L31: 0.25 | M31: 0.25 | N31: 0 | O31: 0 | P31: 0 | Q31: 0 | R31: 0 | S31: 0 | T31: 0 | U31: 0 | V31: 0 | W31: 0 | X31: 0 | Y31: 0 | Z31: 0 | AA31: 0 | AB31: 0 | AC31: 0 | AD31: 0 | AE31: 0 | AF31: 0 | AG31: 0 | AH31: 0 | AI31: 0 | AJ31: 0 | AK31: 0 | AL31: 0 | AM31: 0 | AN31: 0 | AO31: 0 | AP31: 0 | AQ31: 0 | AR31: 0 | AS31: 0 | AT31: 0 | AU31: 0 | AV31: 0 | AW31: 0 | AX31: 0 | AY31: 0 | AZ31: 0 | BA31: 0 | BB31: 0 | BC31: 0 | BD31: 0 | BE31: 0 | BF31: 0 | BG31: 0 | BH31: 0 | BI31: 0 | BJ31: 0 | BK31: 0 | BL31: 0 | BM31: 0 | BN31: 0 | BO31: 0 | BP31: 0 | BQ31: 0 | BR31: 0 | BS31: 0 | BT31: 0 | BU31: 0 | BV31: 0 | BW31: 0 | BX31: 0 | BY31: 0 | BZ31: 0 | CA31: 0 | CB31: 0 | CC31: 0 | CD31: 0 | CE31: 0 | CF31: 0 | CG31: 0 | CH31: 0 | CI31: 0 | CJ31: 0 | CK31: 0 | CL31: 0 | CM31: 0 | CN31: 0 | CO31: 0 | CP31: 0 | CQ31: 0 | CR31: 0 | CS31: 0 | CT31: 0 | CU31: 0 | CV31: 0 | CW31: 0 | CX31: 0 | CY31: 0 | CZ31: 0 | DA31: 0 | DB31: 0 | DC31: 0 | DD31: 0 | DE31: 0 | DF31: 0 | DG31: 0 | DH31: 0 | DI31: 0 | DJ31: 0 | DK31: 0 | DL31: 0 | DM31: 0 | DN31: 0 | DO31: 0 | DP31: 0 | DQ31: 0 | DR31: 0 | DS31: 0 | DT31: 0 | DU31: 0 | DV31: 0 | DW31: 0 | DX31: 0 | DY31: 0 | DZ31: 0 | EA31: 0 | EB31: 0 | EC31: 0 | ED31: 0 | EE31: 0 | EF31: 0 | EG31: 0 | EH31: 0 | EI31: 0 | EJ31: 0 | EK31: 0 | EL31: 0 | EM31: 0 | EN31: 0 | EO31: 0 | EP31: 0 | EQ31: 0 | ER31: 0 | ES31: 0 | ET31: 0 | EU31: 0 | EV31: 0 | EW31: 0 | EX31: 0 | EY31: 0 | EZ31: 0 | FA31: 0 | FB31: 0 | FC31: 0 | FD31: 0 | FE31: 0 | FF31: 0 | FG31: 0 | FH31: 0 | FI31: 0 | FJ31: 0 | FK31: 0 | FL31: 0 | FM31: 0 | FN31: 0 | FO31: 0 | FP31: 0 | FQ31: 0 | FR31: 0 | FS31: 0 | FT31: 0 | FU31: 0 | FV31: 0 | FW31: 0 | FX31: 0 | FY31: 0
A32: Retained (50%) | B32: -0.1656 | C32: -0.1656 | D32: -0.1656 | E32: -1.0328 | F32: -0.1847 | G32: -0.078 | H32: -1.1042 | I32: 0.1416 | J32: 0.3531 | K32: -0.3366 | L32: 0.7863 | M32: 0.2702 | N32: 1.3416 | O32: 1.6048 | P32: 1.8606 | Q32: 1.3662 | R32: 2.3372 | S32: 2.5684 | T32: 2.7174 | U32: 2.8357 | V32: 2.9503 | W32: 3.0612 | X32: 3.0657 | Y32: 2.3771 | Z32: 3.1503 | AA32: 3.2283 | AB32: 3.3035 | AC32: 3.3761 | AD32: 3.4216 | AE32: 2.7728 | AF32: 3.5399 | AG32: 3.612 | AH32: 3.6813 | AI32: 3.7481 | AJ32: 3.8123 | AK32: 3.1816 | AL32: 0 | AM32: 0 | AN32: 0 | AO32: 0 | AP32: 0 | AQ32: 0 | AR32: 0 | AS32: 0 | AT32: 0 | AU32: 0 | AV32: 0 | AW32: 0 | AX32: 0 | AY32: 0 | AZ32: 0 | BA32: 0 | BB32: 0 | BC32: 0 | BD32: 0 | BE32: 0 | BF32: 0 | BG32: 0 | BH32: 0 | BI32: 0 | BJ32: 0 | BK32: 0 | BL32: 0 | BM32: 0 | BN32: 0 | BO32: 0 | BP32: 0 | BQ32: 0 | BR32: 0 | BS32: 0 | BT32: 0 | BU32: 0 | BV32: 0 | BW32: 0 | BX32: 0 | BY32: 0 | BZ32: 0 | CA32: 0 | CB32: 0 | CC32: 0 | CD32: 0 | CE32: 0 | CF32: 0 | CG32: 0 | CH32: 0 | CI32: 0 | CJ32: 0 | CK32: 0 | CL32: 0 | CM32: 0 | CN32: 0 | CO32: 0 | CP32: 0 | CQ32: 0 | CR32: 0 | CS32: 0 | CT32: 0 | CU32: 0 | CV32: 0 | CW32: 0 | CX32: 0 | CY32: 0 | CZ32: 0 | DA32: 0 | DB32: 0 | DC32: 0 | DD32: 0 | DE32: 0 | DF32: 0 | DG32: 0 | DH32: 0 | DI32: 0 | DJ32: 0 | DK32: 0 | DL32: 0 | DM32: 0 | DN32: 0 | DO32: 0 | DP32: 0 | DQ32: 0 | DR32: 0 | DS32: 0 | DT32: 0 | DU32: 0 | DV32: 0 | DW32: 0 | DX32: 0 | DY32: 0 | DZ32: 0 | EA32: 0 | EB32: 0 | EC32: 0 | ED32: 0 | EE32: 0 | EF32: 0 | EG32: 0 | EH32: 0 | EI32: 0 | EJ32: 0 | EK32: 0 | EL32: 0 | EM32: 0 | EN32: 0 | EO32: 0 | EP32: 0 | EQ32: 0 | ER32: 0 | ES32: 0 | ET32: 0 | EU32: 0 | EV32: 0 | EW32: 0 | EX32: 0 | EY32: 0 | EZ32: 0 | FA32: 0 | FB32: 0 | FC32: 0 | FD32: 0 | FE32: 0 | FF32: 0 | FG32: 0 | FH32: 0 | FI32: 0 | FJ32: 0 | FK32: 0 | FL32: 0 | FM32: 0 | FN32: 0 | FO32: 0 | FP32: 0 | FQ32: 0 | FR32: 0 | FS32: 0 | FT32: 0 | FU32: 0 | FV32: 0 | FW32: 0 | FX32: 0 | FY32: 0
A33: Distributable Cash | B33: -0.1656 | C33: -0.1656 | D33: -0.1656 | E33: -1.0328 | F33: -0.1847 | G33: -0.078 | H33: -1.1042 | I33: 0.1416 | J33: 0.3531 | K33: -0.3366 | L33: 0.7863 | M33: 0.2702 | N33: 1.3416 | O33: 1.6048 | P33: 1.8606 | Q33: 1.3662 | R33: 2.3372 | S33: 2.5684 | T33: 2.7174 | U33: 2.8357 | V33: 2.9503 | W33: 3.0612 | X33: 3.0657 | Y33: 2.3771 | Z33: 3.1503 | AA33: 3.2283 | AB33: 3.3035 | AC33: 3.3761 | AD33: 3.4216 | AE33: 2.7728 | AF33: 3.5399 | AG33: 3.612 | AH33: 3.6813 | AI33: 3.7481 | AJ33: 3.8123 | AK33: 3.1816 | AL33: 7.8864 | AM33: 8.0196 | AN33: 8.1476 | AO33: 8.2706 | AP33: 8.3885 | AQ33: 8.5017 | AR33: 8.4245 | AS33: 8.3477 | AT33: 8.2712 | AU33: 8.1952 | AV33: 8.1195 | AW33: 1.5668 | AX33: 7.9231 | AY33: 7.8037 | AZ33: 7.6859 | BA33: 7.5696 | BB33: 7.455 | BC33: 7.3418 | BD33: 7.2302 | BE33: 7.1201 | BF33: 7.0115 | BG33: 6.9043 | BH33: 6.7986 | BI33: -2.5255 | BJ33: 6.5914 | BK33: 6.4899 | BL33: 6.3898 | BM33: 6.291 | BN33: 6.1935 | BO33: 6.0974 | BP33: 6.0025 | BQ33: 5.9089 | BR33: 5.8166 | BS33: 5.7255 | BT33: 5.6356 | BU33: -0.5714 | BV33: 5.4595 | BW33: 5.3732 | BX33: 5.2881 | BY33: 5.2041 | BZ33: 5.1213 | CA33: 5.0395 | CB33: 4.9589 | CC33: 4.8794 | CD33: 4.8009 | CE33: 4.7235 | CF33: 4.6471 | CG33: 1.0895 | CH33: 4.4974 | CI33: 4.424 | CJ33: 4.3517 | CK33: 4.2803 | CL33: 4.2099 | CM33: 4.1404 | CN33: 4.0719 | CO33: 4.0043 | CP33: 3.9375 | CQ33: 3.8717 | CR33: 3.8068 | CS33: 2.5013 | CT33: 3.6796 | CU33: 3.6172 | CV33: 3.5557 | CW33: 3.4951 | CX33: 3.4352 | CY33: 3.3761 | CZ33: 3.3179 | DA33: 3.2604 | DB33: 3.2037 | DC33: 3.1478 | DD33: 3.0926 | DE33: 3.0381 | DF33: 2.9844 | DG33: 2.9314 | DH33: 2.8792 | DI33: 2.8276 | DJ33: 2.7767 | DK33: 2.7265 | DL33: 2.677 | DM33: 2.6281 | DN33: 2.58 | DO33: 2.5324 | DP33: 2.4855 | DQ33: 2.4392 | DR33: 2.3936 | DS33: 2.3485 | DT33: 2.3041 | DU33: 2.2603 | DV33: 2.217 | DW33: 2.1743 | DX33: 2.1322 | DY33: 2.0907 | DZ33: 2.0498 | EA33: 2.0093 | EB33: 1.9695 | EC33: 1.9301 | ED33: 1.8913 | EE33: 1.853 | EF33: 1.8153 | EG33: 1.778 | EH33: 1.7413 | EI33: 1.705 | EJ33: 1.6692 | EK33: 1.6339 | EL33: 1.5991 | EM33: 1.5647 | EN33: 1.5308 | EO33: 1.4974 | EP33: 1.4644 | EQ33: 1.4319 | ER33: 1.3998 | ES33: 1.3681 | ET33: 1.3369 | EU33: 1.306 | EV33: 1.2756 | EW33: 1.2456 | EX33: 1.216 | EY33: 1.1868 | EZ33: 1.158 | FA33: 1.1296 | FB33: 1.1016 | FC33: 1.0739 | FD33: 1.0466 | FE33: 1.0197 | FF33: 0.9931 | FG33: 0.9669 | FH33: 0.9411 | FI33: 0.9156 | FJ33: 0.8904 | FK33: 0.8656 | FL33: 0.8411 | FM33: 0.817 | FN33: 0.7931 | FO33: 0.7696 | FP33: 0.7464 | FQ33: 0.7235 | FR33: 0.701 | FS33: 0.6787 | FT33: 0.6567 | FU33: 0.635 | FV33: 0.6137 | FW33: 0.5926 | FX33: 0.5717 | FY33: 0.5512
A34: Cumulative Distributable | B34: -0.1656 | C34: -0.3312 | D34: -0.4969 | E34: -1.5297 | F34: -1.7144 | G34: -1.7923 | H34: -2.8966 | I34: -2.7549 | J34: -2.4018 | K34: -2.7384 | L34: -1.9521 | M34: -1.6818 | N34: -0.3403 | O34: 1.2645 | P34: 3.1252 | Q34: 4.4914 | R34: 6.8285 | S34: 9.397 | T34: 12.1144 | U34: 14.9502 | V34: 17.9004 | W34: 20.9616 | X34: 24.0273 | Y34: 26.4044 | Z34: 29.5547 | AA34: 32.783 | AB34: 36.0865 | AC34: 39.4626 | AD34: 42.8842 | AE34: 45.657 | AF34: 49.1969 | AG34: 52.8089 | AH34: 56.4902 | AI34: 60.2383 | AJ34: 64.0505 | AK34: 67.2321 | AL34: 75.1185 | AM34: 83.1381 | AN34: 91.2857 | AO34: 99.5563 | AP34: 107.9448 | AQ34: 116.4465 | AR34: 124.871 | AS34: 133.2187 | AT34: 141.4899 | AU34: 149.6851 | AV34: 157.8045 | AW34: 159.3713 | AX34: 167.2944 | AY34: 175.0981 | AZ34: 182.784 | BA34: 190.3536 | BB34: 197.8085 | BC34: 205.1504 | BD34: 212.3806 | BE34: 219.5007 | BF34: 226.5122 | BG34: 233.4166 | BH34: 240.2152 | BI34: 237.6897 | BJ34: 244.2811 | BK34: 250.7711 | BL34: 257.1608 | BM34: 263.4518 | BN34: 269.6453 | BO34: 275.7427 | BP34: 281.7452 | BQ34: 287.6541 | BR34: 293.4706 | BS34: 299.1961 | BT34: 304.8317 | BU34: 304.2603 | BV34: 309.7198 | BW34: 315.0931 | BX34: 320.3812 | BY34: 325.5853 | BZ34: 330.7066 | CA34: 335.7461 | CB34: 340.705 | CC34: 345.5844 | CD34: 350.3853 | CE34: 355.1087 | CF34: 359.7558 | CG34: 360.8453 | CH34: 365.3427 | CI34: 369.7668 | CJ34: 374.1185 | CK34: 378.3988 | CL34: 382.6086 | CM34: 386.7491 | CN34: 390.8209 | CO34: 394.8252 | CP34: 398.7627 | CQ34: 402.6345 | CR34: 406.4413 | CS34: 408.9426 | CT34: 412.6222 | CU34: 416.2394 | CV34: 419.7951 | CW34: 423.2902 | CX34: 426.7254 | CY34: 430.1015 | CZ34: 433.4194 | DA34: 436.6798 | DB34: 439.8836 | DC34: 443.0313 | DD34: 446.1239 | DE34: 449.1621 | DF34: 452.1465 | DG34: 455.0779 | DH34: 457.9571 | DI34: 460.7847 | DJ34: 463.5614 | DK34: 466.2879 | DL34: 468.9649 | DM34: 471.5931 | DN34: 474.173 | DO34: 476.7054 | DP34: 479.1909 | DQ34: 481.6302 | DR34: 484.0237 | DS34: 486.3723 | DT34: 488.6763 | DU34: 490.9366 | DV34: 493.1536 | DW34: 495.3279 | DX34: 497.4602 | DY34: 499.5509 | DZ34: 501.6007 | EA34: 503.61 | EB34: 505.5795 | EC34: 507.5096 | ED34: 509.4009 | EE34: 511.254 | EF34: 513.0693 | EG34: 514.8473 | EH34: 516.5885 | EI34: 518.2935 | EJ34: 519.9627 | EK34: 521.5966 | EL34: 523.1957 | EM34: 524.7604 | EN34: 526.2913 | EO34: 527.7887 | EP34: 529.2531 | EQ34: 530.685 | ER34: 532.0848 | ES34: 533.4529 | ET34: 534.7898 | EU34: 536.0958 | EV34: 537.3714 | EW34: 538.617 | EX34: 539.8331 | EY34: 541.0199 | EZ34: 542.1779 | FA34: 543.3075 | FB34: 544.4091 | FC34: 545.4829 | FD34: 546.5296 | FE34: 547.5492 | FF34: 548.5424 | FG34: 549.5093 | FH34: 550.4504 | FI34: 551.366 | FJ34: 552.2564 | FK34: 553.122 | FL34: 553.9631 | FM34: 554.78 | FN34: 555.5731 | FO34: 556.3428 | FP34: 557.0892 | FQ34: 557.8127 | FR34: 558.5137 | FS34: 559.1923 | FT34: 559.8491 | FU34: 560.4841 | FV34: 561.0977 | FW34: 561.6903 | FX34: 562.262 | FY34: 562.8132

Sheet 4f. Quarterly P&L (Recycle)
A1: QUARTERLY P&L | 8 deals (LIVE)
A3: ($mm) | B3: Y1Q1 | C3: Y1Q2 | D3: Y1Q3 | E3: Y1Q4 | F3: Y2Q1 | G3: Y2Q2 | H3: Y2Q3 | I3: Y2Q4 | J3: Y3Q1 | K3: Y3Q2 | L3: Y3Q3 | M3: Y3Q4 | N3: Y4Q1 | O3: Y4Q2 | P3: Y4Q3 | Q3: Y4Q4 | R3: Y5Q1 | S3: Y5Q2 | T3: Y5Q3 | U3: Y5Q4 | V3: Y6Q1 | W3: Y6Q2 | X3: Y6Q3 | Y3: Y6Q4 | Z3: Y7Q1 | AA3: Y7Q2 | AB3: Y7Q3 | AC3: Y7Q4 | AD3: Y8Q1 | AE3: Y8Q2 | AF3: Y8Q3 | AG3: Y8Q4 | AH3: Y9Q1 | AI3: Y9Q2 | AJ3: Y9Q3 | AK3: Y9Q4 | AL3: Y10Q1 | AM3: Y10Q2 | AN3: Y10Q3 | AO3: Y10Q4 | AP3: Y11Q1 | AQ3: Y11Q2 | AR3: Y11Q3 | AS3: Y11Q4 | AT3: Y12Q1 | AU3: Y12Q2 | AV3: Y12Q3 | AW3: Y12Q4 | AX3: Y13Q1 | AY3: Y13Q2 | AZ3: Y13Q3 | BA3: Y13Q4 | BB3: Y14Q1 | BC3: Y14Q2 | BD3: Y14Q3 | BE3: Y14Q4 | BF3: Y15Q1 | BG3: Y15Q2 | BH3: Y15Q3 | BI3: Y15Q4
A5: Revenue | B5: =SUM(_Engine_R50!P31:P33) -> 0 | C5: =SUM(_Engine_R50!P34:P36) -> 6.2233797 | D5: =SUM(_Engine_R50!P37:P39) -> 10.29254 | E5: =SUM(_Engine_R50!P40:P42) -> 14.236813 | F5: =SUM(_Engine_R50!P43:P45) -> 18.00129 | G5: =SUM(_Engine_R50!P46:P48) -> 23.694936 | H5: =SUM(_Engine_R50!P49:P51) -> 22.991388 | I5: =SUM(_Engine_R50!P52:P54) -> 22.311739 | J5: =SUM(_Engine_R50!P55:P57) -> 21.655116 | K5: =SUM(_Engine_R50!P58:P60) -> 21.02068 | L5: =SUM(_Engine_R50!P61:P63) -> 23.401227 | M5: =SUM(_Engine_R50!P64:P66) -> 24.257865 | N5: =SUM(_Engine_R50!P67:P69) -> 23.628665 | O5: =SUM(_Engine_R50!P70:P72) -> 23.019325 | P5: =SUM(_Engine_R50!P73:P75) -> 22.429143 | Q5: =SUM(_Engine_R50!P76:P78) -> 21.857444 | R5: =SUM(_Engine_R50!P79:P81) -> 21.303579 | S5: =SUM(_Engine_R50!P82:P84) -> 20.766922 | T5: =SUM(_Engine_R50!P85:P87) -> 20.246871 | U5: =SUM(_Engine_R50!P88:P90) -> 19.742845 | V5: =SUM(_Engine_R50!P91:P93) -> 19.254288 | W5: =SUM(_Engine_R50!P94:P96) -> 18.78066 | X5: =SUM(_Engine_R50!P97:P99) -> 18.321444 | Y5: =SUM(_Engine_R50!P100:P102) -> 17.876141 | Z5: =SUM(_Engine_R50!P103:P105) -> 17.444271 | AA5: =SUM(_Engine_R50!P106:P108) -> 17.025373 | AB5: =SUM(_Engine_R50!P109:P111) -> 16.618999 | AC5: =SUM(_Engine_R50!P112:P114) -> 16.224721 | AD5: =SUM(_Engine_R50!P115:P117) -> 15.842126 | AE5: =SUM(_Engine_R50!P118:P120) -> 15.470815 | AF5: =SUM(_Engine_R50!P121:P123) -> 15.110405 | AG5: =SUM(_Engine_R50!P124:P126) -> 14.760527 | AH5: =SUM(_Engine_R50!P127:P129) -> 14.420824 | AI5: =SUM(_Engine_R50!P130:P132) -> 14.090953 | AJ5: =SUM(_Engine_R50!P133:P135) -> 13.770584 | AK5: =SUM(_Engine_R50!P136:P138) -> 13.459398 | AL5: =SUM(_Engine_R50!P139:P141) -> 13.157088 | AM5: =SUM(_Engine_R50!P142:P144) -> 12.863359 | AN5: =SUM(_Engine_R50!P145:P147) -> 12.577925 | AO5: =SUM(_Engine_R50!P148:P150) -> 12.300512 | AP5: =SUM(_Engine_R50!P151:P153) -> 12.030854 | AQ5: =SUM(_Engine_R50!P154:P156) -> 11.768696 | AR5: =SUM(_Engine_R50!P157:P159) -> 11.513793 | AS5: =SUM(_Engine_R50!P160:P162) -> 11.265906 | AT5: =SUM(_Engine_R50!P163:P165) -> 11.024807 | AU5: =SUM(_Engine_R50!P166:P168) -> 10.790276 | AV5: =SUM(_Engine_R50!P169:P171) -> 10.562099 | AW5: =SUM(_Engine_R50!P172:P174) -> 10.340071 | AX5: =SUM(_Engine_R50!P175:P177) -> 10.123995 | AY5: =SUM(_Engine_R50!P178:P180) -> 9.9136802 | AZ5: =SUM(_Engine_R50!P181:P183) -> 9.7089418 | BA5: =SUM(_Engine_R50!P184:P186) -> 9.5096026 | BB5: =SUM(_Engine_R50!P187:P189) -> 9.3154912 | BC5: =SUM(_Engine_R50!P190:P192) -> 9.1264426 | BD5: =SUM(_Engine_R50!P193:P195) -> 8.9422971 | BE5: =SUM(_Engine_R50!P196:P198) -> 8.7629011 | BF5: =SUM(_Engine_R50!P199:P201) -> 8.5881062 | BG5: =SUM(_Engine_R50!P202:P204) -> 8.4177689 | BH5: =SUM(_Engine_R50!P205:P207) -> 8.2517512 | BI5: =SUM(_Engine_R50!P208:P210) -> 8.0899196
A6: Cost of Goods Sold | B6: =SUM(_Engine_R50!Q31:Q33) -> 0 | C6: =SUM(_Engine_R50!Q34:Q36) -> 0.62233797 | D6: =SUM(_Engine_R50!Q37:Q39) -> 1.029254 | E6: =SUM(_Engine_R50!Q40:Q42) -> 1.4236813 | F6: =SUM(_Engine_R50!Q43:Q45) -> 1.800129 | G6: =SUM(_Engine_R50!Q46:Q48) -> 2.3694936 | H6: =SUM(_Engine_R50!Q49:Q51) -> 2.2991388 | I6: =SUM(_Engine_R50!Q52:Q54) -> 2.2311739 | J6: =SUM(_Engine_R50!Q55:Q57) -> 2.1655116 | K6: =SUM(_Engine_R50!Q58:Q60) -> 2.102068 | L6: =SUM(_Engine_R50!Q61:Q63) -> 2.3401227 | M6: =SUM(_Engine_R50!Q64:Q66) -> 2.4257865 | N6: =SUM(_Engine_R50!Q67:Q69) -> 2.3628665 | O6: =SUM(_Engine_R50!Q70:Q72) -> 2.3019325 | P6: =SUM(_Engine_R50!Q73:Q75) -> 2.2429143 | Q6: =SUM(_Engine_R50!Q76:Q78) -> 2.1857444 | R6: =SUM(_Engine_R50!Q79:Q81) -> 2.1303579 | S6: =SUM(_Engine_R50!Q82:Q84) -> 2.0766922 | T6: =SUM(_Engine_R50!Q85:Q87) -> 2.0246871 | U6: =SUM(_Engine_R50!Q88:Q90) -> 1.9742845 | V6: =SUM(_Engine_R50!Q91:Q93) -> 1.9254288 | W6: =SUM(_Engine_R50!Q94:Q96) -> 1.878066 | X6: =SUM(_Engine_R50!Q97:Q99) -> 1.8321444 | Y6: =SUM(_Engine_R50!Q100:Q102) -> 1.7876141 | Z6: =SUM(_Engine_R50!Q103:Q105) -> 1.7444271 | AA6: =SUM(_Engine_R50!Q106:Q108) -> 1.7025373 | AB6: =SUM(_Engine_R50!Q109:Q111) -> 1.6618999 | AC6: =SUM(_Engine_R50!Q112:Q114) -> 1.6224721 | AD6: =SUM(_Engine_R50!Q115:Q117) -> 1.5842126 | AE6: =SUM(_Engine_R50!Q118:Q120) -> 1.5470815 | AF6: =SUM(_Engine_R50!Q121:Q123) -> 1.5110405 | AG6: =SUM(_Engine_R50!Q124:Q126) -> 1.4760527 | AH6: =SUM(_Engine_R50!Q127:Q129) -> 1.4420824 | AI6: =SUM(_Engine_R50!Q130:Q132) -> 1.4090953 | AJ6: =SUM(_Engine_R50!Q133:Q135) -> 1.3770584 | AK6: =SUM(_Engine_R50!Q136:Q138) -> 1.3459398 | AL6: =SUM(_Engine_R50!Q139:Q141) -> 1.3157088 | AM6: =SUM(_Engine_R50!Q142:Q144) -> 1.2863359 | AN6: =SUM(_Engine_R50!Q145:Q147) -> 1.2577925 | AO6: =SUM(_Engine_R50!Q148:Q150) -> 1.2300512 | AP6: =SUM(_Engine_R50!Q151:Q153) -> 1.2030854 | AQ6: =SUM(_Engine_R50!Q154:Q156) -> 1.1768696 | AR6: =SUM(_Engine_R50!Q157:Q159) -> 1.1513793 | AS6: =SUM(_Engine_R50!Q160:Q162) -> 1.1265906 | AT6: =SUM(_Engine_R50!Q163:Q165) -> 1.1024807 | AU6: =SUM(_Engine_R50!Q166:Q168) -> 1.0790276 | AV6: =SUM(_Engine_R50!Q169:Q171) -> 1.0562099 | AW6: =SUM(_Engine_R50!Q172:Q174) -> 1.0340071 | AX6: =SUM(_Engine_R50!Q175:Q177) -> 1.0123995 | AY6: =SUM(_Engine_R50!Q178:Q180) -> 0.99136802 | AZ6: =SUM(_Engine_R50!Q181:Q183) -> 0.97089418 | BA6: =SUM(_Engine_R50!Q184:Q186) -> 0.95096026 | BB6: =SUM(_Engine_R50!Q187:Q189) -> 0.93154912 | BC6: =SUM(_Engine_R50!Q190:Q192) -> 0.91264426 | BD6: =SUM(_Engine_R50!Q193:Q195) -> 0.89422971 | BE6: =SUM(_Engine_R50!Q196:Q198) -> 0.87629011 | BF6: =SUM(_Engine_R50!Q199:Q201) -> 0.85881062 | BG6: =SUM(_Engine_R50!Q202:Q204) -> 0.84177689 | BH6: =SUM(_Engine_R50!Q205:Q207) -> 0.82517512 | BI6: =SUM(_Engine_R50!Q208:Q210) -> 0.80899196
A7: Gross Profit | B7: =B5-B6 -> 0 | C7: =C5-C6 -> 5.6010417 | D7: =D5-D6 -> 9.2632858 | E7: =E5-E6 -> 12.813132 | F7: =F5-F6 -> 16.201161 | G7: =G5-G6 -> 21.325442 | H7: =H5-H6 -> 20.69225 | I7: =I5-I6 -> 20.080565 | ... BI7: =BI5-BI6 -> 7.2809277
A9: Vendor Costs | B9: =SUM(_Engine_R50!R31:R33) -> 0 | C9: =SUM(_Engine_R50!R34:R36) -> 0.31116898 | D9: =SUM(_Engine_R50!R37:R39) -> 0.51462699 | E9: =SUM(_Engine_R50!R40:R42) -> 0.71184067 | F9: =SUM(_Engine_R50!R43:R45) -> 0.90006448 | G9: =SUM(_Engine_R50!R46:R48) -> 1.1847468 | H9: =SUM(_Engine_R50!R49:R51) -> 1.1495694 | I9: =SUM(_Engine_R50!R52:R54) -> 1.1155869 | J9: =SUM(_Engine_R50!R55:R57) -> 1.0827558 | K9: =SUM(_Engine_R50!R58:R60) -> 1.051034 | L9: =SUM(_Engine_R50!R61:R63) -> 1.1700614 | M9: =SUM(_Engine_R50!R64:R66) -> 1.2128933 | N9: =SUM(_Engine_R50!R67:R69) -> 1.1814333 | O9: =SUM(_Engine_R50!R70:R72) -> 1.1509662 | P9: =SUM(_Engine_R50!R73:R75) -> 1.1214571 | Q9: =SUM(_Engine_R50!R76:R78) -> 1.0928722 | R9: =SUM(_Engine_R50!R79:R81) -> 1.0651789 | S9: =SUM(_Engine_R50!R82:R84) -> 1.0383461 | T9: =SUM(_Engine_R50!R85:R87) -> 1.0123435 | U9: =SUM(_Engine_R50!R88:R90) -> 0.98714227 | V9: =SUM(_Engine_R50!R91:R93) -> 0.96271438 | W9: =SUM(_Engine_R50!R94:R96) -> 0.93903298 | X9: =SUM(_Engine_R50!R97:R99) -> 0.91607218 | Y9: =SUM(_Engine_R50!R100:R102) -> 0.89380705 | Z9: =SUM(_Engine_R50!R103:R105) -> 0.87221357 | AA9: =SUM(_Engine_R50!R106:R108) -> 0.85126863 | AB9: =SUM(_Engine_R50!R109:R111) -> 0.83094993 | AC9: =SUM(_Engine_R50!R112:R114) -> 0.81123604 | AD9: =SUM(_Engine_R50!R115:R117) -> 0.79210628 | AE9: =SUM(_Engine_R50!R118:R120) -> 0.77354075 | AF9: =SUM(_Engine_R50!R121:R123) -> 0.75552026 | AG9: =SUM(_Engine_R50!R124:R126) -> 0.73802634 | AH9: =SUM(_Engine_R50!R127:R129) -> 0.72104119 | AI9: =SUM(_Engine_R50!R130:R132) -> 0.70454765 | AJ9: =SUM(_Engine_R50!R133:R135) -> 0.6885292 | AK9: =SUM(_Engine_R50!R136:R138) -> 0.6729699 | AL9: =SUM(_Engine_R50!R139:R141) -> 0.65785442 | AM9: =SUM(_Engine_R50!R142:R144) -> 0.64316796 | AN9: =SUM(_Engine_R50!R145:R147) -> 0.62889626 | AO9: =SUM(_Engine_R50!R148:R150) -> 0.61502559 | AP9: =SUM(_Engine_R50!R151:R153) -> 0.6015427 | AQ9: =SUM(_Engine_R50!R154:R156) -> 0.58843482 | AR9: =SUM(_Engine_R50!R157:R159) -> 0.57568964 | AS9: =SUM(_Engine_R50!R160:R162) -> 0.5632953 | AT9: =SUM(_Engine_R50!R163:R165) -> 0.55124036 | AU9: =SUM(_Engine_R50!R166:R168) -> 0.53951378 | AV9: =SUM(_Engine_R50!R169:R171) -> 0.52810494 | AW9: =SUM(_Engine_R50!R172:R174) -> 0.51700356 | AX9: =SUM(_Engine_R50!R175:R177) -> 0.50619977 | AY9: =SUM(_Engine_R50!R178:R180) -> 0.49568401 | AZ9: =SUM(_Engine_R50!R181:R183) -> 0.48544709 | BA9: =SUM(_Engine_R50!R184:R186) -> 0.47548013 | BB9: =SUM(_Engine_R50!R187:R189) -> 0.46577456 | BC9: =SUM(_Engine_R50!R190:R192) -> 0.45632213 | BD9: =SUM(_Engine_R50!R193:R195) -> 0.44711486 | BE9: =SUM(_Engine_R50!R196:R198) -> 0.43814506 | BF9: =SUM(_Engine_R50!R199:R201) -> 0.42940531 | BG9: =SUM(_Engine_R50!R202:R204) -> 0.42088845 | BH9: =SUM(_Engine_R50!R205:R207) -> 0.41258756 | BI9: =SUM(_Engine_R50!R208:R210) -> 0.40449598
A10: Corporate Allocation | B10: =SUM(_Engine_R50!S31:S33) -> 0 | C10: =SUM(_Engine_R50!S34:S36) -> 0.37340278 | D10: =SUM(_Engine_R50!S37:S39) -> 0.61755238 | E10: =SUM(_Engine_R50!S40:S42) -> 0.8542088 | F10: =SUM(_Engine_R50!S43:S45) -> 1.0800774 | G10: =SUM(_Engine_R50!S46:S48) -> 1.4216961 | H10: =SUM(_Engine_R50!S49:S51) -> 1.3794833 | I10: =SUM(_Engine_R50!S52:S54) -> 1.3387043 | J10: =SUM(_Engine_R50!S55:S57) -> 1.2993069 | K10: =SUM(_Engine_R50!S58:S60) -> 1.2612408 | L10: =SUM(_Engine_R50!S61:S63) -> 1.4040736 | M10: =SUM(_Engine_R50!S64:S66) -> 1.4554719 | N10: =SUM(_Engine_R50!S67:S69) -> 1.4177199 | O10: =SUM(_Engine_R50!S70:S72) -> 1.3811595 | P10: =SUM(_Engine_R50!S73:S75) -> 1.3457486 | Q10: =SUM(_Engine_R50!S76:S78) -> 1.3114466 | R10: =SUM(_Engine_R50!S79:S81) -> 1.2782147 | S10: =SUM(_Engine_R50!S82:S84) -> 1.2460153 | T10: =SUM(_Engine_R50!S85:S87) -> 1.2148122 | U10: =SUM(_Engine_R50!S88:S90) -> 1.1845707 | V10: =SUM(_Engine_R50!S91:S93) -> 1.1552573 | W10: =SUM(_Engine_R50!S94:S96) -> 1.1268396 | X10: =SUM(_Engine_R50!S97:S99) -> 1.0992866 | Y10: =SUM(_Engine_R50!S100:S102) -> 1.0725685 | Z10: =SUM(_Engine_R50!S103:S105) -> 1.0466563 | AA10: =SUM(_Engine_R50!S106:S108) -> 1.0215224 | AB10: =SUM(_Engine_R50!S109:S111) -> 0.99713992 | AC10: =SUM(_Engine_R50!S112:S114) -> 0.97348325 | AD10: =SUM(_Engine_R50!S115:S117) -> 0.95052754 | AE10: =SUM(_Engine_R50!S118:S120) -> 0.9282489 | AF10: =SUM(_Engine_R50!S121:S123) -> 0.90662431 | AG10: =SUM(_Engine_R50!S124:S126) -> 0.88563161 | AH10: =SUM(_Engine_R50!S127:S129) -> 0.86524942 | AI10: =SUM(_Engine_R50!S130:S132) -> 0.84545718 | AJ10: =SUM(_Engine_R50!S133:S135) -> 0.82623504 | AK10: =SUM(_Engine_R50!S136:S138) -> 0.80756388 | AL10: =SUM(_Engine_R50!S139:S141) -> 0.78942531 | AM10: =SUM(_Engine_R50!S142:S144) -> 0.77180155 | AN10: =SUM(_Engine_R50!S145:S147) -> 0.75467552 | AO10: =SUM(_Engine_R50!S148:S150) -> 0.73803071 | AP10: =SUM(_Engine_R50!S151:S153) -> 0.72185124 | AQ10: =SUM(_Engine_R50!S154:S156) -> 0.70612178 | AR10: =SUM(_Engine_R50!S157:S159) -> 0.69082757 | AS10: =SUM(_Engine_R50!S160:S162) -> 0.67595436 | AT10: =SUM(_Engine_R50!S163:S165) -> 0.66148843 | AU10: =SUM(_Engine_R50!S166:S168) -> 0.64741654 | AV10: =SUM(_Engine_R50!S169:S171) -> 0.63372592 | AW10: =SUM(_Engine_R50!S172:S174) -> 0.62040428 | AX10: =SUM(_Engine_R50!S175:S177) -> 0.60743972 | AY10: =SUM(_Engine_R50!S178:S180) -> 0.59482081 | AZ10: =SUM(_Engine_R50!S181:S183) -> 0.58253651 | BA10: =SUM(_Engine_R50!S184:S186) -> 0.57057615 | BB10: =SUM(_Engine_R50!S187:S189) -> 0.55892947 | BC10: =SUM(_Engine_R50!S190:S192) -> 0.54758655 | BD10: =SUM(_Engine_R50!S193:S195) -> 0.53653783 | BE10: =SUM(_Engine_R50!S196:S198) -> 0.52577407 | BF10: =SUM(_Engine_R50!S199:S201) -> 0.51528637 | BG10: =SUM(_Engine_R50!S202:S204) -> 0.50506614 | BH10: =SUM(_Engine_R50!S205:S207) -> 0.49510507 | BI10: =SUM(_Engine_R50!S208:S210) -> 0.48539518
A11: Team Compensation | B11: =SUM(_Engine_R50!D31:D33) -> 0.86431748 | C11: =SUM(_Engine_R50!D34:D36) -> 0.86431748 | D11: =SUM(_Engine_R50!D37:D39) -> 0.86431748 | E11: =SUM(_Engine_R50!D40:D42) -> 0.86431748 | F11: =SUM(_Engine_R50!D43:D45) -> 1.899131 | G11: =SUM(_Engine_R50!D46:D48) -> 1.899131 | H11: =SUM(_Engine_R50!D49:D51) -> 1.899131 | I11: =SUM(_Engine_R50!D52:D54) -> 1.899131 | J11: =SUM(_Engine_R50!D55:D57) -> 1.90925 | K11: =SUM(_Engine_R50!D58:D60) -> 1.90925 | L11: =SUM(_Engine_R50!D61:D63) -> 1.90925 | M11: =SUM(_Engine_R50!D64:D66) -> 1.90925 | N11: =SUM(_Engine_R50!D67:D69) -> 1.90925 | O11: =SUM(_Engine_R50!D70:D72) -> 1.90925 | P11: =SUM(_Engine_R50!D73:D75) -> 1.90925 | Q11: =SUM(_Engine_R50!D76:D78) -> 1.90925 | R11: =SUM(_Engine_R50!D79:D81) -> 1.90925 | S11: =SUM(_Engine_R50!D82:D84) -> 1.90925 | T11: =SUM(_Engine_R50!D85:D87) -> 1.90925 | U11: =SUM(_Engine_R50!D88:D90) -> 1.90925 | V11: =SUM(_Engine_R50!D91:D93) -> 1.90925 | W11: =SUM(_Engine_R50!D94:D96) -> 1.90925 | X11: =SUM(_Engine_R50!D97:D99) -> 1.90925 | Y11: =SUM(_Engine_R50!D100:D102) -> 1.90925 | Z11: =SUM(_Engine_R50!D103:D105) -> 1.90925 | AA11: =SUM(_Engine_R50!D106:D108) -> 1.90925 | AB11: =SUM(_Engine_R50!D109:D111) -> 1.90925 | AC11: =SUM(_Engine_R50!D112:D114) -> 1.90925 | AD11: =SUM(_Engine_R50!D115:D117) -> 1.90925 | AE11: =SUM(_Engine_R50!D118:D120) -> 1.90925 | AF11: =SUM(_Engine_R50!D121:D123) -> 1.90925 | AG11: =SUM(_Engine_R50!D124:D126) -> 1.90925 | AH11: =SUM(_Engine_R50!D127:D129) -> 1.90925 | AI11: =SUM(_Engine_R50!D130:D132) -> 1.90925 | AJ11: =SUM(_Engine_R50!D133:D135) -> 1.90925 | AK11: =SUM(_Engine_R50!D136:D138) -> 1.90925 | AL11: =SUM(_Engine_R50!D139:D141) -> 1.90925 | AM11: =SUM(_Engine_R50!D142:D144) -> 1.90925 | AN11: =SUM(_Engine_R50!D145:D147) -> 1.90925 | AO11: =SUM(_Engine_R50!D148:D150) -> 1.90925 | AP11: =SUM(_Engine_R50!D151:D153) -> 1.90925 | AQ11: =SUM(_Engine_R50!D154:D156) -> 1.90925 | AR11: =SUM(_Engine_R50!D157:D159) -> 1.90925 | AS11: =SUM(_Engine_R50!D160:D162) -> 1.90925 | AT11: =SUM(_Engine_R50!D163:D165) -> 1.90925 | AU11: =SUM(_Engine_R50!D166:D168) -> 1.90925 | AV11: =SUM(_Engine_R50!D169:D171) -> 1.90925 | AW11: =SUM(_Engine_R50!D172:D174) -> 1.90925 | AX11: =SUM(_Engine_R50!D175:D177) -> 1.90925 | AY11: =SUM(_Engine_R50!D178:D180) -> 1.90925 | AZ11: =SUM(_Engine_R50!D181:D183) -> 1.90925 | BA11: =SUM(_Engine_R50!D184:D186) -> 1.90925 | BB11: =SUM(_Engine_R50!D187:D189) -> 1.90925 | BC11: =SUM(_Engine_R50!D190:D192) -> 1.90925 | BD11: =SUM(_Engine_R50!D193:D195) -> 1.90925 | BE11: =SUM(_Engine_R50!D196:D198) -> 1.90925 | BF11: =SUM(_Engine_R50!D199:D201) -> 1.90925 | BG11: =SUM(_Engine_R50!D202:D204) -> 1.90925 | BH11: =SUM(_Engine_R50!D205:D207) -> 1.90925 | BI11: =SUM(_Engine_R50!D208:D210) -> 1.90925
A12: Legacy Headcount | B12: =SUM(_Engine_R50!E31:E33) -> 0 | C12: =SUM(_Engine_R50!E34:E36) -> 2.94 | D12: =SUM(_Engine_R50!E37:E39) -> 3.4066667 | E12: =SUM(_Engine_R50!E40:E42) -> 3.6088889 | F12: =SUM(_Engine_R50!E43:E45) -> 3.5466667 | G12: =SUM(_Engine_R50!E46:E48) -> 4.747037 | H12: =SUM(_Engine_R50!E49:E51) -> 2.5433333 | I12: =SUM(_Engine_R50!E52:E54) -> 1.5555556 | J12: =SUM(_Engine_R50!E55:E57) -> 1.0888889 | K12: =SUM(_Engine_R50!E58:E60) -> 0.7 | L12: =SUM(_Engine_R50!E61:E63) -> 2.5355556 | M12: =SUM(_Engine_R50!E64:E66) -> 1.9885185 | N12: =SUM(_Engine_R50!E67:E69) -> 0.7 | O12: =SUM(_Engine_R50!E70:E72) -> 0.54444444 | P12: =SUM(_Engine_R50!E73:E75) -> 0.42777778 | Q12: =SUM(_Engine_R50!E76:E78) -> 0.31111111 | R12: =SUM(_Engine_R50!E79:E81) -> 0.19444444 | S12: =SUM(_Engine_R50!E82:E84) -> 0.077777778 | T12: =SUM(_Engine_R50!E85:E87) -> 0 | U12: =SUM(_Engine_R50!E88:E90) -> 0 | V12: =SUM(_Engine_R50!E91:E93) -> 0 | W12: =SUM(_Engine_R50!E94:E96) -> 0 | X12: =SUM(_Engine_R50!E97:E99) -> 0 | Y12: =SUM(_Engine_R50!E100:E102) -> 0 | Z12: =SUM(_Engine_R50!E103:E105) -> 0 | AA12: =SUM(_Engine_R50!E106:E108) -> 0 | AB12: =SUM(_Engine_R50!E109:E111) -> 0 | AC12: =SUM(_Engine_R50!E112:E114) -> 0 | AD12: =SUM(_Engine_R50!E115:E117) -> 0 | AE12: =SUM(_Engine_R50!E118:E120) -> 0 | AF12: =SUM(_Engine_R50!E121:E123) -> 0 | AG12: =SUM(_Engine_R50!E124:E126) -> 0 | AH12: =SUM(_Engine_R50!E127:E129) -> 0 | AI12: =SUM(_Engine_R50!E130:E132) -> 0 | AJ12: =SUM(_Engine_R50!E133:E135) -> 0 | AK12: =SUM(_Engine_R50!E136:E138) -> 0 | AL12: =SUM(_Engine_R50!E139:E141) -> 0 | AM12: =SUM(_Engine_R50!E142:E144) -> 0 | AN12: =SUM(_Engine_R50!E145:E147) -> 0 | AO12: =SUM(_Engine_R50!E148:E150) -> 0 | AP12: =SUM(_Engine_R50!E151:E153) -> 0 | AQ12: =SUM(_Engine_R50!E154:E156) -> 0 | AR12: =SUM(_Engine_R50!E157:E159) -> 0 | AS12: =SUM(_Engine_R50!E160:E162) -> 0 | AT12: =SUM(_Engine_R50!E163:E165) -> 0 | AU12: =SUM(_Engine_R50!E166:E168) -> 0 | AV12: =SUM(_Engine_R50!E169:E171) -> 0 | AW12: =SUM(_Engine_R50!E172:E174) -> 0 | AX12: =SUM(_Engine_R50!E175:E177) -> 0 | AY12: =SUM(_Engine_R50!E178:E180) -> 0 | AZ12: =SUM(_Engine_R50!E181:E183) -> 0 | BA12: =SUM(_Engine_R50!E184:E186) -> 0 | BB12: =SUM(_Engine_R50!E187:E189) -> 0 | BC12: =SUM(_Engine_R50!E190:E192) -> 0 | BD12: =SUM(_Engine_R50!E193:E195) -> 0 | BE12: =SUM(_Engine_R50!E196:E198) -> 0 | BF12: =SUM(_Engine_R50!E199:E201) -> 0 | BG12: =SUM(_Engine_R50!E202:E204) -> 0 | BH12: =SUM(_Engine_R50!E205:E207) -> 0 | BI12: =SUM(_Engine_R50!E208:E210) -> 0
A13: Bonus Pool | B13: =SUM(_Engine_R50!U31:U33) -> 0 | C13: =SUM(_Engine_R50!U34:U36) -> 0 | D13: =SUM(_Engine_R50!U37:U39) -> 0 | E13: =SUM(_Engine_R50!U40:U42) -> 0 | F13: =SUM(_Engine_R50!U43:U45) -> 0 | G13: =SUM(_Engine_R50!U46:U48) -> 0 | H13: =SUM(_Engine_R50!U49:U51) -> 0 | I13: =SUM(_Engine_R50!U52:U54) -> 0 | J13: =SUM(_Engine_R50!U55:U57) -> 0 | K13: =SUM(_Engine_R50!U58:U60) -> 0 | L13: =SUM(_Engine_R50!U61:U63) -> 0 | M13: =SUM(_Engine_R50!U64:U66) -> 0 | N13: =SUM(_Engine_R50!U67:U69) -> 0 | O13: =SUM(_Engine_R50!U70:U72) -> 0 | P13: =SUM(_Engine_R50!U73:U75) -> 0 | Q13: =SUM(_Engine_R50!U76:U78) -> 0 | R13: =SUM(_Engine_R50!U79:U81) -> 0 | S13: =SUM(_Engine_R50!U82:U84) -> 0 | T13: =SUM(_Engine_R50!U85:U87) -> 0 | U13: =SUM(_Engine_R50!U88:U90) -> 0 | V13: =SUM(_Engine_R50!U91:U93) -> 0 | W13: =SUM(_Engine_R50!U94:U96) -> 0 | X13: =SUM(_Engine_R50!U97:U99) -> 0 | Y13: =SUM(_Engine_R50!U100:U102) -> 0 | Z13: =SUM(_Engine_R50!U103:U105) -> 0 | AA13: =SUM(_Engine_R50!U106:U108) -> 0 | AB13: =SUM(_Engine_R50!U109:U111) -> 0 | AC13: =SUM(_Engine_R50!U112:U114) -> 0 | AD13: =SUM(_Engine_R50!U115:U117) -> 0 | AE13: =SUM(_Engine_R50!U118:U120) -> 0 | AF13: =SUM(_Engine_R50!U121:U123) -> 0 | AG13: =SUM(_Engine_R50!U124:U126) -> 0 | AH13: =SUM(_Engine_R50!U127:U129) -> 0 | AI13: =SUM(_Engine_R50!U130:U132) -> 0 | AJ13: =SUM(_Engine_R50!U133:U135) -> 0 | AK13: =SUM(_Engine_R50!U136:U138) -> 0 | AL13: =SUM(_Engine_R50!U139:U141) -> 0 | AM13: =SUM(_Engine_R50!U142:U144) -> 0 | AN13: =SUM(_Engine_R50!U145:U147) -> 0 | AO13: =SUM(_Engine_R50!U148:U150) -> 0 | AP13: =SUM(_Engine_R50!U151:U153) -> 0 | AQ13: =SUM(_Engine_R50!U154:U156) -> 0 | AR13: =SUM(_Engine_R50!U157:U159) -> 0 | AS13: =SUM(_Engine_R50!U160:U162) -> 0 | AT13: =SUM(_Engine_R50!U163:U165) -> 0 | AU13: =SUM(_Engine_R50!U166:U168) -> 0 | AV13: =SUM(_Engine_R50!U169:U171) -> 0 | AW13: =SUM(_Engine_R50!U172:U174) -> 0 | AX13: =SUM(_Engine_R50!U175:U177) -> 0 | AY13: =SUM(_Engine_R50!U178:U180) -> 0 | AZ13: =SUM(_Engine_R50!U181:U183) -> 0 | BA13: =SUM(_Engine_R50!U184:U186) -> 0 | BB13: =SUM(_Engine_R50!U187:U189) -> 0 | BC13: =SUM(_Engine_R50!U190:U192) -> 0 | BD13: =SUM(_Engine_R50!U193:U195) -> 0 | BE13: =SUM(_Engine_R50!U196:U198) -> 0 | BF13: =SUM(_Engine_R50!U199:U201) -> 0 | BG13: =SUM(_Engine_R50!U202:U204) -> 0 | BH13: =SUM(_Engine_R50!U205:U207) -> 0 | BI13: =SUM(_Engine_R50!U208:U210) -> 0
A14: Total OpEx | B14: =B9+B10+B11+B12+B13+B6 -> 0.86431748 | C14: =C9+C10+C11+C12+C13+C6 -> 5.1112272 | D14: =D9+D10+D11+D12+D13+D6 -> 6.4324175 | E14: =E9+E10+E11+E12+E13+E6 -> 7.4629372 | F14: =F9+F10+F11+F12+F13+F6 -> 9.2260685 | G14: =G9+G10+G11+G12+G13+G6 -> 11.622104 | H14: =H9+H10+H11+H12+H13+H6 -> 9.2706559 | I14: =I9+I10+I11+I12+I13+I6 -> 8.1401517 | ... BI14: =BI9+BI10+BI11+BI12+BI13+BI6 -> 3.6081331
A16: EBITDA | B16: =SUM(_Engine_R50!V31:V33) -> -0.86431748 | C16: =SUM(_Engine_R50!V34:V36) -> 1.1121525 | D16: =SUM(_Engine_R50!V37:V39) -> 3.8601222 | E16: =SUM(_Engine_R50!V40:V42) -> 6.7738762 | F16: =SUM(_Engine_R50!V43:V45) -> 8.7752211 | G16: =SUM(_Engine_R50!V46:V48) -> 12.072831 | H16: =SUM(_Engine_R50!V49:V51) -> 13.720732 | I16: =SUM(_Engine_R50!V52:V54) -> 14.171587 | J16: =SUM(_Engine_R50!V55:V57) -> 14.109403 | K16: =SUM(_Engine_R50!V58:V60) -> 13.997087 | L16: =SUM(_Engine_R50!V61:V63) -> 14.042164 | M16: =SUM(_Engine_R50!V64:V66) -> 15.265945 | N16: =SUM(_Engine_R50!V67:V69) -> 16.057396 | O16: =SUM(_Engine_R50!V70:V72) -> 15.731572 | P16: =SUM(_Engine_R50!V73:V75) -> 15.381995 | Q16: =SUM(_Engine_R50!V76:V78) -> 15.04702 | R16: =SUM(_Engine_R50!V79:V81) -> 14.726133 | S16: =SUM(_Engine_R50!V82:V84) -> 14.418841 | T16: =SUM(_Engine_R50!V85:V87) -> 14.085778 | U16: =SUM(_Engine_R50!V88:V90) -> 13.687598 | V16: =SUM(_Engine_R50!V91:V93) -> 13.301637 | W16: =SUM(_Engine_R50!V94:V96) -> 12.927471 | X16: =SUM(_Engine_R50!V97:V99) -> 12.564691 | Y16: =SUM(_Engine_R50!V100:V102) -> 12.212901 | Z16: =SUM(_Engine_R50!V103:V105) -> 11.871724 | AA16: =SUM(_Engine_R50!V106:V108) -> 11.540794 | AB16: =SUM(_Engine_R50!V109:V111) -> 11.219759 | AC16: =SUM(_Engine_R50!V112:V114) -> 10.908279 | AD16: =SUM(_Engine_R50!V115:V117) -> 10.606029 | AE16: =SUM(_Engine_R50!V118:V120) -> 10.312694 | AF16: =SUM(_Engine_R50!V121:V123) -> 10.02797 | AG16: =SUM(_Engine_R50!V124:V126) -> 9.7515662 | AH16: =SUM(_Engine_R50!V127:V129) -> 9.4832008 | AI16: =SUM(_Engine_R50!V130:V132) -> 9.2226028 | AJ16: =SUM(_Engine_R50!V133:V135) -> 8.9695113 | AK16: =SUM(_Engine_R50!V136:V138) -> 8.7236745 | AL16: =SUM(_Engine_R50!V139:V141) -> 8.4848499 | AM16: =SUM(_Engine_R50!V142:V144) -> 8.2528038 | AN16: =SUM(_Engine_R50!V145:V147) -> 8.027311 | AO16: =SUM(_Engine_R50!V148:V150) -> 7.8081544 | AP16: =SUM(_Engine_R50!V151:V153) -> 7.5951246 | AQ16: =SUM(_Engine_R50!V154:V156) -> 7.3880201 | AR16: =SUM(_Engine_R50!V157:V159) -> 7.1866463 | AS16: =SUM(_Engine_R50!V160:V162) -> 6.9908157 | AT16: =SUM(_Engine_R50!V163:V165) -> 6.8003477 | AU16: =SUM(_Engine_R50!V166:V168) -> 6.6150678 | AV16: =SUM(_Engine_R50!V169:V171) -> 6.434808 | AW16: =SUM(_Engine_R50!V172:V174) -> 6.2594063 | AX16: =SUM(_Engine_R50!V175:V177) -> 6.0887063 | AY16: =SUM(_Engine_R50!V178:V180) -> 5.9225574 | AZ16: =SUM(_Engine_R50!V181:V183) -> 5.760814 | BA16: =SUM(_Engine_R50!V184:V186) -> 5.603336 | BB16: =SUM(_Engine_R50!V187:V189) -> 5.4499881 | BC16: =SUM(_Engine_R50!V190:V192) -> 5.3006396 | BD16: =SUM(_Engine_R50!V193:V195) -> 5.1551647 | BE16: =SUM(_Engine_R50!V196:V198) -> 5.0134419 | BF16: =SUM(_Engine_R50!V199:V201) -> 4.8753539 | BG16: =SUM(_Engine_R50!V202:V204) -> 4.7407875 | BH16: =SUM(_Engine_R50!V205:V207) -> 4.6096335 | BI16: =SUM(_Engine_R50!V208:V210) -> 4.4817865
A17: Severance | B17: =SUM(_Engine_R50!W31:W33) -> 0 | C17: =SUM(_Engine_R50!W34:W36) -> 2.45 | D17: =SUM(_Engine_R50!W37:W39) -> 2.45 | E17: =SUM(_Engine_R50!W40:W42) -> 2.45 | F17: =SUM(_Engine_R50!W43:W45) -> 0 | G17: =SUM(_Engine_R50!W46:W48) -> 2.45 | H17: =SUM(_Engine_R50!W49:W51) -> 0 | I17: =SUM(_Engine_R50!W52:W54) -> 0 | J17: =SUM(_Engine_R50!W55:W57) -> 0 | K17: =SUM(_Engine_R50!W58:W60) -> 0 | L17: =SUM(_Engine_R50!W61:W63) -> 2.45 | M17: =SUM(_Engine_R50!W64:W66) -> 0 | N17: =SUM(_Engine_R50!W67:W69) -> 0 | O17: =SUM(_Engine_R50!W70:W72) -> 0 | P17: =SUM(_Engine_R50!W73:W75) -> 0 | Q17: =SUM(_Engine_R50!W76:W78) -> 0 | R17: =SUM(_Engine_R50!W79:W81) -> 0 | S17: =SUM(_Engine_R50!W82:W84) -> 0 | T17: =SUM(_Engine_R50!W85:W87) -> 0 | U17: =SUM(_Engine_R50!W88:W90) -> 0 | V17: =SUM(_Engine_R50!W91:W93) -> 0 | W17: =SUM(_Engine_R50!W94:W96) -> 0 | X17: =SUM(_Engine_R50!W97:W99) -> 0 | Y17: =SUM(_Engine_R50!W100:W102) -> 0 | Z17: =SUM(_Engine_R50!W103:W105) -> 0 | AA17: =SUM(_Engine_R50!W106:W108) -> 0 | AB17: =SUM(_Engine_R50!W109:W111) -> 0 | AC17: =SUM(_Engine_R50!W112:W114) -> 0 | AD17: =SUM(_Engine_R50!W115:W117) -> 0 | AE17: =SUM(_Engine_R50!W118:W120) -> 0 | AF17: =SUM(_Engine_R50!W121:W123) -> 0 | AG17: =SUM(_Engine_R50!W124:W126) -> 0 | AH17: =SUM(_Engine_R50!W127:W129) -> 0 | AI17: =SUM(_Engine_R50!W130:W132) -> 0 | AJ17: =SUM(_Engine_R50!W133:W135) -> 0 | AK17: =SUM(_Engine_R50!W136:W138) -> 0 | AL17: =SUM(_Engine_R50!W139:W141) -> 0 | AM17: =SUM(_Engine_R50!W142:W144) -> 0 | AN17: =SUM(_Engine_R50!W145:W147) -> 0 | AO17: =SUM(_Engine_R50!W148:W150) -> 0 | AP17: =SUM(_Engine_R50!W151:W153) -> 0 | AQ17: =SUM(_Engine_R50!W154:W156) -> 0 | AR17: =SUM(_Engine_R50!W157:W159) -> 0 | AS17: =SUM(_Engine_R50!W160:W162) -> 0 | AT17: =SUM(_Engine_R50!W163:W165) -> 0 | AU17: =SUM(_Engine_R50!W166:W168) -> 0 | AV17: =SUM(_Engine_R50!W169:W171) -> 0 | AW17: =SUM(_Engine_R50!W172:W174) -> 0 | AX17: =SUM(_Engine_R50!W175:W177) -> 0 | AY17: =SUM(_Engine_R50!W178:W180) -> 0 | AZ17: =SUM(_Engine_R50!W181:W183) -> 0 | BA17: =SUM(_Engine_R50!W184:W186) -> 0 | BB17: =SUM(_Engine_R50!W187:W189) -> 0 | BC17: =SUM(_Engine_R50!W190:W192) -> 0 | BD17: =SUM(_Engine_R50!W193:W195) -> 0 | BE17: =SUM(_Engine_R50!W196:W198) -> 0 | BF17: =SUM(_Engine_R50!W199:W201) -> 0 | BG17: =SUM(_Engine_R50!W202:W204) -> 0 | BH17: =SUM(_Engine_R50!W205:W207) -> 0 | BI17: =SUM(_Engine_R50!W208:W210) -> 0
A18: Operating Income | B18: =B16-B17 -> -0.86431748 | C18: =C16-C17 -> -1.3378475 | D18: =D16-D17 -> 1.4101222 | E18: =E16-E17 -> 4.3238762 | F18: =F16-F17 -> 8.7752211 | G18: =G16-G17 -> 9.622831 | H18: =H16-H17 -> 13.720732 | I18: =I16-I17 -> 14.171587 | ... BI18: =BI16-BI17 -> 4.4817865
A20: Management Fee | B20: =SUM(_Engine_R50!C31:C33) -> 0.75 | C20: =SUM(_Engine_R50!C34:C36) -> 0.75 | D20: =SUM(_Engine_R50!C37:C39) -> 0.75 | E20: =SUM(_Engine_R50!C40:C42) -> 0.75 | F20: =SUM(_Engine_R50!C43:C45) -> 0.75 | G20: =SUM(_Engine_R50!C46:C48) -> 0.75 | H20: =SUM(_Engine_R50!C49:C51) -> 0 | I20: =SUM(_Engine_R50!C52:C54) -> 0 | J20: =SUM(_Engine_R50!C55:C57) -> 0 | K20: =SUM(_Engine_R50!C58:C60) -> 0 | L20: =SUM(_Engine_R50!C61:C63) -> 0 | M20: =SUM(_Engine_R50!C64:C66) -> 0 | N20: =SUM(_Engine_R50!C67:C69) -> 0 | O20: =SUM(_Engine_R50!C70:C72) -> 0 | P20: =SUM(_Engine_R50!C73:C75) -> 0 | Q20: =SUM(_Engine_R50!C76:C78) -> 0 | R20: =SUM(_Engine_R50!C79:C81) -> 0 | S20: =SUM(_Engine_R50!C82:C84) -> 0 | T20: =SUM(_Engine_R50!C85:C87) -> 0 | U20: =SUM(_Engine_R50!C88:C90) -> 0 | V20: =SUM(_Engine_R50!C91:C93) -> 0 | W20: =SUM(_Engine_R50!C94:C96) -> 0 | X20: =SUM(_Engine_R50!C97:C99) -> 0 | Y20: =SUM(_Engine_R50!C100:C102) -> 0 | Z20: =SUM(_Engine_R50!C103:C105) -> 0 | AA20: =SUM(_Engine_R50!C106:C108) -> 0 | AB20: =SUM(_Engine_R50!C109:C111) -> 0 | AC20: =SUM(_Engine_R50!C112:C114) -> 0 | AD20: =SUM(_Engine_R50!C115:C117) -> 0 | AE20: =SUM(_Engine_R50!C118:C120) -> 0 | AF20: =SUM(_Engine_R50!C121:C123) -> 0 | AG20: =SUM(_Engine_R50!C124:C126) -> 0 | AH20: =SUM(_Engine_R50!C127:C129) -> 0 | AI20: =SUM(_Engine_R50!C130:C132) -> 0 | AJ20: =SUM(_Engine_R50!C133:C135) -> 0 | AK20: =SUM(_Engine_R50!C136:C138) -> 0 | AL20: =SUM(_Engine_R50!C139:C141) -> 0 | AM20: =SUM(_Engine_R50!C142:C144) -> 0 | AN20: =SUM(_Engine_R50!C145:C147) -> 0 | AO20: =SUM(_Engine_R50!C148:C150) -> 0 | AP20: =SUM(_Engine_R50!C151:C153) -> 0 | AQ20: =SUM(_Engine_R50!C154:C156) -> 0 | AR20: =SUM(_Engine_R50!C157:C159) -> 0 | AS20: =SUM(_Engine_R50!C160:C162) -> 0 | AT20: =SUM(_Engine_R50!C163:C165) -> 0 | AU20: =SUM(_Engine_R50!C166:C168) -> 0 | AV20: =SUM(_Engine_R50!C169:C171) -> 0 | AW20: =SUM(_Engine_R50!C172:C174) -> 0 | AX20: =SUM(_Engine_R50!C175:C177) -> 0 | AY20: =SUM(_Engine_R50!C178:C180) -> 0 | AZ20: =SUM(_Engine_R50!C181:C183) -> 0 | BA20: =SUM(_Engine_R50!C184:C186) -> 0 | BB20: =SUM(_Engine_R50!C187:C189) -> 0 | BC20: =SUM(_Engine_R50!C190:C192) -> 0 | BD20: =SUM(_Engine_R50!C193:C195) -> 0 | BE20: =SUM(_Engine_R50!C196:C198) -> 0 | BF20: =SUM(_Engine_R50!C199:C201) -> 0 | BG20: =SUM(_Engine_R50!C202:C204) -> 0 | BH20: =SUM(_Engine_R50!C205:C207) -> 0 | BI20: =SUM(_Engine_R50!C208:C210) -> 0
A21: Retained (50%) | B21: =B18-B20 -> -1.6143175 | C21: =C18-C20 -> -2.0878475 | D21: =D18-D20 -> 0.66012224 | E21: =E18-E20 -> 3.5738762 | F21: =F18-F20 -> 8.0252211 | G21: =G18-G20 -> 8.872831 | H21: =H18-H20 -> 13.720732 | I21: =I18-I20 -> 14.171587 | ... BI21: =BI18-BI20 -> 4.4817865
A22: Distributable Cash | B22: =B21 -> -1.6143175 | C22: =B22+C21 -> -3.702165 | D22: =C22+D21 -> -3.0420428 | E22: =D22+E21 -> 0.5318334 | F22: =E22+F21 -> 8.5570545 | G22: =F22+G21 -> 17.429886 | H22: =G22+H21 -> 31.150618 | I22: =H22+I21 -> 45.322205 | J22: =I22+J21 -> 59.431608 | ... BI22: =BH22+BI21 -> 543.91321
A23: Cumulative | B23: -0.5 | C23: -1.79 | D23: -2.4 | E23: -1.68 | F23: 3.13 | G23: 9.4 | H23: 17.9 | I23: 26.4 | J23: 36.09 | K23: 45.66 | L23: 56.49 | M23: 67.23 | N23: 91.29 | O23: 116.45 | P23: 141.49 | Q23: 159.37 | R23: 182.78 | S23: 205.15 | T23: 226.51 | U23: 237.69 | V23: 257.16 | W23: 275.74 | X23: 293.47 | Y23: 304.26 | Z23: 320.38 | AA23: 335.75 | AB23: 350.39 | AC23: 360.85 | AD23: 374.12 | AE23: 386.75 | AF23: 398.76 | AG23: 408.94 | AH23: 419.8 | AI23: 430.1 | AJ23: 439.88 | AK23: 449.16 | AL23: 457.96 | AM23: 466.29 | AN23: 474.17 | AO23: 481.63 | AP23: 488.68 | AQ23: 495.33 | AR23: 501.6 | AS23: 507.51 | AT23: 513.07 | AU23: 518.29 | AV23: 523.2 | AW23: 527.79 | AX23: 532.08 | AY23: 536.1 | AZ23: 539.83 | BA23: 543.31 | BB23: 546.53 | BC23: 549.51 | BD23: 552.26 | BE23: 554.78 | BF23: 557.09 | BG23: 559.19 | BH23: 561.1 | BI23: 562.81

Sheet 7. Per-Deal Returns
A1: =" PER-DEAL BREAKDOWN | Net Margin per Tab 1 (B26) = " & TEXT('1. Press Assumptions'!$B$26,"0.0%") -> PER-DEAL BREAKDOWN | Net Margin per Tab 1 (B26) = 62.5%
A3: ORIGINAL 5 DEALS
A5: Deal | B5: Type | C5: Outcome | D5: ARR ($mm) | E5: Mult | F5: Purchase | G5: Real NDR | H5: 15Y Rev | I5: 15Y NOI | J5: 15Y Cash | K5: MOIC | L5: IRR
A6: #1 | B6: Type B | C6: WINNER | D6: ='1. Press Assumptions'!$D$89 -> 25 | E6: ='1. Press Assumptions'!$E$89 -> 2 | F6: ='1. Press Assumptions'!$D$89*'1. Press Assumptions'!$E$89 -> 50 | G6: 1 | H6: 377.6 | I6: 226.56 | J6: 223.60576 | K6: 5.8230667 | L6: 0.51328592
A7: #2 | B7: Type A | C7: AVERAGE | D7: ='1. Press Assumptions'!$D$90 -> 25 | E7: ='1. Press Assumptions'!$E$90 -> 1.5 | F7: ='1. Press Assumptions'!$D$90*'1. Press Assumptions'!$E$90 -> 37.5 | G7: 0.85 | H7: 152.53572 | I7: 91.52143 | J7: 88.38255 | K7: 2.3209703 | L7: 0.2679545
A8: #3 | B8: Type A | C8: WINNER | D8: ='1. Press Assumptions'!$D$91 -> 25 | E8: ='1. Press Assumptions'!$E$91 -> 1.25 | F8: ='1. Press Assumptions'!$D$91*'1. Press Assumptions'!$E$91 -> 31.25 | G8: 1 | H8: 428.925 | I8: 257.355 | J8: 253.88146 | K8: 5.271625 | L8: 0.37902769
A9: #4 | B9: Type B | C9: LOSER | D9: ='1. Press Assumptions'!$D$92 -> 25 | E9: ='1. Press Assumptions'!$E$92 -> 1.25 | F9: ='1. Press Assumptions'!$D$92*'1. Press Assumptions'!$E$92 -> 31.25 | G9: 0.8 | H9: 112.52664 | I9: 67.515986 | J9: 64.515586 | K9: 1.9087451 | L9: 0.18867867
A10: #5 | B10: Type A | C10: LOSER | D10: ='1. Press Assumptions'!$D$93 -> 18 | E10: ='1. Press Assumptions'!$E$93 -> 2 | F10: ='1. Press Assumptions'!$D$93*'1. Press Assumptions'!$E$93 -> 36 | G10: 0.8 | H10: 109.54689 | I10: 65.728135 | J10: 62.796975 | K10: 1.901786 | L10: 0.25917619
A13: RECYCLED DEALS (if recycling ON)
A14: Deal | B14: Type | C14: Outcome | D14: ARR ($mm) | E14: Mult | F14: Purchase | G14: Real NDR | H14: 15Y Rev | I14: 15Y NOI | J14: 15Y Cash | K14: MOIC | L14: IRR
A15: #6 | B15: Type A | C15: WINNER | D15: ='1. Press Assumptions'!$D$96 -> 0 | E15: ='1. Press Assumptions'!$E$96 -> 2 | F15: ='1. Press Assumptions'!$D$96*'1. Press Assumptions'!$E$96 -> 0 | G15: 1 | H15: 314 | I15: 188.4 | J15: 185.6304 | K15: 6.18768 | L15: 0.45257635
A16: #7 | B16: Type A | C16: WINNER | D16: ='1. Press Assumptions'!$D$97 -> 0 | E16: ='1. Press Assumptions'!$E$97 -> 2 | F16: ='1. Press Assumptions'!$D$97*'1. Press Assumptions'!$E$97 -> 0 | G16: 1 | H16: 306 | I16: 183.6 | J16: 180.8304 | K16: 6.02768 | L16: 0.65388632
A17: #8 | B17: Type A | C17: AVERAGE | D17: ='1. Press Assumptions'!$D$98 -> 0 | E17: ='1. Press Assumptions'!$E$98 -> 2 | F17: ='1. Press Assumptions'!$D$98*'1. Press Assumptions'!$E$98 -> 0 | G17: 0.85 | H17: 128.91389 | I17: 77.348336 | J17: 74.578736 | K17: 2.4859579 | L17: 0.31182287
A18: #9 | B18: Type A | C18: LOSER | D18: ='1. Press Assumptions'!$D$99 -> 0 | E18: ='1. Press Assumptions'!$E$99 -> 2 | F18: ='1. Press Assumptions'!$D$99*'1. Press Assumptions'!$E$99 -> 0 | G18: 0.8 | H18: 101.23463 | I18: 60.740777 | J18: 57.971177 | K18: 1.9323726 | L18: 0.20197647
A20: LP CASH CONTRIBUTION BY DEAL (Fund I -- 50% Recycle)
A21: Method: each deal's share of portfolio revenue x portfolio EBITDA, then apply LP share of total distributable.
A22: Deal | B22: ARR | C22: NDR | D22: 15Y Revenue | E22: % of Rev | F22: Exit Y10 | G22: LP cash $ | H22: % of LP cash
A23: #1 | B23: =_Engine_R50!$E$6 -> 25 | C23: =_Engine_R50!$G$6 -> 0.95 | D23: =SUM(_Engine_R50!F31:F210)/12 -> 259.2272 | E23: =D23/SUM(D$23:D$27) -> 0.29175838 | F23: =_Engine_R50!F150*'1. Press Assumptions'!$B$116*'1. Press Assumptions'!$B$117 -> 0 | G23: =(D23+F23)/(SUM(D$23:D$27)+SUM(F$23:F$27)) * _Engine_R50!$B$250 -> 131.20931 | H23: =G23/SUM(G$23:G$27) -> 0.29175838
A24: #2 | B24: =_Engine_R50!$E$7 -> 25 | C24: =_Engine_R50!$G$7 -> 0.9 | D24: =SUM(_Engine_R50!G31:G210)/12 -> 186.1446 | E24: =D24/SUM(D$23:D$27) -> 0.20950444 | F24: =_Engine_R50!G150*'1. Press Assumptions'!$B$116*'1. Press Assumptions'!$B$117 -> 0 | G24: =(D24+F24)/(SUM(D$23:D$27)+SUM(F$23:F$27)) * _Engine_R50!$B$250 -> 94.218145 | H24: =G24/SUM(G$23:G$27) -> 0.20950444
A25: #3 | B25: =_Engine_R50!$E$8 -> 25 | C25: =_Engine_R50!$G$8 -> 0.85 | D25: =SUM(_Engine_R50!H31:H210)/12 -> 139.17019 | E25: =D25/SUM(D$23:D$27) -> 0.15663506 | F25: =_Engine_R50!H150*'1. Press Assumptions'!$B$116*'1. Press Assumptions'!$B$117 -> 0 | G25: =(D25+F25)/(SUM(D$23:D$27)+SUM(F$23:F$27)) * _Engine_R50!$B$250 -> 70.441777 | H25: =G25/SUM(G$23:G$27) -> 0.15663506
A26: #4 | B26: =_Engine_R50!$E$9 -> 25 | C26: =_Engine_R50!$G$9 -> 0.85 | D26: =SUM(_Engine_R50!I31:I210)/12 -> 138.2961 | E26: =D26/SUM(D$23:D$27) -> 0.15565128 | F26: =_Engine_R50!I150*'1. Press Assumptions'!$B$116*'1. Press Assumptions'!$B$117 -> 0 | G26: =(D26+F26)/(SUM(D$23:D$27)+SUM(F$23:F$27)) * _Engine_R50!$B$250 -> 69.999351 | H26: =G26/SUM(G$23:G$27) -> 0.15565128
A27: #5 | B27: =_Engine_R50!$E$10 -> 18 | C27: =_Engine_R50!$G$10 -> 0.95 | D27: =SUM(_Engine_R50!J31:J210)/12 -> 165.6615 | E27: =D27/SUM(D$23:D$27) -> 0.18645084 | F27: =_Engine_R50!J150*'1. Press Assumptions'!$B$116*'1. Press Assumptions'!$B$117 -> 0 | G27: =(D27+F27)/(SUM(D$23:D$27)+SUM(F$23:F$27)) * _Engine_R50!$B$250 -> 83.850504 | H27: =G27/SUM(G$23:G$27) -> 0.18645084
A28: TOTAL | D28: =SUM(D23:D27) -> 888.49958 | E28: =SUM(E23:E27) -> 1 | F28: =SUM(F23:F27) -> 0 | G28: =SUM(G23:G27) -> 449.71909 | H28: =SUM(H23:H27) -> 1
A30: Top 2 deals share of LP cash: | B30: =LARGE(G23:G27,1)+LARGE(G23:G27,2) -> 225.42746 | C30: =B30/SUM(G23:G27) -> 0.50126282
A31: Note: per-deal contribution pro-rated by revenue share; fund-level costs are shared.
A33: CONCENTRATION -- 50% RECYCLE (9 deals)
A34: Deal | B34: ARR | C34: NDR | D34: 15Y Revenue | E34: % of Rev | F34: Exit | G34: LP cash $ | H34: % of LP cash
A35: #1 | B35: =_Engine_R50!$E$6 -> 25 | C35: =_Engine_R50!$G$6 -> 0.95 | D35: =SUM(_Engine_R50!F31:F210)/12 -> 259.2272 | E35: =D35/SUM(D$35:D$43) -> 0.29175838 | F35: =_Engine_R50!F150*'1. Press Assumptions'!$B$116*'1. Press Assumptions'!$B$117 -> 0 | G35: =(D35+F35)/(SUM(D$35:D$43)+SUM(F$35:F$43)) * _Engine_R50!$B$250 -> 131.20931 | H35: =G35/SUM(G$35:G$43) -> 0.29175838
A36: #2 | B36: =_Engine_R50!$E$7 -> 25 | C36: =_Engine_R50!$G$7 -> 0.9 | D36: =SUM(_Engine_R50!G31:G210)/12 -> 186.1446 | E36: =D36/SUM(D$35:D$43) -> 0.20950444 | F36: =_Engine_R50!G150*'1. Press Assumptions'!$B$116*'1. Press Assumptions'!$B$117 -> 0 | G36: =(D36+F36)/(SUM(D$35:D$43)+SUM(F$35:F$43)) * _Engine_R50!$B$250 -> 94.218145 | H36: =G36/SUM(G$35:G$43) -> 0.20950444
A37: #3 | B37: =_Engine_R50!$E$8 -> 25 | C37: =_Engine_R50!$G$8 -> 0.85 | D37: =SUM(_Engine_R50!H31:H210)/12 -> 139.17019 | E37: =D37/SUM(D$35:D$43) -> 0.15663506 | F37: =_Engine_R50!H150*'1. Press Assumptions'!$B$116*'1. Press Assumptions'!$B$117 -> 0 | G37: =(D37+F37)/(SUM(D$35:D$43)+SUM(F$35:F$43)) * _Engine_R50!$B$250 -> 70.441777 | H37: =G37/SUM(G$35:G$43) -> 0.15663506
A38: #4 | B38: =_Engine_R50!$E$9 -> 25 | C38: =_Engine_R50!$G$9 -> 0.85 | D38: =SUM(_Engine_R50!I31:I210)/12 -> 138.2961 | E38: =D38/SUM(D$35:D$43) -> 0.15565128 | F38: =_Engine_R50!I150*'1. Press Assumptions'!$B$116*'1. Press Assumptions'!$B$117 -> 0 | G38: =(D38+F38)/(SUM(D$35:D$43)+SUM(F$35:F$43)) * _Engine_R50!$B$250 -> 69.999351 | H38: =G38/SUM(G$35:G$43) -> 0.15565128
A39: #5 | B39: =_Engine_R50!$E$10 -> 18 | C39: =_Engine_R50!$G$10 -> 0.95 | D39: =SUM(_Engine_R50!J31:J210)/12 -> 165.6615 | E39: =D39/SUM(D$35:D$43) -> 0.18645084 | F39: =_Engine_R50!J150*'1. Press Assumptions'!$B$116*'1. Press Assumptions'!$B$117 -> 0 | G39: =(D39+F39)/(SUM(D$35:D$43)+SUM(F$35:F$43)) * _Engine_R50!$B$250 -> 83.850504 | H39: =G39/SUM(G$35:G$43) -> 0.18645084
A40: #6 | B40: =_Engine_R50!$E$11 -> 0 | C40: =_Engine_R50!$G$11 -> 0.95 | D40: =SUM(_Engine_R50!K31:K210)/12 -> 0 | E40: =D40/SUM(D$35:D$43) -> 0 | F40: =_Engine_R50!K150*'1. Press Assumptions'!$B$116*'1. Press Assumptions'!$B$117 -> 0 | G40: =(D40+F40)/(SUM(D$35:D$43)+SUM(F$35:F$43)) * _Engine_R50!$B$250 -> 0 | H40: =G40/SUM(G$35:G$43) -> 0
A41: #7 | B41: =_Engine_R50!$E$12 -> 0 | C41: =_Engine_R50!$G$12 -> 0.95 | D41: =SUM(_Engine_R50!L31:L210)/12 -> 0 | E41: =D41/SUM(D$35:D$43) -> 0 | F41: =_Engine_R50!L150*'1. Press Assumptions'!$B$116*'1. Press Assumptions'!$B$117 -> 0 | G41: =(D41+F41)/(SUM(D$35:D$43)+SUM(F$35:F$43)) * _Engine_R50!$B$250 -> 0 | H41: =G41/SUM(G$35:G$43) -> 0
A42: #8 | B42: =_Engine_R50!$E$13 -> 0 | C42: =_Engine_R50!$G$13 -> 0.95 | D42: =SUM(_Engine_R50!M31:M210)/12 -> 0 | E42: =D42/SUM(D$35:D$43) -> 0 | F42: =_Engine_R50!M150*'1. Press Assumptions'!$B$116*'1. Press Assumptions'!$B$117 -> 0 | G42: =(D42+F42)/(SUM(D$35:D$43)+SUM(F$35:F$43)) * _Engine_R50!$B$250 -> 0 | H42: =G42/SUM(G$35:G$43) -> 0
A43: #9 | B43: =_Engine_R50!$E$14 -> 0 | C43: =_Engine_R50!$G$14 -> 0.95 | D43: =SUM(_Engine_R50!N31:N210)/12 -> 0 | E43: =D43/SUM(D$35:D$43) -> 0 | F43: =_Engine_R50!N150*'1. Press Assumptions'!$B$116*'1. Press Assumptions'!$B$117 -> 0 | G43: =(D43+F43)/(SUM(D$35:D$43)+SUM(F$35:F$43)) * _Engine_R50!$B$250 -> 0 | H43: =G43/SUM(G$35:G$43) -> 0
A44: TOTAL | D44: =SUM(D35:D43) -> 888.49958 | E44: =SUM(E35:E43) -> 1 | F44: =SUM(F35:F43) -> 0 | G44: =SUM(G35:G43) -> 449.71909 | H44: =SUM(H35:H43) -> 1
A46: Top 2 deals % of LP cash | B46: =(LARGE(G35:G43,1)+LARGE(G35:G43,2))/SUM(G35:G43) -> 0.50126282
A47: Top 4 deals % of LP cash | B47: =SUM(LARGE(G35:G43,{1,2,3,4}))/SUM(G35:G43) -> 0.84434872

Sheet 8. Investor Metrics
A1: PRESS CAPITAL -- FUND I INVESTOR METRICS
A2: $150M fund, 50% recycle. Live from _Engine_R50. | B2: LIVE from engine tabs. All 3 scenarios auto-update from Tab 1.
C4: Fund I (50% Recycle)
A6: FUND OVERVIEW
A7: Fund Size | C7: ='1. Press Assumptions'!$B$5/1000000 -> 150
