Workbook

Sheet 1. Press Assumptions
A1: PRESS CAPITAL -- Fund I ASSUMPTIONS
A2: All blue cells are adjustable inputs. Black cells on gray are calculated. | D2: UNDERWRITING SCENARIO set in B136 below (Bear 80% / Base 85% / Bull 90%).
D3: ACTIVE: $150M, 50% RECYCLE. NDR 80/90/100 (Yr1-6) -> 85% decay (Yr7+). 5 base + 3 recycled (M24/32/40).
A4: FUND PARAMETERS
A5: Fund Size ($) | B5: 150000000 | C5: Raised from $150M to fix -$0.4M cushion (LPs slightly increased).
A6: Number of Deals | B6: 5
A7: ARR per Deal ($) | B7: 24000000
A8: Entry Multiple (x ARR) | B8: 1.25
A9: Capital per Deal ($) | B9: 30000000 | E9: ARR x Entry Multiple (auto)
A10: Total Capital Deployed ($) | B10: 150000000 | E10: Deals x Capital per Deal (auto)
A11: Asset Deal % (50% rev haircut Y1) | B11: 0.25
A12: Share Deal % | B12: 0.75 | E12: 1 - Asset Deal %
A13: Leverage / Debt | B13: Zero | E13: No debt at fund or portfolio company level. All cash acquisitions.
A15: RETENTION & GROWTH
A16: Net Dollar Retention -- Base Case | B16: 0.85
A17: Net Dollar Retention -- Homerun | B17: 0.95
A18: Net Dollar Retention -- Looser | B18: 0.8 | E18: Conservative / stress test scenario
A19: NCA % -- Base Case | B19: 0
A20: NCA % -- Homerun | B20: 0.05
A21: Scenario Toggle (1=Base, 2=Homerun) | B21: 1 | E21: 1=Base, 2=Homerun, 3=Looser
A22: Active Retention Rate | B22: 0.85 | E22: Auto from toggle
A23: Active NCA Rate | B23: 0 | E23: Auto from toggle
A25: MARGIN MODEL
A26: Net Margin (flat, all years) | B26: 0.625 | E26: Used in flat-margin tabs (3a-3d). Set to 0 to use component costs.
A28: COST STRUCTURE
A29: All companies assumed breakeven at entry. Adjust per-deal entry margin on Tab 2.
A30: COGS | B30: 0.1 | E30: Ramps from 25% at close to 10% over 6 months
A31: Vendor Costs | B31: 0.05 | E31: Ramps from 10% at close to 5% over 6 months
A32: Corporate Allocation | B32: 0.06 | E32: Flat
A33: Legacy Headcount Expenses | B33: 0 | E33: Acquired company staff. 50% cut day 1, 90% by M6, 100% by M24. Rate derived from entry profit per deal.
A34: Salary Overhead Loading | B34: 0.3 | E34: On top of base salaries
A35: Bonus Pool Threshold | B35: 1 | C35: Set to 100% per GP -- no bonus pool. All margin upside flows to investors. | E35: Included in OpEx. Everything above 62.5% EBITDA margin goes to team.
A37: WATERFALL & DISTRIBUTION
A38: Phase 1: Return of Capital (x) | B38: 1 | E38: 100% to LPs until 1x returned
A39: Preferred Return (Annual) | B39: 0.1 | E39: 10% pref on unreturned capital
A40: Tier 2: LP Split % (1x-2x) | B40: 0.8 | E40: HoldCo gets 20%
A41: Tier 3: LP Split % (2x-3x) | B41: 0.75 | E41: HoldCo gets 25%
A42: Tier 4: LP Split % (above 3x) | B42: 0.7 | E42: HoldCo gets 30% -- perpetual
A43: Mgmt Fee Schedule | B43: 2% Y1 only | E43: 0% after Y1 once 3 deals deployed
A45: TIERED WATERFALL THRESHOLDS
A46: Tier | B46: Threshold (x) | C46: LP Split %
A47: Tier 1 | B47: 1x | C47: 1
A48: Tier 2 | B48: 2x | C48: 0.8
A49: Tier 3 | B49: 3x | C49: 0.75
A50: Tier 4 (above 3x) | C50: 0.7
A52: TEAM & COMPENSATION
A53: CEO Salary ($, base) | B53: 1000000
A54: COO Salary ($, base) | B54: 500000
A55: CFO Salary ($, base) | B55: 500000
A56: CPO Salary ($, base) | B56: 500000
A57: CTO Salary ($, base) | B57: 500000
A58: CRO Salary ($, base) | B58: 500000
A59: Team Steady State Headcount | B59: 20
A60: Direct Reports: 5 at $250K | B60: 250000 | E60: Senior operators (layered in with deals 1-3)
A61: Direct Reports: 9 at $125K | B61: 125000 | E61: Junior operators (layered in with deals 3-5)
A62: ARR Step Threshold ($) | B62: 100000000 | E62: $75M default -- toggle to change tier size
A63: Step-Up Multiplier per Tier | B63: 1.5 | E63: 1.5x = 50% raise per tier; compounds across tiers
A65: DEPLOYMENT TIMING
A66: Fund Start Month (Global) | B66: 1
A67: Deal Closing Schedule (Global Month):
A68: OpCo 1 | B68: 4
A69: OpCo 2 | B69: 8
A70: OpCo 3 | B70: 12
A71: OpCo 4 | B71: 16
A72: OpCo 5 | B72: 20
A73: OpCo 6 (recycled) | B73: 24
A74: OpCo 7 (recycled) | B74: 28
A75: OpCo 8 (recycled) | B75: 32
A76: OpCo 9 (recycled) | B76: 36
A78: CAPITAL RECYCLING
A79: Recycling Enabled (1=Yes, 0=No) | B79: 1 | E79: Toggle off to revert to fixed 5-deal model
A80: Recycle % of Pre-Waterfall NI | B80: 1 | E80: 100% during reinvestment period
A81: Reinvestment Period (months) | B81: 40 | C81: EXTENDED from 36mo. Original 36-month period made 50% Recycle infeasible (cash gap $43.5M). | E81: 3-year lockup; recycle stops after M36
A82: Number of Recycled Deals | B82: 4 | E82: OpCos 6-9, every 4 months
A83: Capital per Recycled Deal ($) | B83: 30000000 | E83: ARR x Entry Multiple (auto)
A84: Total Recycled Capital ($) | B84: 120000000 | E84: 4 x $30M (auto)
A86: PER-DEAL ALLOCATION (Mixed Portfolio + Entry Margins)
A87: Override per-deal NDR here. UW NDR = what was underwritten. Real NDR = actual performance.
A88: PER-DEAL MIX (reference only -- engine uses uniform NDR via scenario picker B136) | B88: Outcome | C88: Profile | D88: ARR ($mm) | E88: Entry Mult | G88: UW NDR | H88: Real NDR | J88: Close M | K88: Close M (#)
A89: #1 | B89: WINNER | C89: STELLAR | D89: 24 | E89: 1.24 | G89: 1.05 | H89: 1 | J89: M4 | K89: 4
A90: #2 | B90: AVERAGE | C90: PLAN | D90: 24 | E90: 1.24 | G90: 0.9 | H90: 0.85 | J90: M7 | K90: 7
A91: #3 | B91: WINNER | C91: STELLAR | D91: 24 | E91: 1.24 | G91: 0.92 | H91: 1 | J91: M10 | K91: 10
A92: #4 | B92: LOSER | C92: DUD | D92: 24 | E92: 1.24 | G92: 1.03 | H92: 0.8 | J92: M12 | K92: 12
A93: #5 | B93: LOSER | C93: DUD | D93: 24 | E93: 1.24 | G93: 0.9 | H93: 0.8 | J93: M16 | K93: 16
A95: Recycled deals (corrected to feasible timing: M36/48/60/72)
A96: #6 | B96: WINNER | C96: STELLAR | D96: 24 | E96: 1.2 | G96: 1.05 | H96: 1 | J96: M24 | K96: 24
A97: #7 | B97: WINNER | C97: STELLAR | D97: 24 | E97: 1.2 | G97: 1.05 | H97: 1 | J97: M28 | K97: 32
A98: #8 | B98: AVERAGE | C98: PLAN | D98: 24 | E98: 1.2 | G98: 0.9 | H98: 0.85 | J98: M32 | K98: 40
A99: #9 | B99: LOSER | C99: DUD | D99: 0 | E99: 1.2 | G99: 0.9 | H99: 0.8 | J99: M36 | K99: 51
A100: R100-SPECIFIC recycled close months (faster -- only feasible at 100% retention)
A101: OpCo #6 (R100 close) | D101: 24 | E101: 1.25 | H101: 1 | K101: 24
A102: OpCo #7 (R100 close) | D102: 24 | E102: 1.25 | H102: 1 | K102: 28
A103: OpCo #8 (R100 close) | B103: 140 | D103: 24 | E103: 1.25 | H103: 0.85 | K103: 32
A104: OpCo #9 (R100 close) | B104: 200000 | D104: 24 | E104: 1.25 | H104: 0.8 | K104: 36
A105: R100 recycle period (months) | B105: 36 | C105: R100 keeps original 36mo period (only feasible at 100% retention). | E105: Severance paid on base, not loaded
A106: Avg Tenure (years) | B106: 4 | E106: Drives severance weeks per person
A107: Weeks Severance per Year of Service | B107: 2 | E107: Lean policy
A108: Severance Cap (weeks) | B108: 12 | E108: Max weeks per individual
A109: Avg Severance Weeks per FTE (auto) | B109: 8 | E109: MIN(weeks_per_yr x tenure, cap)
A110: Avg Severance per FTE ($) (auto) | B110: 35000 | C110: Raised from $17.3K to $35K/FTE (16 weeks vs 8 weeks). Matches US senior tech norms. | E110: Base salary basis
...

Sheet 2. LP Economics
A1: LP ECONOMICS BY COMMITMENT SIZE
A2: Live from engines. Returns are SIZE-INVARIANT (DPI/IRR same across commit sizes). Cash scales linearly.
A3: =" Active scenario (Tab 1 B136): " & '1. Press Assumptions'!$B$136 & " | Toggle Bull / Base / Bear on Tab 1 to recalc this tab."
B4: $5M | E4: $10M | H4: $25M
B5: No Recycle | C5: 50% Recycle | D5: 100% Recycle | E5: No Recycle | F5: 50% Recycle | G5: 100% Recycle | H5: No Recycle | I5: 50% Recycle | J5: 100% Recycle
A7: FUND PARTICIPATION
A8: Commitment | B8: 5 | C8: 5 | D8: 5 | E8: 10 | F8: 10 | G8: 10 | H8: 25 | I8: 25 | J8: 25
A9: Payback (months) | B9: TBD | C9: TBD | D9: TBD | E9: TBD | F9: TBD | G9: TBD | H9: TBD | I9: TBD | J9: TBD
A11: 10-YEAR RETURNS
A12: LP Net IRR (Staged) | B12: ='_Engine_NR'!$B$277 | C12: ='_Engine_R50'!$B$277 | D12: ='_Engine_R100'!$B$277 | E12: ='_Engine_NR'!$B$277 | F12: ='_Engine_R50'!$B$277 | G12: ='_Engine_R100'!$B$277 | H12: ='_Engine_NR'!$B$277 | I12: ='_Engine_R50'!$B$277 | J12: ='_Engine_R100'!$B$277
A13: LP MOIC / DPI | B13: ='_Engine_NR'!$B$254 | C13: ='_Engine_R50'!$B$254 | D13: ='_Engine_R100'!$B$254 | E13: ='_Engine_NR'!$B$254 | F13: ='_Engine_R50'!$B$254 | G13: ='_Engine_R100'!$B$254 | H13: ='_Engine_NR'!$B$254 | I13: ='_Engine_R50'!$B$254 | J13: ='_Engine_R100'!$B$254
A14: Cash Distributed | B14: =B13*B8 | C14: =C13*C8 | D14: =D13*D8 | E14: =E13*E8 | F14: =F13*F8 | G14: =G13*G8 | H14: =H13*H8 | I14: =I13*I8 | J14: =J13*J8
A16: 15-YEAR RETURNS
A17: LP Net IRR (Staged) | B17: ='_Engine_NR'!$B$276 | C17: ='_Engine_R50'!$B$276 | D17: ='_Engine_R100'!$B$276 | E17: ='_Engine_NR'!$B$276 | F17: ='_Engine_R50'!$B$276 | G17: ='_Engine_R100'!$B$276 | H17: ='_Engine_NR'!$B$276 | I17: ='_Engine_R50'!$B$276 | J17: ='_Engine_R100'!$B$276
A18: LP MOIC / DPI | B18: ='_Engine_NR'!$B$252 | C18: ='_Engine_R50'!$B$252 | D18: ='_Engine_R100'!$B$252 | E18: ='_Engine_NR'!$B$252 | F18: ='_Engine_R50'!$B$252 | G18: ='_Engine_R100'!$B$252 | H18: ='_Engine_NR'!$B$252 | I18: ='_Engine_R50'!$B$252 | J18: ='_Engine_R100'!$B$252
A19: Total Cash | B19: =B18*B8 | C19: =C18*C8 | D19: =D18*D8 | E19: =E18*E8 | F19: =F18*F8 | G19: =G18*G8 | H19: =H18*H8 | I19: =I18*I8 | J19: =J18*J8
A21: NOTE: returns above are identical across commitment sizes (the model has no LP class differentiation).
A22: See Tab 11 for NDR x Margin joint sensitivity. See Tab 20 for quarterly cash schedule.
B31: 0 | C31: 0 | D31: 0 | E31: 0 | F31: 0 | G31: 0 | H31: 0 | I31: 0 | J31: 0
D32: 0 | G32: 0 | J32: 0
D33: 0 | G33: 0 | J33: 0
B45: 0 | E45: 0 | H45: 0
A50: POTENTIAL LP CLASS STRUCTURE (placeholder -- not in deck)
A51: Class | B51: Min commit | C51: Mgmt fee discount | D51: Co-invest pro-rata | E51: LPAC seat | F51: Notes
A52: Standard | B52: $1M | C52: None | D52: None | E52: No | F52: Default class. No structural differentiation in deck.
A53: Co-invest eligible | B53: $10M | C53: None | D53: Yes (placeholder) | E53: No | F53: Not actually offered.
A54: LPAC | B54: $25M | C54: None | D54: Yes (placeholder) | E54: Yes (placeholder) | F54: Standard market term.
A55: Anchor | B55: $50M+ | C55: 25-50% (placeholder) | D55: Yes (placeholder) | E55: Yes (placeholder) | F55: Anchor LPs typically negotiate fee discount.
A56: LP should ask: are any of the above terms negotiable? Side-letter MFN clause? Anchor commitments?

Sheet 3. Deal Allocation
A1: PRESS CAPITAL -- DEAL ALLOCATION
A2: =" Scenario-driven. NDR = "&TEXT(IF('1. Press Assumptions'!$B$136="Bear",0.8,IF('1. Press Assumptions'!$B$136="Bull",0.9,0.85)),"0%")&" (Tab 1 B136). 1.24x entry. 50/50 sev split."
A4: Deal | B4: ARR ($mm) | C4: Entry Mult | D4: Gross Price | E4: Sev Disc | F4: Net Price | G4: NDR | H4: Entry Profit | I4: Close Mo
A5: #1 | B5: ='1. Press Assumptions'!$D$89 | C5: ='1. Press Assumptions'!$E$89 | D5: =B5*C5 | E5: =B5*0.1154*0.5 | F5: =D5-E5 | G5: =IF('1. Press Assumptions'!$B$136="Bear",0.8,IF('1. Press Assumptions'!$B$136="Bull",0.9,0.85)) | H5: 0 | I5: ="M"&'1. Press Assumptions'!$K$89
A6: #2 | B6: ='1. Press Assumptions'!$D$90 | C6: ='1. Press Assumptions'!$E$90 | D6: =B6*C6 | E6: =B6*0.1154*0.5 | F6: =D6-E6 | G6: =IF('1. Press Assumptions'!$B$136="Bear",0.8,IF('1. Press Assumptions'!$B$136="Bull",0.9,0.85)) | H6: 0 | I6: ="M"&'1. Press Assumptions'!$K$90
A7: #3 | B7: ='1. Press Assumptions'!$D$91 | C7: ='1. Press Assumptions'!$E$91 | D7: =B7*C7 | E7: =B7*0.1154*0.5 | F7: =D7-E7 | G7: =IF('1. Press Assumptions'!$B$136="Bear",0.8,IF('1. Press Assumptions'!$B$136="Bull",0.9,0.85)) | H7: 0 | I7: ="M"&'1. Press Assumptions'!$K$91
A8: #4 | B8: ='1. Press Assumptions'!$D$92 | C8: ='1. Press Assumptions'!$E$92 | D8: =B8*C8 | E8: =B8*0.1154*0.5 | F8: =D8-E8 | G8: =IF('1. Press Assumptions'!$B$136="Bear",0.8,IF('1. Press Assumptions'!$B$136="Bull",0.9,0.85)) | H8: 0 | I8: ="M"&'1. Press Assumptions'!$K$92
A9: #5 | B9: ='1. Press Assumptions'!$D$93 | C9: ='1. Press Assumptions'!$E$93 | D9: =B9*C9 | E9: =B9*0.1154*0.5 | F9: =D9-E9 | G9: =IF('1. Press Assumptions'!$B$136="Bear",0.8,IF('1. Press Assumptions'!$B$136="Bull",0.9,0.85)) | H9: 0 | I9: ="M"&'1. Press Assumptions'!$K$93
A11: TOTAL | B11: =SUM(B5:B9) | D11: =SUM(D5:D9) | E11: =SUM(E5:E9) | F11: =SUM(F5:F9)
A13: RECYCLED DEALS (50% retention, M1-36)
A14: Deal | B14: ARR ($mm) | C14: Entry Mult | D14: Gross Price | E14: Sev Disc | F14: Net Price | G14: NDR | H14: Entry Profit | I14: Close Mo
A15: #6 | B15: ='1. Press Assumptions'!$D$96 | C15: ='1. Press Assumptions'!$E$96 | D15: =B15*C15 | E15: =B15*0.1154*0.5 | F15: =D15-E15 | G15: =IF('1. Press Assumptions'!$B$136="Bear",0.8,IF('1. Press Assumptions'!$B$136="Bull",0.9,0.85)) | H15: 0 | I15: ="M"&'1. Press Assumptions'!$K$96
A16: #7 | B16: ='1. Press Assumptions'!$D$97 | C16: ='1. Press Assumptions'!$E$97 | D16: =B16*C16 | E16: =B16*0.1154*0.5 | F16: =D16-E16 | G16: =IF('1. Press Assumptions'!$B$136="Bear",0.8,IF('1. Press Assumptions'!$B$136="Bull",0.9,0.85)) | H16: 0 | I16: ="M"&'1. Press Assumptions'!$K$97
A17: #8 | B17: ='1. Press Assumptions'!$D$98 | C17: ='1. Press Assumptions'!$E$98 | D17: =B17*C17 | E17: =B17*0.1154*0.5 | F17: =D17-E17 | G17: =IF('1. Press Assumptions'!$B$136="Bear",0.8,IF('1. Press Assumptions'!$B$136="Bull",0.9,0.85)) | H17: 0 | I17: ="M"&'1. Press Assumptions'!$K$98
A18: #9 | B18: ='1. Press Assumptions'!$D$99 | C18: ='1. Press Assumptions'!$E$99 | D18: =B18*C18 | E18: =B18*0.1154*0.5 | F18: =D18-E18 | G18: =IF('1. Press Assumptions'!$B$136="Bear",0.8,IF('1. Press Assumptions'!$B$136="Bull",0.9,0.85)) | H18: 0 | I18: ="M"&'1. Press Assumptions'!$K$99
A42: Green = premium (profitable + growing). Gold = par. Red = distress discount.

Sheet 4a. Annual P&L (No Recycle)
A1: PRESS CAPITAL -- FUND I P&L | NO RECYCLING | I1: ="Active scenario: " & '1. Press Assumptions'!$B$136 & " (toggle on Tab 1 B136)"
A2: 5 deals @ $24M ARR. Per-deal NDR mix.. LIVE from _Engine_NR -- Tab 1 inputs flow through.
A3: ($mm) | B3: Total | C3: Year 1 | D3: Year 2 | E3: Year 3 | F3: Year 4 | G3: Year 5 | H3: Year 6 | I3: Year 7 | J3: Year 8 | K3: Year 9 | L3: Year 10 | M3: Year 11 | N3: Year 12 | O3: Year 13 | P3: Year 14 | Q3: Year 15
A5: Revenue | B5: =SUM(C5:Q5) | C5: ='_Engine_NR'!B215 | D5: ='_Engine_NR'!B216 | E5: ='_Engine_NR'!B217 | F5: ='_Engine_NR'!B218 | G5: ='_Engine_NR'!B219 | H5: ='_Engine_NR'!B220 | I5: ='_Engine_NR'!B221 | J5: ='_Engine_NR'!B222 | K5: ='_Engine_NR'!B223 | L5: ='_Engine_NR'!B224 | M5: ='_Engine_NR'!B225 | N5: ='_Engine_NR'!B226 | O5: ='_Engine_NR'!B227 | P5: ='_Engine_NR'!B228 | Q5: ='_Engine_NR'!B229
A6: Cost of Goods Sold | B6: =SUM(C6:Q6) | C6: ='_Engine_NR'!C215 | D6: ='_Engine_NR'!C216 | E6: ='_Engine_NR'!C217 | F6: ='_Engine_NR'!C218 | G6: ='_Engine_NR'!C219 | H6: ='_Engine_NR'!C220 | I6: ='_Engine_NR'!C221 | J6: ='_Engine_NR'!C222 | K6: ='_Engine_NR'!C223 | L6: ='_Engine_NR'!C224 | M6: ='_Engine_NR'!C225 | N6: ='_Engine_NR'!C226 | O6: ='_Engine_NR'!C227 | P6: ='_Engine_NR'!C228 | Q6: ='_Engine_NR'!C229
A7: Gross Profit | B7: =SUM(C7:Q7) | C7: =C5-C6 | D7: =D5-D6 | E7: =E5-E6 | F7: =F5-F6 | G7: =G5-G6 | H7: =H5-H6 | I7: =I5-I6 | J7: =J5-J6 | ... Q7: =Q5-Q6
A9: Operating Expenses
A10: Vendor Costs | B10: =SUM(C10:Q10) | C10: ='_Engine_NR'!D215 | D10: ='_Engine_NR'!D216 | E10: ='_Engine_NR'!D217 | F10: ='_Engine_NR'!D218 | G10: ='_Engine_NR'!D219 | H10: ='_Engine_NR'!D220 | I10: ='_Engine_NR'!D221 | J10: ='_Engine_NR'!D222 | K10: ='_Engine_NR'!D223 | L10: ='_Engine_NR'!D224 | M10: ='_Engine_NR'!D225 | N10: ='_Engine_NR'!D226 | O10: ='_Engine_NR'!D227 | P10: ='_Engine_NR'!D228 | Q10: ='_Engine_NR'!D229
A11: Corporate Allocation | B11: =SUM(C11:Q11) | C11: ='_Engine_NR'!E215 | D11: ='_Engine_NR'!E216 | E11: ='_Engine_NR'!E217 | F11: ='_Engine_NR'!E218 | G11: ='_Engine_NR'!E219 | H11: ='_Engine_NR'!E220 | I11: ='_Engine_NR'!E221 | J11: ='_Engine_NR'!E222 | K11: ='_Engine_NR'!E223 | L11: ='_Engine_NR'!E224 | M11: ='_Engine_NR'!E225 | N11: ='_Engine_NR'!E226 | O11: ='_Engine_NR'!E227 | P11: ='_Engine_NR'!E228 | Q11: ='_Engine_NR'!E229
A12: Team Compensation | B12: =SUM(C12:Q12) | C12: ='_Engine_NR'!F215 | D12: ='_Engine_NR'!F216 | E12: ='_Engine_NR'!F217 | F12: ='_Engine_NR'!F218 | G12: ='_Engine_NR'!F219 | H12: ='_Engine_NR'!F220 | I12: ='_Engine_NR'!F221 | J12: ='_Engine_NR'!F222 | K12: ='_Engine_NR'!F223 | L12: ='_Engine_NR'!F224 | M12: ='_Engine_NR'!F225 | N12: ='_Engine_NR'!F226 | O12: ='_Engine_NR'!F227 | P12: ='_Engine_NR'!F228 | Q12: ='_Engine_NR'!F229
A13: Legacy Headcount Expenses | B13: =SUM(C13:Q13) | C13: ='_Engine_NR'!G215 | D13: ='_Engine_NR'!G216 | E13: ='_Engine_NR'!G217 | F13: ='_Engine_NR'!G218 | G13: ='_Engine_NR'!G219 | H13: ='_Engine_NR'!G220 | I13: ='_Engine_NR'!G221 | J13: ='_Engine_NR'!G222 | K13: ='_Engine_NR'!G223 | L13: ='_Engine_NR'!G224 | M13: ='_Engine_NR'!G225 | N13: ='_Engine_NR'!G226 | O13: ='_Engine_NR'!G227 | P13: ='_Engine_NR'!G228 | Q13: ='_Engine_NR'!G229
A14: Bonus Pool | B14: =SUM(C14:Q14) | C14: ='_Engine_NR'!H215 | D14: ='_Engine_NR'!H216 | E14: ='_Engine_NR'!H217 | F14: ='_Engine_NR'!H218 | G14: ='_Engine_NR'!H219 | H14: ='_Engine_NR'!H220 | I14: ='_Engine_NR'!H221 | J14: ='_Engine_NR'!H222 | K14: ='_Engine_NR'!H223 | L14: ='_Engine_NR'!H224 | M14: ='_Engine_NR'!H225 | N14: ='_Engine_NR'!H226 | O14: ='_Engine_NR'!H227 | P14: ='_Engine_NR'!H228 | Q14: ='_Engine_NR'!H229
A15: Total Operating Expenses | B15: =SUM(C15:Q15) | C15: =C10+C11+C12+C13+C14 | D15: =D10+D11+D12+D13+D14 | E15: =E10+E11+E12+E13+E14 | F15: =F10+F11+F12+F13+F14 | G15: =G10+G11+G12+G13+G14 | H15: =H10+H11+H12+H13+H14 | I15: =I10+I11+I12+I13+I14 | J15: =J10+J11+J12+J13+J14 | ... Q15: =Q10+Q11+Q12+Q13+Q14
A17: EBITDA | B17: =SUM(C17:Q17) | C17: ='_Engine_NR'!I215 | D17: ='_Engine_NR'!I216 | E17: ='_Engine_NR'!I217 | F17: ='_Engine_NR'!I218 | G17: ='_Engine_NR'!I219 | H17: ='_Engine_NR'!I220 | I17: ='_Engine_NR'!I221 | J17: ='_Engine_NR'!I222 | K17: ='_Engine_NR'!I223 | L17: ='_Engine_NR'!I224 | M17: ='_Engine_NR'!I225 | N17: ='_Engine_NR'!I226 | O17: ='_Engine_NR'!I227 | P17: ='_Engine_NR'!I228 | Q17: ='_Engine_NR'!I229
A18: EBITDA Margin | B18: =B17/B5 | C18: =IF(C5=0,0,C17/C5) | D18: =IF(D5=0,0,D17/D5) | E18: =IF(E5=0,0,E17/E5) | F18: =IF(F5=0,0,F17/F5) | G18: =IF(G5=0,0,G17/G5) | H18: =IF(H5=0,0,H17/H5) | I18: =IF(I5=0,0,I17/I5) | J18: =IF(J5=0,0,J17/J5) | ... Q18: =IF(Q5=0,0,Q17/Q5)
A20: Severance (Press 50%) | B20: =SUM(C20:Q20) | C20: ='_Engine_NR'!J215 | D20: ='_Engine_NR'!J216 | E20: ='_Engine_NR'!J217 | F20: ='_Engine_NR'!J218 | G20: ='_Engine_NR'!J219 | H20: ='_Engine_NR'!J220 | I20: ='_Engine_NR'!J221 | J20: ='_Engine_NR'!J222 | K20: ='_Engine_NR'!J223 | L20: ='_Engine_NR'!J224 | M20: ='_Engine_NR'!J225 | N20: ='_Engine_NR'!J226 | O20: ='_Engine_NR'!J227 | P20: ='_Engine_NR'!J228 | Q20: ='_Engine_NR'!J229
A21: Operating Income | B21: =B17-B20 | C21: =C17-C20 | D21: =D17-D20 | E21: =E17-E20 | F21: =F17-F20 | G21: =G17-G20 | H21: =H17-H20 | I21: =I17-I20 | ... Q21: =Q17-Q20
A23: Management Fee | B23: =SUM(C23:Q23) | C23: ='_Engine_NR'!K215 | D23: ='_Engine_NR'!K216 | E23: ='_Engine_NR'!K217 | F23: ='_Engine_NR'!K218 | G23: ='_Engine_NR'!K219 | H23: ='_Engine_NR'!K220 | I23: ='_Engine_NR'!K221 | J23: ='_Engine_NR'!K222 | K23: ='_Engine_NR'!K223 | L23: ='_Engine_NR'!K224 | M23: ='_Engine_NR'!K225 | N23: ='_Engine_NR'!K226 | O23: ='_Engine_NR'!K227 | P23: ='_Engine_NR'!K228 | Q23: ='_Engine_NR'!K229
A24: Distributable Cash | B24: =SUM(C24:Q24) | C24: =C21-C23 | D24: =D21-D23 | E24: =E21-E23 | F24: =F21-F23 | G24: =G21-G23 | H24: =H21-H23 | I24: =I21-I23 | J24: =J21-J23 | ... Q24: =Q21-Q23
A25: Cumulative Distributable | B25: =Q25 | C25: =C24 | D25: =C25+D24 | E25: =D25+E24 | F25: =E25+F24 | G25: =F25+G24 | H25: =G25+H24 | I25: =H25+I24 | J25: =I25+J24 | K25: =J25+K24 | ... Q25: =P25+Q24

Sheet 4b. Annual P&L (Recycle)
A1: PRESS CAPITAL -- FUND I P&L | 50% RECYCLE x 36mo | I1: ="Active scenario: " & '1. Press Assumptions'!$B$136 & " (toggle on Tab 1 B136)"
A2: 8 deals @ $24M ARR. 50% retained M1-36.. LIVE from _Engine_R50.
A3: ($mm) | B3: Total | C3: Year 1 | D3: Year 2 | E3: Year 3 | F3: Year 4 | G3: Year 5 | H3: Year 6 | I3: Year 7 | J3: Year 8 | K3: Year 9 | L3: Year 10 | M3: Year 11 | N3: Year 12 | O3: Year 13 | P3: Year 14 | Q3: Year 15
A5: Revenue | B5: =SUM(C5:Q5) | C5: ='_Engine_R50'!B215 | D5: ='_Engine_R50'!B216 | E5: ='_Engine_R50'!B217 | F5: ='_Engine_R50'!B218 | G5: ='_Engine_R50'!B219 | H5: ='_Engine_R50'!B220 | I5: ='_Engine_R50'!B221 | J5: ='_Engine_R50'!B222 | K5: ='_Engine_R50'!B223 | L5: ='_Engine_R50'!B224 | M5: ='_Engine_R50'!B225 | N5: ='_Engine_R50'!B226 | O5: ='_Engine_R50'!B227 | P5: ='_Engine_R50'!B228 | Q5: ='_Engine_R50'!B229
A6: Cost of Goods Sold | B6: =SUM(C6:Q6) | C6: ='_Engine_R50'!C215 | D6: ='_Engine_R50'!C216 | E6: ='_Engine_R50'!C217 | F6: ='_Engine_R50'!C218 | G6: ='_Engine_R50'!C219 | H6: ='_Engine_R50'!C220 | I6: ='_Engine_R50'!C221 | J6: ='_Engine_R50'!C222 | K6: ='_Engine_R50'!C223 | L6: ='_Engine_R50'!C224 | M6: ='_Engine_R50'!C225 | N6: ='_Engine_R50'!C226 | O6: ='_Engine_R50'!C227 | P6: ='_Engine_R50'!C228 | Q6: ='_Engine_R50'!C229
A7: Gross Profit | B7: =SUM(C7:Q7) | C7: =C5-C6 | D7: =D5-D6 | E7: =E5-E6 | F7: =F5-F6 | G7: =G5-G6 | H7: =H5-H6 | I7: =I5-I6 | J7: =J5-J6 | ... Q7: =Q5-Q6
A9: Operating Expenses
A10: Vendor Costs | B10: =SUM(C10:Q10) | C10: ='_Engine_R50'!D215 | D10: ='_Engine_R50'!D216 | E10: ='_Engine_R50'!D217 | F10: ='_Engine_R50'!D218 | G10: ='_Engine_R50'!D219 | H10: ='_Engine_R50'!D220 | I10: ='_Engine_R50'!D221 | J10: ='_Engine_R50'!D222 | K10: ='_Engine_R50'!D223 | L10: ='_Engine_R50'!D224 | M10: ='_Engine_R50'!D225 | N10: ='_Engine_R50'!D226 | O10: ='_Engine_R50'!D227 | P10: ='_Engine_R50'!D228 | Q10: ='_Engine_R50'!D229
A11: Corporate Allocation | B11: =SUM(C11:Q11) | C11: ='_Engine_R50'!E215 | D11: ='_Engine_R50'!E216 | E11: ='_Engine_R50'!E217 | F11: ='_Engine_R50'!E218 | G11: ='_Engine_R50'!E219 | H11: ='_Engine_R50'!E220 | I11: ='_Engine_R50'!E221 | J11: ='_Engine_R50'!E222 | K11: ='_Engine_R50'!E223 | L11: ='_Engine_R50'!E224 | M11: ='_Engine_R50'!E225 | N11: ='_Engine_R50'!E226 | O11: ='_Engine_R50'!E227 | P11: ='_Engine_R50'!E228 | Q11: ='_Engine_R50'!E229
A12: Team Compensation | B12: =SUM(C12:Q12) | C12: ='_Engine_R50'!F215 | D12: ='_Engine_R50'!F216 | E12: ='_Engine_R50'!F217 | F12: ='_Engine_R50'!F218 | G12: ='_Engine_R50'!F219 | H12: ='_Engine_R50'!F220 | I12: ='_Engine_R50'!F221 | J12: ='_Engine_R50'!F222 | K12: ='_Engine_R50'!F223 | L12: ='_Engine_R50'!F224 | M12: ='_Engine_R50'!F225 | N12: ='_Engine_R50'!F226 | O12: ='_Engine_R50'!F227 | P12: ='_Engine_R50'!F228 | Q12: ='_Engine_R50'!F229
A13: Legacy Headcount Expenses | B13: =SUM(C13:Q13) | C13: ='_Engine_R50'!G215 | D13: ='_Engine_R50'!G216 | E13: ='_Engine_R50'!G217 | F13: ='_Engine_R50'!G218 | G13: ='_Engine_R50'!G219 | H13: ='_Engine_R50'!G220 | I13: ='_Engine_R50'!G221 | J13: ='_Engine_R50'!G222 | K13: ='_Engine_R50'!G223 | L13: ='_Engine_R50'!G224 | M13: ='_Engine_R50'!G225 | N13: ='_Engine_R50'!G226 | O13: ='_Engine_R50'!G227 | P13: ='_Engine_R50'!G228 | Q13: ='_Engine_R50'!G229
A14: Bonus Pool | B14: =SUM(C14:Q14) | C14: ='_Engine_R50'!H215 | D14: ='_Engine_R50'!H216 | E14: ='_Engine_R50'!H217 | F14: ='_Engine_R50'!H218 | G14: ='_Engine_R50'!H219 | H14: ='_Engine_R50'!H220 | I14: ='_Engine_R50'!H221 | J14: ='_Engine_R50'!H222 | K14: ='_Engine_R50'!H223 | L14: ='_Engine_R50'!H224 | M14: ='_Engine_R50'!H225 | N14: ='_Engine_R50'!H226 | O14: ='_Engine_R50'!H227 | P14: ='_Engine_R50'!H228 | Q14: ='_Engine_R50'!H229
A15: Total Operating Expenses | B15: =SUM(C15:Q15) | C15: =C10+C11+C12+C13+C14 | D15: =D10+D11+D12+D13+D14 | E15: =E10+E11+E12+E13+E14 | F15: =F10+F11+F12+F13+F14 | G15: =G10+G11+G12+G13+G14 | H15: =H10+H11+H12+H13+H14 | I15: =I10+I11+I12+I13+I14 | J15: =J10+J11+J12+J13+J14 | ... Q15: =Q10+Q11+Q12+Q13+Q14
A17: EBITDA | B17: =SUM(C17:Q17) | C17: ='_Engine_R50'!I215 | D17: ='_Engine_R50'!I216 | E17: ='_Engine_R50'!I217 | F17: ='_Engine_R50'!I218 | G17: ='_Engine_R50'!I219 | H17: ='_Engine_R50'!I220 | I17: ='_Engine_R50'!I221 | J17: ='_Engine_R50'!I222 | K17: ='_Engine_R50'!I223 | L17: ='_Engine_R50'!I224 | M17: ='_Engine_R50'!I225 | N17: ='_Engine_R50'!I226 | O17: ='_Engine_R50'!I227 | P17: ='_Engine_R50'!I228 | Q17: ='_Engine_R50'!I229
A18: EBITDA Margin | B18: =B17/B5 | C18: =IF(C5=0,0,C17/C5) | D18: =IF(D5=0,0,D17/D5) | E18: =IF(E5=0,0,E17/E5) | F18: =IF(F5=0,0,F17/F5) | G18: =IF(G5=0,0,G17/G5) | H18: =IF(H5=0,0,H17/H5) | I18: =IF(I5=0,0,I17/I5) | J18: =IF(J5=0,0,J17/J5) | ... Q18: =IF(Q5=0,0,Q17/Q5)
A20: Severance (Press 50%) | B20: =SUM(C20:Q20) | C20: ='_Engine_R50'!J215 | D20: ='_Engine_R50'!J216 | E20: ='_Engine_R50'!J217 | F20: ='_Engine_R50'!J218 | G20: ='_Engine_R50'!J219 | H20: ='_Engine_R50'!J220 | I20: ='_Engine_R50'!J221 | J20: ='_Engine_R50'!J222 | K20: ='_Engine_R50'!J223 | L20: ='_Engine_R50'!J224 | M20: ='_Engine_R50'!J225 | N20: ='_Engine_R50'!J226 | O20: ='_Engine_R50'!J227 | P20: ='_Engine_R50'!J228 | Q20: ='_Engine_R50'!J229
A21: Operating Income | B21: =B17-B20 | C21: =C17-C20 | D21: =D17-D20 | E21: =E17-E20 | F21: =F17-F20 | G21: =G17-G20 | H21: =H17-H20 | I21: =I17-I20 | ... Q21: =Q17-Q20
A23: Management Fee | B23: =SUM(C23:Q23) | C23: ='_Engine_R50'!K215 | D23: ='_Engine_R50'!K216 | E23: ='_Engine_R50'!K217 | F23: ='_Engine_R50'!K218 | G23: ='_Engine_R50'!K219 | H23: ='_Engine_R50'!K220 | I23: ='_Engine_R50'!K221 | J23: ='_Engine_R50'!K222 | K23: ='_Engine_R50'!K223 | L23: ='_Engine_R50'!K224 | M23: ='_Engine_R50'!K225 | N23: ='_Engine_R50'!K226 | O23: ='_Engine_R50'!K227 | P23: ='_Engine_R50'!K228 | Q23: ='_Engine_R50'!K229
A24: Retained for Recycling (50%) | B24: =SUM(C24:Q24) | C24: ='_Engine_R50'!M215 | D24: ='_Engine_R50'!M216 | E24: ='_Engine_R50'!M217 | F24: ='_Engine_R50'!M218 | G24: ='_Engine_R50'!M219 | H24: ='_Engine_R50'!M220 | I24: ='_Engine_R50'!M221 | J24: ='_Engine_R50'!M222 | K24: ='_Engine_R50'!M223 | L24: ='_Engine_R50'!M224 | M24: ='_Engine_R50'!M225 | N24: ='_Engine_R50'!M226 | O24: ='_Engine_R50'!M227 | P24: ='_Engine_R50'!M228 | Q24: ='_Engine_R50'!M229
A25: Distributable Cash | B25: =SUM(C25:Q25) | C25: ='_Engine_R50'!P215 | D25: ='_Engine_R50'!P216 | E25: ='_Engine_R50'!P217 | F25: ='_Engine_R50'!P218 | G25: ='_Engine_R50'!P219 | H25: ='_Engine_R50'!P220 | I25: ='_Engine_R50'!P221 | J25: ='_Engine_R50'!P222 | K25: ='_Engine_R50'!P223 | L25: ='_Engine_R50'!P224 | M25: ='_Engine_R50'!P225 | N25: ='_Engine_R50'!P226 | O25: ='_Engine_R50'!P227 | P25: ='_Engine_R50'!P228 | Q25: ='_Engine_R50'!P229
A26: Cumulative Distributable | B26: =Q26 | C26: =C25 | D26: =C26+D25 | E26: =D26+E25 | F26: =E26+F25 | G26: =F26+G25 | H26: =G26+H25 | I26: =H26+I25 | J26: =I26+J25 | K26: =J26+K25 | ... Q26: =P26+Q25

Sheet 4g. Annual P&L (100% Recycle)
A1: PRESS CAPITAL -- FUND I P&L | 100% RECYCLE x 36mo | I1: ="Active scenario: " & '1. Press Assumptions'!$B$136 & " (toggle on Tab 1 B136)"
A2: 9 deals @ $24M ARR. 100% retained M1-36.. LIVE from _Engine_R100.
A3: ($mm) | B3: Total | C3: Year 1 | D3: Year 2 | E3: Year 3 | F3: Year 4 | G3: Year 5 | H3: Year 6 | I3: Year 7 | J3: Year 8 | K3: Year 9 | L3: Year 10 | M3: Year 11 | N3: Year 12 | O3: Year 13 | P3: Year 14 | Q3: Year 15
A5: Revenue | B5: =SUM(C5:Q5) | C5: ='_Engine_R100'!B215 | D5: ='_Engine_R100'!B216 | E5: ='_Engine_R100'!B217 | F5: ='_Engine_R100'!B218 | G5: ='_Engine_R100'!B219 | H5: ='_Engine_R100'!B220 | I5: ='_Engine_R100'!B221 | J5: ='_Engine_R100'!B222 | K5: ='_Engine_R100'!B223 | L5: ='_Engine_R100'!B224 | M5: ='_Engine_R100'!B225 | N5: ='_Engine_R100'!B226 | O5: ='_Engine_R100'!B227 | P5: ='_Engine_R100'!B228 | Q5: ='_Engine_R100'!B229
A6: Cost of Goods Sold | B6: =SUM(C6:Q6) | C6: ='_Engine_R100'!C215 | D6: ='_Engine_R100'!C216 | E6: ='_Engine_R100'!C217 | F6: ='_Engine_R100'!C218 | G6: ='_Engine_R100'!C219 | H6: ='_Engine_R100'!C220 | I6: ='_Engine_R100'!C221 | J6: ='_Engine_R100'!C222 | K6: ='_Engine_R100'!C223 | L6: ='_Engine_R100'!C224 | M6: ='_Engine_R100'!C225 | N6: ='_Engine_R100'!C226 | O6: ='_Engine_R100'!C227 | P6: ='_Engine_R100'!C228 | Q6: ='_Engine_R100'!C229
A7: Gross Profit | B7: =SUM(C7:Q7) | C7: =C5-C6 | D7: =D5-D6 | E7: =E5-E6 | F7: =F5-F6 | G7: =G5-G6 | H7: =H5-H6 | I7: =I5-I6 | J7: =J5-J6 | ... Q7: =Q5-Q6
A9: Operating Expenses
A10: Vendor Costs | B10: =SUM(C10:Q10) | C10: ='_Engine_R100'!D215 | D10: ='_Engine_R100'!D216 | E10: ='_Engine_R100'!D217 | F10: ='_Engine_R100'!D218 | G10: ='_Engine_R100'!D219 | H10: ='_Engine_R100'!D220 | I10: ='_Engine_R100'!D221 | J10: ='_Engine_R100'!D222 | K10: ='_Engine_R100'!D223 | L10: ='_Engine_R100'!D224 | M10: ='_Engine_R100'!D225 | N10: ='_Engine_R100'!D226 | O10: ='_Engine_R100'!D227 | P10: ='_Engine_R100'!D228 | Q10: ='_Engine_R100'!D229
A11: Corporate Allocation | B11: =SUM(C11:Q11) | C11: ='_Engine_R100'!E215 | D11: ='_Engine_R100'!E216 | E11: ='_Engine_R100'!E217 | F11: ='_Engine_R100'!E218 | G11: ='_Engine_R100'!E219 | H11: ='_Engine_R100'!E220 | I11: ='_Engine_R100'!E221 | J11: ='_Engine_R100'!E222 | K11: ='_Engine_R100'!E223 | L11: ='_Engine_R100'!E224 | M11: ='_Engine_R100'!E225 | N11: ='_Engine_R100'!E226 | O11: ='_Engine_R100'!E227 | P11: ='_Engine_R100'!E228 | Q11: ='_Engine_R100'!E229
A12: Team Compensation | B12: =SUM(C12:Q12) | C12: ='_Engine_R100'!F215 | D12: ='_Engine_R100'!F216 | E12: ='_Engine_R100'!F217 | F12: ='_Engine_R100'!F218 | G12: ='_Engine_R100'!F219 | H12: ='_Engine_R100'!F220 | I12: ='_Engine_R100'!F221 | J12: ='_Engine_R100'!F222 | K12: ='_Engine_R100'!F223 | L12: ='_Engine_R100'!F224 | M12: ='_Engine_R100'!F225 | N12: ='_Engine_R100'!F226 | O12: ='_Engine_R100'!F227 | P12: ='_Engine_R100'!F228 | Q12: ='_Engine_R100'!F229
A13: Legacy Headcount Expenses | B13: =SUM(C13:Q13) | C13: ='_Engine_R100'!G215 | D13: ='_Engine_R100'!G216 | E13: ='_Engine_R100'!G217 | F13: ='_Engine_R100'!G218 | G13: ='_Engine_R100'!G219 | H13: ='_Engine_R100'!G220 | I13: ='_Engine_R100'!G221 | J13: ='_Engine_R100'!G222 | K13: ='_Engine_R100'!G223 | L13: ='_Engine_R100'!G224 | M13: ='_Engine_R100'!G225 | N13: ='_Engine_R100'!G226 | O13: ='_Engine_R100'!G227 | P13: ='_Engine_R100'!G228 | Q13: ='_Engine_R100'!G229
A14: Bonus Pool | B14: =SUM(C14:Q14) | C14: ='_Engine_R100'!H215 | D14: ='_Engine_R100'!H216 | E14: ='_Engine_R100'!H217 | F14: ='_Engine_R100'!H218 | G14: ='_Engine_R100'!H219 | H14: ='_Engine_R100'!H220 | I14: ='_Engine_R100'!H221 | J14: ='_Engine_R100'!H222 | K14: ='_Engine_R100'!H223 | L14: ='_Engine_R100'!H224 | M14: ='_Engine_R100'!H225 | N14: ='_Engine_R100'!H226 | O14: ='_Engine_R100'!H227 | P14: ='_Engine_R100'!H228 | Q14: ='_Engine_R100'!H229
A15: Total Operating Expenses | B15: =SUM(C15:Q15) | C15: =C10+C11+C12+C13+C14 | D15: =D10+D11+D12+D13+D14 | E15: =E10+E11+E12+E13+E14 | F15: =F10+F11+F12+F13+F14 | G15: =G10+G11+G12+G13+G14 | H15: =H10+H11+H12+H13+H14 | I15: =I10+I11+I12+I13+I14 | J15: =J10+J11+J12+J13+J14 | ... Q15: =Q10+Q11+Q12+Q13+Q14
A17: EBITDA | B17: =SUM(C17:Q17) | C17: ='_Engine_R100'!I215 | D17: ='_Engine_R100'!I216 | E17: ='_Engine_R100'!I217 | F17: ='_Engine_R100'!I218 | G17: ='_Engine_R100'!I219 | H17: ='_Engine_R100'!I220 | I17: ='_Engine_R100'!I221 | J17: ='_Engine_R100'!I222 | K17: ='_Engine_R100'!I223 | L17: ='_Engine_R100'!I224 | M17: ='_Engine_R100'!I225 | N17: ='_Engine_R100'!I226 | O17: ='_Engine_R100'!I227 | P17: ='_Engine_R100'!I228 | Q17: ='_Engine_R100'!I229
A18: EBITDA Margin | B18: =B17/B5 | C18: =IF(C5=0,0,C17/C5) | D18: =IF(D5=0,0,D17/D5) | E18: =IF(E5=0,0,E17/E5) | F18: =IF(F5=0,0,F17/F5) | G18: =IF(G5=0,0,G17/G5) | H18: =IF(H5=0,0,H17/H5) | I18: =IF(I5=0,0,I17/I5) | J18: =IF(J5=0,0,J17/J5) | ... Q18: =IF(Q5=0,0,Q17/Q5)
A20: Severance (Press 50%) | B20: =SUM(C20:Q20) | C20: ='_Engine_R100'!J215 | D20: ='_Engine_R100'!J216 | E20: ='_Engine_R100'!J217 | F20: ='_Engine_R100'!J218 | G20: ='_Engine_R100'!J219 | H20: ='_Engine_R100'!J220 | I20: ='_Engine_R100'!J221 | J20: ='_Engine_R100'!J222 | K20: ='_Engine_R100'!J223 | L20: ='_Engine_R100'!J224 | M20: ='_Engine_R100'!J225 | N20: ='_Engine_R100'!J226 | O20: ='_Engine_R100'!J227 | P20: ='_Engine_R100'!J228 | Q20: ='_Engine_R100'!J229
A21: Operating Income | B21: =B17-B20 | C21: =C17-C20 | D21: =D17-D20 | E21: =E17-E20 | F21: =F17-F20 | G21: =G17-G20 | H21: =H17-H20 | I21: =I17-I20 | ... Q21: =Q17-Q20
A23: Management Fee | B23: =SUM(C23:Q23) | C23: ='_Engine_R100'!K215 | D23: ='_Engine_R100'!K216 | E23: ='_Engine_R100'!K217 | F23: ='_Engine_R100'!K218 | G23: ='_Engine_R100'!K219 | H23: ='_Engine_R100'!K220 | I23: ='_Engine_R100'!K221 | J23: ='_Engine_R100'!K222 | K23: ='_Engine_R100'!K223 | L23: ='_Engine_R100'!K224 | M23: ='_Engine_R100'!K225 | N23: ='_Engine_R100'!K226 | O23: ='_Engine_R100'!K227 | P23: ='_Engine_R100'!K228 | Q23: ='_Engine_R100'!K229
A24: Retained for Recycling (100%) | B24: =SUM(C24:Q24) | C24: ='_Engine_R100'!M215 | D24: ='_Engine_R100'!M216 | E24: ='_Engine_R100'!M217 | F24: ='_Engine_R100'!M218 | G24: ='_Engine_R100'!M219 | H24: ='_Engine_R100'!M220 | I24: ='_Engine_R100'!M221 | J24: ='_Engine_R100'!M222 | K24: ='_Engine_R100'!M223 | L24: ='_Engine_R100'!M224 | M24: ='_Engine_R100'!M225 | N24: ='_Engine_R100'!M226 | O24: ='_Engine_R100'!M227 | P24: ='_Engine_R100'!M228 | Q24: ='_Engine_R100'!M229
A25: Distributable Cash | B25: =SUM(C25:Q25) | C25: ='_Engine_R100'!P215 | D25: ='_Engine_R100'!P216 | E25: ='_Engine_R100'!P217 | F25: ='_Engine_R100'!P218 | G25: ='_Engine_R100'!P219 | H25: ='_Engine_R100'!P220 | I25: ='_Engine_R100'!P221 | J25: ='_Engine_R100'!P222 | K25: ='_Engine_R100'!P223 | L25: ='_Engine_R100'!P224 | M25: ='_Engine_R100'!P225 | N25: ='_Engine_R100'!P226 | O25: ='_Engine_R100'!P227 | P25: ='_Engine_R100'!P228 | Q25: ='_Engine_R100'!P229
A26: Cumulative Distributable | B26: =Q26 | C26: =C25 | D26: =C26+D25 | E26: =D26+E25 | F26: =E26+F25 | G26: =F26+G25 | H26: =G26+H25 | I26: =H26+I25 | J26: =I26+J25 | K26: =J26+K25 | ... Q26: =P26+Q25

Sheet 4c. Monthly P&L (No Recycle)
A1: MONTHLY P&L | 5 deals @ $24M ARR (LIVE)
A3: ($mm) | B3: M1 | C3: M2 | D3: M3 | E3: M4 | F3: M5 | G3: M6 | H3: M7 | I3: M8 | J3: M9 | K3: M10 | L3: M11 | M3: M12 | N3: M13 | O3: M14 | P3: M15 | Q3: M16 | R3: M17 | S3: M18 | T3: M19 | U3: M20 | V3: M21 | W3: M22 | X3: M23 | Y3: M24 | Z3: M25 | AA3: M26 | AB3: M27 | AC3: M28 | AD3: M29 | AE3: M30 | AF3: M31 | AG3: M32 | AH3: M33 | AI3: M34 | AJ3: M35 | AK3: M36 | AL3: M37 | AM3: M38 | AN3: M39 | AO3: M40 | AP3: M41 | AQ3: M42 | AR3: M43 | AS3: M44 | AT3: M45 | AU3: M46 | AV3: M47 | AW3: M48 | AX3: M49 | AY3: M50 | AZ3: M51 | BA3: M52 | BB3: M53 | BC3: M54 | BD3: M55 | BE3: M56 | BF3: M57 | BG3: M58 | BH3: M59 | BI3: M60 | BJ3: M61 | BK3: M62 | BL3: M63 | BM3: M64 | BN3: M65 | BO3: M66 | BP3: M67 | BQ3: M68 | BR3: M69 | BS3: M70 | BT3: M71 | BU3: M72 | BV3: M73 | BW3: M74 | BX3: M75 | BY3: M76 | BZ3: M77 | CA3: M78 | CB3: M79 | CC3: M80 | CD3: M81 | CE3: M82 | CF3: M83 | CG3: M84 | CH3: M85 | CI3: M86 | CJ3: M87 | CK3: M88 | CL3: M89 | CM3: M90 | CN3: M91 | CO3: M92 | CP3: M93 | CQ3: M94 | CR3: M95 | CS3: M96 | CT3: M97 | CU3: M98 | CV3: M99 | CW3: M100 | CX3: M101 | CY3: M102 | CZ3: M103 | DA3: M104 | DB3: M105 | DC3: M106 | DD3: M107 | DE3: M108 | DF3: M109 | DG3: M110 | DH3: M111 | DI3: M112 | DJ3: M113 | DK3: M114 | DL3: M115 | DM3: M116 | DN3: M117 | DO3: M118 | DP3: M119 | DQ3: M120 | DR3: M121 | DS3: M122 | DT3: M123 | DU3: M124 | DV3: M125 | DW3: M126 | DX3: M127 | DY3: M128 | DZ3: M129 | EA3: M130 | EB3: M131 | EC3: M132 | ED3: M133 | EE3: M134 | EF3: M135 | EG3: M136 | EH3: M137 | EI3: M138 | EJ3: M139 | EK3: M140 | EL3: M141 | EM3: M142 | EN3: M143 | EO3: M144 | EP3: M145 | EQ3: M146 | ER3: M147 | ES3: M148 | ET3: M149 | EU3: M150 | EV3: M151 | EW3: M152 | EX3: M153 | EY3: M154 | EZ3: M155 | FA3: M156 | FB3: M157 | FC3: M158 | FD3: M159 | FE3: M160 | FF3: M161 | FG3: M162 | FH3: M163 | FI3: M164 | FJ3: M165 | FK3: M166 | FL3: M167 | FM3: M168 | FN3: M169 | FO3: M170 | FP3: M171 | FQ3: M172 | FR3: M173 | FS3: M174 | FT3: M175 | FU3: M176 | FV3: M177 | FW3: M178 | FX3: M179 | FY3: M180
A5: Revenue by Deal
A6: Deal #1 | B6: ='_Engine_NR'!F31/12 | C6: ='_Engine_NR'!F32/12 | D6: ='_Engine_NR'!F33/12 | E6: ='_Engine_NR'!F34/12 | F6: ='_Engine_NR'!F35/12 | G6: ='_Engine_NR'!F36/12 | H6: ='_Engine_NR'!F37/12 | I6: ='_Engine_NR'!F38/12 | J6: ='_Engine_NR'!F39/12 | K6: ='_Engine_NR'!F40/12 | L6: ='_Engine_NR'!F41/12 | M6: ='_Engine_NR'!F42/12 | N6: ='_Engine_NR'!F43/12 | O6: ='_Engine_NR'!F44/12 | P6: ='_Engine_NR'!F45/12 | Q6: ='_Engine_NR'!F46/12 | R6: ='_Engine_NR'!F47/12 | S6: ='_Engine_NR'!F48/12 | T6: ='_Engine_NR'!F49/12 | U6: ='_Engine_NR'!F50/12 | V6: ='_Engine_NR'!F51/12 | W6: ='_Engine_NR'!F52/12 | X6: ='_Engine_NR'!F53/12 | Y6: ='_Engine_NR'!F54/12 | Z6: ='_Engine_NR'!F55/12 | AA6: ='_Engine_NR'!F56/12 | AB6: ='_Engine_NR'!F57/12 | AC6: ='_Engine_NR'!F58/12 | AD6: ='_Engine_NR'!F59/12 | AE6: ='_Engine_NR'!F60/12 | AF6: ='_Engine_NR'!F61/12 | AG6: ='_Engine_NR'!F62/12 | AH6: ='_Engine_NR'!F63/12 | AI6: ='_Engine_NR'!F64/12 | AJ6: ='_Engine_NR'!F65/12 | AK6: ='_Engine_NR'!F66/12 | AL6: ='_Engine_NR'!F67/12 | AM6: ='_Engine_NR'!F68/12 | AN6: ='_Engine_NR'!F69/12 | AO6: ='_Engine_NR'!F70/12 | AP6: ='_Engine_NR'!F71/12 | AQ6: ='_Engine_NR'!F72/12 | AR6: ='_Engine_NR'!F73/12 | AS6: ='_Engine_NR'!F74/12 | AT6: ='_Engine_NR'!F75/12 | AU6: ='_Engine_NR'!F76/12 | AV6: ='_Engine_NR'!F77/12 | AW6: ='_Engine_NR'!F78/12 | AX6: ='_Engine_NR'!F79/12 | AY6: ='_Engine_NR'!F80/12 | AZ6: ='_Engine_NR'!F81/12 | BA6: ='_Engine_NR'!F82/12 | BB6: ='_Engine_NR'!F83/12 | BC6: ='_Engine_NR'!F84/12 | BD6: ='_Engine_NR'!F85/12 | BE6: ='_Engine_NR'!F86/12 | BF6: ='_Engine_NR'!F87/12 | BG6: ='_Engine_NR'!F88/12 | BH6: ='_Engine_NR'!F89/12 | BI6: ='_Engine_NR'!F90/12 | BJ6: ='_Engine_NR'!F91/12 | BK6: ='_Engine_NR'!F92/12 | BL6: ='_Engine_NR'!F93/12 | BM6: ='_Engine_NR'!F94/12 | BN6: ='_Engine_NR'!F95/12 | BO6: ='_Engine_NR'!F96/12 | BP6: ='_Engine_NR'!F97/12 | BQ6: ='_Engine_NR'!F98/12 | BR6: ='_Engine_NR'!F99/12 | BS6: ='_Engine_NR'!F100/12 | BT6: ='_Engine_NR'!F101/12 | BU6: ='_Engine_NR'!F102/12 | BV6: ='_Engine_NR'!F103/12 | BW6: ='_Engine_NR'!F104/12 | BX6: ='_Engine_NR'!F105/12 | BY6: ='_Engine_NR'!F106/12 | BZ6: ='_Engine_NR'!F107/12 | CA6: ='_Engine_NR'!F108/12 | CB6: ='_Engine_NR'!F109/12 | CC6: ='_Engine_NR'!F110/12 | CD6: ='_Engine_NR'!F111/12 | CE6: ='_Engine_NR'!F112/12 | CF6: ='_Engine_NR'!F113/12 | CG6: ='_Engine_NR'!F114/12 | CH6: ='_Engine_NR'!F115/12 | CI6: ='_Engine_NR'!F116/12 | CJ6: ='_Engine_NR'!F117/12 | CK6: ='_Engine_NR'!F118/12 | CL6: ='_Engine_NR'!F119/12 | CM6: ='_Engine_NR'!F120/12 | CN6: ='_Engine_NR'!F121/12 | CO6: ='_Engine_NR'!F122/12 | CP6: ='_Engine_NR'!F123/12 | CQ6: ='_Engine_NR'!F124/12 | CR6: ='_Engine_NR'!F125/12 | CS6: ='_Engine_NR'!F126/12 | CT6: ='_Engine_NR'!F127/12 | CU6: ='_Engine_NR'!F128/12 | CV6: ='_Engine_NR'!F129/12 | CW6: ='_Engine_NR'!F130/12 | CX6: ='_Engine_NR'!F131/12 | CY6: ='_Engine_NR'!F132/12 | CZ6: ='_Engine_NR'!F133/12 | DA6: ='_Engine_NR'!F134/12 | DB6: ='_Engine_NR'!F135/12 | DC6: ='_Engine_NR'!F136/12 | DD6: ='_Engine_NR'!F137/12 | DE6: ='_Engine_NR'!F138/12 | DF6: ='_Engine_NR'!F139/12 | DG6: ='_Engine_NR'!F140/12 | DH6: ='_Engine_NR'!F141/12 | DI6: ='_Engine_NR'!F142/12 | DJ6: ='_Engine_NR'!F143/12 | DK6: ='_Engine_NR'!F144/12 | DL6: ='_Engine_NR'!F145/12 | DM6: ='_Engine_NR'!F146/12 | DN6: ='_Engine_NR'!F147/12 | DO6: ='_Engine_NR'!F148/12 | DP6: ='_Engine_NR'!F149/12 | DQ6: ='_Engine_NR'!F150/12 | DR6: ='_Engine_NR'!F151/12 | DS6: ='_Engine_NR'!F152/12 | DT6: ='_Engine_NR'!F153/12 | DU6: ='_Engine_NR'!F154/12 | DV6: ='_Engine_NR'!F155/12 | DW6: ='_Engine_NR'!F156/12 | DX6: ='_Engine_NR'!F157/12 | DY6: ='_Engine_NR'!F158/12 | DZ6: ='_Engine_NR'!F159/12 | EA6: ='_Engine_NR'!F160/12 | EB6: ='_Engine_NR'!F161/12 | EC6: ='_Engine_NR'!F162/12 | ED6: ='_Engine_NR'!F163/12 | EE6: ='_Engine_NR'!F164/12 | EF6: ='_Engine_NR'!F165/12 | EG6: ='_Engine_NR'!F166/12 | EH6: ='_Engine_NR'!F167/12 | EI6: ='_Engine_NR'!F168/12 | EJ6: ='_Engine_NR'!F169/12 | EK6: ='_Engine_NR'!F170/12 | EL6: ='_Engine_NR'!F171/12 | EM6: ='_Engine_NR'!F172/12 | EN6: ='_Engine_NR'!F173/12 | EO6: ='_Engine_NR'!F174/12 | EP6: ='_Engine_NR'!F175/12 | EQ6: ='_Engine_NR'!F176/12 | ER6: ='_Engine_NR'!F177/12 | ES6: ='_Engine_NR'!F178/12 | ET6: ='_Engine_NR'!F179/12 | EU6: ='_Engine_NR'!F180/12 | EV6: ='_Engine_NR'!F181/12 | EW6: ='_Engine_NR'!F182/12 | EX6: ='_Engine_NR'!F183/12 | EY6: ='_Engine_NR'!F184/12 | EZ6: ='_Engine_NR'!F185/12 | FA6: ='_Engine_NR'!F186/12 | FB6: ='_Engine_NR'!F187/12 | FC6: ='_Engine_NR'!F188/12 | FD6: ='_Engine_NR'!F189/12 | FE6: ='_Engine_NR'!F190/12 | FF6: ='_Engine_NR'!F191/12 | FG6: ='_Engine_NR'!F192/12 | FH6: ='_Engine_NR'!F193/12 | FI6: ='_Engine_NR'!F194/12 | FJ6: ='_Engine_NR'!F195/12 | FK6: ='_Engine_NR'!F196/12 | FL6: ='_Engine_NR'!F197/12 | FM6: ='_Engine_NR'!F198/12 | FN6: ='_Engine_NR'!F199/12 | FO6: ='_Engine_NR'!F200/12 | FP6: ='_Engine_NR'!F201/12 | FQ6: ='_Engine_NR'!F202/12 | FR6: ='_Engine_NR'!F203/12 | FS6: ='_Engine_NR'!F204/12 | FT6: ='_Engine_NR'!F205/12 | FU6: ='_Engine_NR'!F206/12 | FV6: ='_Engine_NR'!F207/12 | FW6: ='_Engine_NR'!F208/12 | FX6: ='_Engine_NR'!F209/12 | FY6: ='_Engine_NR'!F210/12
A7: Deal #2 | B7: ='_Engine_NR'!G31/12 | C7: ='_Engine_NR'!G32/12 | D7: ='_Engine_NR'!G33/12 | E7: ='_Engine_NR'!G34/12 | F7: ='_Engine_NR'!G35/12 | G7: ='_Engine_NR'!G36/12 | H7: ='_Engine_NR'!G37/12 | I7: ='_Engine_NR'!G38/12 | J7: ='_Engine_NR'!G39/12 | K7: ='_Engine_NR'!G40/12 | L7: ='_Engine_NR'!G41/12 | M7: ='_Engine_NR'!G42/12 | N7: ='_Engine_NR'!G43/12 | O7: ='_Engine_NR'!G44/12 | P7: ='_Engine_NR'!G45/12 | Q7: ='_Engine_NR'!G46/12 | R7: ='_Engine_NR'!G47/12 | S7: ='_Engine_NR'!G48/12 | T7: ='_Engine_NR'!G49/12 | U7: ='_Engine_NR'!G50/12 | V7: ='_Engine_NR'!G51/12 | W7: ='_Engine_NR'!G52/12 | X7: ='_Engine_NR'!G53/12 | Y7: ='_Engine_NR'!G54/12 | Z7: ='_Engine_NR'!G55/12 | AA7: ='_Engine_NR'!G56/12 | AB7: ='_Engine_NR'!G57/12 | AC7: ='_Engine_NR'!G58/12 | AD7: ='_Engine_NR'!G59/12 | AE7: ='_Engine_NR'!G60/12 | AF7: ='_Engine_NR'!G61/12 | AG7: ='_Engine_NR'!G62/12 | AH7: ='_Engine_NR'!G63/12 | AI7: ='_Engine_NR'!G64/12 | AJ7: ='_Engine_NR'!G65/12 | AK7: ='_Engine_NR'!G66/12 | AL7: ='_Engine_NR'!G67/12 | AM7: ='_Engine_NR'!G68/12 | AN7: ='_Engine_NR'!G69/12 | AO7: ='_Engine_NR'!G70/12 | AP7: ='_Engine_NR'!G71/12 | AQ7: ='_Engine_NR'!G72/12 | AR7: ='_Engine_NR'!G73/12 | AS7: ='_Engine_NR'!G74/12 | AT7: ='_Engine_NR'!G75/12 | AU7: ='_Engine_NR'!G76/12 | AV7: ='_Engine_NR'!G77/12 | AW7: ='_Engine_NR'!G78/12 | AX7: ='_Engine_NR'!G79/12 | AY7: ='_Engine_NR'!G80/12 | AZ7: ='_Engine_NR'!G81/12 | BA7: ='_Engine_NR'!G82/12 | BB7: ='_Engine_NR'!G83/12 | BC7: ='_Engine_NR'!G84/12 | BD7: ='_Engine_NR'!G85/12 | BE7: ='_Engine_NR'!G86/12 | BF7: ='_Engine_NR'!G87/12 | BG7: ='_Engine_NR'!G88/12 | BH7: ='_Engine_NR'!G89/12 | BI7: ='_Engine_NR'!G90/12 | BJ7: ='_Engine_NR'!G91/12 | BK7: ='_Engine_NR'!G92/12 | BL7: ='_Engine_NR'!G93/12 | BM7: ='_Engine_NR'!G94/12 | BN7: ='_Engine_NR'!G95/12 | BO7: ='_Engine_NR'!G96/12 | BP7: ='_Engine_NR'!G97/12 | BQ7: ='_Engine_NR'!G98/12 | BR7: ='_Engine_NR'!G99/12 | BS7: ='_Engine_NR'!G100/12 | BT7: ='_Engine_NR'!G101/12 | BU7: ='_Engine_NR'!G102/12 | BV7: ='_Engine_NR'!G103/12 | BW7: ='_Engine_NR'!G104/12 | BX7: ='_Engine_NR'!G105/12 | BY7: ='_Engine_NR'!G106/12 | BZ7: ='_Engine_NR'!G107/12 | CA7: ='_Engine_NR'!G108/12 | CB7: ='_Engine_NR'!G109/12 | CC7: ='_Engine_NR'!G110/12 | CD7: ='_Engine_NR'!G111/12 | CE7: ='_Engine_NR'!G112/12 | CF7: ='_Engine_NR'!G113/12 | CG7: ='_Engine_NR'!G114/12 | CH7: ='_Engine_NR'!G115/12 | CI7: ='_Engine_NR'!G116/12 | CJ7: ='_Engine_NR'!G117/12 | CK7: ='_Engine_NR'!G118/12 | CL7: ='_Engine_NR'!G119/12 | CM7: ='_Engine_NR'!G120/12 | CN7: ='_Engine_NR'!G121/12 | CO7: ='_Engine_NR'!G122/12 | CP7: ='_Engine_NR'!G123/12 | CQ7: ='_Engine_NR'!G124/12 | CR7: ='_Engine_NR'!G125/12 | CS7: ='_Engine_NR'!G126/12 | CT7: ='_Engine_NR'!G127/12 | CU7: ='_Engine_NR'!G128/12 | CV7: ='_Engine_NR'!G129/12 | CW7: ='_Engine_NR'!G130/12 | CX7: ='_Engine_NR'!G131/12 | CY7: ='_Engine_NR'!G132/12 | CZ7: ='_Engine_NR'!G133/12 | DA7: ='_Engine_NR'!G134/12 | DB7: ='_Engine_NR'!G135/12 | DC7: ='_Engine_NR'!G136/12 | DD7: ='_Engine_NR'!G137/12 | DE7: ='_Engine_NR'!G138/12 | DF7: ='_Engine_NR'!G139/12 | DG7: ='_Engine_NR'!G140/12 | DH7: ='_Engine_NR'!G141/12 | DI7: ='_Engine_NR'!G142/12 | DJ7: ='_Engine_NR'!G143/12 | DK7: ='_Engine_NR'!G144/12 | DL7: ='_Engine_NR'!G145/12 | DM7: ='_Engine_NR'!G146/12 | DN7: ='_Engine_NR'!G147/12 | DO7: ='_Engine_NR'!G148/12 | DP7: ='_Engine_NR'!G149/12 | DQ7: ='_Engine_NR'!G150/12 | DR7: ='_Engine_NR'!G151/12 | DS7: ='_Engine_NR'!G152/12 | DT7: ='_Engine_NR'!G153/12 | DU7: ='_Engine_NR'!G154/12 | DV7: ='_Engine_NR'!G155/12 | DW7: ='_Engine_NR'!G156/12 | DX7: ='_Engine_NR'!G157/12 | DY7: ='_Engine_NR'!G158/12 | DZ7: ='_Engine_NR'!G159/12 | EA7: ='_Engine_NR'!G160/12 | EB7: ='_Engine_NR'!G161/12 | EC7: ='_Engine_NR'!G162/12 | ED7: ='_Engine_NR'!G163/12 | EE7: ='_Engine_NR'!G164/12 | EF7: ='_Engine_NR'!G165/12 | EG7: ='_Engine_NR'!G166/12 | EH7: ='_Engine_NR'!G167/12 | EI7: ='_Engine_NR'!G168/12 | EJ7: ='_Engine_NR'!G169/12 | EK7: ='_Engine_NR'!G170/12 | EL7: ='_Engine_NR'!G171/12 | EM7: ='_Engine_NR'!G172/12 | EN7: ='_Engine_NR'!G173/12 | EO7: ='_Engine_NR'!G174/12 | EP7: ='_Engine_NR'!G175/12 | EQ7: ='_Engine_NR'!G176/12 | ER7: ='_Engine_NR'!G177/12 | ES7: ='_Engine_NR'!G178/12 | ET7: ='_Engine_NR'!G179/12 | EU7: ='_Engine_NR'!G180/12 | EV7: ='_Engine_NR'!G181/12 | EW7: ='_Engine_NR'!G182/12 | EX7: ='_Engine_NR'!G183/12 | EY7: ='_Engine_NR'!G184/12 | EZ7: ='_Engine_NR'!G185/12 | FA7: ='_Engine_NR'!G186/12 | FB7: ='_Engine_NR'!G187/12 | FC7: ='_Engine_NR'!G188/12 | FD7: ='_Engine_NR'!G189/12 | FE7: ='_Engine_NR'!G190/12 | FF7: ='_Engine_NR'!G191/12 | FG7: ='_Engine_NR'!G192/12 | FH7: ='_Engine_NR'!G193/12 | FI7: ='_Engine_NR'!G194/12 | FJ7: ='_Engine_NR'!G195/12 | FK7: ='_Engine_NR'!G196/12 | FL7: ='_Engine_NR'!G197/12 | FM7: ='_Engine_NR'!G198/12 | FN7: ='_Engine_NR'!G199/12 | FO7: ='_Engine_NR'!G200/12 | FP7: ='_Engine_NR'!G201/12 | FQ7: ='_Engine_NR'!G202/12 | FR7: ='_Engine_NR'!G203/12 | FS7: ='_Engine_NR'!G204/12 | FT7: ='_Engine_NR'!G205/12 | FU7: ='_Engine_NR'!G206/12 | FV7: ='_Engine_NR'!G207/12 | FW7: ='_Engine_NR'!G208/12 | FX7: ='_Engine_NR'!G209/12 | FY7: ='_Engine_NR'!G210/12
A8: Deal #3 | B8: ='_Engine_NR'!H31/12 | C8: ='_Engine_NR'!H32/12 | D8: ='_Engine_NR'!H33/12 | E8: ='_Engine_NR'!H34/12 | F8: ='_Engine_NR'!H35/12 | G8: ='_Engine_NR'!H36/12 | H8: ='_Engine_NR'!H37/12 | I8: ='_Engine_NR'!H38/12 | J8: ='_Engine_NR'!H39/12 | K8: ='_Engine_NR'!H40/12 | L8: ='_Engine_NR'!H41/12 | M8: ='_Engine_NR'!H42/12 | N8: ='_Engine_NR'!H43/12 | O8: ='_Engine_NR'!H44/12 | P8: ='_Engine_NR'!H45/12 | Q8: ='_Engine_NR'!H46/12 | R8: ='_Engine_NR'!H47/12 | S8: ='_Engine_NR'!H48/12 | T8: ='_Engine_NR'!H49/12 | U8: ='_Engine_NR'!H50/12 | V8: ='_Engine_NR'!H51/12 | W8: ='_Engine_NR'!H52/12 | X8: ='_Engine_NR'!H53/12 | Y8: ='_Engine_NR'!H54/12 | Z8: ='_Engine_NR'!H55/12 | AA8: ='_Engine_NR'!H56/12 | AB8: ='_Engine_NR'!H57/12 | AC8: ='_Engine_NR'!H58/12 | AD8: ='_Engine_NR'!H59/12 | AE8: ='_Engine_NR'!H60/12 | AF8: ='_Engine_NR'!H61/12 | AG8: ='_Engine_NR'!H62/12 | AH8: ='_Engine_NR'!H63/12 | AI8: ='_Engine_NR'!H64/12 | AJ8: ='_Engine_NR'!H65/12 | AK8: ='_Engine_NR'!H66/12 | AL8: ='_Engine_NR'!H67/12 | AM8: ='_Engine_NR'!H68/12 | AN8: ='_Engine_NR'!H69/12 | AO8: ='_Engine_NR'!H70/12 | AP8: ='_Engine_NR'!H71/12 | AQ8: ='_Engine_NR'!H72/12 | AR8: ='_Engine_NR'!H73/12 | AS8: ='_Engine_NR'!H74/12 | AT8: ='_Engine_NR'!H75/12 | AU8: ='_Engine_NR'!H76/12 | AV8: ='_Engine_NR'!H77/12 | AW8: ='_Engine_NR'!H78/12 | AX8: ='_Engine_NR'!H79/12 | AY8: ='_Engine_NR'!H80/12 | AZ8: ='_Engine_NR'!H81/12 | BA8: ='_Engine_NR'!H82/12 | BB8: ='_Engine_NR'!H83/12 | BC8: ='_Engine_NR'!H84/12 | BD8: ='_Engine_NR'!H85/12 | BE8: ='_Engine_NR'!H86/12 | BF8: ='_Engine_NR'!H87/12 | BG8: ='_Engine_NR'!H88/12 | BH8: ='_Engine_NR'!H89/12 | BI8: ='_Engine_NR'!H90/12 | BJ8: ='_Engine_NR'!H91/12 | BK8: ='_Engine_NR'!H92/12 | BL8: ='_Engine_NR'!H93/12 | BM8: ='_Engine_NR'!H94/12 | BN8: ='_Engine_NR'!H95/12 | BO8: ='_Engine_NR'!H96/12 | BP8: ='_Engine_NR'!H97/12 | BQ8: ='_Engine_NR'!H98/12 | BR8: ='_Engine_NR'!H99/12 | BS8: ='_Engine_NR'!H100/12 | BT8: ='_Engine_NR'!H101/12 | BU8: ='_Engine_NR'!H102/12 | BV8: ='_Engine_NR'!H103/12 | BW8: ='_Engine_NR'!H104/12 | BX8: ='_Engine_NR'!H105/12 | BY8: ='_Engine_NR'!H106/12 | BZ8: ='_Engine_NR'!H107/12 | CA8: ='_Engine_NR'!H108/12 | CB8: ='_Engine_NR'!H109/12 | CC8: ='_Engine_NR'!H110/12 | CD8: ='_Engine_NR'!H111/12 | CE8: ='_Engine_NR'!H112/12 | CF8: ='_Engine_NR'!H113/12 | CG8: ='_Engine_NR'!H114/12 | CH8: ='_Engine_NR'!H115/12 | CI8: ='_Engine_NR'!H116/12 | CJ8: ='_Engine_NR'!H117/12 | CK8: ='_Engine_NR'!H118/12 | CL8: ='_Engine_NR'!H119/12 | CM8: ='_Engine_NR'!H120/12 | CN8: ='_Engine_NR'!H121/12 | CO8: ='_Engine_NR'!H122/12 | CP8: ='_Engine_NR'!H123/12 | CQ8: ='_Engine_NR'!H124/12 | CR8: ='_Engine_NR'!H125/12 | CS8: ='_Engine_NR'!H126/12 | CT8: ='_Engine_NR'!H127/12 | CU8: ='_Engine_NR'!H128/12 | CV8: ='_Engine_NR'!H129/12 | CW8: ='_Engine_NR'!H130/12 | CX8: ='_Engine_NR'!H131/12 | CY8: ='_Engine_NR'!H132/12 | CZ8: ='_Engine_NR'!H133/12 | DA8: ='_Engine_NR'!H134/12 | DB8: ='_Engine_NR'!H135/12 | DC8: ='_Engine_NR'!H136/12 | DD8: ='_Engine_NR'!H137/12 | DE8: ='_Engine_NR'!H138/12 | DF8: ='_Engine_NR'!H139/12 | DG8: ='_Engine_NR'!H140/12 | DH8: ='_Engine_NR'!H141/12 | DI8: ='_Engine_NR'!H142/12 | DJ8: ='_Engine_NR'!H143/12 | DK8: ='_Engine_NR'!H144/12 | DL8: ='_Engine_NR'!H145/12 | DM8: ='_Engine_NR'!H146/12 | DN8: ='_Engine_NR'!H147/12 | DO8: ='_Engine_NR'!H148/12 | DP8: ='_Engine_NR'!H149/12 | DQ8: ='_Engine_NR'!H150/12 | DR8: ='_Engine_NR'!H151/12 | DS8: ='_Engine_NR'!H152/12 | DT8: ='_Engine_NR'!H153/12 | DU8: ='_Engine_NR'!H154/12 | DV8: ='_Engine_NR'!H155/12 | DW8: ='_Engine_NR'!H156/12 | DX8: ='_Engine_NR'!H157/12 | DY8: ='_Engine_NR'!H158/12 | DZ8: ='_Engine_NR'!H159/12 | EA8: ='_Engine_NR'!H160/12 | EB8: ='_Engine_NR'!H161/12 | EC8: ='_Engine_NR'!H162/12 | ED8: ='_Engine_NR'!H163/12 | EE8: ='_Engine_NR'!H164/12 | EF8: ='_Engine_NR'!H165/12 | EG8: ='_Engine_NR'!H166/12 | EH8: ='_Engine_NR'!H167/12 | EI8: ='_Engine_NR'!H168/12 | EJ8: ='_Engine_NR'!H169/12 | EK8: ='_Engine_NR'!H170/12 | EL8: ='_Engine_NR'!H171/12 | EM8: ='_Engine_NR'!H172/12 | EN8: ='_Engine_NR'!H173/12 | EO8: ='_Engine_NR'!H174/12 | EP8: ='_Engine_NR'!H175/12 | EQ8: ='_Engine_NR'!H176/12 | ER8: ='_Engine_NR'!H177/12 | ES8: ='_Engine_NR'!H178/12 | ET8: ='_Engine_NR'!H179/12 | EU8: ='_Engine_NR'!H180/12 | EV8: ='_Engine_NR'!H181/12 | EW8: ='_Engine_NR'!H182/12 | EX8: ='_Engine_NR'!H183/12 | EY8: ='_Engine_NR'!H184/12 | EZ8: ='_Engine_NR'!H185/12 | FA8: ='_Engine_NR'!H186/12 | FB8: ='_Engine_NR'!H187/12 | FC8: ='_Engine_NR'!H188/12 | FD8: ='_Engine_NR'!H189/12 | FE8: ='_Engine_NR'!H190/12 | FF8: ='_Engine_NR'!H191/12 | FG8: ='_Engine_NR'!H192/12 | FH8: ='_Engine_NR'!H193/12 | FI8: ='_Engine_NR'!H194/12 | FJ8: ='_Engine_NR'!H195/12 | FK8: ='_Engine_NR'!H196/12 | FL8: ='_Engine_NR'!H197/12 | FM8: ='_Engine_NR'!H198/12 | FN8: ='_Engine_NR'!H199/12 | FO8: ='_Engine_NR'!H200/12 | FP8: ='_Engine_NR'!H201/12 | FQ8: ='_Engine_NR'!H202/12 | FR8: ='_Engine_NR'!H203/12 | FS8: ='_Engine_NR'!H204/12 | FT8: ='_Engine_NR'!H205/12 | FU8: ='_Engine_NR'!H206/12 | FV8: ='_Engine_NR'!H207/12 | FW8: ='_Engine_NR'!H208/12 | FX8: ='_Engine_NR'!H209/12 | FY8: ='_Engine_NR'!H210/12
A9: Deal #4 | B9: ='_Engine_NR'!I31/12 | C9: ='_Engine_NR'!I32/12 | D9: ='_Engine_NR'!I33/12 | E9: ='_Engine_NR'!I34/12 | F9: ='_Engine_NR'!I35/12 | G9: ='_Engine_NR'!I36/12 | H9: ='_Engine_NR'!I37/12 | I9: ='_Engine_NR'!I38/12 | J9: ='_Engine_NR'!I39/12 | K9: ='_Engine_NR'!I40/12 | L9: ='_Engine_NR'!I41/12 | M9: ='_Engine_NR'!I42/12 | N9: ='_Engine_NR'!I43/12 | O9: ='_Engine_NR'!I44/12 | P9: ='_Engine_NR'!I45/12 | Q9: ='_Engine_NR'!I46/12 | R9: ='_Engine_NR'!I47/12 | S9: ='_Engine_NR'!I48/12 | T9: ='_Engine_NR'!I49/12 | U9: ='_Engine_NR'!I50/12 | V9: ='_Engine_NR'!I51/12 | W9: ='_Engine_NR'!I52/12 | X9: ='_Engine_NR'!I53/12 | Y9: ='_Engine_NR'!I54/12 | Z9: ='_Engine_NR'!I55/12 | AA9: ='_Engine_NR'!I56/12 | AB9: ='_Engine_NR'!I57/12 | AC9: ='_Engine_NR'!I58/12 | AD9: ='_Engine_NR'!I59/12 | AE9: ='_Engine_NR'!I60/12 | AF9: ='_Engine_NR'!I61/12 | AG9: ='_Engine_NR'!I62/12 | AH9: ='_Engine_NR'!I63/12 | AI9: ='_Engine_NR'!I64/12 | AJ9: ='_Engine_NR'!I65/12 | AK9: ='_Engine_NR'!I66/12 | AL9: ='_Engine_NR'!I67/12 | AM9: ='_Engine_NR'!I68/12 | AN9: ='_Engine_NR'!I69/12 | AO9: ='_Engine_NR'!I70/12 | AP9: ='_Engine_NR'!I71/12 | AQ9: ='_Engine_NR'!I72/12 | AR9: ='_Engine_NR'!I73/12 | AS9: ='_Engine_NR'!I74/12 | AT9: ='_Engine_NR'!I75/12 | AU9: ='_Engine_NR'!I76/12 | AV9: ='_Engine_NR'!I77/12 | AW9: ='_Engine_NR'!I78/12 | AX9: ='_Engine_NR'!I79/12 | AY9: ='_Engine_NR'!I80/12 | AZ9: ='_Engine_NR'!I81/12 | BA9: ='_Engine_NR'!I82/12 | BB9: ='_Engine_NR'!I83/12 | BC9: ='_Engine_NR'!I84/12 | BD9: ='_Engine_NR'!I85/12 | BE9: ='_Engine_NR'!I86/12 | BF9: ='_Engine_NR'!I87/12 | BG9: ='_Engine_NR'!I88/12 | BH9: ='_Engine_NR'!I89/12 | BI9: ='_Engine_NR'!I90/12 | BJ9: ='_Engine_NR'!I91/12 | BK9: ='_Engine_NR'!I92/12 | BL9: ='_Engine_NR'!I93/12 | BM9: ='_Engine_NR'!I94/12 | BN9: ='_Engine_NR'!I95/12 | BO9: ='_Engine_NR'!I96/12 | BP9: ='_Engine_NR'!I97/12 | BQ9: ='_Engine_NR'!I98/12 | BR9: ='_Engine_NR'!I99/12 | BS9: ='_Engine_NR'!I100/12 | BT9: ='_Engine_NR'!I101/12 | BU9: ='_Engine_NR'!I102/12 | BV9: ='_Engine_NR'!I103/12 | BW9: ='_Engine_NR'!I104/12 | BX9: ='_Engine_NR'!I105/12 | BY9: ='_Engine_NR'!I106/12 | BZ9: ='_Engine_NR'!I107/12 | CA9: ='_Engine_NR'!I108/12 | CB9: ='_Engine_NR'!I109/12 | CC9: ='_Engine_NR'!I110/12 | CD9: ='_Engine_NR'!I111/12 | CE9: ='_Engine_NR'!I112/12 | CF9: ='_Engine_NR'!I113/12 | CG9: ='_Engine_NR'!I114/12 | CH9: ='_Engine_NR'!I115/12 | CI9: ='_Engine_NR'!I116/12 | CJ9: ='_Engine_NR'!I117/12 | CK9: ='_Engine_NR'!I118/12 | CL9: ='_Engine_NR'!I119/12 | CM9: ='_Engine_NR'!I120/12 | CN9: ='_Engine_NR'!I121/12 | CO9: ='_Engine_NR'!I122/12 | CP9: ='_Engine_NR'!I123/12 | CQ9: ='_Engine_NR'!I124/12 | CR9: ='_Engine_NR'!I125/12 | CS9: ='_Engine_NR'!I126/12 | CT9: ='_Engine_NR'!I127/12 | CU9: ='_Engine_NR'!I128/12 | CV9: ='_Engine_NR'!I129/12 | CW9: ='_Engine_NR'!I130/12 | CX9: ='_Engine_NR'!I131/12 | CY9: ='_Engine_NR'!I132/12 | CZ9: ='_Engine_NR'!I133/12 | DA9: ='_Engine_NR'!I134/12 | DB9: ='_Engine_NR'!I135/12 | DC9: ='_Engine_NR'!I136/12 | DD9: ='_Engine_NR'!I137/12 | DE9: ='_Engine_NR'!I138/12 | DF9: ='_Engine_NR'!I139/12 | DG9: ='_Engine_NR'!I140/12 | DH9: ='_Engine_NR'!I141/12 | DI9: ='_Engine_NR'!I142/12 | DJ9: ='_Engine_NR'!I143/12 | DK9: ='_Engine_NR'!I144/12 | DL9: ='_Engine_NR'!I145/12 | DM9: ='_Engine_NR'!I146/12 | DN9: ='_Engine_NR'!I147/12 | DO9: ='_Engine_NR'!I148/12 | DP9: ='_Engine_NR'!I149/12 | DQ9: ='_Engine_NR'!I150/12 | DR9: ='_Engine_NR'!I151/12 | DS9: ='_Engine_NR'!I152/12 | DT9: ='_Engine_NR'!I153/12 | DU9: ='_Engine_NR'!I154/12 | DV9: ='_Engine_NR'!I155/12 | DW9: ='_Engine_NR'!I156/12 | DX9: ='_Engine_NR'!I157/12 | DY9: ='_Engine_NR'!I158/12 | DZ9: ='_Engine_NR'!I159/12 | EA9: ='_Engine_NR'!I160/12 | EB9: ='_Engine_NR'!I161/12 | EC9: ='_Engine_NR'!I162/12 | ED9: ='_Engine_NR'!I163/12 | EE9: ='_Engine_NR'!I164/12 | EF9: ='_Engine_NR'!I165/12 | EG9: ='_Engine_NR'!I166/12 | EH9: ='_Engine_NR'!I167/12 | EI9: ='_Engine_NR'!I168/12 | EJ9: ='_Engine_NR'!I169/12 | EK9: ='_Engine_NR'!I170/12 | EL9: ='_Engine_NR'!I171/12 | EM9: ='_Engine_NR'!I172/12 | EN9: ='_Engine_NR'!I173/12 | EO9: ='_Engine_NR'!I174/12 | EP9: ='_Engine_NR'!I175/12 | EQ9: ='_Engine_NR'!I176/12 | ER9: ='_Engine_NR'!I177/12 | ES9: ='_Engine_NR'!I178/12 | ET9: ='_Engine_NR'!I179/12 | EU9: ='_Engine_NR'!I180/12 | EV9: ='_Engine_NR'!I181/12 | EW9: ='_Engine_NR'!I182/12 | EX9: ='_Engine_NR'!I183/12 | EY9: ='_Engine_NR'!I184/12 | EZ9: ='_Engine_NR'!I185/12 | FA9: ='_Engine_NR'!I186/12 | FB9: ='_Engine_NR'!I187/12 | FC9: ='_Engine_NR'!I188/12 | FD9: ='_Engine_NR'!I189/12 | FE9: ='_Engine_NR'!I190/12 | FF9: ='_Engine_NR'!I191/12 | FG9: ='_Engine_NR'!I192/12 | FH9: ='_Engine_NR'!I193/12 | FI9: ='_Engine_NR'!I194/12 | FJ9: ='_Engine_NR'!I195/12 | FK9: ='_Engine_NR'!I196/12 | FL9: ='_Engine_NR'!I197/12 | FM9: ='_Engine_NR'!I198/12 | FN9: ='_Engine_NR'!I199/12 | FO9: ='_Engine_NR'!I200/12 | FP9: ='_Engine_NR'!I201/12 | FQ9: ='_Engine_NR'!I202/12 | FR9: ='_Engine_NR'!I203/12 | FS9: ='_Engine_NR'!I204/12 | FT9: ='_Engine_NR'!I205/12 | FU9: ='_Engine_NR'!I206/12 | FV9: ='_Engine_NR'!I207/12 | FW9: ='_Engine_NR'!I208/12 | FX9: ='_Engine_NR'!I209/12 | FY9: ='_Engine_NR'!I210/12
A10: Deal #5 | B10: ='_Engine_NR'!J31/12 | C10: ='_Engine_NR'!J32/12 | D10: ='_Engine_NR'!J33/12 | E10: ='_Engine_NR'!J34/12 | F10: ='_Engine_NR'!J35/12 | G10: ='_Engine_NR'!J36/12 | H10: ='_Engine_NR'!J37/12 | I10: ='_Engine_NR'!J38/12 | J10: ='_Engine_NR'!J39/12 | K10: ='_Engine_NR'!J40/12 | L10: ='_Engine_NR'!J41/12 | M10: ='_Engine_NR'!J42/12 | N10: ='_Engine_NR'!J43/12 | O10: ='_Engine_NR'!J44/12 | P10: ='_Engine_NR'!J45/12 | Q10: ='_Engine_NR'!J46/12 | R10: ='_Engine_NR'!J47/12 | S10: ='_Engine_NR'!J48/12 | T10: ='_Engine_NR'!J49/12 | U10: ='_Engine_NR'!J50/12 | V10: ='_Engine_NR'!J51/12 | W10: ='_Engine_NR'!J52/12 | X10: ='_Engine_NR'!J53/12 | Y10: ='_Engine_NR'!J54/12 | Z10: ='_Engine_NR'!J55/12 | AA10: ='_Engine_NR'!J56/12 | AB10: ='_Engine_NR'!J57/12 | AC10: ='_Engine_NR'!J58/12 | AD10: ='_Engine_NR'!J59/12 | AE10: ='_Engine_NR'!J60/12 | AF10: ='_Engine_NR'!J61/12 | AG10: ='_Engine_NR'!J62/12 | AH10: ='_Engine_NR'!J63/12 | AI10: ='_Engine_NR'!J64/12 | AJ10: ='_Engine_NR'!J65/12 | AK10: ='_Engine_NR'!J66/12 | AL10: ='_Engine_NR'!J67/12 | AM10: ='_Engine_NR'!J68/12 | AN10: ='_Engine_NR'!J69/12 | AO10: ='_Engine_NR'!J70/12 | AP10: ='_Engine_NR'!J71/12 | AQ10: ='_Engine_NR'!J72/12 | AR10: ='_Engine_NR'!J73/12 | AS10: ='_Engine_NR'!J74/12 | AT10: ='_Engine_NR'!J75/12 | AU10: ='_Engine_NR'!J76/12 | AV10: ='_Engine_NR'!J77/12 | AW10: ='_Engine_NR'!J78/12 | AX10: ='_Engine_NR'!J79/12 | AY10: ='_Engine_NR'!J80/12 | AZ10: ='_Engine_NR'!J81/12 | BA10: ='_Engine_NR'!J82/12 | BB10: ='_Engine_NR'!J83/12 | BC10: ='_Engine_NR'!J84/12 | BD10: ='_Engine_NR'!J85/12 | BE10: ='_Engine_NR'!J86/12 | BF10: ='_Engine_NR'!J87/12 | BG10: ='_Engine_NR'!J88/12 | BH10: ='_Engine_NR'!J89/12 | BI10: ='_Engine_NR'!J90/12 | BJ10: ='_Engine_NR'!J91/12 | BK10: ='_Engine_NR'!J92/12 | BL10: ='_Engine_NR'!J93/12 | BM10: ='_Engine_NR'!J94/12 | BN10: ='_Engine_NR'!J95/12 | BO10: ='_Engine_NR'!J96/12 | BP10: ='_Engine_NR'!J97/12 | BQ10: ='_Engine_NR'!J98/12 | BR10: ='_Engine_NR'!J99/12 | BS10: ='_Engine_NR'!J100/12 | BT10: ='_Engine_NR'!J101/12 | BU10: ='_Engine_NR'!J102/12 | BV10: ='_Engine_NR'!J103/12 | BW10: ='_Engine_NR'!J104/12 | BX10: ='_Engine_NR'!J105/12 | BY10: ='_Engine_NR'!J106/12 | BZ10: ='_Engine_NR'!J107/12 | CA10: ='_Engine_NR'!J108/12 | CB10: ='_Engine_NR'!J109/12 | CC10: ='_Engine_NR'!J110/12 | CD10: ='_Engine_NR'!J111/12 | CE10: ='_Engine_NR'!J112/12 | CF10: ='_Engine_NR'!J113/12 | CG10: ='_Engine_NR'!J114/12 | CH10: ='_Engine_NR'!J115/12 | CI10: ='_Engine_NR'!J116/12 | CJ10: ='_Engine_NR'!J117/12 | CK10: ='_Engine_NR'!J118/12 | CL10: ='_Engine_NR'!J119/12 | CM10: ='_Engine_NR'!J120/12 | CN10: ='_Engine_NR'!J121/12 | CO10: ='_Engine_NR'!J122/12 | CP10: ='_Engine_NR'!J123/12 | CQ10: ='_Engine_NR'!J124/12 | CR10: ='_Engine_NR'!J125/12 | CS10: ='_Engine_NR'!J126/12 | CT10: ='_Engine_NR'!J127/12 | CU10: ='_Engine_NR'!J128/12 | CV10: ='_Engine_NR'!J129/12 | CW10: ='_Engine_NR'!J130/12 | CX10: ='_Engine_NR'!J131/12 | CY10: ='_Engine_NR'!J132/12 | CZ10: ='_Engine_NR'!J133/12 | DA10: ='_Engine_NR'!J134/12 | DB10: ='_Engine_NR'!J135/12 | DC10: ='_Engine_NR'!J136/12 | DD10: ='_Engine_NR'!J137/12 | DE10: ='_Engine_NR'!J138/12 | DF10: ='_Engine_NR'!J139/12 | DG10: ='_Engine_NR'!J140/12 | DH10: ='_Engine_NR'!J141/12 | DI10: ='_Engine_NR'!J142/12 | DJ10: ='_Engine_NR'!J143/12 | DK10: ='_Engine_NR'!J144/12 | DL10: ='_Engine_NR'!J145/12 | DM10: ='_Engine_NR'!J146/12 | DN10: ='_Engine_NR'!J147/12 | DO10: ='_Engine_NR'!J148/12 | DP10: ='_Engine_NR'!J149/12 | DQ10: ='_Engine_NR'!J150/12 | DR10: ='_Engine_NR'!J151/12 | DS10: ='_Engine_NR'!J152/12 | DT10: ='_Engine_NR'!J153/12 | DU10: ='_Engine_NR'!J154/12 | DV10: ='_Engine_NR'!J155/12 | DW10: ='_Engine_NR'!J156/12 | DX10: ='_Engine_NR'!J157/12 | DY10: ='_Engine_NR'!J158/12 | DZ10: ='_Engine_NR'!J159/12 | EA10: ='_Engine_NR'!J160/12 | EB10: ='_Engine_NR'!J161/12 | EC10: ='_Engine_NR'!J162/12 | ED10: ='_Engine_NR'!J163/12 | EE10: ='_Engine_NR'!J164/12 | EF10: ='_Engine_NR'!J165/12 | EG10: ='_Engine_NR'!J166/12 | EH10: ='_Engine_NR'!J167/12 | EI10: ='_Engine_NR'!J168/12 | EJ10: ='_Engine_NR'!J169/12 | EK10: ='_Engine_NR'!J170/12 | EL10: ='_Engine_NR'!J171/12 | EM10: ='_Engine_NR'!J172/12 | EN10: ='_Engine_NR'!J173/12 | EO10: ='_Engine_NR'!J174/12 | EP10: ='_Engine_NR'!J175/12 | EQ10: ='_Engine_NR'!J176/12 | ER10: ='_Engine_NR'!J177/12 | ES10: ='_Engine_NR'!J178/12 | ET10: ='_Engine_NR'!J179/12 | EU10: ='_Engine_NR'!J180/12 | EV10: ='_Engine_NR'!J181/12 | EW10: ='_Engine_NR'!J182/12 | EX10: ='_Engine_NR'!J183/12 | EY10: ='_Engine_NR'!J184/12 | EZ10: ='_Engine_NR'!J185/12 | FA10: ='_Engine_NR'!J186/12 | FB10: ='_Engine_NR'!J187/12 | FC10: ='_Engine_NR'!J188/12 | FD10: ='_Engine_NR'!J189/12 | FE10: ='_Engine_NR'!J190/12 | FF10: ='_Engine_NR'!J191/12 | FG10: ='_Engine_NR'!J192/12 | FH10: ='_Engine_NR'!J193/12 | FI10: ='_Engine_NR'!J194/12 | FJ10: ='_Engine_NR'!J195/12 | FK10: ='_Engine_NR'!J196/12 | FL10: ='_Engine_NR'!J197/12 | FM10: ='_Engine_NR'!J198/12 | FN10: ='_Engine_NR'!J199/12 | FO10: ='_Engine_NR'!J200/12 | FP10: ='_Engine_NR'!J201/12 | FQ10: ='_Engine_NR'!J202/12 | FR10: ='_Engine_NR'!J203/12 | FS10: ='_Engine_NR'!J204/12 | FT10: ='_Engine_NR'!J205/12 | FU10: ='_Engine_NR'!J206/12 | FV10: ='_Engine_NR'!J207/12 | FW10: ='_Engine_NR'!J208/12 | FX10: ='_Engine_NR'!J209/12 | FY10: ='_Engine_NR'!J210/12
A12: Portfolio P&L
A13: Revenue | B13: ='_Engine_NR'!L31 | C13: ='_Engine_NR'!L32 | D13: ='_Engine_NR'!L33 | E13: ='_Engine_NR'!L34 | F13: ='_Engine_NR'!L35 | G13: ='_Engine_NR'!L36 | H13: ='_Engine_NR'!L37 | I13: ='_Engine_NR'!L38 | J13: ='_Engine_NR'!L39 | K13: ='_Engine_NR'!L40 | L13: ='_Engine_NR'!L41 | M13: ='_Engine_NR'!L42 | N13: ='_Engine_NR'!L43 | O13: ='_Engine_NR'!L44 | P13: ='_Engine_NR'!L45 | Q13: ='_Engine_NR'!L46 | R13: ='_Engine_NR'!L47 | S13: ='_Engine_NR'!L48 | T13: ='_Engine_NR'!L49 | U13: ='_Engine_NR'!L50 | V13: ='_Engine_NR'!L51 | W13: ='_Engine_NR'!L52 | X13: ='_Engine_NR'!L53 | Y13: ='_Engine_NR'!L54 | Z13: ='_Engine_NR'!L55 | AA13: ='_Engine_NR'!L56 | AB13: ='_Engine_NR'!L57 | AC13: ='_Engine_NR'!L58 | AD13: ='_Engine_NR'!L59 | AE13: ='_Engine_NR'!L60 | AF13: ='_Engine_NR'!L61 | AG13: ='_Engine_NR'!L62 | AH13: ='_Engine_NR'!L63 | AI13: ='_Engine_NR'!L64 | AJ13: ='_Engine_NR'!L65 | AK13: ='_Engine_NR'!L66 | AL13: ='_Engine_NR'!L67 | AM13: ='_Engine_NR'!L68 | AN13: ='_Engine_NR'!L69 | AO13: ='_Engine_NR'!L70 | AP13: ='_Engine_NR'!L71 | AQ13: ='_Engine_NR'!L72 | AR13: ='_Engine_NR'!L73 | AS13: ='_Engine_NR'!L74 | AT13: ='_Engine_NR'!L75 | AU13: ='_Engine_NR'!L76 | AV13: ='_Engine_NR'!L77 | AW13: ='_Engine_NR'!L78 | AX13: ='_Engine_NR'!L79 | AY13: ='_Engine_NR'!L80 | AZ13: ='_Engine_NR'!L81 | BA13: ='_Engine_NR'!L82 | BB13: ='_Engine_NR'!L83 | BC13: ='_Engine_NR'!L84 | BD13: ='_Engine_NR'!L85 | BE13: ='_Engine_NR'!L86 | BF13: ='_Engine_NR'!L87 | BG13: ='_Engine_NR'!L88 | BH13: ='_Engine_NR'!L89 | BI13: ='_Engine_NR'!L90 | BJ13: ='_Engine_NR'!L91 | BK13: ='_Engine_NR'!L92 | BL13: ='_Engine_NR'!L93 | BM13: ='_Engine_NR'!L94 | BN13: ='_Engine_NR'!L95 | BO13: ='_Engine_NR'!L96 | BP13: ='_Engine_NR'!L97 | BQ13: ='_Engine_NR'!L98 | BR13: ='_Engine_NR'!L99 | BS13: ='_Engine_NR'!L100 | BT13: ='_Engine_NR'!L101 | BU13: ='_Engine_NR'!L102 | BV13: ='_Engine_NR'!L103 | BW13: ='_Engine_NR'!L104 | BX13: ='_Engine_NR'!L105 | BY13: ='_Engine_NR'!L106 | BZ13: ='_Engine_NR'!L107 | CA13: ='_Engine_NR'!L108 | CB13: ='_Engine_NR'!L109 | CC13: ='_Engine_NR'!L110 | CD13: ='_Engine_NR'!L111 | CE13: ='_Engine_NR'!L112 | CF13: ='_Engine_NR'!L113 | CG13: ='_Engine_NR'!L114 | CH13: ='_Engine_NR'!L115 | CI13: ='_Engine_NR'!L116 | CJ13: ='_Engine_NR'!L117 | CK13: ='_Engine_NR'!L118 | CL13: ='_Engine_NR'!L119 | CM13: ='_Engine_NR'!L120 | CN13: ='_Engine_NR'!L121 | CO13: ='_Engine_NR'!L122 | CP13: ='_Engine_NR'!L123 | CQ13: ='_Engine_NR'!L124 | CR13: ='_Engine_NR'!L125 | CS13: ='_Engine_NR'!L126 | CT13: ='_Engine_NR'!L127 | CU13: ='_Engine_NR'!L128 | CV13: ='_Engine_NR'!L129 | CW13: ='_Engine_NR'!L130 | CX13: ='_Engine_NR'!L131 | CY13: ='_Engine_NR'!L132 | CZ13: ='_Engine_NR'!L133 | DA13: ='_Engine_NR'!L134 | DB13: ='_Engine_NR'!L135 | DC13: ='_Engine_NR'!L136 | DD13: ='_Engine_NR'!L137 | DE13: ='_Engine_NR'!L138 | DF13: ='_Engine_NR'!L139 | DG13: ='_Engine_NR'!L140 | DH13: ='_Engine_NR'!L141 | DI13: ='_Engine_NR'!L142 | DJ13: ='_Engine_NR'!L143 | DK13: ='_Engine_NR'!L144 | DL13: ='_Engine_NR'!L145 | DM13: ='_Engine_NR'!L146 | DN13: ='_Engine_NR'!L147 | DO13: ='_Engine_NR'!L148 | DP13: ='_Engine_NR'!L149 | DQ13: ='_Engine_NR'!L150 | DR13: ='_Engine_NR'!L151 | DS13: ='_Engine_NR'!L152 | DT13: ='_Engine_NR'!L153 | DU13: ='_Engine_NR'!L154 | DV13: ='_Engine_NR'!L155 | DW13: ='_Engine_NR'!L156 | DX13: ='_Engine_NR'!L157 | DY13: ='_Engine_NR'!L158 | DZ13: ='_Engine_NR'!L159 | EA13: ='_Engine_NR'!L160 | EB13: ='_Engine_NR'!L161 | EC13: ='_Engine_NR'!L162 | ED13: ='_Engine_NR'!L163 | EE13: ='_Engine_NR'!L164 | EF13: ='_Engine_NR'!L165 | EG13: ='_Engine_NR'!L166 | EH13: ='_Engine_NR'!L167 | EI13: ='_Engine_NR'!L168 | EJ13: ='_Engine_NR'!L169 | EK13: ='_Engine_NR'!L170 | EL13: ='_Engine_NR'!L171 | EM13: ='_Engine_NR'!L172 | EN13: ='_Engine_NR'!L173 | EO13: ='_Engine_NR'!L174 | EP13: ='_Engine_NR'!L175 | EQ13: ='_Engine_NR'!L176 | ER13: ='_Engine_NR'!L177 | ES13: ='_Engine_NR'!L178 | ET13: ='_Engine_NR'!L179 | EU13: ='_Engine_NR'!L180 | EV13: ='_Engine_NR'!L181 | EW13: ='_Engine_NR'!L182 | EX13: ='_Engine_NR'!L183 | EY13: ='_Engine_NR'!L184 | EZ13: ='_Engine_NR'!L185 | FA13: ='_Engine_NR'!L186 | FB13: ='_Engine_NR'!L187 | FC13: ='_Engine_NR'!L188 | FD13: ='_Engine_NR'!L189 | FE13: ='_Engine_NR'!L190 | FF13: ='_Engine_NR'!L191 | FG13: ='_Engine_NR'!L192 | FH13: ='_Engine_NR'!L193 | FI13: ='_Engine_NR'!L194 | FJ13: ='_Engine_NR'!L195 | FK13: ='_Engine_NR'!L196 | FL13: ='_Engine_NR'!L197 | FM13: ='_Engine_NR'!L198 | FN13: ='_Engine_NR'!L199 | FO13: ='_Engine_NR'!L200 | FP13: ='_Engine_NR'!L201 | FQ13: ='_Engine_NR'!L202 | FR13: ='_Engine_NR'!L203 | FS13: ='_Engine_NR'!L204 | FT13: ='_Engine_NR'!L205 | FU13: ='_Engine_NR'!L206 | FV13: ='_Engine_NR'!L207 | FW13: ='_Engine_NR'!L208 | FX13: ='_Engine_NR'!L209 | FY13: ='_Engine_NR'!L210
A14: Cost of Goods Sold | B14: ='_Engine_NR'!M31 | C14: ='_Engine_NR'!M32 | D14: ='_Engine_NR'!M33 | E14: ='_Engine_NR'!M34 | F14: ='_Engine_NR'!M35 | G14: ='_Engine_NR'!M36 | H14: ='_Engine_NR'!M37 | I14: ='_Engine_NR'!M38 | J14: ='_Engine_NR'!M39 | K14: ='_Engine_NR'!M40 | L14: ='_Engine_NR'!M41 | M14: ='_Engine_NR'!M42 | N14: ='_Engine_NR'!M43 | O14: ='_Engine_NR'!M44 | P14: ='_Engine_NR'!M45 | Q14: ='_Engine_NR'!M46 | R14: ='_Engine_NR'!M47 | S14: ='_Engine_NR'!M48 | T14: ='_Engine_NR'!M49 | U14: ='_Engine_NR'!M50 | V14: ='_Engine_NR'!M51 | W14: ='_Engine_NR'!M52 | X14: ='_Engine_NR'!M53 | Y14: ='_Engine_NR'!M54 | Z14: ='_Engine_NR'!M55 | AA14: ='_Engine_NR'!M56 | AB14: ='_Engine_NR'!M57 | AC14: ='_Engine_NR'!M58 | AD14: ='_Engine_NR'!M59 | AE14: ='_Engine_NR'!M60 | AF14: ='_Engine_NR'!M61 | AG14: ='_Engine_NR'!M62 | AH14: ='_Engine_NR'!M63 | AI14: ='_Engine_NR'!M64 | AJ14: ='_Engine_NR'!M65 | AK14: ='_Engine_NR'!M66 | AL14: ='_Engine_NR'!M67 | AM14: ='_Engine_NR'!M68 | AN14: ='_Engine_NR'!M69 | AO14: ='_Engine_NR'!M70 | AP14: ='_Engine_NR'!M71 | AQ14: ='_Engine_NR'!M72 | AR14: ='_Engine_NR'!M73 | AS14: ='_Engine_NR'!M74 | AT14: ='_Engine_NR'!M75 | AU14: ='_Engine_NR'!M76 | AV14: ='_Engine_NR'!M77 | AW14: ='_Engine_NR'!M78 | AX14: ='_Engine_NR'!M79 | AY14: ='_Engine_NR'!M80 | AZ14: ='_Engine_NR'!M81 | BA14: ='_Engine_NR'!M82 | BB14: ='_Engine_NR'!M83 | BC14: ='_Engine_NR'!M84 | BD14: ='_Engine_NR'!M85 | BE14: ='_Engine_NR'!M86 | BF14: ='_Engine_NR'!M87 | BG14: ='_Engine_NR'!M88 | BH14: ='_Engine_NR'!M89 | BI14: ='_Engine_NR'!M90 | BJ14: ='_Engine_NR'!M91 | BK14: ='_Engine_NR'!M92 | BL14: ='_Engine_NR'!M93 | BM14: ='_Engine_NR'!M94 | BN14: ='_Engine_NR'!M95 | BO14: ='_Engine_NR'!M96 | BP14: ='_Engine_NR'!M97 | BQ14: ='_Engine_NR'!M98 | BR14: ='_Engine_NR'!M99 | BS14: ='_Engine_NR'!M100 | BT14: ='_Engine_NR'!M101 | BU14: ='_Engine_NR'!M102 | BV14: ='_Engine_NR'!M103 | BW14: ='_Engine_NR'!M104 | BX14: ='_Engine_NR'!M105 | BY14: ='_Engine_NR'!M106 | BZ14: ='_Engine_NR'!M107 | CA14: ='_Engine_NR'!M108 | CB14: ='_Engine_NR'!M109 | CC14: ='_Engine_NR'!M110 | CD14: ='_Engine_NR'!M111 | CE14: ='_Engine_NR'!M112 | CF14: ='_Engine_NR'!M113 | CG14: ='_Engine_NR'!M114 | CH14: ='_Engine_NR'!M115 | CI14: ='_Engine_NR'!M116 | CJ14: ='_Engine_NR'!M117 | CK14: ='_Engine_NR'!M118 | CL14: ='_Engine_NR'!M119 | CM14: ='_Engine_NR'!M120 | CN14: ='_Engine_NR'!M121 | CO14: ='_Engine_NR'!M122 | CP14: ='_Engine_NR'!M123 | CQ14: ='_Engine_NR'!M124 | CR14: ='_Engine_NR'!M125 | CS14: ='_Engine_NR'!M126 | CT14: ='_Engine_NR'!M127 | CU14: ='_Engine_NR'!M128 | CV14: ='_Engine_NR'!M129 | CW14: ='_Engine_NR'!M130 | CX14: ='_Engine_NR'!M131 | CY14: ='_Engine_NR'!M132 | CZ14: ='_Engine_NR'!M133 | DA14: ='_Engine_NR'!M134 | DB14: ='_Engine_NR'!M135 | DC14: ='_Engine_NR'!M136 | DD14: ='_Engine_NR'!M137 | DE14: ='_Engine_NR'!M138 | DF14: ='_Engine_NR'!M139 | DG14: ='_Engine_NR'!M140 | DH14: ='_Engine_NR'!M141 | DI14: ='_Engine_NR'!M142 | DJ14: ='_Engine_NR'!M143 | DK14: ='_Engine_NR'!M144 | DL14: ='_Engine_NR'!M145 | DM14: ='_Engine_NR'!M146 | DN14: ='_Engine_NR'!M147 | DO14: ='_Engine_NR'!M148 | DP14: ='_Engine_NR'!M149 | DQ14: ='_Engine_NR'!M150 | DR14: ='_Engine_NR'!M151 | DS14: ='_Engine_NR'!M152 | DT14: ='_Engine_NR'!M153 | DU14: ='_Engine_NR'!M154 | DV14: ='_Engine_NR'!M155 | DW14: ='_Engine_NR'!M156 | DX14: ='_Engine_NR'!M157 | DY14: ='_Engine_NR'!M158 | DZ14: ='_Engine_NR'!M159 | EA14: ='_Engine_NR'!M160 | EB14: ='_Engine_NR'!M161 | EC14: ='_Engine_NR'!M162 | ED14: ='_Engine_NR'!M163 | EE14: ='_Engine_NR'!M164 | EF14: ='_Engine_NR'!M165 | EG14: ='_Engine_NR'!M166 | EH14: ='_Engine_NR'!M167 | EI14: ='_Engine_NR'!M168 | EJ14: ='_Engine_NR'!M169 | EK14: ='_Engine_NR'!M170 | EL14: ='_Engine_NR'!M171 | EM14: ='_Engine_NR'!M172 | EN14: ='_Engine_NR'!M173 | EO14: ='_Engine_NR'!M174 | EP14: ='_Engine_NR'!M175 | EQ14: ='_Engine_NR'!M176 | ER14: ='_Engine_NR'!M177 | ES14: ='_Engine_NR'!M178 | ET14: ='_Engine_NR'!M179 | EU14: ='_Engine_NR'!M180 | EV14: ='_Engine_NR'!M181 | EW14: ='_Engine_NR'!M182 | EX14: ='_Engine_NR'!M183 | EY14: ='_Engine_NR'!M184 | EZ14: ='_Engine_NR'!M185 | FA14: ='_Engine_NR'!M186 | FB14: ='_Engine_NR'!M187 | FC14: ='_Engine_NR'!M188 | FD14: ='_Engine_NR'!M189 | FE14: ='_Engine_NR'!M190 | FF14: ='_Engine_NR'!M191 | FG14: ='_Engine_NR'!M192 | FH14: ='_Engine_NR'!M193 | FI14: ='_Engine_NR'!M194 | FJ14: ='_Engine_NR'!M195 | FK14: ='_Engine_NR'!M196 | FL14: ='_Engine_NR'!M197 | FM14: ='_Engine_NR'!M198 | FN14: ='_Engine_NR'!M199 | FO14: ='_Engine_NR'!M200 | FP14: ='_Engine_NR'!M201 | FQ14: ='_Engine_NR'!M202 | FR14: ='_Engine_NR'!M203 | FS14: ='_Engine_NR'!M204 | FT14: ='_Engine_NR'!M205 | FU14: ='_Engine_NR'!M206 | FV14: ='_Engine_NR'!M207 | FW14: ='_Engine_NR'!M208 | FX14: ='_Engine_NR'!M209 | FY14: ='_Engine_NR'!M210
A15: Gross Profit | B15: =B13-B14 | C15: =C13-C14 | D15: =D13-D14 | E15: =E13-E14 | F15: =F13-F14 | G15: =G13-G14 | H15: =H13-H14 | I15: =I13-I14 | ... FY15: =FY13-FY14
A17: Vendor Costs | B17: ='_Engine_NR'!N31 | C17: ='_Engine_NR'!N32 | D17: ='_Engine_NR'!N33 | E17: ='_Engine_NR'!N34 | F17: ='_Engine_NR'!N35 | G17: ='_Engine_NR'!N36 | H17: ='_Engine_NR'!N37 | I17: ='_Engine_NR'!N38 | J17: ='_Engine_NR'!N39 | K17: ='_Engine_NR'!N40 | L17: ='_Engine_NR'!N41 | M17: ='_Engine_NR'!N42 | N17: ='_Engine_NR'!N43 | O17: ='_Engine_NR'!N44 | P17: ='_Engine_NR'!N45 | Q17: ='_Engine_NR'!N46 | R17: ='_Engine_NR'!N47 | S17: ='_Engine_NR'!N48 | T17: ='_Engine_NR'!N49 | U17: ='_Engine_NR'!N50 | V17: ='_Engine_NR'!N51 | W17: ='_Engine_NR'!N52 | X17: ='_Engine_NR'!N53 | Y17: ='_Engine_NR'!N54 | Z17: ='_Engine_NR'!N55 | AA17: ='_Engine_NR'!N56 | AB17: ='_Engine_NR'!N57 | AC17: ='_Engine_NR'!N58 | AD17: ='_Engine_NR'!N59 | AE17: ='_Engine_NR'!N60 | AF17: ='_Engine_NR'!N61 | AG17: ='_Engine_NR'!N62 | AH17: ='_Engine_NR'!N63 | AI17: ='_Engine_NR'!N64 | AJ17: ='_Engine_NR'!N65 | AK17: ='_Engine_NR'!N66 | AL17: ='_Engine_NR'!N67 | AM17: ='_Engine_NR'!N68 | AN17: ='_Engine_NR'!N69 | AO17: ='_Engine_NR'!N70 | AP17: ='_Engine_NR'!N71 | AQ17: ='_Engine_NR'!N72 | AR17: ='_Engine_NR'!N73 | AS17: ='_Engine_NR'!N74 | AT17: ='_Engine_NR'!N75 | AU17: ='_Engine_NR'!N76 | AV17: ='_Engine_NR'!N77 | AW17: ='_Engine_NR'!N78 | AX17: ='_Engine_NR'!N79 | AY17: ='_Engine_NR'!N80 | AZ17: ='_Engine_NR'!N81 | BA17: ='_Engine_NR'!N82 | BB17: ='_Engine_NR'!N83 | BC17: ='_Engine_NR'!N84 | BD17: ='_Engine_NR'!N85 | BE17: ='_Engine_NR'!N86 | BF17: ='_Engine_NR'!N87 | BG17: ='_Engine_NR'!N88 | BH17: ='_Engine_NR'!N89 | BI17: ='_Engine_NR'!N90 | BJ17: ='_Engine_NR'!N91 | BK17: ='_Engine_NR'!N92 | BL17: ='_Engine_NR'!N93 | BM17: ='_Engine_NR'!N94 | BN17: ='_Engine_NR'!N95 | BO17: ='_Engine_NR'!N96 | BP17: ='_Engine_NR'!N97 | BQ17: ='_Engine_NR'!N98 | BR17: ='_Engine_NR'!N99 | BS17: ='_Engine_NR'!N100 | BT17: ='_Engine_NR'!N101 | BU17: ='_Engine_NR'!N102 | BV17: ='_Engine_NR'!N103 | BW17: ='_Engine_NR'!N104 | BX17: ='_Engine_NR'!N105 | BY17: ='_Engine_NR'!N106 | BZ17: ='_Engine_NR'!N107 | CA17: ='_Engine_NR'!N108 | CB17: ='_Engine_NR'!N109 | CC17: ='_Engine_NR'!N110 | CD17: ='_Engine_NR'!N111 | CE17: ='_Engine_NR'!N112 | CF17: ='_Engine_NR'!N113 | CG17: ='_Engine_NR'!N114 | CH17: ='_Engine_NR'!N115 | CI17: ='_Engine_NR'!N116 | CJ17: ='_Engine_NR'!N117 | CK17: ='_Engine_NR'!N118 | CL17: ='_Engine_NR'!N119 | CM17: ='_Engine_NR'!N120 | CN17: ='_Engine_NR'!N121 | CO17: ='_Engine_NR'!N122 | CP17: ='_Engine_NR'!N123 | CQ17: ='_Engine_NR'!N124 | CR17: ='_Engine_NR'!N125 | CS17: ='_Engine_NR'!N126 | CT17: ='_Engine_NR'!N127 | CU17: ='_Engine_NR'!N128 | CV17: ='_Engine_NR'!N129 | CW17: ='_Engine_NR'!N130 | CX17: ='_Engine_NR'!N131 | CY17: ='_Engine_NR'!N132 | CZ17: ='_Engine_NR'!N133 | DA17: ='_Engine_NR'!N134 | DB17: ='_Engine_NR'!N135 | DC17: ='_Engine_NR'!N136 | DD17: ='_Engine_NR'!N137 | DE17: ='_Engine_NR'!N138 | DF17: ='_Engine_NR'!N139 | DG17: ='_Engine_NR'!N140 | DH17: ='_Engine_NR'!N141 | DI17: ='_Engine_NR'!N142 | DJ17: ='_Engine_NR'!N143 | DK17: ='_Engine_NR'!N144 | DL17: ='_Engine_NR'!N145 | DM17: ='_Engine_NR'!N146 | DN17: ='_Engine_NR'!N147 | DO17: ='_Engine_NR'!N148 | DP17: ='_Engine_NR'!N149 | DQ17: ='_Engine_NR'!N150 | DR17: ='_Engine_NR'!N151 | DS17: ='_Engine_NR'!N152 | DT17: ='_Engine_NR'!N153 | DU17: ='_Engine_NR'!N154 | DV17: ='_Engine_NR'!N155 | DW17: ='_Engine_NR'!N156 | DX17: ='_Engine_NR'!N157 | DY17: ='_Engine_NR'!N158 | DZ17: ='_Engine_NR'!N159 | EA17: ='_Engine_NR'!N160 | EB17: ='_Engine_NR'!N161 | EC17: ='_Engine_NR'!N162 | ED17: ='_Engine_NR'!N163 | EE17: ='_Engine_NR'!N164 | EF17: ='_Engine_NR'!N165 | EG17: ='_Engine_NR'!N166 | EH17: ='_Engine_NR'!N167 | EI17: ='_Engine_NR'!N168 | EJ17: ='_Engine_NR'!N169 | EK17: ='_Engine_NR'!N170 | EL17: ='_Engine_NR'!N171 | EM17: ='_Engine_NR'!N172 | EN17: ='_Engine_NR'!N173 | EO17: ='_Engine_NR'!N174 | EP17: ='_Engine_NR'!N175 | EQ17: ='_Engine_NR'!N176 | ER17: ='_Engine_NR'!N177 | ES17: ='_Engine_NR'!N178 | ET17: ='_Engine_NR'!N179 | EU17: ='_Engine_NR'!N180 | EV17: ='_Engine_NR'!N181 | EW17: ='_Engine_NR'!N182 | EX17: ='_Engine_NR'!N183 | EY17: ='_Engine_NR'!N184 | EZ17: ='_Engine_NR'!N185 | FA17: ='_Engine_NR'!N186 | FB17: ='_Engine_NR'!N187 | FC17: ='_Engine_NR'!N188 | FD17: ='_Engine_NR'!N189 | FE17: ='_Engine_NR'!N190 | FF17: ='_Engine_NR'!N191 | FG17: ='_Engine_NR'!N192 | FH17: ='_Engine_NR'!N193 | FI17: ='_Engine_NR'!N194 | FJ17: ='_Engine_NR'!N195 | FK17: ='_Engine_NR'!N196 | FL17: ='_Engine_NR'!N197 | FM17: ='_Engine_NR'!N198 | FN17: ='_Engine_NR'!N199 | FO17: ='_Engine_NR'!N200 | FP17: ='_Engine_NR'!N201 | FQ17: ='_Engine_NR'!N202 | FR17: ='_Engine_NR'!N203 | FS17: ='_Engine_NR'!N204 | FT17: ='_Engine_NR'!N205 | FU17: ='_Engine_NR'!N206 | FV17: ='_Engine_NR'!N207 | FW17: ='_Engine_NR'!N208 | FX17: ='_Engine_NR'!N209 | FY17: ='_Engine_NR'!N210
A18: Corporate Allocation | B18: ='_Engine_NR'!O31 | C18: ='_Engine_NR'!O32 | D18: ='_Engine_NR'!O33 | E18: ='_Engine_NR'!O34 | F18: ='_Engine_NR'!O35 | G18: ='_Engine_NR'!O36 | H18: ='_Engine_NR'!O37 | I18: ='_Engine_NR'!O38 | J18: ='_Engine_NR'!O39 | K18: ='_Engine_NR'!O40 | L18: ='_Engine_NR'!O41 | M18: ='_Engine_NR'!O42 | N18: ='_Engine_NR'!O43 | O18: ='_Engine_NR'!O44 | P18: ='_Engine_NR'!O45 | Q18: ='_Engine_NR'!O46 | R18: ='_Engine_NR'!O47 | S18: ='_Engine_NR'!O48 | T18: ='_Engine_NR'!O49 | U18: ='_Engine_NR'!O50 | V18: ='_Engine_NR'!O51 | W18: ='_Engine_NR'!O52 | X18: ='_Engine_NR'!O53 | Y18: ='_Engine_NR'!O54 | Z18: ='_Engine_NR'!O55 | AA18: ='_Engine_NR'!O56 | AB18: ='_Engine_NR'!O57 | AC18: ='_Engine_NR'!O58 | AD18: ='_Engine_NR'!O59 | AE18: ='_Engine_NR'!O60 | AF18: ='_Engine_NR'!O61 | AG18: ='_Engine_NR'!O62 | AH18: ='_Engine_NR'!O63 | AI18: ='_Engine_NR'!O64 | AJ18: ='_Engine_NR'!O65 | AK18: ='_Engine_NR'!O66 | AL18: ='_Engine_NR'!O67 | AM18: ='_Engine_NR'!O68 | AN18: ='_Engine_NR'!O69 | AO18: ='_Engine_NR'!O70 | AP18: ='_Engine_NR'!O71 | AQ18: ='_Engine_NR'!O72 | AR18: ='_Engine_NR'!O73 | AS18: ='_Engine_NR'!O74 | AT18: ='_Engine_NR'!O75 | AU18: ='_Engine_NR'!O76 | AV18: ='_Engine_NR'!O77 | AW18: ='_Engine_NR'!O78 | AX18: ='_Engine_NR'!O79 | AY18: ='_Engine_NR'!O80 | AZ18: ='_Engine_NR'!O81 | BA18: ='_Engine_NR'!O82 | BB18: ='_Engine_NR'!O83 | BC18: ='_Engine_NR'!O84 | BD18: ='_Engine_NR'!O85 | BE18: ='_Engine_NR'!O86 | BF18: ='_Engine_NR'!O87 | BG18: ='_Engine_NR'!O88 | BH18: ='_Engine_NR'!O89 | BI18: ='_Engine_NR'!O90 | BJ18: ='_Engine_NR'!O91 | BK18: ='_Engine_NR'!O92 | BL18: ='_Engine_NR'!O93 | BM18: ='_Engine_NR'!O94 | BN18: ='_Engine_NR'!O95 | BO18: ='_Engine_NR'!O96 | BP18: ='_Engine_NR'!O97 | BQ18: ='_Engine_NR'!O98 | BR18: ='_Engine_NR'!O99 | BS18: ='_Engine_NR'!O100 | BT18: ='_Engine_NR'!O101 | BU18: ='_Engine_NR'!O102 | BV18: ='_Engine_NR'!O103 | BW18: ='_Engine_NR'!O104 | BX18: ='_Engine_NR'!O105 | BY18: ='_Engine_NR'!O106 | BZ18: ='_Engine_NR'!O107 | CA18: ='_Engine_NR'!O108 | CB18: ='_Engine_NR'!O109 | CC18: ='_Engine_NR'!O110 | CD18: ='_Engine_NR'!O111 | CE18: ='_Engine_NR'!O112 | CF18: ='_Engine_NR'!O113 | CG18: ='_Engine_NR'!O114 | CH18: ='_Engine_NR'!O115 | CI18: ='_Engine_NR'!O116 | CJ18: ='_Engine_NR'!O117 | CK18: ='_Engine_NR'!O118 | CL18: ='_Engine_NR'!O119 | CM18: ='_Engine_NR'!O120 | CN18: ='_Engine_NR'!O121 | CO18: ='_Engine_NR'!O122 | CP18: ='_Engine_NR'!O123 | CQ18: ='_Engine_NR'!O124 | CR18: ='_Engine_NR'!O125 | CS18: ='_Engine_NR'!O126 | CT18: ='_Engine_NR'!O127 | CU18: ='_Engine_NR'!O128 | CV18: ='_Engine_NR'!O129 | CW18: ='_Engine_NR'!O130 | CX18: ='_Engine_NR'!O131 | CY18: ='_Engine_NR'!O132 | CZ18: ='_Engine_NR'!O133 | DA18: ='_Engine_NR'!O134 | DB18: ='_Engine_NR'!O135 | DC18: ='_Engine_NR'!O136 | DD18: ='_Engine_NR'!O137 | DE18: ='_Engine_NR'!O138 | DF18: ='_Engine_NR'!O139 | DG18: ='_Engine_NR'!O140 | DH18: ='_Engine_NR'!O141 | DI18: ='_Engine_NR'!O142 | DJ18: ='_Engine_NR'!O143 | DK18: ='_Engine_NR'!O144 | DL18: ='_Engine_NR'!O145 | DM18: ='_Engine_NR'!O146 | DN18: ='_Engine_NR'!O147 | DO18: ='_Engine_NR'!O148 | DP18: ='_Engine_NR'!O149 | DQ18: ='_Engine_NR'!O150 | DR18: ='_Engine_NR'!O151 | DS18: ='_Engine_NR'!O152 | DT18: ='_Engine_NR'!O153 | DU18: ='_Engine_NR'!O154 | DV18: ='_Engine_NR'!O155 | DW18: ='_Engine_NR'!O156 | DX18: ='_Engine_NR'!O157 | DY18: ='_Engine_NR'!O158 | DZ18: ='_Engine_NR'!O159 | EA18: ='_Engine_NR'!O160 | EB18: ='_Engine_NR'!O161 | EC18: ='_Engine_NR'!O162 | ED18: ='_Engine_NR'!O163 | EE18: ='_Engine_NR'!O164 | EF18: ='_Engine_NR'!O165 | EG18: ='_Engine_NR'!O166 | EH18: ='_Engine_NR'!O167 | EI18: ='_Engine_NR'!O168 | EJ18: ='_Engine_NR'!O169 | EK18: ='_Engine_NR'!O170 | EL18: ='_Engine_NR'!O171 | EM18: ='_Engine_NR'!O172 | EN18: ='_Engine_NR'!O173 | EO18: ='_Engine_NR'!O174 | EP18: ='_Engine_NR'!O175 | EQ18: ='_Engine_NR'!O176 | ER18: ='_Engine_NR'!O177 | ES18: ='_Engine_NR'!O178 | ET18: ='_Engine_NR'!O179 | EU18: ='_Engine_NR'!O180 | EV18: ='_Engine_NR'!O181 | EW18: ='_Engine_NR'!O182 | EX18: ='_Engine_NR'!O183 | EY18: ='_Engine_NR'!O184 | EZ18: ='_Engine_NR'!O185 | FA18: ='_Engine_NR'!O186 | FB18: ='_Engine_NR'!O187 | FC18: ='_Engine_NR'!O188 | FD18: ='_Engine_NR'!O189 | FE18: ='_Engine_NR'!O190 | FF18: ='_Engine_NR'!O191 | FG18: ='_Engine_NR'!O192 | FH18: ='_Engine_NR'!O193 | FI18: ='_Engine_NR'!O194 | FJ18: ='_Engine_NR'!O195 | FK18: ='_Engine_NR'!O196 | FL18: ='_Engine_NR'!O197 | FM18: ='_Engine_NR'!O198 | FN18: ='_Engine_NR'!O199 | FO18: ='_Engine_NR'!O200 | FP18: ='_Engine_NR'!O201 | FQ18: ='_Engine_NR'!O202 | FR18: ='_Engine_NR'!O203 | FS18: ='_Engine_NR'!O204 | FT18: ='_Engine_NR'!O205 | FU18: ='_Engine_NR'!O206 | FV18: ='_Engine_NR'!O207 | FW18: ='_Engine_NR'!O208 | FX18: ='_Engine_NR'!O209 | FY18: ='_Engine_NR'!O210
A19: Team Compensation | B19: ='_Engine_NR'!D31 | C19: ='_Engine_NR'!D32 | D19: ='_Engine_NR'!D33 | E19: ='_Engine_NR'!D34 | F19: ='_Engine_NR'!D35 | G19: ='_Engine_NR'!D36 | H19: ='_Engine_NR'!D37 | I19: ='_Engine_NR'!D38 | J19: ='_Engine_NR'!D39 | K19: ='_Engine_NR'!D40 | L19: ='_Engine_NR'!D41 | M19: ='_Engine_NR'!D42 | N19: ='_Engine_NR'!D43 | O19: ='_Engine_NR'!D44 | P19: ='_Engine_NR'!D45 | Q19: ='_Engine_NR'!D46 | R19: ='_Engine_NR'!D47 | S19: ='_Engine_NR'!D48 | T19: ='_Engine_NR'!D49 | U19: ='_Engine_NR'!D50 | V19: ='_Engine_NR'!D51 | W19: ='_Engine_NR'!D52 | X19: ='_Engine_NR'!D53 | Y19: ='_Engine_NR'!D54 | Z19: ='_Engine_NR'!D55 | AA19: ='_Engine_NR'!D56 | AB19: ='_Engine_NR'!D57 | AC19: ='_Engine_NR'!D58 | AD19: ='_Engine_NR'!D59 | AE19: ='_Engine_NR'!D60 | AF19: ='_Engine_NR'!D61 | AG19: ='_Engine_NR'!D62 | AH19: ='_Engine_NR'!D63 | AI19: ='_Engine_NR'!D64 | AJ19: ='_Engine_NR'!D65 | AK19: ='_Engine_NR'!D66 | AL19: ='_Engine_NR'!D67 | AM19: ='_Engine_NR'!D68 | AN19: ='_Engine_NR'!D69 | AO19: ='_Engine_NR'!D70 | AP19: ='_Engine_NR'!D71 | AQ19: ='_Engine_NR'!D72 | AR19: ='_Engine_NR'!D73 | AS19: ='_Engine_NR'!D74 | AT19: ='_Engine_NR'!D75 | AU19: ='_Engine_NR'!D76 | AV19: ='_Engine_NR'!D77 | AW19: ='_Engine_NR'!D78 | AX19: ='_Engine_NR'!D79 | AY19: ='_Engine_NR'!D80 | AZ19: ='_Engine_NR'!D81 | BA19: ='_Engine_NR'!D82 | BB19: ='_Engine_NR'!D83 | BC19: ='_Engine_NR'!D84 | BD19: ='_Engine_NR'!D85 | BE19: ='_Engine_NR'!D86 | BF19: ='_Engine_NR'!D87 | BG19: ='_Engine_NR'!D88 | BH19: ='_Engine_NR'!D89 | BI19: ='_Engine_NR'!D90 | BJ19: ='_Engine_NR'!D91 | BK19: ='_Engine_NR'!D92 | BL19: ='_Engine_NR'!D93 | BM19: ='_Engine_NR'!D94 | BN19: ='_Engine_NR'!D95 | BO19: ='_Engine_NR'!D96 | BP19: ='_Engine_NR'!D97 | BQ19: ='_Engine_NR'!D98 | BR19: ='_Engine_NR'!D99 | BS19: ='_Engine_NR'!D100 | BT19: ='_Engine_NR'!D101 | BU19: ='_Engine_NR'!D102 | BV19: ='_Engine_NR'!D103 | BW19: ='_Engine_NR'!D104 | BX19: ='_Engine_NR'!D105 | BY19: ='_Engine_NR'!D106 | BZ19: ='_Engine_NR'!D107 | CA19: ='_Engine_NR'!D108 | CB19: ='_Engine_NR'!D109 | CC19: ='_Engine_NR'!D110 | CD19: ='_Engine_NR'!D111 | CE19: ='_Engine_NR'!D112 | CF19: ='_Engine_NR'!D113 | CG19: ='_Engine_NR'!D114 | CH19: ='_Engine_NR'!D115 | CI19: ='_Engine_NR'!D116 | CJ19: ='_Engine_NR'!D117 | CK19: ='_Engine_NR'!D118 | CL19: ='_Engine_NR'!D119 | CM19: ='_Engine_NR'!D120 | CN19: ='_Engine_NR'!D121 | CO19: ='_Engine_NR'!D122 | CP19: ='_Engine_NR'!D123 | CQ19: ='_Engine_NR'!D124 | CR19: ='_Engine_NR'!D125 | CS19: ='_Engine_NR'!D126 | CT19: ='_Engine_NR'!D127 | CU19: ='_Engine_NR'!D128 | CV19: ='_Engine_NR'!D129 | CW19: ='_Engine_NR'!D130 | CX19: ='_Engine_NR'!D131 | CY19: ='_Engine_NR'!D132 | CZ19: ='_Engine_NR'!D133 | DA19: ='_Engine_NR'!D134 | DB19: ='_Engine_NR'!D135 | DC19: ='_Engine_NR'!D136 | DD19: ='_Engine_NR'!D137 | DE19: ='_Engine_NR'!D138 | DF19: ='_Engine_NR'!D139 | DG19: ='_Engine_NR'!D140 | DH19: ='_Engine_NR'!D141 | DI19: ='_Engine_NR'!D142 | DJ19: ='_Engine_NR'!D143 | DK19: ='_Engine_NR'!D144 | DL19: ='_Engine_NR'!D145 | DM19: ='_Engine_NR'!D146 | DN19: ='_Engine_NR'!D147 | DO19: ='_Engine_NR'!D148 | DP19: ='_Engine_NR'!D149 | DQ19: ='_Engine_NR'!D150 | DR19: ='_Engine_NR'!D151 | DS19: ='_Engine_NR'!D152 | DT19: ='_Engine_NR'!D153 | DU19: ='_Engine_NR'!D154 | DV19: ='_Engine_NR'!D155 | DW19: ='_Engine_NR'!D156 | DX19: ='_Engine_NR'!D157 | DY19: ='_Engine_NR'!D158 | DZ19: ='_Engine_NR'!D159 | EA19: ='_Engine_NR'!D160 | EB19: ='_Engine_NR'!D161 | EC19: ='_Engine_NR'!D162 | ED19: ='_Engine_NR'!D163 | EE19: ='_Engine_NR'!D164 | EF19: ='_Engine_NR'!D165 | EG19: ='_Engine_NR'!D166 | EH19: ='_Engine_NR'!D167 | EI19: ='_Engine_NR'!D168 | EJ19: ='_Engine_NR'!D169 | EK19: ='_Engine_NR'!D170 | EL19: ='_Engine_NR'!D171 | EM19: ='_Engine_NR'!D172 | EN19: ='_Engine_NR'!D173 | EO19: ='_Engine_NR'!D174 | EP19: ='_Engine_NR'!D175 | EQ19: ='_Engine_NR'!D176 | ER19: ='_Engine_NR'!D177 | ES19: ='_Engine_NR'!D178 | ET19: ='_Engine_NR'!D179 | EU19: ='_Engine_NR'!D180 | EV19: ='_Engine_NR'!D181 | EW19: ='_Engine_NR'!D182 | EX19: ='_Engine_NR'!D183 | EY19: ='_Engine_NR'!D184 | EZ19: ='_Engine_NR'!D185 | FA19: ='_Engine_NR'!D186 | FB19: ='_Engine_NR'!D187 | FC19: ='_Engine_NR'!D188 | FD19: ='_Engine_NR'!D189 | FE19: ='_Engine_NR'!D190 | FF19: ='_Engine_NR'!D191 | FG19: ='_Engine_NR'!D192 | FH19: ='_Engine_NR'!D193 | FI19: ='_Engine_NR'!D194 | FJ19: ='_Engine_NR'!D195 | FK19: ='_Engine_NR'!D196 | FL19: ='_Engine_NR'!D197 | FM19: ='_Engine_NR'!D198 | FN19: ='_Engine_NR'!D199 | FO19: ='_Engine_NR'!D200 | FP19: ='_Engine_NR'!D201 | FQ19: ='_Engine_NR'!D202 | FR19: ='_Engine_NR'!D203 | FS19: ='_Engine_NR'!D204 | FT19: ='_Engine_NR'!D205 | FU19: ='_Engine_NR'!D206 | FV19: ='_Engine_NR'!D207 | FW19: ='_Engine_NR'!D208 | FX19: ='_Engine_NR'!D209 | FY19: ='_Engine_NR'!D210
A20: Legacy Headcount Expenses | B20: ='_Engine_NR'!E31 | C20: ='_Engine_NR'!E32 | D20: ='_Engine_NR'!E33 | E20: ='_Engine_NR'!E34 | F20: ='_Engine_NR'!E35 | G20: ='_Engine_NR'!E36 | H20: ='_Engine_NR'!E37 | I20: ='_Engine_NR'!E38 | J20: ='_Engine_NR'!E39 | K20: ='_Engine_NR'!E40 | L20: ='_Engine_NR'!E41 | M20: ='_Engine_NR'!E42 | N20: ='_Engine_NR'!E43 | O20: ='_Engine_NR'!E44 | P20: ='_Engine_NR'!E45 | Q20: ='_Engine_NR'!E46 | R20: ='_Engine_NR'!E47 | S20: ='_Engine_NR'!E48 | T20: ='_Engine_NR'!E49 | U20: ='_Engine_NR'!E50 | V20: ='_Engine_NR'!E51 | W20: ='_Engine_NR'!E52 | X20: ='_Engine_NR'!E53 | Y20: ='_Engine_NR'!E54 | Z20: ='_Engine_NR'!E55 | AA20: ='_Engine_NR'!E56 | AB20: ='_Engine_NR'!E57 | AC20: ='_Engine_NR'!E58 | AD20: ='_Engine_NR'!E59 | AE20: ='_Engine_NR'!E60 | AF20: ='_Engine_NR'!E61 | AG20: ='_Engine_NR'!E62 | AH20: ='_Engine_NR'!E63 | AI20: ='_Engine_NR'!E64 | AJ20: ='_Engine_NR'!E65 | AK20: ='_Engine_NR'!E66 | AL20: ='_Engine_NR'!E67 | AM20: ='_Engine_NR'!E68 | AN20: ='_Engine_NR'!E69 | AO20: ='_Engine_NR'!E70 | AP20: ='_Engine_NR'!E71 | AQ20: ='_Engine_NR'!E72 | AR20: ='_Engine_NR'!E73 | AS20: ='_Engine_NR'!E74 | AT20: ='_Engine_NR'!E75 | AU20: ='_Engine_NR'!E76 | AV20: ='_Engine_NR'!E77 | AW20: ='_Engine_NR'!E78 | AX20: ='_Engine_NR'!E79 | AY20: ='_Engine_NR'!E80 | AZ20: ='_Engine_NR'!E81 | BA20: ='_Engine_NR'!E82 | BB20: ='_Engine_NR'!E83 | BC20: ='_Engine_NR'!E84 | BD20: ='_Engine_NR'!E85 | BE20: ='_Engine_NR'!E86 | BF20: ='_Engine_NR'!E87 | BG20: ='_Engine_NR'!E88 | BH20: ='_Engine_NR'!E89 | BI20: ='_Engine_NR'!E90 | BJ20: ='_Engine_NR'!E91 | BK20: ='_Engine_NR'!E92 | BL20: ='_Engine_NR'!E93 | BM20: ='_Engine_NR'!E94 | BN20: ='_Engine_NR'!E95 | BO20: ='_Engine_NR'!E96 | BP20: ='_Engine_NR'!E97 | BQ20: ='_Engine_NR'!E98 | BR20: ='_Engine_NR'!E99 | BS20: ='_Engine_NR'!E100 | BT20: ='_Engine_NR'!E101 | BU20: ='_Engine_NR'!E102 | BV20: ='_Engine_NR'!E103 | BW20: ='_Engine_NR'!E104 | BX20: ='_Engine_NR'!E105 | BY20: ='_Engine_NR'!E106 | BZ20: ='_Engine_NR'!E107 | CA20: ='_Engine_NR'!E108 | CB20: ='_Engine_NR'!E109 | CC20: ='_Engine_NR'!E110 | CD20: ='_Engine_NR'!E111 | CE20: ='_Engine_NR'!E112 | CF20: ='_Engine_NR'!E113 | CG20: ='_Engine_NR'!E114 | CH20: ='_Engine_NR'!E115 | CI20: ='_Engine_NR'!E116 | CJ20: ='_Engine_NR'!E117 | CK20: ='_Engine_NR'!E118 | CL20: ='_Engine_NR'!E119 | CM20: ='_Engine_NR'!E120 | CN20: ='_Engine_NR'!E121 | CO20: ='_Engine_NR'!E122 | CP20: ='_Engine_NR'!E123 | CQ20: ='_Engine_NR'!E124 | CR20: ='_Engine_NR'!E125 | CS20: ='_Engine_NR'!E126 | CT20: ='_Engine_NR'!E127 | CU20: ='_Engine_NR'!E128 | CV20: ='_Engine_NR'!E129 | CW20: ='_Engine_NR'!E130 | CX20: ='_Engine_NR'!E131 | CY20: ='_Engine_NR'!E132 | CZ20: ='_Engine_NR'!E133 | DA20: ='_Engine_NR'!E134 | DB20: ='_Engine_NR'!E135 | DC20: ='_Engine_NR'!E136 | DD20: ='_Engine_NR'!E137 | DE20: ='_Engine_NR'!E138 | DF20: ='_Engine_NR'!E139 | DG20: ='_Engine_NR'!E140 | DH20: ='_Engine_NR'!E141 | DI20: ='_Engine_NR'!E142 | DJ20: ='_Engine_NR'!E143 | DK20: ='_Engine_NR'!E144 | DL20: ='_Engine_NR'!E145 | DM20: ='_Engine_NR'!E146 | DN20: ='_Engine_NR'!E147 | DO20: ='_Engine_NR'!E148 | DP20: ='_Engine_NR'!E149 | DQ20: ='_Engine_NR'!E150 | DR20: ='_Engine_NR'!E151 | DS20: ='_Engine_NR'!E152 | DT20: ='_Engine_NR'!E153 | DU20: ='_Engine_NR'!E154 | DV20: ='_Engine_NR'!E155 | DW20: ='_Engine_NR'!E156 | DX20: ='_Engine_NR'!E157 | DY20: ='_Engine_NR'!E158 | DZ20: ='_Engine_NR'!E159 | EA20: ='_Engine_NR'!E160 | EB20: ='_Engine_NR'!E161 | EC20: ='_Engine_NR'!E162 | ED20: ='_Engine_NR'!E163 | EE20: ='_Engine_NR'!E164 | EF20: ='_Engine_NR'!E165 | EG20: ='_Engine_NR'!E166 | EH20: ='_Engine_NR'!E167 | EI20: ='_Engine_NR'!E168 | EJ20: ='_Engine_NR'!E169 | EK20: ='_Engine_NR'!E170 | EL20: ='_Engine_NR'!E171 | EM20: ='_Engine_NR'!E172 | EN20: ='_Engine_NR'!E173 | EO20: ='_Engine_NR'!E174 | EP20: ='_Engine_NR'!E175 | EQ20: ='_Engine_NR'!E176 | ER20: ='_Engine_NR'!E177 | ES20: ='_Engine_NR'!E178 | ET20: ='_Engine_NR'!E179 | EU20: ='_Engine_NR'!E180 | EV20: ='_Engine_NR'!E181 | EW20: ='_Engine_NR'!E182 | EX20: ='_Engine_NR'!E183 | EY20: ='_Engine_NR'!E184 | EZ20: ='_Engine_NR'!E185 | FA20: ='_Engine_NR'!E186 | FB20: ='_Engine_NR'!E187 | FC20: ='_Engine_NR'!E188 | FD20: ='_Engine_NR'!E189 | FE20: ='_Engine_NR'!E190 | FF20: ='_Engine_NR'!E191 | FG20: ='_Engine_NR'!E192 | FH20: ='_Engine_NR'!E193 | FI20: ='_Engine_NR'!E194 | FJ20: ='_Engine_NR'!E195 | FK20: ='_Engine_NR'!E196 | FL20: ='_Engine_NR'!E197 | FM20: ='_Engine_NR'!E198 | FN20: ='_Engine_NR'!E199 | FO20: ='_Engine_NR'!E200 | FP20: ='_Engine_NR'!E201 | FQ20: ='_Engine_NR'!E202 | FR20: ='_Engine_NR'!E203 | FS20: ='_Engine_NR'!E204 | FT20: ='_Engine_NR'!E205 | FU20: ='_Engine_NR'!E206 | FV20: ='_Engine_NR'!E207 | FW20: ='_Engine_NR'!E208 | FX20: ='_Engine_NR'!E209 | FY20: ='_Engine_NR'!E210
A21: Bonus Pool | B21: ='_Engine_NR'!Q31 | C21: ='_Engine_NR'!Q32 | D21: ='_Engine_NR'!Q33 | E21: ='_Engine_NR'!Q34 | F21: ='_Engine_NR'!Q35 | G21: ='_Engine_NR'!Q36 | H21: ='_Engine_NR'!Q37 | I21: ='_Engine_NR'!Q38 | J21: ='_Engine_NR'!Q39 | K21: ='_Engine_NR'!Q40 | L21: ='_Engine_NR'!Q41 | M21: ='_Engine_NR'!Q42 | N21: ='_Engine_NR'!Q43 | O21: ='_Engine_NR'!Q44 | P21: ='_Engine_NR'!Q45 | Q21: ='_Engine_NR'!Q46 | R21: ='_Engine_NR'!Q47 | S21: ='_Engine_NR'!Q48 | T21: ='_Engine_NR'!Q49 | U21: ='_Engine_NR'!Q50 | V21: ='_Engine_NR'!Q51 | W21: ='_Engine_NR'!Q52 | X21: ='_Engine_NR'!Q53 | Y21: ='_Engine_NR'!Q54 | Z21: ='_Engine_NR'!Q55 | AA21: ='_Engine_NR'!Q56 | AB21: ='_Engine_NR'!Q57 | AC21: ='_Engine_NR'!Q58 | AD21: ='_Engine_NR'!Q59 | AE21: ='_Engine_NR'!Q60 | AF21: ='_Engine_NR'!Q61 | AG21: ='_Engine_NR'!Q62 | AH21: ='_Engine_NR'!Q63 | AI21: ='_Engine_NR'!Q64 | AJ21: ='_Engine_NR'!Q65 | AK21: ='_Engine_NR'!Q66 | AL21: ='_Engine_NR'!Q67 | AM21: ='_Engine_NR'!Q68 | AN21: ='_Engine_NR'!Q69 | AO21: ='_Engine_NR'!Q70 | AP21: ='_Engine_NR'!Q71 | AQ21: ='_Engine_NR'!Q72 | AR21: ='_Engine_NR'!Q73 | AS21: ='_Engine_NR'!Q74 | AT21: ='_Engine_NR'!Q75 | AU21: ='_Engine_NR'!Q76 | AV21: ='_Engine_NR'!Q77 | AW21: ='_Engine_NR'!Q78 | AX21: ='_Engine_NR'!Q79 | AY21: ='_Engine_NR'!Q80 | AZ21: ='_Engine_NR'!Q81 | BA21: ='_Engine_NR'!Q82 | BB21: ='_Engine_NR'!Q83 | BC21: ='_Engine_NR'!Q84 | BD21: ='_Engine_NR'!Q85 | BE21: ='_Engine_NR'!Q86 | BF21: ='_Engine_NR'!Q87 | BG21: ='_Engine_NR'!Q88 | BH21: ='_Engine_NR'!Q89 | BI21: ='_Engine_NR'!Q90 | BJ21: ='_Engine_NR'!Q91 | BK21: ='_Engine_NR'!Q92 | BL21: ='_Engine_NR'!Q93 | BM21: ='_Engine_NR'!Q94 | BN21: ='_Engine_NR'!Q95 | BO21: ='_Engine_NR'!Q96 | BP21: ='_Engine_NR'!Q97 | BQ21: ='_Engine_NR'!Q98 | BR21: ='_Engine_NR'!Q99 | BS21: ='_Engine_NR'!Q100 | BT21: ='_Engine_NR'!Q101 | BU21: ='_Engine_NR'!Q102 | BV21: ='_Engine_NR'!Q103 | BW21: ='_Engine_NR'!Q104 | BX21: ='_Engine_NR'!Q105 | BY21: ='_Engine_NR'!Q106 | BZ21: ='_Engine_NR'!Q107 | CA21: ='_Engine_NR'!Q108 | CB21: ='_Engine_NR'!Q109 | CC21: ='_Engine_NR'!Q110 | CD21: ='_Engine_NR'!Q111 | CE21: ='_Engine_NR'!Q112 | CF21: ='_Engine_NR'!Q113 | CG21: ='_Engine_NR'!Q114 | CH21: ='_Engine_NR'!Q115 | CI21: ='_Engine_NR'!Q116 | CJ21: ='_Engine_NR'!Q117 | CK21: ='_Engine_NR'!Q118 | CL21: ='_Engine_NR'!Q119 | CM21: ='_Engine_NR'!Q120 | CN21: ='_Engine_NR'!Q121 | CO21: ='_Engine_NR'!Q122 | CP21: ='_Engine_NR'!Q123 | CQ21: ='_Engine_NR'!Q124 | CR21: ='_Engine_NR'!Q125 | CS21: ='_Engine_NR'!Q126 | CT21: ='_Engine_NR'!Q127 | CU21: ='_Engine_NR'!Q128 | CV21: ='_Engine_NR'!Q129 | CW21: ='_Engine_NR'!Q130 | CX21: ='_Engine_NR'!Q131 | CY21: ='_Engine_NR'!Q132 | CZ21: ='_Engine_NR'!Q133 | DA21: ='_Engine_NR'!Q134 | DB21: ='_Engine_NR'!Q135 | DC21: ='_Engine_NR'!Q136 | DD21: ='_Engine_NR'!Q137 | DE21: ='_Engine_NR'!Q138 | DF21: ='_Engine_NR'!Q139 | DG21: ='_Engine_NR'!Q140 | DH21: ='_Engine_NR'!Q141 | DI21: ='_Engine_NR'!Q142 | DJ21: ='_Engine_NR'!Q143 | DK21: ='_Engine_NR'!Q144 | DL21: ='_Engine_NR'!Q145 | DM21: ='_Engine_NR'!Q146 | DN21: ='_Engine_NR'!Q147 | DO21: ='_Engine_NR'!Q148 | DP21: ='_Engine_NR'!Q149 | DQ21: ='_Engine_NR'!Q150 | DR21: ='_Engine_NR'!Q151 | DS21: ='_Engine_NR'!Q152 | DT21: ='_Engine_NR'!Q153 | DU21: ='_Engine_NR'!Q154 | DV21: ='_Engine_NR'!Q155 | DW21: ='_Engine_NR'!Q156 | DX21: ='_Engine_NR'!Q157 | DY21: ='_Engine_NR'!Q158 | DZ21: ='_Engine_NR'!Q159 | EA21: ='_Engine_NR'!Q160 | EB21: ='_Engine_NR'!Q161 | EC21: ='_Engine_NR'!Q162 | ED21: ='_Engine_NR'!Q163 | EE21: ='_Engine_NR'!Q164 | EF21: ='_Engine_NR'!Q165 | EG21: ='_Engine_NR'!Q166 | EH21: ='_Engine_NR'!Q167 | EI21: ='_Engine_NR'!Q168 | EJ21: ='_Engine_NR'!Q169 | EK21: ='_Engine_NR'!Q170 | EL21: ='_Engine_NR'!Q171 | EM21: ='_Engine_NR'!Q172 | EN21: ='_Engine_NR'!Q173 | EO21: ='_Engine_NR'!Q174 | EP21: ='_Engine_NR'!Q175 | EQ21: ='_Engine_NR'!Q176 | ER21: ='_Engine_NR'!Q177 | ES21: ='_Engine_NR'!Q178 | ET21: ='_Engine_NR'!Q179 | EU21: ='_Engine_NR'!Q180 | EV21: ='_Engine_NR'!Q181 | EW21: ='_Engine_NR'!Q182 | EX21: ='_Engine_NR'!Q183 | EY21: ='_Engine_NR'!Q184 | EZ21: ='_Engine_NR'!Q185 | FA21: ='_Engine_NR'!Q186 | FB21: ='_Engine_NR'!Q187 | FC21: ='_Engine_NR'!Q188 | FD21: ='_Engine_NR'!Q189 | FE21: ='_Engine_NR'!Q190 | FF21: ='_Engine_NR'!Q191 | FG21: ='_Engine_NR'!Q192 | FH21: ='_Engine_NR'!Q193 | FI21: ='_Engine_NR'!Q194 | FJ21: ='_Engine_NR'!Q195 | FK21: ='_Engine_NR'!Q196 | FL21: ='_Engine_NR'!Q197 | FM21: ='_Engine_NR'!Q198 | FN21: ='_Engine_NR'!Q199 | FO21: ='_Engine_NR'!Q200 | FP21: ='_Engine_NR'!Q201 | FQ21: ='_Engine_NR'!Q202 | FR21: ='_Engine_NR'!Q203 | FS21: ='_Engine_NR'!Q204 | FT21: ='_Engine_NR'!Q205 | FU21: ='_Engine_NR'!Q206 | FV21: ='_Engine_NR'!Q207 | FW21: ='_Engine_NR'!Q208 | FX21: ='_Engine_NR'!Q209 | FY21: ='_Engine_NR'!Q210
A22: Total Operating Expenses | B22: =B17+B18+B19+B20+B21+B14 | C22: =C17+C18+C19+C20+C21+C14 | D22: =D17+D18+D19+D20+D21+D14 | E22: =E17+E18+E19+E20+E21+E14 | F22: =F17+F18+F19+F20+F21+F14 | G22: =G17+G18+G19+G20+G21+G14 | H22: =H17+H18+H19+H20+H21+H14 | I22: =I17+I18+I19+I20+I21+I14 | ... FY22: =FY17+FY18+FY19+FY20+FY21+FY14
A24: EBITDA | B24: ='_Engine_NR'!R31 | C24: ='_Engine_NR'!R32 | D24: ='_Engine_NR'!R33 | E24: ='_Engine_NR'!R34 | F24: ='_Engine_NR'!R35 | G24: ='_Engine_NR'!R36 | H24: ='_Engine_NR'!R37 | I24: ='_Engine_NR'!R38 | J24: ='_Engine_NR'!R39 | K24: ='_Engine_NR'!R40 | L24: ='_Engine_NR'!R41 | M24: ='_Engine_NR'!R42 | N24: ='_Engine_NR'!R43 | O24: ='_Engine_NR'!R44 | P24: ='_Engine_NR'!R45 | Q24: ='_Engine_NR'!R46 | R24: ='_Engine_NR'!R47 | S24: ='_Engine_NR'!R48 | T24: ='_Engine_NR'!R49 | U24: ='_Engine_NR'!R50 | V24: ='_Engine_NR'!R51 | W24: ='_Engine_NR'!R52 | X24: ='_Engine_NR'!R53 | Y24: ='_Engine_NR'!R54 | Z24: ='_Engine_NR'!R55 | AA24: ='_Engine_NR'!R56 | AB24: ='_Engine_NR'!R57 | AC24: ='_Engine_NR'!R58 | AD24: ='_Engine_NR'!R59 | AE24: ='_Engine_NR'!R60 | AF24: ='_Engine_NR'!R61 | AG24: ='_Engine_NR'!R62 | AH24: ='_Engine_NR'!R63 | AI24: ='_Engine_NR'!R64 | AJ24: ='_Engine_NR'!R65 | AK24: ='_Engine_NR'!R66 | AL24: ='_Engine_NR'!R67 | AM24: ='_Engine_NR'!R68 | AN24: ='_Engine_NR'!R69 | AO24: ='_Engine_NR'!R70 | AP24: ='_Engine_NR'!R71 | AQ24: ='_Engine_NR'!R72 | AR24: ='_Engine_NR'!R73 | AS24: ='_Engine_NR'!R74 | AT24: ='_Engine_NR'!R75 | AU24: ='_Engine_NR'!R76 | AV24: ='_Engine_NR'!R77 | AW24: ='_Engine_NR'!R78 | AX24: ='_Engine_NR'!R79 | AY24: ='_Engine_NR'!R80 | AZ24: ='_Engine_NR'!R81 | BA24: ='_Engine_NR'!R82 | BB24: ='_Engine_NR'!R83 | BC24: ='_Engine_NR'!R84 | BD24: ='_Engine_NR'!R85 | BE24: ='_Engine_NR'!R86 | BF24: ='_Engine_NR'!R87 | BG24: ='_Engine_NR'!R88 | BH24: ='_Engine_NR'!R89 | BI24: ='_Engine_NR'!R90 | BJ24: ='_Engine_NR'!R91 | BK24: ='_Engine_NR'!R92 | BL24: ='_Engine_NR'!R93 | BM24: ='_Engine_NR'!R94 | BN24: ='_Engine_NR'!R95 | BO24: ='_Engine_NR'!R96 | BP24: ='_Engine_NR'!R97 | BQ24: ='_Engine_NR'!R98 | BR24: ='_Engine_NR'!R99 | BS24: ='_Engine_NR'!R100 | BT24: ='_Engine_NR'!R101 | BU24: ='_Engine_NR'!R102 | BV24: ='_Engine_NR'!R103 | BW24: ='_Engine_NR'!R104 | BX24: ='_Engine_NR'!R105 | BY24: ='_Engine_NR'!R106 | BZ24: ='_Engine_NR'!R107 | CA24: ='_Engine_NR'!R108 | CB24: ='_Engine_NR'!R109 | CC24: ='_Engine_NR'!R110 | CD24: ='_Engine_NR'!R111 | CE24: ='_Engine_NR'!R112 | CF24: ='_Engine_NR'!R113 | CG24: ='_Engine_NR'!R114 | CH24: ='_Engine_NR'!R115 | CI24: ='_Engine_NR'!R116 | CJ24: ='_Engine_NR'!R117 | CK24: ='_Engine_NR'!R118 | CL24: ='_Engine_NR'!R119 | CM24: ='_Engine_NR'!R120 | CN24: ='_Engine_NR'!R121 | CO24: ='_Engine_NR'!R122 | CP24: ='_Engine_NR'!R123 | CQ24: ='_Engine_NR'!R124 | CR24: ='_Engine_NR'!R125 | CS24: ='_Engine_NR'!R126 | CT24: ='_Engine_NR'!R127 | CU24: ='_Engine_NR'!R128 | CV24: ='_Engine_NR'!R129 | CW24: ='_Engine_NR'!R130 | CX24: ='_Engine_NR'!R131 | CY24: ='_Engine_NR'!R132 | CZ24: ='_Engine_NR'!R133 | DA24: ='_Engine_NR'!R134 | DB24: ='_Engine_NR'!R135 | DC24: ='_Engine_NR'!R136 | DD24: ='_Engine_NR'!R137 | DE24: ='_Engine_NR'!R138 | DF24: ='_Engine_NR'!R139 | DG24: ='_Engine_NR'!R140 | DH24: ='_Engine_NR'!R141 | DI24: ='_Engine_NR'!R142 | DJ24: ='_Engine_NR'!R143 | DK24: ='_Engine_NR'!R144 | DL24: ='_Engine_NR'!R145 | DM24: ='_Engine_NR'!R146 | DN24: ='_Engine_NR'!R147 | DO24: ='_Engine_NR'!R148 | DP24: ='_Engine_NR'!R149 | DQ24: ='_Engine_NR'!R150 | DR24: ='_Engine_NR'!R151 | DS24: ='_Engine_NR'!R152 | DT24: ='_Engine_NR'!R153 | DU24: ='_Engine_NR'!R154 | DV24: ='_Engine_NR'!R155 | DW24: ='_Engine_NR'!R156 | DX24: ='_Engine_NR'!R157 | DY24: ='_Engine_NR'!R158 | DZ24: ='_Engine_NR'!R159 | EA24: ='_Engine_NR'!R160 | EB24: ='_Engine_NR'!R161 | EC24: ='_Engine_NR'!R162 | ED24: ='_Engine_NR'!R163 | EE24: ='_Engine_NR'!R164 | EF24: ='_Engine_NR'!R165 | EG24: ='_Engine_NR'!R166 | EH24: ='_Engine_NR'!R167 | EI24: ='_Engine_NR'!R168 | EJ24: ='_Engine_NR'!R169 | EK24: ='_Engine_NR'!R170 | EL24: ='_Engine_NR'!R171 | EM24: ='_Engine_NR'!R172 | EN24: ='_Engine_NR'!R173 | EO24: ='_Engine_NR'!R174 | EP24: ='_Engine_NR'!R175 | EQ24: ='_Engine_NR'!R176 | ER24: ='_Engine_NR'!R177 | ES24: ='_Engine_NR'!R178 | ET24: ='_Engine_NR'!R179 | EU24: ='_Engine_NR'!R180 | EV24: ='_Engine_NR'!R181 | EW24: ='_Engine_NR'!R182 | EX24: ='_Engine_NR'!R183 | EY24: ='_Engine_NR'!R184 | EZ24: ='_Engine_NR'!R185 | FA24: ='_Engine_NR'!R186 | FB24: ='_Engine_NR'!R187 | FC24: ='_Engine_NR'!R188 | FD24: ='_Engine_NR'!R189 | FE24: ='_Engine_NR'!R190 | FF24: ='_Engine_NR'!R191 | FG24: ='_Engine_NR'!R192 | FH24: ='_Engine_NR'!R193 | FI24: ='_Engine_NR'!R194 | FJ24: ='_Engine_NR'!R195 | FK24: ='_Engine_NR'!R196 | FL24: ='_Engine_NR'!R197 | FM24: ='_Engine_NR'!R198 | FN24: ='_Engine_NR'!R199 | FO24: ='_Engine_NR'!R200 | FP24: ='_Engine_NR'!R201 | FQ24: ='_Engine_NR'!R202 | FR24: ='_Engine_NR'!R203 | FS24: ='_Engine_NR'!R204 | FT24: ='_Engine_NR'!R205 | FU24: ='_Engine_NR'!R206 | FV24: ='_Engine_NR'!R207 | FW24: ='_Engine_NR'!R208 | FX24: ='_Engine_NR'!R209 | FY24: ='_Engine_NR'!R210
A25: Severance (Press 50%) | B25: ='_Engine_NR'!S31 | C25: ='_Engine_NR'!S32 | D25: ='_Engine_NR'!S33 | E25: ='_Engine_NR'!S34 | F25: ='_Engine_NR'!S35 | G25: ='_Engine_NR'!S36 | H25: ='_Engine_NR'!S37 | I25: ='_Engine_NR'!S38 | J25: ='_Engine_NR'!S39 | K25: ='_Engine_NR'!S40 | L25: ='_Engine_NR'!S41 | M25: ='_Engine_NR'!S42 | N25: ='_Engine_NR'!S43 | O25: ='_Engine_NR'!S44 | P25: ='_Engine_NR'!S45 | Q25: ='_Engine_NR'!S46 | R25: ='_Engine_NR'!S47 | S25: ='_Engine_NR'!S48 | T25: ='_Engine_NR'!S49 | U25: ='_Engine_NR'!S50 | V25: ='_Engine_NR'!S51 | W25: ='_Engine_NR'!S52 | X25: ='_Engine_NR'!S53 | Y25: ='_Engine_NR'!S54 | Z25: ='_Engine_NR'!S55 | AA25: ='_Engine_NR'!S56 | AB25: ='_Engine_NR'!S57 | AC25: ='_Engine_NR'!S58 | AD25: ='_Engine_NR'!S59 | AE25: ='_Engine_NR'!S60 | AF25: ='_Engine_NR'!S61 | AG25: ='_Engine_NR'!S62 | AH25: ='_Engine_NR'!S63 | AI25: ='_Engine_NR'!S64 | AJ25: ='_Engine_NR'!S65 | AK25: ='_Engine_NR'!S66 | AL25: ='_Engine_NR'!S67 | AM25: ='_Engine_NR'!S68 | AN25: ='_Engine_NR'!S69 | AO25: ='_Engine_NR'!S70 | AP25: ='_Engine_NR'!S71 | AQ25: ='_Engine_NR'!S72 | AR25: ='_Engine_NR'!S73 | AS25: ='_Engine_NR'!S74 | AT25: ='_Engine_NR'!S75 | AU25: ='_Engine_NR'!S76 | AV25: ='_Engine_NR'!S77 | AW25: ='_Engine_NR'!S78 | AX25: ='_Engine_NR'!S79 | AY25: ='_Engine_NR'!S80 | AZ25: ='_Engine_NR'!S81 | BA25: ='_Engine_NR'!S82 | BB25: ='_Engine_NR'!S83 | BC25: ='_Engine_NR'!S84 | BD25: ='_Engine_NR'!S85 | BE25: ='_Engine_NR'!S86 | BF25: ='_Engine_NR'!S87 | BG25: ='_Engine_NR'!S88 | BH25: ='_Engine_NR'!S89 | BI25: ='_Engine_NR'!S90 | BJ25: ='_Engine_NR'!S91 | BK25: ='_Engine_NR'!S92 | BL25: ='_Engine_NR'!S93 | BM25: ='_Engine_NR'!S94 | BN25: ='_Engine_NR'!S95 | BO25: ='_Engine_NR'!S96 | BP25: ='_Engine_NR'!S97 | BQ25: ='_Engine_NR'!S98 | BR25: ='_Engine_NR'!S99 | BS25: ='_Engine_NR'!S100 | BT25: ='_Engine_NR'!S101 | BU25: ='_Engine_NR'!S102 | BV25: ='_Engine_NR'!S103 | BW25: ='_Engine_NR'!S104 | BX25: ='_Engine_NR'!S105 | BY25: ='_Engine_NR'!S106 | BZ25: ='_Engine_NR'!S107 | CA25: ='_Engine_NR'!S108 | CB25: ='_Engine_NR'!S109 | CC25: ='_Engine_NR'!S110 | CD25: ='_Engine_NR'!S111 | CE25: ='_Engine_NR'!S112 | CF25: ='_Engine_NR'!S113 | CG25: ='_Engine_NR'!S114 | CH25: ='_Engine_NR'!S115 | CI25: ='_Engine_NR'!S116 | CJ25: ='_Engine_NR'!S117 | CK25: ='_Engine_NR'!S118 | CL25: ='_Engine_NR'!S119 | CM25: ='_Engine_NR'!S120 | CN25: ='_Engine_NR'!S121 | CO25: ='_Engine_NR'!S122 | CP25: ='_Engine_NR'!S123 | CQ25: ='_Engine_NR'!S124 | CR25: ='_Engine_NR'!S125 | CS25: ='_Engine_NR'!S126 | CT25: ='_Engine_NR'!S127 | CU25: ='_Engine_NR'!S128 | CV25: ='_Engine_NR'!S129 | CW25: ='_Engine_NR'!S130 | CX25: ='_Engine_NR'!S131 | CY25: ='_Engine_NR'!S132 | CZ25: ='_Engine_NR'!S133 | DA25: ='_Engine_NR'!S134 | DB25: ='_Engine_NR'!S135 | DC25: ='_Engine_NR'!S136 | DD25: ='_Engine_NR'!S137 | DE25: ='_Engine_NR'!S138 | DF25: ='_Engine_NR'!S139 | DG25: ='_Engine_NR'!S140 | DH25: ='_Engine_NR'!S141 | DI25: ='_Engine_NR'!S142 | DJ25: ='_Engine_NR'!S143 | DK25: ='_Engine_NR'!S144 | DL25: ='_Engine_NR'!S145 | DM25: ='_Engine_NR'!S146 | DN25: ='_Engine_NR'!S147 | DO25: ='_Engine_NR'!S148 | DP25: ='_Engine_NR'!S149 | DQ25: ='_Engine_NR'!S150 | DR25: ='_Engine_NR'!S151 | DS25: ='_Engine_NR'!S152 | DT25: ='_Engine_NR'!S153 | DU25: ='_Engine_NR'!S154 | DV25: ='_Engine_NR'!S155 | DW25: ='_Engine_NR'!S156 | DX25: ='_Engine_NR'!S157 | DY25: ='_Engine_NR'!S158 | DZ25: ='_Engine_NR'!S159 | EA25: ='_Engine_NR'!S160 | EB25: ='_Engine_NR'!S161 | EC25: ='_Engine_NR'!S162 | ED25: ='_Engine_NR'!S163 | EE25: ='_Engine_NR'!S164 | EF25: ='_Engine_NR'!S165 | EG25: ='_Engine_NR'!S166 | EH25: ='_Engine_NR'!S167 | EI25: ='_Engine_NR'!S168 | EJ25: ='_Engine_NR'!S169 | EK25: ='_Engine_NR'!S170 | EL25: ='_Engine_NR'!S171 | EM25: ='_Engine_NR'!S172 | EN25: ='_Engine_NR'!S173 | EO25: ='_Engine_NR'!S174 | EP25: ='_Engine_NR'!S175 | EQ25: ='_Engine_NR'!S176 | ER25: ='_Engine_NR'!S177 | ES25: ='_Engine_NR'!S178 | ET25: ='_Engine_NR'!S179 | EU25: ='_Engine_NR'!S180 | EV25: ='_Engine_NR'!S181 | EW25: ='_Engine_NR'!S182 | EX25: ='_Engine_NR'!S183 | EY25: ='_Engine_NR'!S184 | EZ25: ='_Engine_NR'!S185 | FA25: ='_Engine_NR'!S186 | FB25: ='_Engine_NR'!S187 | FC25: ='_Engine_NR'!S188 | FD25: ='_Engine_NR'!S189 | FE25: ='_Engine_NR'!S190 | FF25: ='_Engine_NR'!S191 | FG25: ='_Engine_NR'!S192 | FH25: ='_Engine_NR'!S193 | FI25: ='_Engine_NR'!S194 | FJ25: ='_Engine_NR'!S195 | FK25: ='_Engine_NR'!S196 | FL25: ='_Engine_NR'!S197 | FM25: ='_Engine_NR'!S198 | FN25: ='_Engine_NR'!S199 | FO25: ='_Engine_NR'!S200 | FP25: ='_Engine_NR'!S201 | FQ25: ='_Engine_NR'!S202 | FR25: ='_Engine_NR'!S203 | FS25: ='_Engine_NR'!S204 | FT25: ='_Engine_NR'!S205 | FU25: ='_Engine_NR'!S206 | FV25: ='_Engine_NR'!S207 | FW25: ='_Engine_NR'!S208 | FX25: ='_Engine_NR'!S209 | FY25: ='_Engine_NR'!S210
A26: Operating Income | B26: =B24-B25 | C26: =C24-C25 | D26: =D24-D25 | E26: =E24-E25 | F26: =F24-F25 | G26: =G24-G25 | H26: =H24-H25 | I26: =I24-I25 | ... FY26: =FY24-FY25
A28: Management Fee | B28: ='_Engine_NR'!C31 | C28: ='_Engine_NR'!C32 | D28: ='_Engine_NR'!C33 | E28: ='_Engine_NR'!C34 | F28: ='_Engine_NR'!C35 | G28: ='_Engine_NR'!C36 | H28: ='_Engine_NR'!C37 | I28: ='_Engine_NR'!C38 | J28: ='_Engine_NR'!C39 | K28: ='_Engine_NR'!C40 | L28: ='_Engine_NR'!C41 | M28: ='_Engine_NR'!C42 | N28: ='_Engine_NR'!C43 | O28: ='_Engine_NR'!C44 | P28: ='_Engine_NR'!C45 | Q28: ='_Engine_NR'!C46 | R28: ='_Engine_NR'!C47 | S28: ='_Engine_NR'!C48 | T28: ='_Engine_NR'!C49 | U28: ='_Engine_NR'!C50 | V28: ='_Engine_NR'!C51 | W28: ='_Engine_NR'!C52 | X28: ='_Engine_NR'!C53 | Y28: ='_Engine_NR'!C54 | Z28: ='_Engine_NR'!C55 | AA28: ='_Engine_NR'!C56 | AB28: ='_Engine_NR'!C57 | AC28: ='_Engine_NR'!C58 | AD28: ='_Engine_NR'!C59 | AE28: ='_Engine_NR'!C60 | AF28: ='_Engine_NR'!C61 | AG28: ='_Engine_NR'!C62 | AH28: ='_Engine_NR'!C63 | AI28: ='_Engine_NR'!C64 | AJ28: ='_Engine_NR'!C65 | AK28: ='_Engine_NR'!C66 | AL28: ='_Engine_NR'!C67 | AM28: ='_Engine_NR'!C68 | AN28: ='_Engine_NR'!C69 | AO28: ='_Engine_NR'!C70 | AP28: ='_Engine_NR'!C71 | AQ28: ='_Engine_NR'!C72 | AR28: ='_Engine_NR'!C73 | AS28: ='_Engine_NR'!C74 | AT28: ='_Engine_NR'!C75 | AU28: ='_Engine_NR'!C76 | AV28: ='_Engine_NR'!C77 | AW28: ='_Engine_NR'!C78 | AX28: ='_Engine_NR'!C79 | AY28: ='_Engine_NR'!C80 | AZ28: ='_Engine_NR'!C81 | BA28: ='_Engine_NR'!C82 | BB28: ='_Engine_NR'!C83 | BC28: ='_Engine_NR'!C84 | BD28: ='_Engine_NR'!C85 | BE28: ='_Engine_NR'!C86 | BF28: ='_Engine_NR'!C87 | BG28: ='_Engine_NR'!C88 | BH28: ='_Engine_NR'!C89 | BI28: ='_Engine_NR'!C90 | BJ28: ='_Engine_NR'!C91 | BK28: ='_Engine_NR'!C92 | BL28: ='_Engine_NR'!C93 | BM28: ='_Engine_NR'!C94 | BN28: ='_Engine_NR'!C95 | BO28: ='_Engine_NR'!C96 | BP28: ='_Engine_NR'!C97 | BQ28: ='_Engine_NR'!C98 | BR28: ='_Engine_NR'!C99 | BS28: ='_Engine_NR'!C100 | BT28: ='_Engine_NR'!C101 | BU28: ='_Engine_NR'!C102 | BV28: ='_Engine_NR'!C103 | BW28: ='_Engine_NR'!C104 | BX28: ='_Engine_NR'!C105 | BY28: ='_Engine_NR'!C106 | BZ28: ='_Engine_NR'!C107 | CA28: ='_Engine_NR'!C108 | CB28: ='_Engine_NR'!C109 | CC28: ='_Engine_NR'!C110 | CD28: ='_Engine_NR'!C111 | CE28: ='_Engine_NR'!C112 | CF28: ='_Engine_NR'!C113 | CG28: ='_Engine_NR'!C114 | CH28: ='_Engine_NR'!C115 | CI28: ='_Engine_NR'!C116 | CJ28: ='_Engine_NR'!C117 | CK28: ='_Engine_NR'!C118 | CL28: ='_Engine_NR'!C119 | CM28: ='_Engine_NR'!C120 | CN28: ='_Engine_NR'!C121 | CO28: ='_Engine_NR'!C122 | CP28: ='_Engine_NR'!C123 | CQ28: ='_Engine_NR'!C124 | CR28: ='_Engine_NR'!C125 | CS28: ='_Engine_NR'!C126 | CT28: ='_Engine_NR'!C127 | CU28: ='_Engine_NR'!C128 | CV28: ='_Engine_NR'!C129 | CW28: ='_Engine_NR'!C130 | CX28: ='_Engine_NR'!C131 | CY28: ='_Engine_NR'!C132 | CZ28: ='_Engine_NR'!C133 | DA28: ='_Engine_NR'!C134 | DB28: ='_Engine_NR'!C135 | DC28: ='_Engine_NR'!C136 | DD28: ='_Engine_NR'!C137 | DE28: ='_Engine_NR'!C138 | DF28: ='_Engine_NR'!C139 | DG28: ='_Engine_NR'!C140 | DH28: ='_Engine_NR'!C141 | DI28: ='_Engine_NR'!C142 | DJ28: ='_Engine_NR'!C143 | DK28: ='_Engine_NR'!C144 | DL28: ='_Engine_NR'!C145 | DM28: ='_Engine_NR'!C146 | DN28: ='_Engine_NR'!C147 | DO28: ='_Engine_NR'!C148 | DP28: ='_Engine_NR'!C149 | DQ28: ='_Engine_NR'!C150 | DR28: ='_Engine_NR'!C151 | DS28: ='_Engine_NR'!C152 | DT28: ='_Engine_NR'!C153 | DU28: ='_Engine_NR'!C154 | DV28: ='_Engine_NR'!C155 | DW28: ='_Engine_NR'!C156 | DX28: ='_Engine_NR'!C157 | DY28: ='_Engine_NR'!C158 | DZ28: ='_Engine_NR'!C159 | EA28: ='_Engine_NR'!C160 | EB28: ='_Engine_NR'!C161 | EC28: ='_Engine_NR'!C162 | ED28: ='_Engine_NR'!C163 | EE28: ='_Engine_NR'!C164 | EF28: ='_Engine_NR'!C165 | EG28: ='_Engine_NR'!C166 | EH28: ='_Engine_NR'!C167 | EI28: ='_Engine_NR'!C168 | EJ28: ='_Engine_NR'!C169 | EK28: ='_Engine_NR'!C170 | EL28: ='_Engine_NR'!C171 | EM28: ='_Engine_NR'!C172 | EN28: ='_Engine_NR'!C173 | EO28: ='_Engine_NR'!C174 | EP28: ='_Engine_NR'!C175 | EQ28: ='_Engine_NR'!C176 | ER28: ='_Engine_NR'!C177 | ES28: ='_Engine_NR'!C178 | ET28: ='_Engine_NR'!C179 | EU28: ='_Engine_NR'!C180 | EV28: ='_Engine_NR'!C181 | EW28: ='_Engine_NR'!C182 | EX28: ='_Engine_NR'!C183 | EY28: ='_Engine_NR'!C184 | EZ28: ='_Engine_NR'!C185 | FA28: ='_Engine_NR'!C186 | FB28: ='_Engine_NR'!C187 | FC28: ='_Engine_NR'!C188 | FD28: ='_Engine_NR'!C189 | FE28: ='_Engine_NR'!C190 | FF28: ='_Engine_NR'!C191 | FG28: ='_Engine_NR'!C192 | FH28: ='_Engine_NR'!C193 | FI28: ='_Engine_NR'!C194 | FJ28: ='_Engine_NR'!C195 | FK28: ='_Engine_NR'!C196 | FL28: ='_Engine_NR'!C197 | FM28: ='_Engine_NR'!C198 | FN28: ='_Engine_NR'!C199 | FO28: ='_Engine_NR'!C200 | FP28: ='_Engine_NR'!C201 | FQ28: ='_Engine_NR'!C202 | FR28: ='_Engine_NR'!C203 | FS28: ='_Engine_NR'!C204 | FT28: ='_Engine_NR'!C205 | FU28: ='_Engine_NR'!C206 | FV28: ='_Engine_NR'!C207 | FW28: ='_Engine_NR'!C208 | FX28: ='_Engine_NR'!C209 | FY28: ='_Engine_NR'!C210
A29: Distributable Cash | B29: ='_Engine_NR'!V31 | C29: ='_Engine_NR'!V32 | D29: ='_Engine_NR'!V33 | E29: ='_Engine_NR'!V34 | F29: ='_Engine_NR'!V35 | G29: ='_Engine_NR'!V36 | H29: ='_Engine_NR'!V37 | I29: ='_Engine_NR'!V38 | J29: ='_Engine_NR'!V39 | K29: ='_Engine_NR'!V40 | L29: ='_Engine_NR'!V41 | M29: ='_Engine_NR'!V42 | N29: ='_Engine_NR'!V43 | O29: ='_Engine_NR'!V44 | P29: ='_Engine_NR'!V45 | Q29: ='_Engine_NR'!V46 | R29: ='_Engine_NR'!V47 | S29: ='_Engine_NR'!V48 | T29: ='_Engine_NR'!V49 | U29: ='_Engine_NR'!V50 | V29: ='_Engine_NR'!V51 | W29: ='_Engine_NR'!V52 | X29: ='_Engine_NR'!V53 | Y29: ='_Engine_NR'!V54 | Z29: ='_Engine_NR'!V55 | AA29: ='_Engine_NR'!V56 | AB29: ='_Engine_NR'!V57 | AC29: ='_Engine_NR'!V58 | AD29: ='_Engine_NR'!V59 | AE29: ='_Engine_NR'!V60 | AF29: ='_Engine_NR'!V61 | AG29: ='_Engine_NR'!V62 | AH29: ='_Engine_NR'!V63 | AI29: ='_Engine_NR'!V64 | AJ29: ='_Engine_NR'!V65 | AK29: ='_Engine_NR'!V66 | AL29: ='_Engine_NR'!V67 | AM29: ='_Engine_NR'!V68 | AN29: ='_Engine_NR'!V69 | AO29: ='_Engine_NR'!V70 | AP29: ='_Engine_NR'!V71 | AQ29: ='_Engine_NR'!V72 | AR29: ='_Engine_NR'!V73 | AS29: ='_Engine_NR'!V74 | AT29: ='_Engine_NR'!V75 | AU29: ='_Engine_NR'!V76 | AV29: ='_Engine_NR'!V77 | AW29: ='_Engine_NR'!V78 | AX29: ='_Engine_NR'!V79 | AY29: ='_Engine_NR'!V80 | AZ29: ='_Engine_NR'!V81 | BA29: ='_Engine_NR'!V82 | BB29: ='_Engine_NR'!V83 | BC29: ='_Engine_NR'!V84 | BD29: ='_Engine_NR'!V85 | BE29: ='_Engine_NR'!V86 | BF29: ='_Engine_NR'!V87 | BG29: ='_Engine_NR'!V88 | BH29: ='_Engine_NR'!V89 | BI29: ='_Engine_NR'!V90 | BJ29: ='_Engine_NR'!V91 | BK29: ='_Engine_NR'!V92 | BL29: ='_Engine_NR'!V93 | BM29: ='_Engine_NR'!V94 | BN29: ='_Engine_NR'!V95 | BO29: ='_Engine_NR'!V96 | BP29: ='_Engine_NR'!V97 | BQ29: ='_Engine_NR'!V98 | BR29: ='_Engine_NR'!V99 | BS29: ='_Engine_NR'!V100 | BT29: ='_Engine_NR'!V101 | BU29: ='_Engine_NR'!V102 | BV29: ='_Engine_NR'!V103 | BW29: ='_Engine_NR'!V104 | BX29: ='_Engine_NR'!V105 | BY29: ='_Engine_NR'!V106 | BZ29: ='_Engine_NR'!V107 | CA29: ='_Engine_NR'!V108 | CB29: ='_Engine_NR'!V109 | CC29: ='_Engine_NR'!V110 | CD29: ='_Engine_NR'!V111 | CE29: ='_Engine_NR'!V112 | CF29: ='_Engine_NR'!V113 | CG29: ='_Engine_NR'!V114 | CH29: ='_Engine_NR'!V115 | CI29: ='_Engine_NR'!V116 | CJ29: ='_Engine_NR'!V117 | CK29: ='_Engine_NR'!V118 | CL29: ='_Engine_NR'!V119 | CM29: ='_Engine_NR'!V120 | CN29: ='_Engine_NR'!V121 | CO29: ='_Engine_NR'!V122 | CP29: ='_Engine_NR'!V123 | CQ29: ='_Engine_NR'!V124 | CR29: ='_Engine_NR'!V125 | CS29: ='_Engine_NR'!V126 | CT29: ='_Engine_NR'!V127 | CU29: ='_Engine_NR'!V128 | CV29: ='_Engine_NR'!V129 | CW29: ='_Engine_NR'!V130 | CX29: ='_Engine_NR'!V131 | CY29: ='_Engine_NR'!V132 | CZ29: ='_Engine_NR'!V133 | DA29: ='_Engine_NR'!V134 | DB29: ='_Engine_NR'!V135 | DC29: ='_Engine_NR'!V136 | DD29: ='_Engine_NR'!V137 | DE29: ='_Engine_NR'!V138 | DF29: ='_Engine_NR'!V139 | DG29: ='_Engine_NR'!V140 | DH29: ='_Engine_NR'!V141 | DI29: ='_Engine_NR'!V142 | DJ29: ='_Engine_NR'!V143 | DK29: ='_Engine_NR'!V144 | DL29: ='_Engine_NR'!V145 | DM29: ='_Engine_NR'!V146 | DN29: ='_Engine_NR'!V147 | DO29: ='_Engine_NR'!V148 | DP29: ='_Engine_NR'!V149 | DQ29: ='_Engine_NR'!V150 | DR29: ='_Engine_NR'!V151 | DS29: ='_Engine_NR'!V152 | DT29: ='_Engine_NR'!V153 | DU29: ='_Engine_NR'!V154 | DV29: ='_Engine_NR'!V155 | DW29: ='_Engine_NR'!V156 | DX29: ='_Engine_NR'!V157 | DY29: ='_Engine_NR'!V158 | DZ29: ='_Engine_NR'!V159 | EA29: ='_Engine_NR'!V160 | EB29: ='_Engine_NR'!V161 | EC29: ='_Engine_NR'!V162 | ED29: ='_Engine_NR'!V163 | EE29: ='_Engine_NR'!V164 | EF29: ='_Engine_NR'!V165 | EG29: ='_Engine_NR'!V166 | EH29: ='_Engine_NR'!V167 | EI29: ='_Engine_NR'!V168 | EJ29: ='_Engine_NR'!V169 | EK29: ='_Engine_NR'!V170 | EL29: ='_Engine_NR'!V171 | EM29: ='_Engine_NR'!V172 | EN29: ='_Engine_NR'!V173 | EO29: ='_Engine_NR'!V174 | EP29: ='_Engine_NR'!V175 | EQ29: ='_Engine_NR'!V176 | ER29: ='_Engine_NR'!V177 | ES29: ='_Engine_NR'!V178 | ET29: ='_Engine_NR'!V179 | EU29: ='_Engine_NR'!V180 | EV29: ='_Engine_NR'!V181 | EW29: ='_Engine_NR'!V182 | EX29: ='_Engine_NR'!V183 | EY29: ='_Engine_NR'!V184 | EZ29: ='_Engine_NR'!V185 | FA29: ='_Engine_NR'!V186 | FB29: ='_Engine_NR'!V187 | FC29: ='_Engine_NR'!V188 | FD29: ='_Engine_NR'!V189 | FE29: ='_Engine_NR'!V190 | FF29: ='_Engine_NR'!V191 | FG29: ='_Engine_NR'!V192 | FH29: ='_Engine_NR'!V193 | FI29: ='_Engine_NR'!V194 | FJ29: ='_Engine_NR'!V195 | FK29: ='_Engine_NR'!V196 | FL29: ='_Engine_NR'!V197 | FM29: ='_Engine_NR'!V198 | FN29: ='_Engine_NR'!V199 | FO29: ='_Engine_NR'!V200 | FP29: ='_Engine_NR'!V201 | FQ29: ='_Engine_NR'!V202 | FR29: ='_Engine_NR'!V203 | FS29: ='_Engine_NR'!V204 | FT29: ='_Engine_NR'!V205 | FU29: ='_Engine_NR'!V206 | FV29: ='_Engine_NR'!V207 | FW29: ='_Engine_NR'!V208 | FX29: ='_Engine_NR'!V209 | FY29: ='_Engine_NR'!V210
A30: Cumulative Distributable | B30: -0.3312 | C30: -0.6625 | D30: -0.9937 | E30: -3.0594 | F30: -3.4287 | G30: -3.5847 | H30: -5.7932 | I30: -5.5099 | J30: -4.8036 | K30: -5.4768 | L30: -3.9041 | M30: -3.3637 | N30: -0.6805 | O30: 2.5291 | P30: 6.2503 | Q30: 8.9828 | R30: 13.6571 | S30: 18.7939 | T30: 24.2288 | U30: 29.9003 | V30: 35.8009 | W30: 41.9232 | X30: 48.0546 | Y30: 54.1935 | Z30: 60.2886 | AA30: 66.3397 | AB30: 72.3466 | AC30: 78.3094 | AD30: 84.1792 | AE30: 89.9571 | AF30: 95.6445 | AG30: 101.2425 | AH30: 106.7524 | AI30: 112.1753 | AJ30: 117.5124 | AK30: 117.749 | AL30: 122.918 | AM30: 128.0046 | AN30: 133.0099 | AO30: 137.9351 | AP30: 142.7812 | AQ30: 147.5492 | AR30: 152.2403 | AS30: 156.8554 | AT30: 161.3956 | AU30: 165.8619 | AV30: 170.2552 | AW30: 171.7711 | AX30: 176.0215 | AY30: 180.2019 | AZ30: 184.3133 | BA30: 188.3565 | BB30: 192.3324 | BC30: 196.2421 | BD30: 200.0863 | BE30: 203.8659 | BF30: 207.5819 | BG30: 211.235 | BH30: 214.8262 | BI30: 217.6899 | BJ30: 221.1595 | BK30: 224.5697 | BL30: 227.9211 | BM30: 231.2146 | BN30: 234.451 | BO30: 237.631 | BP30: 240.7554 | BQ30: 243.8249 | BR30: 246.8402 | BS30: 249.8022 | BT30: 252.7115 | BU30: 255.5688 | BV30: 258.3748 | BW30: 261.1302 | BX30: 263.8357 | BY30: 266.492 | BZ30: 269.0997 | CA30: 271.6595 | CB30: 274.172 | CC30: 276.6379 | CD30: 279.0577 | CE30: 281.4322 | CF30: 283.7619 | CG30: 286.0474 | CH30: 288.2893 | CI30: 290.4882 | CJ30: 292.6447 | CK30: 294.7593 | CL30: 296.8327 | CM30: 298.8653 | CN30: 300.8577 | CO30: 302.8105 | CP30: 304.7242 | CQ30: 306.5993 | CR30: 308.4363 | CS30: 310.2358 | CT30: 311.9982 | CU30: 313.7241 | CV30: 315.4139 | CW30: 317.0681 | CX30: 318.6873 | CY30: 320.2718 | CZ30: 321.8221 | DA30: 323.3388 | DB30: 324.8222 | DC30: 326.2729 | DD30: 327.6911 | DE30: 329.0775 | DF30: 330.4323 | DG30: 331.7561 | DH30: 333.0492 | DI30: 334.3121 | DJ30: 335.5452 | DK30: 336.7489 | DL30: 337.9235 | DM30: 339.0694 | DN30: 340.1871 | DO30: 341.277 | DP30: 342.3393 | DQ30: 343.3745 | DR30: 344.3829 | DS30: 345.3649 | DT30: 346.3209 | DU30: 347.2511 | DV30: 348.156 | DW30: 349.0359 | DX30: 349.8911 | DY30: 350.722 | DZ30: 351.5289 | EA30: 352.312 | EB30: 353.0718 | EC30: 353.8085 | ED30: 354.5224 | EE30: 355.214 | EF30: 355.8833 | EG30: 356.5308 | EH30: 357.1568 | EI30: 357.7615 | EJ30: 358.3452 | EK30: 358.9083 | EL30: 359.4509 | EM30: 359.9734 | EN30: 360.476 | EO30: 360.959 | EP30: 361.4226 | EQ30: 361.8672 | ER30: 362.293 | ES30: 362.7002 | ET30: 363.089 | EU30: 363.4598 | EV30: 363.8128 | EW30: 364.1482 | EX30: 364.4662 | EY30: 364.7671 | EZ30: 365.0511 | FA30: 365.3184 | FB30: 365.5693 | FC30: 365.804 | FD30: 366.0227 | FE30: 366.2256 | FF30: 366.413 | FG30: 366.5849 | FH30: 366.7418 | FI30: 366.8836 | FJ30: 367.0107 | FK30: 367.1233 | FL30: 367.2215 | FM30: 367.3055 | FN30: 367.3756 | FO30: 367.4319 | FP30: 367.4746 | FQ30: 367.5038 | FR30: 367.5199 | FS30: 367.5229 | FT30: 367.5129 | FU30: 367.4903 | FV30: 367.4552 | FW30: 367.4076 | FX30: 367.3479 | FY30: 367.2762

Sheet 4d. Monthly P&L (Recycle)
A1: MONTHLY P&L | 8 deals @ $24M ARR (LIVE)
A3: ($mm) | B3: M1 | C3: M2 | D3: M3 | E3: M4 | F3: M5 | G3: M6 | H3: M7 | I3: M8 | J3: M9 | K3: M10 | L3: M11 | M3: M12 | N3: M13 | O3: M14 | P3: M15 | Q3: M16 | R3: M17 | S3: M18 | T3: M19 | U3: M20 | V3: M21 | W3: M22 | X3: M23 | Y3: M24 | Z3: M25 | AA3: M26 | AB3: M27 | AC3: M28 | AD3: M29 | AE3: M30 | AF3: M31 | AG3: M32 | AH3: M33 | AI3: M34 | AJ3: M35 | AK3: M36 | AL3: M37 | AM3: M38 | AN3: M39 | AO3: M40 | AP3: M41 | AQ3: M42 | AR3: M43 | AS3: M44 | AT3: M45 | AU3: M46 | AV3: M47 | AW3: M48 | AX3: M49 | AY3: M50 | AZ3: M51 | BA3: M52 | BB3: M53 | BC3: M54 | BD3: M55 | BE3: M56 | BF3: M57 | BG3: M58 | BH3: M59 | BI3: M60 | BJ3: M61 | BK3: M62 | BL3: M63 | BM3: M64 | BN3: M65 | BO3: M66 | BP3: M67 | BQ3: M68 | BR3: M69 | BS3: M70 | BT3: M71 | BU3: M72 | BV3: M73 | BW3: M74 | BX3: M75 | BY3: M76 | BZ3: M77 | CA3: M78 | CB3: M79 | CC3: M80 | CD3: M81 | CE3: M82 | CF3: M83 | CG3: M84 | CH3: M85 | CI3: M86 | CJ3: M87 | CK3: M88 | CL3: M89 | CM3: M90 | CN3: M91 | CO3: M92 | CP3: M93 | CQ3: M94 | CR3: M95 | CS3: M96 | CT3: M97 | CU3: M98 | CV3: M99 | CW3: M100 | CX3: M101 | CY3: M102 | CZ3: M103 | DA3: M104 | DB3: M105 | DC3: M106 | DD3: M107 | DE3: M108 | DF3: M109 | DG3: M110 | DH3: M111 | DI3: M112 | DJ3: M113 | DK3: M114 | DL3: M115 | DM3: M116 | DN3: M117 | DO3: M118 | DP3: M119 | DQ3: M120 | DR3: M121 | DS3: M122 | DT3: M123 | DU3: M124 | DV3: M125 | DW3: M126 | DX3: M127 | DY3: M128 | DZ3: M129 | EA3: M130 | EB3: M131 | EC3: M132 | ED3: M133 | EE3: M134 | EF3: M135 | EG3: M136 | EH3: M137 | EI3: M138 | EJ3: M139 | EK3: M140 | EL3: M141 | EM3: M142 | EN3: M143 | EO3: M144 | EP3: M145 | EQ3: M146 | ER3: M147 | ES3: M148 | ET3: M149 | EU3: M150 | EV3: M151 | EW3: M152 | EX3: M153 | EY3: M154 | EZ3: M155 | FA3: M156 | FB3: M157 | FC3: M158 | FD3: M159 | FE3: M160 | FF3: M161 | FG3: M162 | FH3: M163 | FI3: M164 | FJ3: M165 | FK3: M166 | FL3: M167 | FM3: M168 | FN3: M169 | FO3: M170 | FP3: M171 | FQ3: M172 | FR3: M173 | FS3: M174 | FT3: M175 | FU3: M176 | FV3: M177 | FW3: M178 | FX3: M179 | FY3: M180
A5: Revenue by Deal
A6: Deal #1 | B6: ='_Engine_R50'!F31/12 | C6: ='_Engine_R50'!F32/12 | D6: ='_Engine_R50'!F33/12 | E6: ='_Engine_R50'!F34/12 | F6: ='_Engine_R50'!F35/12 | G6: ='_Engine_R50'!F36/12 | H6: ='_Engine_R50'!F37/12 | I6: ='_Engine_R50'!F38/12 | J6: ='_Engine_R50'!F39/12 | K6: ='_Engine_R50'!F40/12 | L6: ='_Engine_R50'!F41/12 | M6: ='_Engine_R50'!F42/12 | N6: ='_Engine_R50'!F43/12 | O6: ='_Engine_R50'!F44/12 | P6: ='_Engine_R50'!F45/12 | Q6: ='_Engine_R50'!F46/12 | R6: ='_Engine_R50'!F47/12 | S6: ='_Engine_R50'!F48/12 | T6: ='_Engine_R50'!F49/12 | U6: ='_Engine_R50'!F50/12 | V6: ='_Engine_R50'!F51/12 | W6: ='_Engine_R50'!F52/12 | X6: ='_Engine_R50'!F53/12 | Y6: ='_Engine_R50'!F54/12 | Z6: ='_Engine_R50'!F55/12 | AA6: ='_Engine_R50'!F56/12 | AB6: ='_Engine_R50'!F57/12 | AC6: ='_Engine_R50'!F58/12 | AD6: ='_Engine_R50'!F59/12 | AE6: ='_Engine_R50'!F60/12 | AF6: ='_Engine_R50'!F61/12 | AG6: ='_Engine_R50'!F62/12 | AH6: ='_Engine_R50'!F63/12 | AI6: ='_Engine_R50'!F64/12 | AJ6: ='_Engine_R50'!F65/12 | AK6: ='_Engine_R50'!F66/12 | AL6: ='_Engine_R50'!F67/12 | AM6: ='_Engine_R50'!F68/12 | AN6: ='_Engine_R50'!F69/12 | AO6: ='_Engine_R50'!F70/12 | AP6: ='_Engine_R50'!F71/12 | AQ6: ='_Engine_R50'!F72/12 | AR6: ='_Engine_R50'!F73/12 | AS6: ='_Engine_R50'!F74/12 | AT6: ='_Engine_R50'!F75/12 | AU6: ='_Engine_R50'!F76/12 | AV6: ='_Engine_R50'!F77/12 | AW6: ='_Engine_R50'!F78/12 | AX6: ='_Engine_R50'!F79/12 | AY6: ='_Engine_R50'!F80/12 | AZ6: ='_Engine_R50'!F81/12 | BA6: ='_Engine_R50'!F82/12 | BB6: ='_Engine_R50'!F83/12 | BC6: ='_Engine_R50'!F84/12 | BD6: ='_Engine_R50'!F85/12 | BE6: ='_Engine_R50'!F86/12 | BF6: ='_Engine_R50'!F87/12 | BG6: ='_Engine_R50'!F88/12 | BH6: ='_Engine_R50'!F89/12 | BI6: ='_Engine_R50'!F90/12 | BJ6: ='_Engine_R50'!F91/12 | BK6: ='_Engine_R50'!F92/12 | BL6: ='_Engine_R50'!F93/12 | BM6: ='_Engine_R50'!F94/12 | BN6: ='_Engine_R50'!F95/12 | BO6: ='_Engine_R50'!F96/12 | BP6: ='_Engine_R50'!F97/12 | BQ6: ='_Engine_R50'!F98/12 | BR6: ='_Engine_R50'!F99/12 | BS6: ='_Engine_R50'!F100/12 | BT6: ='_Engine_R50'!F101/12 | BU6: ='_Engine_R50'!F102/12 | BV6: ='_Engine_R50'!F103/12 | BW6: ='_Engine_R50'!F104/12 | BX6: ='_Engine_R50'!F105/12 | BY6: ='_Engine_R50'!F106/12 | BZ6: ='_Engine_R50'!F107/12 | CA6: ='_Engine_R50'!F108/12 | CB6: ='_Engine_R50'!F109/12 | CC6: ='_Engine_R50'!F110/12 | CD6: ='_Engine_R50'!F111/12 | CE6: ='_Engine_R50'!F112/12 | CF6: ='_Engine_R50'!F113/12 | CG6: ='_Engine_R50'!F114/12 | CH6: ='_Engine_R50'!F115/12 | CI6: ='_Engine_R50'!F116/12 | CJ6: ='_Engine_R50'!F117/12 | CK6: ='_Engine_R50'!F118/12 | CL6: ='_Engine_R50'!F119/12 | CM6: ='_Engine_R50'!F120/12 | CN6: ='_Engine_R50'!F121/12 | CO6: ='_Engine_R50'!F122/12 | CP6: ='_Engine_R50'!F123/12 | CQ6: ='_Engine_R50'!F124/12 | CR6: ='_Engine_R50'!F125/12 | CS6: ='_Engine_R50'!F126/12 | CT6: ='_Engine_R50'!F127/12 | CU6: ='_Engine_R50'!F128/12 | CV6: ='_Engine_R50'!F129/12 | CW6: ='_Engine_R50'!F130/12 | CX6: ='_Engine_R50'!F131/12 | CY6: ='_Engine_R50'!F132/12 | CZ6: ='_Engine_R50'!F133/12 | DA6: ='_Engine_R50'!F134/12 | DB6: ='_Engine_R50'!F135/12 | DC6: ='_Engine_R50'!F136/12 | DD6: ='_Engine_R50'!F137/12 | DE6: ='_Engine_R50'!F138/12 | DF6: ='_Engine_R50'!F139/12 | DG6: ='_Engine_R50'!F140/12 | DH6: ='_Engine_R50'!F141/12 | DI6: ='_Engine_R50'!F142/12 | DJ6: ='_Engine_R50'!F143/12 | DK6: ='_Engine_R50'!F144/12 | DL6: ='_Engine_R50'!F145/12 | DM6: ='_Engine_R50'!F146/12 | DN6: ='_Engine_R50'!F147/12 | DO6: ='_Engine_R50'!F148/12 | DP6: ='_Engine_R50'!F149/12 | DQ6: ='_Engine_R50'!F150/12 | DR6: ='_Engine_R50'!F151/12 | DS6: ='_Engine_R50'!F152/12 | DT6: ='_Engine_R50'!F153/12 | DU6: ='_Engine_R50'!F154/12 | DV6: ='_Engine_R50'!F155/12 | DW6: ='_Engine_R50'!F156/12 | DX6: ='_Engine_R50'!F157/12 | DY6: ='_Engine_R50'!F158/12 | DZ6: ='_Engine_R50'!F159/12 | EA6: ='_Engine_R50'!F160/12 | EB6: ='_Engine_R50'!F161/12 | EC6: ='_Engine_R50'!F162/12 | ED6: ='_Engine_R50'!F163/12 | EE6: ='_Engine_R50'!F164/12 | EF6: ='_Engine_R50'!F165/12 | EG6: ='_Engine_R50'!F166/12 | EH6: ='_Engine_R50'!F167/12 | EI6: ='_Engine_R50'!F168/12 | EJ6: ='_Engine_R50'!F169/12 | EK6: ='_Engine_R50'!F170/12 | EL6: ='_Engine_R50'!F171/12 | EM6: ='_Engine_R50'!F172/12 | EN6: ='_Engine_R50'!F173/12 | EO6: ='_Engine_R50'!F174/12 | EP6: ='_Engine_R50'!F175/12 | EQ6: ='_Engine_R50'!F176/12 | ER6: ='_Engine_R50'!F177/12 | ES6: ='_Engine_R50'!F178/12 | ET6: ='_Engine_R50'!F179/12 | EU6: ='_Engine_R50'!F180/12 | EV6: ='_Engine_R50'!F181/12 | EW6: ='_Engine_R50'!F182/12 | EX6: ='_Engine_R50'!F183/12 | EY6: ='_Engine_R50'!F184/12 | EZ6: ='_Engine_R50'!F185/12 | FA6: ='_Engine_R50'!F186/12 | FB6: ='_Engine_R50'!F187/12 | FC6: ='_Engine_R50'!F188/12 | FD6: ='_Engine_R50'!F189/12 | FE6: ='_Engine_R50'!F190/12 | FF6: ='_Engine_R50'!F191/12 | FG6: ='_Engine_R50'!F192/12 | FH6: ='_Engine_R50'!F193/12 | FI6: ='_Engine_R50'!F194/12 | FJ6: ='_Engine_R50'!F195/12 | FK6: ='_Engine_R50'!F196/12 | FL6: ='_Engine_R50'!F197/12 | FM6: ='_Engine_R50'!F198/12 | FN6: ='_Engine_R50'!F199/12 | FO6: ='_Engine_R50'!F200/12 | FP6: ='_Engine_R50'!F201/12 | FQ6: ='_Engine_R50'!F202/12 | FR6: ='_Engine_R50'!F203/12 | FS6: ='_Engine_R50'!F204/12 | FT6: ='_Engine_R50'!F205/12 | FU6: ='_Engine_R50'!F206/12 | FV6: ='_Engine_R50'!F207/12 | FW6: ='_Engine_R50'!F208/12 | FX6: ='_Engine_R50'!F209/12 | FY6: ='_Engine_R50'!F210/12
A7: Deal #2 | B7: ='_Engine_R50'!G31/12 | C7: ='_Engine_R50'!G32/12 | D7: ='_Engine_R50'!G33/12 | E7: ='_Engine_R50'!G34/12 | F7: ='_Engine_R50'!G35/12 | G7: ='_Engine_R50'!G36/12 | H7: ='_Engine_R50'!G37/12 | I7: ='_Engine_R50'!G38/12 | J7: ='_Engine_R50'!G39/12 | K7: ='_Engine_R50'!G40/12 | L7: ='_Engine_R50'!G41/12 | M7: ='_Engine_R50'!G42/12 | N7: ='_Engine_R50'!G43/12 | O7: ='_Engine_R50'!G44/12 | P7: ='_Engine_R50'!G45/12 | Q7: ='_Engine_R50'!G46/12 | R7: ='_Engine_R50'!G47/12 | S7: ='_Engine_R50'!G48/12 | T7: ='_Engine_R50'!G49/12 | U7: ='_Engine_R50'!G50/12 | V7: ='_Engine_R50'!G51/12 | W7: ='_Engine_R50'!G52/12 | X7: ='_Engine_R50'!G53/12 | Y7: ='_Engine_R50'!G54/12 | Z7: ='_Engine_R50'!G55/12 | AA7: ='_Engine_R50'!G56/12 | AB7: ='_Engine_R50'!G57/12 | AC7: ='_Engine_R50'!G58/12 | AD7: ='_Engine_R50'!G59/12 | AE7: ='_Engine_R50'!G60/12 | AF7: ='_Engine_R50'!G61/12 | AG7: ='_Engine_R50'!G62/12 | AH7: ='_Engine_R50'!G63/12 | AI7: ='_Engine_R50'!G64/12 | AJ7: ='_Engine_R50'!G65/12 | AK7: ='_Engine_R50'!G66/12 | AL7: ='_Engine_R50'!G67/12 | AM7: ='_Engine_R50'!G68/12 | AN7: ='_Engine_R50'!G69/12 | AO7: ='_Engine_R50'!G70/12 | AP7: ='_Engine_R50'!G71/12 | AQ7: ='_Engine_R50'!G72/12 | AR7: ='_Engine_R50'!G73/12 | AS7: ='_Engine_R50'!G74/12 | AT7: ='_Engine_R50'!G75/12 | AU7: ='_Engine_R50'!G76/12 | AV7: ='_Engine_R50'!G77/12 | AW7: ='_Engine_R50'!G78/12 | AX7: ='_Engine_R50'!G79/12 | AY7: ='_Engine_R50'!G80/12 | AZ7: ='_Engine_R50'!G81/12 | BA7: ='_Engine_R50'!G82/12 | BB7: ='_Engine_R50'!G83/12 | BC7: ='_Engine_R50'!G84/12 | BD7: ='_Engine_R50'!G85/12 | BE7: ='_Engine_R50'!G86/12 | BF7: ='_Engine_R50'!G87/12 | BG7: ='_Engine_R50'!G88/12 | BH7: ='_Engine_R50'!G89/12 | BI7: ='_Engine_R50'!G90/12 | BJ7: ='_Engine_R50'!G91/12 | BK7: ='_Engine_R50'!G92/12 | BL7: ='_Engine_R50'!G93/12 | BM7: ='_Engine_R50'!G94/12 | BN7: ='_Engine_R50'!G95/12 | BO7: ='_Engine_R50'!G96/12 | BP7: ='_Engine_R50'!G97/12 | BQ7: ='_Engine_R50'!G98/12 | BR7: ='_Engine_R50'!G99/12 | BS7: ='_Engine_R50'!G100/12 | BT7: ='_Engine_R50'!G101/12 | BU7: ='_Engine_R50'!G102/12 | BV7: ='_Engine_R50'!G103/12 | BW7: ='_Engine_R50'!G104/12 | BX7: ='_Engine_R50'!G105/12 | BY7: ='_Engine_R50'!G106/12 | BZ7: ='_Engine_R50'!G107/12 | CA7: ='_Engine_R50'!G108/12 | CB7: ='_Engine_R50'!G109/12 | CC7: ='_Engine_R50'!G110/12 | CD7: ='_Engine_R50'!G111/12 | CE7: ='_Engine_R50'!G112/12 | CF7: ='_Engine_R50'!G113/12 | CG7: ='_Engine_R50'!G114/12 | CH7: ='_Engine_R50'!G115/12 | CI7: ='_Engine_R50'!G116/12 | CJ7: ='_Engine_R50'!G117/12 | CK7: ='_Engine_R50'!G118/12 | CL7: ='_Engine_R50'!G119/12 | CM7: ='_Engine_R50'!G120/12 | CN7: ='_Engine_R50'!G121/12 | CO7: ='_Engine_R50'!G122/12 | CP7: ='_Engine_R50'!G123/12 | CQ7: ='_Engine_R50'!G124/12 | CR7: ='_Engine_R50'!G125/12 | CS7: ='_Engine_R50'!G126/12 | CT7: ='_Engine_R50'!G127/12 | CU7: ='_Engine_R50'!G128/12 | CV7: ='_Engine_R50'!G129/12 | CW7: ='_Engine_R50'!G130/12 | CX7: ='_Engine_R50'!G131/12 | CY7: ='_Engine_R50'!G132/12 | CZ7: ='_Engine_R50'!G133/12 | DA7: ='_Engine_R50'!G134/12 | DB7: ='_Engine_R50'!G135/12 | DC7: ='_Engine_R50'!G136/12 | DD7: ='_Engine_R50'!G137/12 | DE7: ='_Engine_R50'!G138/12 | DF7: ='_Engine_R50'!G139/12 | DG7: ='_Engine_R50'!G140/12 | DH7: ='_Engine_R50'!G141/12 | DI7: ='_Engine_R50'!G142/12 | DJ7: ='_Engine_R50'!G143/12 | DK7: ='_Engine_R50'!G144/12 | DL7: ='_Engine_R50'!G145/12 | DM7: ='_Engine_R50'!G146/12 | DN7: ='_Engine_R50'!G147/12 | DO7: ='_Engine_R50'!G148/12 | DP7: ='_Engine_R50'!G149/12 | DQ7: ='_Engine_R50'!G150/12 | DR7: ='_Engine_R50'!G151/12 | DS7: ='_Engine_R50'!G152/12 | DT7: ='_Engine_R50'!G153/12 | DU7: ='_Engine_R50'!G154/12 | DV7: ='_Engine_R50'!G155/12 | DW7: ='_Engine_R50'!G156/12 | DX7: ='_Engine_R50'!G157/12 | DY7: ='_Engine_R50'!G158/12 | DZ7: ='_Engine_R50'!G159/12 | EA7: ='_Engine_R50'!G160/12 | EB7: ='_Engine_R50'!G161/12 | EC7: ='_Engine_R50'!G162/12 | ED7: ='_Engine_R50'!G163/12 | EE7: ='_Engine_R50'!G164/12 | EF7: ='_Engine_R50'!G165/12 | EG7: ='_Engine_R50'!G166/12 | EH7: ='_Engine_R50'!G167/12 | EI7: ='_Engine_R50'!G168/12 | EJ7: ='_Engine_R50'!G169/12 | EK7: ='_Engine_R50'!G170/12 | EL7: ='_Engine_R50'!G171/12 | EM7: ='_Engine_R50'!G172/12 | EN7: ='_Engine_R50'!G173/12 | EO7: ='_Engine_R50'!G174/12 | EP7: ='_Engine_R50'!G175/12 | EQ7: ='_Engine_R50'!G176/12 | ER7: ='_Engine_R50'!G177/12 | ES7: ='_Engine_R50'!G178/12 | ET7: ='_Engine_R50'!G179/12 | EU7: ='_Engine_R50'!G180/12 | EV7: ='_Engine_R50'!G181/12 | EW7: ='_Engine_R50'!G182/12 | EX7: ='_Engine_R50'!G183/12 | EY7: ='_Engine_R50'!G184/12 | EZ7: ='_Engine_R50'!G185/12 | FA7: ='_Engine_R50'!G186/12 | FB7: ='_Engine_R50'!G187/12 | FC7: ='_Engine_R50'!G188/12 | FD7: ='_Engine_R50'!G189/12 | FE7: ='_Engine_R50'!G190/12 | FF7: ='_Engine_R50'!G191/12 | FG7: ='_Engine_R50'!G192/12 | FH7: ='_Engine_R50'!G193/12 | FI7: ='_Engine_R50'!G194/12 | FJ7: ='_Engine_R50'!G195/12 | FK7: ='_Engine_R50'!G196/12 | FL7: ='_Engine_R50'!G197/12 | FM7: ='_Engine_R50'!G198/12 | FN7: ='_Engine_R50'!G199/12 | FO7: ='_Engine_R50'!G200/12 | FP7: ='_Engine_R50'!G201/12 | FQ7: ='_Engine_R50'!G202/12 | FR7: ='_Engine_R50'!G203/12 | FS7: ='_Engine_R50'!G204/12 | FT7: ='_Engine_R50'!G205/12 | FU7: ='_Engine_R50'!G206/12 | FV7: ='_Engine_R50'!G207/12 | FW7: ='_Engine_R50'!G208/12 | FX7: ='_Engine_R50'!G209/12 | FY7: ='_Engine_R50'!G210/12
A8: Deal #3 | B8: ='_Engine_R50'!H31/12 | C8: ='_Engine_R50'!H32/12 | D8: ='_Engine_R50'!H33/12 | E8: ='_Engine_R50'!H34/12 | F8: ='_Engine_R50'!H35/12 | G8: ='_Engine_R50'!H36/12 | H8: ='_Engine_R50'!H37/12 | I8: ='_Engine_R50'!H38/12 | J8: ='_Engine_R50'!H39/12 | K8: ='_Engine_R50'!H40/12 | L8: ='_Engine_R50'!H41/12 | M8: ='_Engine_R50'!H42/12 | N8: ='_Engine_R50'!H43/12 | O8: ='_Engine_R50'!H44/12 | P8: ='_Engine_R50'!H45/12 | Q8: ='_Engine_R50'!H46/12 | R8: ='_Engine_R50'!H47/12 | S8: ='_Engine_R50'!H48/12 | T8: ='_Engine_R50'!H49/12 | U8: ='_Engine_R50'!H50/12 | V8: ='_Engine_R50'!H51/12 | W8: ='_Engine_R50'!H52/12 | X8: ='_Engine_R50'!H53/12 | Y8: ='_Engine_R50'!H54/12 | Z8: ='_Engine_R50'!H55/12 | AA8: ='_Engine_R50'!H56/12 | AB8: ='_Engine_R50'!H57/12 | AC8: ='_Engine_R50'!H58/12 | AD8: ='_Engine_R50'!H59/12 | AE8: ='_Engine_R50'!H60/12 | AF8: ='_Engine_R50'!H61/12 | AG8: ='_Engine_R50'!H62/12 | AH8: ='_Engine_R50'!H63/12 | AI8: ='_Engine_R50'!H64/12 | AJ8: ='_Engine_R50'!H65/12 | AK8: ='_Engine_R50'!H66/12 | AL8: ='_Engine_R50'!H67/12 | AM8: ='_Engine_R50'!H68/12 | AN8: ='_Engine_R50'!H69/12 | AO8: ='_Engine_R50'!H70/12 | AP8: ='_Engine_R50'!H71/12 | AQ8: ='_Engine_R50'!H72/12 | AR8: ='_Engine_R50'!H73/12 | AS8: ='_Engine_R50'!H74/12 | AT8: ='_Engine_R50'!H75/12 | AU8: ='_Engine_R50'!H76/12 | AV8: ='_Engine_R50'!H77/12 | AW8: ='_Engine_R50'!H78/12 | AX8: ='_Engine_R50'!H79/12 | AY8: ='_Engine_R50'!H80/12 | AZ8: ='_Engine_R50'!H81/12 | BA8: ='_Engine_R50'!H82/12 | BB8: ='_Engine_R50'!H83/12 | BC8: ='_Engine_R50'!H84/12 | BD8: ='_Engine_R50'!H85/12 | BE8: ='_Engine_R50'!H86/12 | BF8: ='_Engine_R50'!H87/12 | BG8: ='_Engine_R50'!H88/12 | BH8: ='_Engine_R50'!H89/12 | BI8: ='_Engine_R50'!H90/12 | BJ8: ='_Engine_R50'!H91/12 | BK8: ='_Engine_R50'!H92/12 | BL8: ='_Engine_R50'!H93/12 | BM8: ='_Engine_R50'!H94/12 | BN8: ='_Engine_R50'!H95/12 | BO8: ='_Engine_R50'!H96/12 | BP8: ='_Engine_R50'!H97/12 | BQ8: ='_Engine_R50'!H98/12 | BR8: ='_Engine_R50'!H99/12 | BS8: ='_Engine_R50'!H100/12 | BT8: ='_Engine_R50'!H101/12 | BU8: ='_Engine_R50'!H102/12 | BV8: ='_Engine_R50'!H103/12 | BW8: ='_Engine_R50'!H104/12 | BX8: ='_Engine_R50'!H105/12 | BY8: ='_Engine_R50'!H106/12 | BZ8: ='_Engine_R50'!H107/12 | CA8: ='_Engine_R50'!H108/12 | CB8: ='_Engine_R50'!H109/12 | CC8: ='_Engine_R50'!H110/12 | CD8: ='_Engine_R50'!H111/12 | CE8: ='_Engine_R50'!H112/12 | CF8: ='_Engine_R50'!H113/12 | CG8: ='_Engine_R50'!H114/12 | CH8: ='_Engine_R50'!H115/12 | CI8: ='_Engine_R50'!H116/12 | CJ8: ='_Engine_R50'!H117/12 | CK8: ='_Engine_R50'!H118/12 | CL8: ='_Engine_R50'!H119/12 | CM8: ='_Engine_R50'!H120/12 | CN8: ='_Engine_R50'!H121/12 | CO8: ='_Engine_R50'!H122/12 | CP8: ='_Engine_R50'!H123/12 | CQ8: ='_Engine_R50'!H124/12 | CR8: ='_Engine_R50'!H125/12 | CS8: ='_Engine_R50'!H126/12 | CT8: ='_Engine_R50'!H127/12 | CU8: ='_Engine_R50'!H128/12 | CV8: ='_Engine_R50'!H129/12 | CW8: ='_Engine_R50'!H130/12 | CX8: ='_Engine_R50'!H131/12 | CY8: ='_Engine_R50'!H132/12 | CZ8: ='_Engine_R50'!H133/12 | DA8: ='_Engine_R50'!H134/12 | DB8: ='_Engine_R50'!H135/12 | DC8: ='_Engine_R50'!H136/12 | DD8: ='_Engine_R50'!H137/12 | DE8: ='_Engine_R50'!H138/12 | DF8: ='_Engine_R50'!H139/12 | DG8: ='_Engine_R50'!H140/12 | DH8: ='_Engine_R50'!H141/12 | DI8: ='_Engine_R50'!H142/12 | DJ8: ='_Engine_R50'!H143/12 | DK8: ='_Engine_R50'!H144/12 | DL8: ='_Engine_R50'!H145/12 | DM8: ='_Engine_R50'!H146/12 | DN8: ='_Engine_R50'!H147/12 | DO8: ='_Engine_R50'!H148/12 | DP8: ='_Engine_R50'!H149/12 | DQ8: ='_Engine_R50'!H150/12 | DR8: ='_Engine_R50'!H151/12 | DS8: ='_Engine_R50'!H152/12 | DT8: ='_Engine_R50'!H153/12 | DU8: ='_Engine_R50'!H154/12 | DV8: ='_Engine_R50'!H155/12 | DW8: ='_Engine_R50'!H156/12 | DX8: ='_Engine_R50'!H157/12 | DY8: ='_Engine_R50'!H158/12 | DZ8: ='_Engine_R50'!H159/12 | EA8: ='_Engine_R50'!H160/12 | EB8: ='_Engine_R50'!H161/12 | EC8: ='_Engine_R50'!H162/12 | ED8: ='_Engine_R50'!H163/12 | EE8: ='_Engine_R50'!H164/12 | EF8: ='_Engine_R50'!H165/12 | EG8: ='_Engine_R50'!H166/12 | EH8: ='_Engine_R50'!H167/12 | EI8: ='_Engine_R50'!H168/12 | EJ8: ='_Engine_R50'!H169/12 | EK8: ='_Engine_R50'!H170/12 | EL8: ='_Engine_R50'!H171/12 | EM8: ='_Engine_R50'!H172/12 | EN8: ='_Engine_R50'!H173/12 | EO8: ='_Engine_R50'!H174/12 | EP8: ='_Engine_R50'!H175/12 | EQ8: ='_Engine_R50'!H176/12 | ER8: ='_Engine_R50'!H177/12 | ES8: ='_Engine_R50'!H178/12 | ET8: ='_Engine_R50'!H179/12 | EU8: ='_Engine_R50'!H180/12 | EV8: ='_Engine_R50'!H181/12 | EW8: ='_Engine_R50'!H182/12 | EX8: ='_Engine_R50'!H183/12 | EY8: ='_Engine_R50'!H184/12 | EZ8: ='_Engine_R50'!H185/12 | FA8: ='_Engine_R50'!H186/12 | FB8: ='_Engine_R50'!H187/12 | FC8: ='_Engine_R50'!H188/12 | FD8: ='_Engine_R50'!H189/12 | FE8: ='_Engine_R50'!H190/12 | FF8: ='_Engine_R50'!H191/12 | FG8: ='_Engine_R50'!H192/12 | FH8: ='_Engine_R50'!H193/12 | FI8: ='_Engine_R50'!H194/12 | FJ8: ='_Engine_R50'!H195/12 | FK8: ='_Engine_R50'!H196/12 | FL8: ='_Engine_R50'!H197/12 | FM8: ='_Engine_R50'!H198/12 | FN8: ='_Engine_R50'!H199/12 | FO8: ='_Engine_R50'!H200/12 | FP8: ='_Engine_R50'!H201/12 | FQ8: ='_Engine_R50'!H202/12 | FR8: ='_Engine_R50'!H203/12 | FS8: ='_Engine_R50'!H204/12 | FT8: ='_Engine_R50'!H205/12 | FU8: ='_Engine_R50'!H206/12 | FV8: ='_Engine_R50'!H207/12 | FW8: ='_Engine_R50'!H208/12 | FX8: ='_Engine_R50'!H209/12 | FY8: ='_Engine_R50'!H210/12
A9: Deal #4 | B9: ='_Engine_R50'!I31/12 | C9: ='_Engine_R50'!I32/12 | D9: ='_Engine_R50'!I33/12 | E9: ='_Engine_R50'!I34/12 | F9: ='_Engine_R50'!I35/12 | G9: ='_Engine_R50'!I36/12 | H9: ='_Engine_R50'!I37/12 | I9: ='_Engine_R50'!I38/12 | J9: ='_Engine_R50'!I39/12 | K9: ='_Engine_R50'!I40/12 | L9: ='_Engine_R50'!I41/12 | M9: ='_Engine_R50'!I42/12 | N9: ='_Engine_R50'!I43/12 | O9: ='_Engine_R50'!I44/12 | P9: ='_Engine_R50'!I45/12 | Q9: ='_Engine_R50'!I46/12 | R9: ='_Engine_R50'!I47/12 | S9: ='_Engine_R50'!I48/12 | T9: ='_Engine_R50'!I49/12 | U9: ='_Engine_R50'!I50/12 | V9: ='_Engine_R50'!I51/12 | W9: ='_Engine_R50'!I52/12 | X9: ='_Engine_R50'!I53/12 | Y9: ='_Engine_R50'!I54/12 | Z9: ='_Engine_R50'!I55/12 | AA9: ='_Engine_R50'!I56/12 | AB9: ='_Engine_R50'!I57/12 | AC9: ='_Engine_R50'!I58/12 | AD9: ='_Engine_R50'!I59/12 | AE9: ='_Engine_R50'!I60/12 | AF9: ='_Engine_R50'!I61/12 | AG9: ='_Engine_R50'!I62/12 | AH9: ='_Engine_R50'!I63/12 | AI9: ='_Engine_R50'!I64/12 | AJ9: ='_Engine_R50'!I65/12 | AK9: ='_Engine_R50'!I66/12 | AL9: ='_Engine_R50'!I67/12 | AM9: ='_Engine_R50'!I68/12 | AN9: ='_Engine_R50'!I69/12 | AO9: ='_Engine_R50'!I70/12 | AP9: ='_Engine_R50'!I71/12 | AQ9: ='_Engine_R50'!I72/12 | AR9: ='_Engine_R50'!I73/12 | AS9: ='_Engine_R50'!I74/12 | AT9: ='_Engine_R50'!I75/12 | AU9: ='_Engine_R50'!I76/12 | AV9: ='_Engine_R50'!I77/12 | AW9: ='_Engine_R50'!I78/12 | AX9: ='_Engine_R50'!I79/12 | AY9: ='_Engine_R50'!I80/12 | AZ9: ='_Engine_R50'!I81/12 | BA9: ='_Engine_R50'!I82/12 | BB9: ='_Engine_R50'!I83/12 | BC9: ='_Engine_R50'!I84/12 | BD9: ='_Engine_R50'!I85/12 | BE9: ='_Engine_R50'!I86/12 | BF9: ='_Engine_R50'!I87/12 | BG9: ='_Engine_R50'!I88/12 | BH9: ='_Engine_R50'!I89/12 | BI9: ='_Engine_R50'!I90/12 | BJ9: ='_Engine_R50'!I91/12 | BK9: ='_Engine_R50'!I92/12 | BL9: ='_Engine_R50'!I93/12 | BM9: ='_Engine_R50'!I94/12 | BN9: ='_Engine_R50'!I95/12 | BO9: ='_Engine_R50'!I96/12 | BP9: ='_Engine_R50'!I97/12 | BQ9: ='_Engine_R50'!I98/12 | BR9: ='_Engine_R50'!I99/12 | BS9: ='_Engine_R50'!I100/12 | BT9: ='_Engine_R50'!I101/12 | BU9: ='_Engine_R50'!I102/12 | BV9: ='_Engine_R50'!I103/12 | BW9: ='_Engine_R50'!I104/12 | BX9: ='_Engine_R50'!I105/12 | BY9: ='_Engine_R50'!I106/12 | BZ9: ='_Engine_R50'!I107/12 | CA9: ='_Engine_R50'!I108/12 | CB9: ='_Engine_R50'!I109/12 | CC9: ='_Engine_R50'!I110/12 | CD9: ='_Engine_R50'!I111/12 | CE9: ='_Engine_R50'!I112/12 | CF9: ='_Engine_R50'!I113/12 | CG9: ='_Engine_R50'!I114/12 | CH9: ='_Engine_R50'!I115/12 | CI9: ='_Engine_R50'!I116/12 | CJ9: ='_Engine_R50'!I117/12 | CK9: ='_Engine_R50'!I118/12 | CL9: ='_Engine_R50'!I119/12 | CM9: ='_Engine_R50'!I120/12 | CN9: ='_Engine_R50'!I121/12 | CO9: ='_Engine_R50'!I122/12 | CP9: ='_Engine_R50'!I123/12 | CQ9: ='_Engine_R50'!I124/12 | CR9: ='_Engine_R50'!I125/12 | CS9: ='_Engine_R50'!I126/12 | CT9: ='_Engine_R50'!I127/12 | CU9: ='_Engine_R50'!I128/12 | CV9: ='_Engine_R50'!I129/12 | CW9: ='_Engine_R50'!I130/12 | CX9: ='_Engine_R50'!I131/12 | CY9: ='_Engine_R50'!I132/12 | CZ9: ='_Engine_R50'!I133/12 | DA9: ='_Engine_R50'!I134/12 | DB9: ='_Engine_R50'!I135/12 | DC9: ='_Engine_R50'!I136/12 | DD9: ='_Engine_R50'!I137/12 | DE9: ='_Engine_R50'!I138/12 | DF9: ='_Engine_R50'!I139/12 | DG9: ='_Engine_R50'!I140/12 | DH9: ='_Engine_R50'!I141/12 | DI9: ='_Engine_R50'!I142/12 | DJ9: ='_Engine_R50'!I143/12 | DK9: ='_Engine_R50'!I144/12 | DL9: ='_Engine_R50'!I145/12 | DM9: ='_Engine_R50'!I146/12 | DN9: ='_Engine_R50'!I147/12 | DO9: ='_Engine_R50'!I148/12 | DP9: ='_Engine_R50'!I149/12 | DQ9: ='_Engine_R50'!I150/12 | DR9: ='_Engine_R50'!I151/12 | DS9: ='_Engine_R50'!I152/12 | DT9: ='_Engine_R50'!I153/12 | DU9: ='_Engine_R50'!I154/12 | DV9: ='_Engine_R50'!I155/12 | DW9: ='_Engine_R50'!I156/12 | DX9: ='_Engine_R50'!I157/12 | DY9: ='_Engine_R50'!I158/12 | DZ9: ='_Engine_R50'!I159/12 | EA9: ='_Engine_R50'!I160/12 | EB9: ='_Engine_R50'!I161/12 | EC9: ='_Engine_R50'!I162/12 | ED9: ='_Engine_R50'!I163/12 | EE9: ='_Engine_R50'!I164/12 | EF9: ='_Engine_R50'!I165/12 | EG9: ='_Engine_R50'!I166/12 | EH9: ='_Engine_R50'!I167/12 | EI9: ='_Engine_R50'!I168/12 | EJ9: ='_Engine_R50'!I169/12 | EK9: ='_Engine_R50'!I170/12 | EL9: ='_Engine_R50'!I171/12 | EM9: ='_Engine_R50'!I172/12 | EN9: ='_Engine_R50'!I173/12 | EO9: ='_Engine_R50'!I174/12 | EP9: ='_Engine_R50'!I175/12 | EQ9: ='_Engine_R50'!I176/12 | ER9: ='_Engine_R50'!I177/12 | ES9: ='_Engine_R50'!I178/12 | ET9: ='_Engine_R50'!I179/12 | EU9: ='_Engine_R50'!I180/12 | EV9: ='_Engine_R50'!I181/12 | EW9: ='_Engine_R50'!I182/12 | EX9: ='_Engine_R50'!I183/12 | EY9: ='_Engine_R50'!I184/12 | EZ9: ='_Engine_R50'!I185/12 | FA9: ='_Engine_R50'!I186/12 | FB9: ='_Engine_R50'!I187/12 | FC9: ='_Engine_R50'!I188/12 | FD9: ='_Engine_R50'!I189/12 | FE9: ='_Engine_R50'!I190/12 | FF9: ='_Engine_R50'!I191/12 | FG9: ='_Engine_R50'!I192/12 | FH9: ='_Engine_R50'!I193/12 | FI9: ='_Engine_R50'!I194/12 | FJ9: ='_Engine_R50'!I195/12 | FK9: ='_Engine_R50'!I196/12 | FL9: ='_Engine_R50'!I197/12 | FM9: ='_Engine_R50'!I198/12 | FN9: ='_Engine_R50'!I199/12 | FO9: ='_Engine_R50'!I200/12 | FP9: ='_Engine_R50'!I201/12 | FQ9: ='_Engine_R50'!I202/12 | FR9: ='_Engine_R50'!I203/12 | FS9: ='_Engine_R50'!I204/12 | FT9: ='_Engine_R50'!I205/12 | FU9: ='_Engine_R50'!I206/12 | FV9: ='_Engine_R50'!I207/12 | FW9: ='_Engine_R50'!I208/12 | FX9: ='_Engine_R50'!I209/12 | FY9: ='_Engine_R50'!I210/12
A10: Deal #5 | B10: ='_Engine_R50'!J31/12 | C10: ='_Engine_R50'!J32/12 | D10: ='_Engine_R50'!J33/12 | E10: ='_Engine_R50'!J34/12 | F10: ='_Engine_R50'!J35/12 | G10: ='_Engine_R50'!J36/12 | H10: ='_Engine_R50'!J37/12 | I10: ='_Engine_R50'!J38/12 | J10: ='_Engine_R50'!J39/12 | K10: ='_Engine_R50'!J40/12 | L10: ='_Engine_R50'!J41/12 | M10: ='_Engine_R50'!J42/12 | N10: ='_Engine_R50'!J43/12 | O10: ='_Engine_R50'!J44/12 | P10: ='_Engine_R50'!J45/12 | Q10: ='_Engine_R50'!J46/12 | R10: ='_Engine_R50'!J47/12 | S10: ='_Engine_R50'!J48/12 | T10: ='_Engine_R50'!J49/12 | U10: ='_Engine_R50'!J50/12 | V10: ='_Engine_R50'!J51/12 | W10: ='_Engine_R50'!J52/12 | X10: ='_Engine_R50'!J53/12 | Y10: ='_Engine_R50'!J54/12 | Z10: ='_Engine_R50'!J55/12 | AA10: ='_Engine_R50'!J56/12 | AB10: ='_Engine_R50'!J57/12 | AC10: ='_Engine_R50'!J58/12 | AD10: ='_Engine_R50'!J59/12 | AE10: ='_Engine_R50'!J60/12 | AF10: ='_Engine_R50'!J61/12 | AG10: ='_Engine_R50'!J62/12 | AH10: ='_Engine_R50'!J63/12 | AI10: ='_Engine_R50'!J64/12 | AJ10: ='_Engine_R50'!J65/12 | AK10: ='_Engine_R50'!J66/12 | AL10: ='_Engine_R50'!J67/12 | AM10: ='_Engine_R50'!J68/12 | AN10: ='_Engine_R50'!J69/12 | AO10: ='_Engine_R50'!J70/12 | AP10: ='_Engine_R50'!J71/12 | AQ10: ='_Engine_R50'!J72/12 | AR10: ='_Engine_R50'!J73/12 | AS10: ='_Engine_R50'!J74/12 | AT10: ='_Engine_R50'!J75/12 | AU10: ='_Engine_R50'!J76/12 | AV10: ='_Engine_R50'!J77/12 | AW10: ='_Engine_R50'!J78/12 | AX10: ='_Engine_R50'!J79/12 | AY10: ='_Engine_R50'!J80/12 | AZ10: ='_Engine_R50'!J81/12 | BA10: ='_Engine_R50'!J82/12 | BB10: ='_Engine_R50'!J83/12 | BC10: ='_Engine_R50'!J84/12 | BD10: ='_Engine_R50'!J85/12 | BE10: ='_Engine_R50'!J86/12 | BF10: ='_Engine_R50'!J87/12 | BG10: ='_Engine_R50'!J88/12 | BH10: ='_Engine_R50'!J89/12 | BI10: ='_Engine_R50'!J90/12 | BJ10: ='_Engine_R50'!J91/12 | BK10: ='_Engine_R50'!J92/12 | BL10: ='_Engine_R50'!J93/12 | BM10: ='_Engine_R50'!J94/12 | BN10: ='_Engine_R50'!J95/12 | BO10: ='_Engine_R50'!J96/12 | BP10: ='_Engine_R50'!J97/12 | BQ10: ='_Engine_R50'!J98/12 | BR10: ='_Engine_R50'!J99/12 | BS10: ='_Engine_R50'!J100/12 | BT10: ='_Engine_R50'!J101/12 | BU10: ='_Engine_R50'!J102/12 | BV10: ='_Engine_R50'!J103/12 | BW10: ='_Engine_R50'!J104/12 | BX10: ='_Engine_R50'!J105/12 | BY10: ='_Engine_R50'!J106/12 | BZ10: ='_Engine_R50'!J107/12 | CA10: ='_Engine_R50'!J108/12 | CB10: ='_Engine_R50'!J109/12 | CC10: ='_Engine_R50'!J110/12 | CD10: ='_Engine_R50'!J111/12 | CE10: ='_Engine_R50'!J112/12 | CF10: ='_Engine_R50'!J113/12 | CG10: ='_Engine_R50'!J114/12 | CH10: ='_Engine_R50'!J115/12 | CI10: ='_Engine_R50'!J116/12 | CJ10: ='_Engine_R50'!J117/12 | CK10: ='_Engine_R50'!J118/12 | CL10: ='_Engine_R50'!J119/12 | CM10: ='_Engine_R50'!J120/12 | CN10: ='_Engine_R50'!J121/12 | CO10: ='_Engine_R50'!J122/12 | CP10: ='_Engine_R50'!J123/12 | CQ10: ='_Engine_R50'!J124/12 | CR10: ='_Engine_R50'!J125/12 | CS10: ='_Engine_R50'!J126/12 | CT10: ='_Engine_R50'!J127/12 | CU10: ='_Engine_R50'!J128/12 | CV10: ='_Engine_R50'!J129/12 | CW10: ='_Engine_R50'!J130/12 | CX10: ='_Engine_R50'!J131/12 | CY10: ='_Engine_R50'!J132/12 | CZ10: ='_Engine_R50'!J133/12 | DA10: ='_Engine_R50'!J134/12 | DB10: ='_Engine_R50'!J135/12 | DC10: ='_Engine_R50'!J136/12 | DD10: ='_Engine_R50'!J137/12 | DE10: ='_Engine_R50'!J138/12 | DF10: ='_Engine_R50'!J139/12 | DG10: ='_Engine_R50'!J140/12 | DH10: ='_Engine_R50'!J141/12 | DI10: ='_Engine_R50'!J142/12 | DJ10: ='_Engine_R50'!J143/12 | DK10: ='_Engine_R50'!J144/12 | DL10: ='_Engine_R50'!J145/12 | DM10: ='_Engine_R50'!J146/12 | DN10: ='_Engine_R50'!J147/12 | DO10: ='_Engine_R50'!J148/12 | DP10: ='_Engine_R50'!J149/12 | DQ10: ='_Engine_R50'!J150/12 | DR10: ='_Engine_R50'!J151/12 | DS10: ='_Engine_R50'!J152/12 | DT10: ='_Engine_R50'!J153/12 | DU10: ='_Engine_R50'!J154/12 | DV10: ='_Engine_R50'!J155/12 | DW10: ='_Engine_R50'!J156/12 | DX10: ='_Engine_R50'!J157/12 | DY10: ='_Engine_R50'!J158/12 | DZ10: ='_Engine_R50'!J159/12 | EA10: ='_Engine_R50'!J160/12 | EB10: ='_Engine_R50'!J161/12 | EC10: ='_Engine_R50'!J162/12 | ED10: ='_Engine_R50'!J163/12 | EE10: ='_Engine_R50'!J164/12 | EF10: ='_Engine_R50'!J165/12 | EG10: ='_Engine_R50'!J166/12 | EH10: ='_Engine_R50'!J167/12 | EI10: ='_Engine_R50'!J168/12 | EJ10: ='_Engine_R50'!J169/12 | EK10: ='_Engine_R50'!J170/12 | EL10: ='_Engine_R50'!J171/12 | EM10: ='_Engine_R50'!J172/12 | EN10: ='_Engine_R50'!J173/12 | EO10: ='_Engine_R50'!J174/12 | EP10: ='_Engine_R50'!J175/12 | EQ10: ='_Engine_R50'!J176/12 | ER10: ='_Engine_R50'!J177/12 | ES10: ='_Engine_R50'!J178/12 | ET10: ='_Engine_R50'!J179/12 | EU10: ='_Engine_R50'!J180/12 | EV10: ='_Engine_R50'!J181/12 | EW10: ='_Engine_R50'!J182/12 | EX10: ='_Engine_R50'!J183/12 | EY10: ='_Engine_R50'!J184/12 | EZ10: ='_Engine_R50'!J185/12 | FA10: ='_Engine_R50'!J186/12 | FB10: ='_Engine_R50'!J187/12 | FC10: ='_Engine_R50'!J188/12 | FD10: ='_Engine_R50'!J189/12 | FE10: ='_Engine_R50'!J190/12 | FF10: ='_Engine_R50'!J191/12 | FG10: ='_Engine_R50'!J192/12 | FH10: ='_Engine_R50'!J193/12 | FI10: ='_Engine_R50'!J194/12 | FJ10: ='_Engine_R50'!J195/12 | FK10: ='_Engine_R50'!J196/12 | FL10: ='_Engine_R50'!J197/12 | FM10: ='_Engine_R50'!J198/12 | FN10: ='_Engine_R50'!J199/12 | FO10: ='_Engine_R50'!J200/12 | FP10: ='_Engine_R50'!J201/12 | FQ10: ='_Engine_R50'!J202/12 | FR10: ='_Engine_R50'!J203/12 | FS10: ='_Engine_R50'!J204/12 | FT10: ='_Engine_R50'!J205/12 | FU10: ='_Engine_R50'!J206/12 | FV10: ='_Engine_R50'!J207/12 | FW10: ='_Engine_R50'!J208/12 | FX10: ='_Engine_R50'!J209/12 | FY10: ='_Engine_R50'!J210/12
A11: Deal #6 | B11: ='_Engine_R50'!K31/12 | C11: ='_Engine_R50'!K32/12 | D11: ='_Engine_R50'!K33/12 | E11: ='_Engine_R50'!K34/12 | F11: ='_Engine_R50'!K35/12 | G11: ='_Engine_R50'!K36/12 | H11: ='_Engine_R50'!K37/12 | I11: ='_Engine_R50'!K38/12 | J11: ='_Engine_R50'!K39/12 | K11: ='_Engine_R50'!K40/12 | L11: ='_Engine_R50'!K41/12 | M11: ='_Engine_R50'!K42/12 | N11: ='_Engine_R50'!K43/12 | O11: ='_Engine_R50'!K44/12 | P11: ='_Engine_R50'!K45/12 | Q11: ='_Engine_R50'!K46/12 | R11: ='_Engine_R50'!K47/12 | S11: ='_Engine_R50'!K48/12 | T11: ='_Engine_R50'!K49/12 | U11: ='_Engine_R50'!K50/12 | V11: ='_Engine_R50'!K51/12 | W11: ='_Engine_R50'!K52/12 | X11: ='_Engine_R50'!K53/12 | Y11: ='_Engine_R50'!K54/12 | Z11: ='_Engine_R50'!K55/12 | AA11: ='_Engine_R50'!K56/12 | AB11: ='_Engine_R50'!K57/12 | AC11: ='_Engine_R50'!K58/12 | AD11: ='_Engine_R50'!K59/12 | AE11: ='_Engine_R50'!K60/12 | AF11: ='_Engine_R50'!K61/12 | AG11: ='_Engine_R50'!K62/12 | AH11: ='_Engine_R50'!K63/12 | AI11: ='_Engine_R50'!K64/12 | AJ11: ='_Engine_R50'!K65/12 | AK11: ='_Engine_R50'!K66/12 | AL11: ='_Engine_R50'!K67/12 | AM11: ='_Engine_R50'!K68/12 | AN11: ='_Engine_R50'!K69/12 | AO11: ='_Engine_R50'!K70/12 | AP11: ='_Engine_R50'!K71/12 | AQ11: ='_Engine_R50'!K72/12 | AR11: ='_Engine_R50'!K73/12 | AS11: ='_Engine_R50'!K74/12 | AT11: ='_Engine_R50'!K75/12 | AU11: ='_Engine_R50'!K76/12 | AV11: ='_Engine_R50'!K77/12 | AW11: ='_Engine_R50'!K78/12 | AX11: ='_Engine_R50'!K79/12 | AY11: ='_Engine_R50'!K80/12 | AZ11: ='_Engine_R50'!K81/12 | BA11: ='_Engine_R50'!K82/12 | BB11: ='_Engine_R50'!K83/12 | BC11: ='_Engine_R50'!K84/12 | BD11: ='_Engine_R50'!K85/12 | BE11: ='_Engine_R50'!K86/12 | BF11: ='_Engine_R50'!K87/12 | BG11: ='_Engine_R50'!K88/12 | BH11: ='_Engine_R50'!K89/12 | BI11: ='_Engine_R50'!K90/12 | BJ11: ='_Engine_R50'!K91/12 | BK11: ='_Engine_R50'!K92/12 | BL11: ='_Engine_R50'!K93/12 | BM11: ='_Engine_R50'!K94/12 | BN11: ='_Engine_R50'!K95/12 | BO11: ='_Engine_R50'!K96/12 | BP11: ='_Engine_R50'!K97/12 | BQ11: ='_Engine_R50'!K98/12 | BR11: ='_Engine_R50'!K99/12 | BS11: ='_Engine_R50'!K100/12 | BT11: ='_Engine_R50'!K101/12 | BU11: ='_Engine_R50'!K102/12 | BV11: ='_Engine_R50'!K103/12 | BW11: ='_Engine_R50'!K104/12 | BX11: ='_Engine_R50'!K105/12 | BY11: ='_Engine_R50'!K106/12 | BZ11: ='_Engine_R50'!K107/12 | CA11: ='_Engine_R50'!K108/12 | CB11: ='_Engine_R50'!K109/12 | CC11: ='_Engine_R50'!K110/12 | CD11: ='_Engine_R50'!K111/12 | CE11: ='_Engine_R50'!K112/12 | CF11: ='_Engine_R50'!K113/12 | CG11: ='_Engine_R50'!K114/12 | CH11: ='_Engine_R50'!K115/12 | CI11: ='_Engine_R50'!K116/12 | CJ11: ='_Engine_R50'!K117/12 | CK11: ='_Engine_R50'!K118/12 | CL11: ='_Engine_R50'!K119/12 | CM11: ='_Engine_R50'!K120/12 | CN11: ='_Engine_R50'!K121/12 | CO11: ='_Engine_R50'!K122/12 | CP11: ='_Engine_R50'!K123/12 | CQ11: ='_Engine_R50'!K124/12 | CR11: ='_Engine_R50'!K125/12 | CS11: ='_Engine_R50'!K126/12 | CT11: ='_Engine_R50'!K127/12 | CU11: ='_Engine_R50'!K128/12 | CV11: ='_Engine_R50'!K129/12 | CW11: ='_Engine_R50'!K130/12 | CX11: ='_Engine_R50'!K131/12 | CY11: ='_Engine_R50'!K132/12 | CZ11: ='_Engine_R50'!K133/12 | DA11: ='_Engine_R50'!K134/12 | DB11: ='_Engine_R50'!K135/12 | DC11: ='_Engine_R50'!K136/12 | DD11: ='_Engine_R50'!K137/12 | DE11: ='_Engine_R50'!K138/12 | DF11: ='_Engine_R50'!K139/12 | DG11: ='_Engine_R50'!K140/12 | DH11: ='_Engine_R50'!K141/12 | DI11: ='_Engine_R50'!K142/12 | DJ11: ='_Engine_R50'!K143/12 | DK11: ='_Engine_R50'!K144/12 | DL11: ='_Engine_R50'!K145/12 | DM11: ='_Engine_R50'!K146/12 | DN11: ='_Engine_R50'!K147/12 | DO11: ='_Engine_R50'!K148/12 | DP11: ='_Engine_R50'!K149/12 | DQ11: ='_Engine_R50'!K150/12 | DR11: ='_Engine_R50'!K151/12 | DS11: ='_Engine_R50'!K152/12 | DT11: ='_Engine_R50'!K153/12 | DU11: ='_Engine_R50'!K154/12 | DV11: ='_Engine_R50'!K155/12 | DW11: ='_Engine_R50'!K156/12 | DX11: ='_Engine_R50'!K157/12 | DY11: ='_Engine_R50'!K158/12 | DZ11: ='_Engine_R50'!K159/12 | EA11: ='_Engine_R50'!K160/12 | EB11: ='_Engine_R50'!K161/12 | EC11: ='_Engine_R50'!K162/12 | ED11: ='_Engine_R50'!K163/12 | EE11: ='_Engine_R50'!K164/12 | EF11: ='_Engine_R50'!K165/12 | EG11: ='_Engine_R50'!K166/12 | EH11: ='_Engine_R50'!K167/12 | EI11: ='_Engine_R50'!K168/12 | EJ11: ='_Engine_R50'!K169/12 | EK11: ='_Engine_R50'!K170/12 | EL11: ='_Engine_R50'!K171/12 | EM11: ='_Engine_R50'!K172/12 | EN11: ='_Engine_R50'!K173/12 | EO11: ='_Engine_R50'!K174/12 | EP11: ='_Engine_R50'!K175/12 | EQ11: ='_Engine_R50'!K176/12 | ER11: ='_Engine_R50'!K177/12 | ES11: ='_Engine_R50'!K178/12 | ET11: ='_Engine_R50'!K179/12 | EU11: ='_Engine_R50'!K180/12 | EV11: ='_Engine_R50'!K181/12 | EW11: ='_Engine_R50'!K182/12 | EX11: ='_Engine_R50'!K183/12 | EY11: ='_Engine_R50'!K184/12 | EZ11: ='_Engine_R50'!K185/12 | FA11: ='_Engine_R50'!K186/12 | FB11: ='_Engine_R50'!K187/12 | FC11: ='_Engine_R50'!K188/12 | FD11: ='_Engine_R50'!K189/12 | FE11: ='_Engine_R50'!K190/12 | FF11: ='_Engine_R50'!K191/12 | FG11: ='_Engine_R50'!K192/12 | FH11: ='_Engine_R50'!K193/12 | FI11: ='_Engine_R50'!K194/12 | FJ11: ='_Engine_R50'!K195/12 | FK11: ='_Engine_R50'!K196/12 | FL11: ='_Engine_R50'!K197/12 | FM11: ='_Engine_R50'!K198/12 | FN11: ='_Engine_R50'!K199/12 | FO11: ='_Engine_R50'!K200/12 | FP11: ='_Engine_R50'!K201/12 | FQ11: ='_Engine_R50'!K202/12 | FR11: ='_Engine_R50'!K203/12 | FS11: ='_Engine_R50'!K204/12 | FT11: ='_Engine_R50'!K205/12 | FU11: ='_Engine_R50'!K206/12 | FV11: ='_Engine_R50'!K207/12 | FW11: ='_Engine_R50'!K208/12 | FX11: ='_Engine_R50'!K209/12 | FY11: ='_Engine_R50'!K210/12
A12: Deal #7 | B12: ='_Engine_R50'!L31/12 | C12: ='_Engine_R50'!L32/12 | D12: ='_Engine_R50'!L33/12 | E12: ='_Engine_R50'!L34/12 | F12: ='_Engine_R50'!L35/12 | G12: ='_Engine_R50'!L36/12 | H12: ='_Engine_R50'!L37/12 | I12: ='_Engine_R50'!L38/12 | J12: ='_Engine_R50'!L39/12 | K12: ='_Engine_R50'!L40/12 | L12: ='_Engine_R50'!L41/12 | M12: ='_Engine_R50'!L42/12 | N12: ='_Engine_R50'!L43/12 | O12: ='_Engine_R50'!L44/12 | P12: ='_Engine_R50'!L45/12 | Q12: ='_Engine_R50'!L46/12 | R12: ='_Engine_R50'!L47/12 | S12: ='_Engine_R50'!L48/12 | T12: ='_Engine_R50'!L49/12 | U12: ='_Engine_R50'!L50/12 | V12: ='_Engine_R50'!L51/12 | W12: ='_Engine_R50'!L52/12 | X12: ='_Engine_R50'!L53/12 | Y12: ='_Engine_R50'!L54/12 | Z12: ='_Engine_R50'!L55/12 | AA12: ='_Engine_R50'!L56/12 | AB12: ='_Engine_R50'!L57/12 | AC12: ='_Engine_R50'!L58/12 | AD12: ='_Engine_R50'!L59/12 | AE12: ='_Engine_R50'!L60/12 | AF12: ='_Engine_R50'!L61/12 | AG12: ='_Engine_R50'!L62/12 | AH12: ='_Engine_R50'!L63/12 | AI12: ='_Engine_R50'!L64/12 | AJ12: ='_Engine_R50'!L65/12 | AK12: ='_Engine_R50'!L66/12 | AL12: ='_Engine_R50'!L67/12 | AM12: ='_Engine_R50'!L68/12 | AN12: ='_Engine_R50'!L69/12 | AO12: ='_Engine_R50'!L70/12 | AP12: ='_Engine_R50'!L71/12 | AQ12: ='_Engine_R50'!L72/12 | AR12: ='_Engine_R50'!L73/12 | AS12: ='_Engine_R50'!L74/12 | AT12: ='_Engine_R50'!L75/12 | AU12: ='_Engine_R50'!L76/12 | AV12: ='_Engine_R50'!L77/12 | AW12: ='_Engine_R50'!L78/12 | AX12: ='_Engine_R50'!L79/12 | AY12: ='_Engine_R50'!L80/12 | AZ12: ='_Engine_R50'!L81/12 | BA12: ='_Engine_R50'!L82/12 | BB12: ='_Engine_R50'!L83/12 | BC12: ='_Engine_R50'!L84/12 | BD12: ='_Engine_R50'!L85/12 | BE12: ='_Engine_R50'!L86/12 | BF12: ='_Engine_R50'!L87/12 | BG12: ='_Engine_R50'!L88/12 | BH12: ='_Engine_R50'!L89/12 | BI12: ='_Engine_R50'!L90/12 | BJ12: ='_Engine_R50'!L91/12 | BK12: ='_Engine_R50'!L92/12 | BL12: ='_Engine_R50'!L93/12 | BM12: ='_Engine_R50'!L94/12 | BN12: ='_Engine_R50'!L95/12 | BO12: ='_Engine_R50'!L96/12 | BP12: ='_Engine_R50'!L97/12 | BQ12: ='_Engine_R50'!L98/12 | BR12: ='_Engine_R50'!L99/12 | BS12: ='_Engine_R50'!L100/12 | BT12: ='_Engine_R50'!L101/12 | BU12: ='_Engine_R50'!L102/12 | BV12: ='_Engine_R50'!L103/12 | BW12: ='_Engine_R50'!L104/12 | BX12: ='_Engine_R50'!L105/12 | BY12: ='_Engine_R50'!L106/12 | BZ12: ='_Engine_R50'!L107/12 | CA12: ='_Engine_R50'!L108/12 | CB12: ='_Engine_R50'!L109/12 | CC12: ='_Engine_R50'!L110/12 | CD12: ='_Engine_R50'!L111/12 | CE12: ='_Engine_R50'!L112/12 | CF12: ='_Engine_R50'!L113/12 | CG12: ='_Engine_R50'!L114/12 | CH12: ='_Engine_R50'!L115/12 | CI12: ='_Engine_R50'!L116/12 | CJ12: ='_Engine_R50'!L117/12 | CK12: ='_Engine_R50'!L118/12 | CL12: ='_Engine_R50'!L119/12 | CM12: ='_Engine_R50'!L120/12 | CN12: ='_Engine_R50'!L121/12 | CO12: ='_Engine_R50'!L122/12 | CP12: ='_Engine_R50'!L123/12 | CQ12: ='_Engine_R50'!L124/12 | CR12: ='_Engine_R50'!L125/12 | CS12: ='_Engine_R50'!L126/12 | CT12: ='_Engine_R50'!L127/12 | CU12: ='_Engine_R50'!L128/12 | CV12: ='_Engine_R50'!L129/12 | CW12: ='_Engine_R50'!L130/12 | CX12: ='_Engine_R50'!L131/12 | CY12: ='_Engine_R50'!L132/12 | CZ12: ='_Engine_R50'!L133/12 | DA12: ='_Engine_R50'!L134/12 | DB12: ='_Engine_R50'!L135/12 | DC12: ='_Engine_R50'!L136/12 | DD12: ='_Engine_R50'!L137/12 | DE12: ='_Engine_R50'!L138/12 | DF12: ='_Engine_R50'!L139/12 | DG12: ='_Engine_R50'!L140/12 | DH12: ='_Engine_R50'!L141/12 | DI12: ='_Engine_R50'!L142/12 | DJ12: ='_Engine_R50'!L143/12 | DK12: ='_Engine_R50'!L144/12 | DL12: ='_Engine_R50'!L145/12 | DM12: ='_Engine_R50'!L146/12 | DN12: ='_Engine_R50'!L147/12 | DO12: ='_Engine_R50'!L148/12 | DP12: ='_Engine_R50'!L149/12 | DQ12: ='_Engine_R50'!L150/12 | DR12: ='_Engine_R50'!L151/12 | DS12: ='_Engine_R50'!L152/12 | DT12: ='_Engine_R50'!L153/12 | DU12: ='_Engine_R50'!L154/12 | DV12: ='_Engine_R50'!L155/12 | DW12: ='_Engine_R50'!L156/12 | DX12: ='_Engine_R50'!L157/12 | DY12: ='_Engine_R50'!L158/12 | DZ12: ='_Engine_R50'!L159/12 | EA12: ='_Engine_R50'!L160/12 | EB12: ='_Engine_R50'!L161/12 | EC12: ='_Engine_R50'!L162/12 | ED12: ='_Engine_R50'!L163/12 | EE12: ='_Engine_R50'!L164/12 | EF12: ='_Engine_R50'!L165/12 | EG12: ='_Engine_R50'!L166/12 | EH12: ='_Engine_R50'!L167/12 | EI12: ='_Engine_R50'!L168/12 | EJ12: ='_Engine_R50'!L169/12 | EK12: ='_Engine_R50'!L170/12 | EL12: ='_Engine_R50'!L171/12 | EM12: ='_Engine_R50'!L172/12 | EN12: ='_Engine_R50'!L173/12 | EO12: ='_Engine_R50'!L174/12 | EP12: ='_Engine_R50'!L175/12 | EQ12: ='_Engine_R50'!L176/12 | ER12: ='_Engine_R50'!L177/12 | ES12: ='_Engine_R50'!L178/12 | ET12: ='_Engine_R50'!L179/12 | EU12: ='_Engine_R50'!L180/12 | EV12: ='_Engine_R50'!L181/12 | EW12: ='_Engine_R50'!L182/12 | EX12: ='_Engine_R50'!L183/12 | EY12: ='_Engine_R50'!L184/12 | EZ12: ='_Engine_R50'!L185/12 | FA12: ='_Engine_R50'!L186/12 | FB12: ='_Engine_R50'!L187/12 | FC12: ='_Engine_R50'!L188/12 | FD12: ='_Engine_R50'!L189/12 | FE12: ='_Engine_R50'!L190/12 | FF12: ='_Engine_R50'!L191/12 | FG12: ='_Engine_R50'!L192/12 | FH12: ='_Engine_R50'!L193/12 | FI12: ='_Engine_R50'!L194/12 | FJ12: ='_Engine_R50'!L195/12 | FK12: ='_Engine_R50'!L196/12 | FL12: ='_Engine_R50'!L197/12 | FM12: ='_Engine_R50'!L198/12 | FN12: ='_Engine_R50'!L199/12 | FO12: ='_Engine_R50'!L200/12 | FP12: ='_Engine_R50'!L201/12 | FQ12: ='_Engine_R50'!L202/12 | FR12: ='_Engine_R50'!L203/12 | FS12: ='_Engine_R50'!L204/12 | FT12: ='_Engine_R50'!L205/12 | FU12: ='_Engine_R50'!L206/12 | FV12: ='_Engine_R50'!L207/12 | FW12: ='_Engine_R50'!L208/12 | FX12: ='_Engine_R50'!L209/12 | FY12: ='_Engine_R50'!L210/12
A13: Deal #8 | B13: ='_Engine_R50'!P31 | C13: ='_Engine_R50'!P32 | D13: ='_Engine_R50'!P33 | E13: ='_Engine_R50'!P34 | F13: ='_Engine_R50'!P35 | G13: ='_Engine_R50'!P36 | H13: ='_Engine_R50'!P37 | I13: ='_Engine_R50'!P38 | J13: ='_Engine_R50'!P39 | K13: ='_Engine_R50'!P40 | L13: ='_Engine_R50'!P41 | M13: ='_Engine_R50'!P42 | N13: ='_Engine_R50'!P43 | O13: ='_Engine_R50'!P44 | P13: ='_Engine_R50'!P45 | Q13: ='_Engine_R50'!P46 | R13: ='_Engine_R50'!P47 | S13: ='_Engine_R50'!P48 | T13: ='_Engine_R50'!P49 | U13: ='_Engine_R50'!P50 | V13: ='_Engine_R50'!P51 | W13: ='_Engine_R50'!P52 | X13: ='_Engine_R50'!P53 | Y13: ='_Engine_R50'!P54 | Z13: ='_Engine_R50'!P55 | AA13: ='_Engine_R50'!P56 | AB13: ='_Engine_R50'!P57 | AC13: ='_Engine_R50'!P58 | AD13: ='_Engine_R50'!P59 | AE13: ='_Engine_R50'!P60 | AF13: ='_Engine_R50'!P61 | AG13: ='_Engine_R50'!P62 | AH13: ='_Engine_R50'!P63 | AI13: ='_Engine_R50'!P64 | AJ13: ='_Engine_R50'!P65 | AK13: ='_Engine_R50'!P66 | AL13: ='_Engine_R50'!P67 | AM13: ='_Engine_R50'!P68 | AN13: ='_Engine_R50'!P69 | AO13: ='_Engine_R50'!P70 | AP13: ='_Engine_R50'!P71 | AQ13: ='_Engine_R50'!P72 | AR13: ='_Engine_R50'!P73 | AS13: ='_Engine_R50'!P74 | AT13: ='_Engine_R50'!P75 | AU13: ='_Engine_R50'!P76 | AV13: ='_Engine_R50'!P77 | AW13: ='_Engine_R50'!P78 | AX13: ='_Engine_R50'!P79 | AY13: ='_Engine_R50'!P80 | AZ13: ='_Engine_R50'!P81 | BA13: ='_Engine_R50'!P82 | BB13: ='_Engine_R50'!P83 | BC13: ='_Engine_R50'!P84 | BD13: ='_Engine_R50'!P85 | BE13: ='_Engine_R50'!P86 | BF13: ='_Engine_R50'!P87 | BG13: ='_Engine_R50'!P88 | BH13: ='_Engine_R50'!P89 | BI13: ='_Engine_R50'!P90 | BJ13: ='_Engine_R50'!P91 | BK13: ='_Engine_R50'!P92 | BL13: ='_Engine_R50'!P93 | BM13: ='_Engine_R50'!P94 | BN13: ='_Engine_R50'!P95 | BO13: ='_Engine_R50'!P96 | BP13: ='_Engine_R50'!P97 | BQ13: ='_Engine_R50'!P98 | BR13: ='_Engine_R50'!P99 | BS13: ='_Engine_R50'!P100 | BT13: ='_Engine_R50'!P101 | BU13: ='_Engine_R50'!P102 | BV13: ='_Engine_R50'!P103 | BW13: ='_Engine_R50'!P104 | BX13: ='_Engine_R50'!P105 | BY13: ='_Engine_R50'!P106 | BZ13: ='_Engine_R50'!P107 | CA13: ='_Engine_R50'!P108 | CB13: ='_Engine_R50'!P109 | CC13: ='_Engine_R50'!P110 | CD13: ='_Engine_R50'!P111 | CE13: ='_Engine_R50'!P112 | CF13: ='_Engine_R50'!P113 | CG13: ='_Engine_R50'!P114 | CH13: ='_Engine_R50'!P115 | CI13: ='_Engine_R50'!P116 | CJ13: ='_Engine_R50'!P117 | CK13: ='_Engine_R50'!P118 | CL13: ='_Engine_R50'!P119 | CM13: ='_Engine_R50'!P120 | CN13: ='_Engine_R50'!P121 | CO13: ='_Engine_R50'!P122 | CP13: ='_Engine_R50'!P123 | CQ13: ='_Engine_R50'!P124 | CR13: ='_Engine_R50'!P125 | CS13: ='_Engine_R50'!P126 | CT13: ='_Engine_R50'!P127 | CU13: ='_Engine_R50'!P128 | CV13: ='_Engine_R50'!P129 | CW13: ='_Engine_R50'!P130 | CX13: ='_Engine_R50'!P131 | CY13: ='_Engine_R50'!P132 | CZ13: ='_Engine_R50'!P133 | DA13: ='_Engine_R50'!P134 | DB13: ='_Engine_R50'!P135 | DC13: ='_Engine_R50'!P136 | DD13: ='_Engine_R50'!P137 | DE13: ='_Engine_R50'!P138 | DF13: ='_Engine_R50'!P139 | DG13: ='_Engine_R50'!P140 | DH13: ='_Engine_R50'!P141 | DI13: ='_Engine_R50'!P142 | DJ13: ='_Engine_R50'!P143 | DK13: ='_Engine_R50'!P144 | DL13: ='_Engine_R50'!P145 | DM13: ='_Engine_R50'!P146 | DN13: ='_Engine_R50'!P147 | DO13: ='_Engine_R50'!P148 | DP13: ='_Engine_R50'!P149 | DQ13: ='_Engine_R50'!P150 | DR13: ='_Engine_R50'!P151 | DS13: ='_Engine_R50'!P152 | DT13: ='_Engine_R50'!P153 | DU13: ='_Engine_R50'!P154 | DV13: ='_Engine_R50'!P155 | DW13: ='_Engine_R50'!P156 | DX13: ='_Engine_R50'!P157 | DY13: ='_Engine_R50'!P158 | DZ13: ='_Engine_R50'!P159 | EA13: ='_Engine_R50'!P160 | EB13: ='_Engine_R50'!P161 | EC13: ='_Engine_R50'!P162 | ED13: ='_Engine_R50'!P163 | EE13: ='_Engine_R50'!P164 | EF13: ='_Engine_R50'!P165 | EG13: ='_Engine_R50'!P166 | EH13: ='_Engine_R50'!P167 | EI13: ='_Engine_R50'!P168 | EJ13: ='_Engine_R50'!P169 | EK13: ='_Engine_R50'!P170 | EL13: ='_Engine_R50'!P171 | EM13: ='_Engine_R50'!P172 | EN13: ='_Engine_R50'!P173 | EO13: ='_Engine_R50'!P174 | EP13: ='_Engine_R50'!P175 | EQ13: ='_Engine_R50'!P176 | ER13: ='_Engine_R50'!P177 | ES13: ='_Engine_R50'!P178 | ET13: ='_Engine_R50'!P179 | EU13: ='_Engine_R50'!P180 | EV13: ='_Engine_R50'!P181 | EW13: ='_Engine_R50'!P182 | EX13: ='_Engine_R50'!P183 | EY13: ='_Engine_R50'!P184 | EZ13: ='_Engine_R50'!P185 | FA13: ='_Engine_R50'!P186 | FB13: ='_Engine_R50'!P187 | FC13: ='_Engine_R50'!P188 | FD13: ='_Engine_R50'!P189 | FE13: ='_Engine_R50'!P190 | FF13: ='_Engine_R50'!P191 | FG13: ='_Engine_R50'!P192 | FH13: ='_Engine_R50'!P193 | FI13: ='_Engine_R50'!P194 | FJ13: ='_Engine_R50'!P195 | FK13: ='_Engine_R50'!P196 | FL13: ='_Engine_R50'!P197 | FM13: ='_Engine_R50'!P198 | FN13: ='_Engine_R50'!P199 | FO13: ='_Engine_R50'!P200 | FP13: ='_Engine_R50'!P201 | FQ13: ='_Engine_R50'!P202 | FR13: ='_Engine_R50'!P203 | FS13: ='_Engine_R50'!P204 | FT13: ='_Engine_R50'!P205 | FU13: ='_Engine_R50'!P206 | FV13: ='_Engine_R50'!P207 | FW13: ='_Engine_R50'!P208 | FX13: ='_Engine_R50'!P209 | FY13: ='_Engine_R50'!P210
B14: ='_Engine_R50'!Q31 | C14: ='_Engine_R50'!Q32 | D14: ='_Engine_R50'!Q33 | E14: ='_Engine_R50'!Q34 | F14: ='_Engine_R50'!Q35 | G14: ='_Engine_R50'!Q36 | H14: ='_Engine_R50'!Q37 | I14: ='_Engine_R50'!Q38 | J14: ='_Engine_R50'!Q39 | K14: ='_Engine_R50'!Q40 | L14: ='_Engine_R50'!Q41 | M14: ='_Engine_R50'!Q42 | N14: ='_Engine_R50'!Q43 | O14: ='_Engine_R50'!Q44 | P14: ='_Engine_R50'!Q45 | Q14: ='_Engine_R50'!Q46 | R14: ='_Engine_R50'!Q47 | S14: ='_Engine_R50'!Q48 | T14: ='_Engine_R50'!Q49 | U14: ='_Engine_R50'!Q50 | V14: ='_Engine_R50'!Q51 | W14: ='_Engine_R50'!Q52 | X14: ='_Engine_R50'!Q53 | Y14: ='_Engine_R50'!Q54 | Z14: ='_Engine_R50'!Q55 | AA14: ='_Engine_R50'!Q56 | AB14: ='_Engine_R50'!Q57 | AC14: ='_Engine_R50'!Q58 | AD14: ='_Engine_R50'!Q59 | AE14: ='_Engine_R50'!Q60 | AF14: ='_Engine_R50'!Q61 | AG14: ='_Engine_R50'!Q62 | AH14: ='_Engine_R50'!Q63 | AI14: ='_Engine_R50'!Q64 | AJ14: ='_Engine_R50'!Q65 | AK14: ='_Engine_R50'!Q66 | AL14: ='_Engine_R50'!Q67 | AM14: ='_Engine_R50'!Q68 | AN14: ='_Engine_R50'!Q69 | AO14: ='_Engine_R50'!Q70 | AP14: ='_Engine_R50'!Q71 | AQ14: ='_Engine_R50'!Q72 | AR14: ='_Engine_R50'!Q73 | AS14: ='_Engine_R50'!Q74 | AT14: ='_Engine_R50'!Q75 | AU14: ='_Engine_R50'!Q76 | AV14: ='_Engine_R50'!Q77 | AW14: ='_Engine_R50'!Q78 | AX14: ='_Engine_R50'!Q79 | AY14: ='_Engine_R50'!Q80 | AZ14: ='_Engine_R50'!Q81 | BA14: ='_Engine_R50'!Q82 | BB14: ='_Engine_R50'!Q83 | BC14: ='_Engine_R50'!Q84 | BD14: ='_Engine_R50'!Q85 | BE14: ='_Engine_R50'!Q86 | BF14: ='_Engine_R50'!Q87 | BG14: ='_Engine_R50'!Q88 | BH14: ='_Engine_R50'!Q89 | BI14: ='_Engine_R50'!Q90 | BJ14: ='_Engine_R50'!Q91 | BK14: ='_Engine_R50'!Q92 | BL14: ='_Engine_R50'!Q93 | BM14: ='_Engine_R50'!Q94 | BN14: ='_Engine_R50'!Q95 | BO14: ='_Engine_R50'!Q96 | BP14: ='_Engine_R50'!Q97 | BQ14: ='_Engine_R50'!Q98 | BR14: ='_Engine_R50'!Q99 | BS14: ='_Engine_R50'!Q100 | BT14: ='_Engine_R50'!Q101 | BU14: ='_Engine_R50'!Q102 | BV14: ='_Engine_R50'!Q103 | BW14: ='_Engine_R50'!Q104 | BX14: ='_Engine_R50'!Q105 | BY14: ='_Engine_R50'!Q106 | BZ14: ='_Engine_R50'!Q107 | CA14: ='_Engine_R50'!Q108 | CB14: ='_Engine_R50'!Q109 | CC14: ='_Engine_R50'!Q110 | CD14: ='_Engine_R50'!Q111 | CE14: ='_Engine_R50'!Q112 | CF14: ='_Engine_R50'!Q113 | CG14: ='_Engine_R50'!Q114 | CH14: ='_Engine_R50'!Q115 | CI14: ='_Engine_R50'!Q116 | CJ14: ='_Engine_R50'!Q117 | CK14: ='_Engine_R50'!Q118 | CL14: ='_Engine_R50'!Q119 | CM14: ='_Engine_R50'!Q120 | CN14: ='_Engine_R50'!Q121 | CO14: ='_Engine_R50'!Q122 | CP14: ='_Engine_R50'!Q123 | CQ14: ='_Engine_R50'!Q124 | CR14: ='_Engine_R50'!Q125 | CS14: ='_Engine_R50'!Q126 | CT14: ='_Engine_R50'!Q127 | CU14: ='_Engine_R50'!Q128 | CV14: ='_Engine_R50'!Q129 | CW14: ='_Engine_R50'!Q130 | CX14: ='_Engine_R50'!Q131 | CY14: ='_Engine_R50'!Q132 | CZ14: ='_Engine_R50'!Q133 | DA14: ='_Engine_R50'!Q134 | DB14: ='_Engine_R50'!Q135 | DC14: ='_Engine_R50'!Q136 | DD14: ='_Engine_R50'!Q137 | DE14: ='_Engine_R50'!Q138 | DF14: ='_Engine_R50'!Q139 | DG14: ='_Engine_R50'!Q140 | DH14: ='_Engine_R50'!Q141 | DI14: ='_Engine_R50'!Q142 | DJ14: ='_Engine_R50'!Q143 | DK14: ='_Engine_R50'!Q144 | DL14: ='_Engine_R50'!Q145 | DM14: ='_Engine_R50'!Q146 | DN14: ='_Engine_R50'!Q147 | DO14: ='_Engine_R50'!Q148 | DP14: ='_Engine_R50'!Q149 | DQ14: ='_Engine_R50'!Q150 | DR14: ='_Engine_R50'!Q151 | DS14: ='_Engine_R50'!Q152 | DT14: ='_Engine_R50'!Q153 | DU14: ='_Engine_R50'!Q154 | DV14: ='_Engine_R50'!Q155 | DW14: ='_Engine_R50'!Q156 | DX14: ='_Engine_R50'!Q157 | DY14: ='_Engine_R50'!Q158 | DZ14: ='_Engine_R50'!Q159 | EA14: ='_Engine_R50'!Q160 | EB14: ='_Engine_R50'!Q161 | EC14: ='_Engine_R50'!Q162 | ED14: ='_Engine_R50'!Q163 | EE14: ='_Engine_R50'!Q164 | EF14: ='_Engine_R50'!Q165 | EG14: ='_Engine_R50'!Q166 | EH14: ='_Engine_R50'!Q167 | EI14: ='_Engine_R50'!Q168 | EJ14: ='_Engine_R50'!Q169 | EK14: ='_Engine_R50'!Q170 | EL14: ='_Engine_R50'!Q171 | EM14: ='_Engine_R50'!Q172 | EN14: ='_Engine_R50'!Q173 | EO14: ='_Engine_R50'!Q174 | EP14: ='_Engine_R50'!Q175 | EQ14: ='_Engine_R50'!Q176 | ER14: ='_Engine_R50'!Q177 | ES14: ='_Engine_R50'!Q178 | ET14: ='_Engine_R50'!Q179 | EU14: ='_Engine_R50'!Q180 | EV14: ='_Engine_R50'!Q181 | EW14: ='_Engine_R50'!Q182 | EX14: ='_Engine_R50'!Q183 | EY14: ='_Engine_R50'!Q184 | EZ14: ='_Engine_R50'!Q185 | FA14: ='_Engine_R50'!Q186 | FB14: ='_Engine_R50'!Q187 | FC14: ='_Engine_R50'!Q188 | FD14: ='_Engine_R50'!Q189 | FE14: ='_Engine_R50'!Q190 | FF14: ='_Engine_R50'!Q191 | FG14: ='_Engine_R50'!Q192 | FH14: ='_Engine_R50'!Q193 | FI14: ='_Engine_R50'!Q194 | FJ14: ='_Engine_R50'!Q195 | FK14: ='_Engine_R50'!Q196 | FL14: ='_Engine_R50'!Q197 | FM14: ='_Engine_R50'!Q198 | FN14: ='_Engine_R50'!Q199 | FO14: ='_Engine_R50'!Q200 | FP14: ='_Engine_R50'!Q201 | FQ14: ='_Engine_R50'!Q202 | FR14: ='_Engine_R50'!Q203 | FS14: ='_Engine_R50'!Q204 | FT14: ='_Engine_R50'!Q205 | FU14: ='_Engine_R50'!Q206 | FV14: ='_Engine_R50'!Q207 | FW14: ='_Engine_R50'!Q208 | FX14: ='_Engine_R50'!Q209 | FY14: ='_Engine_R50'!Q210
A15: Portfolio P&L | B15: =B13-B14 | C15: =C13-C14 | D15: =D13-D14 | E15: =E13-E14 | F15: =F13-F14 | G15: =G13-G14 | H15: =H13-H14 | I15: =I13-I14 | ... FY15: =FY13-FY14
A16: Revenue | B16: 0 | C16: 0 | D16: 0 | E16: 2.1333 | F16: 2.1046 | G16: 2.0763 | H16: 4.3151 | I16: 4.257 | J16: 4.1997 | K16: 6.6516 | L16: 6.5621 | M16: 8.6405 | N16: 8.5243 | O16: 8.4096 | P16: 8.2965 | Q16: 10.3015 | R16: 10.163 | S16: 10.0263 | T16: 9.8914 | U16: 9.7583 | V16: 9.6271 | W16: 9.4976 | X16: 9.3698 | Y16: 11.2438 | Z16: 11.0925 | AA16: 10.9433 | AB16: 10.7961 | AC16: 10.6508 | AD16: 10.5076 | AE16: 12.3662 | AF16: 12.1999 | AG16: 12.0358 | AH16: 11.8739 | AI16: 11.7141 | AJ16: 11.5566 | AK16: 13.4011 | AL16: 13.2208 | AM16: 13.043 | AN16: 12.8675 | AO16: 12.6944 | AP16: 12.5237 | AQ16: 12.3552 | AR16: 12.189 | AS16: 12.025 | AT16: 11.8633 | AU16: 11.7037 | AV16: 11.5463 | AW16: 11.3909 | AX16: 11.2377 | AY16: 11.0865 | AZ16: 10.9374 | BA16: 10.7903 | BB16: 10.6451 | BC16: 10.5019 | BD16: 10.3606 | BE16: 10.2213 | BF16: 10.0838 | BG16: 9.9481 | BH16: 9.8143 | BI16: 9.6823 | BJ16: 9.552 | BK16: 9.4236 | BL16: 9.2968 | BM16: 9.1717 | BN16: 9.0484 | BO16: 8.9266 | BP16: 8.8066 | BQ16: 8.6881 | BR16: 8.5712 | BS16: 8.4559 | BT16: 8.3422 | BU16: 8.2299 | BV16: 8.1192 | BW16: 8.01 | BX16: 7.9023 | BY16: 7.796 | BZ16: 7.6911 | CA16: 7.5876 | CB16: 7.4856 | CC16: 7.3849 | CD16: 7.2855 | CE16: 7.1875 | CF16: 7.0908 | CG16: 6.9955 | CH16: 6.9014 | CI16: 6.8085 | CJ16: 6.7169 | CK16: 6.6266 | CL16: 6.5374 | CM16: 6.4495 | CN16: 6.3627 | CO16: 6.2771 | CP16: 6.1927 | CQ16: 6.1094 | CR16: 6.0272 | CS16: 5.9461 | CT16: 5.8662 | CU16: 5.7872 | CV16: 5.7094 | CW16: 5.6326 | CX16: 5.5568 | CY16: 5.4821 | CZ16: 5.4083 | DA16: 5.3356 | DB16: 5.2638 | DC16: 5.193 | DD16: 5.1231 | DE16: 5.0542 | DF16: 4.9862 | DG16: 4.9192 | DH16: 4.853 | DI16: 4.7877 | DJ16: 4.7233 | DK16: 4.6598 | DL16: 4.5971 | DM16: 4.5352 | DN16: 4.4742 | DO16: 4.414 | DP16: 4.3547 | DQ16: 4.2961 | DR16: 4.2383 | DS16: 4.1813 | DT16: 4.125 | DU16: 4.0695 | DV16: 4.0148 | DW16: 3.9608 | DX16: 3.9075 | DY16: 3.855 | DZ16: 3.8031 | EA16: 3.7519 | EB16: 3.7015 | EC16: 3.6517 | ED16: 3.6025 | EE16: 3.5541 | EF16: 3.5063 | EG16: 3.4591 | EH16: 3.4126 | EI16: 3.3667 | EJ16: 3.3214 | EK16: 3.2767 | EL16: 3.2326 | EM16: 3.1891 | EN16: 3.1462 | EO16: 3.1039 | EP16: 3.0622 | EQ16: 3.021 | ER16: 2.9803 | ES16: 2.9402 | ET16: 2.9007 | EU16: 2.8617 | EV16: 2.8232 | EW16: 2.7852 | EX16: 2.7477 | EY16: 2.7108 | EZ16: 2.6743 | FA16: 2.6383 | FB16: 2.6028 | FC16: 2.5678 | FD16: 2.5333 | FE16: 2.4992 | FF16: 2.4656 | FG16: 2.4324 | FH16: 2.3997 | FI16: 2.3674 | FJ16: 2.3356 | FK16: 2.3042 | FL16: 2.2732 | FM16: 2.2426 | FN16: 2.2124 | FO16: 2.1827 | FP16: 2.1533 | FQ16: 2.1243 | FR16: 2.0958 | FS16: 2.0676 | FT16: 2.0397 | FU16: 2.0123 | FV16: 1.9852 | FW16: 1.9585 | FX16: 1.9322 | FY16: 1.9062
A17: Cost of Goods Sold | B17: ='_Engine_R50'!R31 | C17: ='_Engine_R50'!R32 | D17: ='_Engine_R50'!R33 | E17: ='_Engine_R50'!R34 | F17: ='_Engine_R50'!R35 | G17: ='_Engine_R50'!R36 | H17: ='_Engine_R50'!R37 | I17: ='_Engine_R50'!R38 | J17: ='_Engine_R50'!R39 | K17: ='_Engine_R50'!R40 | L17: ='_Engine_R50'!R41 | M17: ='_Engine_R50'!R42 | N17: ='_Engine_R50'!R43 | O17: ='_Engine_R50'!R44 | P17: ='_Engine_R50'!R45 | Q17: ='_Engine_R50'!R46 | R17: ='_Engine_R50'!R47 | S17: ='_Engine_R50'!R48 | T17: ='_Engine_R50'!R49 | U17: ='_Engine_R50'!R50 | V17: ='_Engine_R50'!R51 | W17: ='_Engine_R50'!R52 | X17: ='_Engine_R50'!R53 | Y17: ='_Engine_R50'!R54 | Z17: ='_Engine_R50'!R55 | AA17: ='_Engine_R50'!R56 | AB17: ='_Engine_R50'!R57 | AC17: ='_Engine_R50'!R58 | AD17: ='_Engine_R50'!R59 | AE17: ='_Engine_R50'!R60 | AF17: ='_Engine_R50'!R61 | AG17: ='_Engine_R50'!R62 | AH17: ='_Engine_R50'!R63 | AI17: ='_Engine_R50'!R64 | AJ17: ='_Engine_R50'!R65 | AK17: ='_Engine_R50'!R66 | AL17: ='_Engine_R50'!R67 | AM17: ='_Engine_R50'!R68 | AN17: ='_Engine_R50'!R69 | AO17: ='_Engine_R50'!R70 | AP17: ='_Engine_R50'!R71 | AQ17: ='_Engine_R50'!R72 | AR17: ='_Engine_R50'!R73 | AS17: ='_Engine_R50'!R74 | AT17: ='_Engine_R50'!R75 | AU17: ='_Engine_R50'!R76 | AV17: ='_Engine_R50'!R77 | AW17: ='_Engine_R50'!R78 | AX17: ='_Engine_R50'!R79 | AY17: ='_Engine_R50'!R80 | AZ17: ='_Engine_R50'!R81 | BA17: ='_Engine_R50'!R82 | BB17: ='_Engine_R50'!R83 | BC17: ='_Engine_R50'!R84 | BD17: ='_Engine_R50'!R85 | BE17: ='_Engine_R50'!R86 | BF17: ='_Engine_R50'!R87 | BG17: ='_Engine_R50'!R88 | BH17: ='_Engine_R50'!R89 | BI17: ='_Engine_R50'!R90 | BJ17: ='_Engine_R50'!R91 | BK17: ='_Engine_R50'!R92 | BL17: ='_Engine_R50'!R93 | BM17: ='_Engine_R50'!R94 | BN17: ='_Engine_R50'!R95 | BO17: ='_Engine_R50'!R96 | BP17: ='_Engine_R50'!R97 | BQ17: ='_Engine_R50'!R98 | BR17: ='_Engine_R50'!R99 | BS17: ='_Engine_R50'!R100 | BT17: ='_Engine_R50'!R101 | BU17: ='_Engine_R50'!R102 | BV17: ='_Engine_R50'!R103 | BW17: ='_Engine_R50'!R104 | BX17: ='_Engine_R50'!R105 | BY17: ='_Engine_R50'!R106 | BZ17: ='_Engine_R50'!R107 | CA17: ='_Engine_R50'!R108 | CB17: ='_Engine_R50'!R109 | CC17: ='_Engine_R50'!R110 | CD17: ='_Engine_R50'!R111 | CE17: ='_Engine_R50'!R112 | CF17: ='_Engine_R50'!R113 | CG17: ='_Engine_R50'!R114 | CH17: ='_Engine_R50'!R115 | CI17: ='_Engine_R50'!R116 | CJ17: ='_Engine_R50'!R117 | CK17: ='_Engine_R50'!R118 | CL17: ='_Engine_R50'!R119 | CM17: ='_Engine_R50'!R120 | CN17: ='_Engine_R50'!R121 | CO17: ='_Engine_R50'!R122 | CP17: ='_Engine_R50'!R123 | CQ17: ='_Engine_R50'!R124 | CR17: ='_Engine_R50'!R125 | CS17: ='_Engine_R50'!R126 | CT17: ='_Engine_R50'!R127 | CU17: ='_Engine_R50'!R128 | CV17: ='_Engine_R50'!R129 | CW17: ='_Engine_R50'!R130 | CX17: ='_Engine_R50'!R131 | CY17: ='_Engine_R50'!R132 | CZ17: ='_Engine_R50'!R133 | DA17: ='_Engine_R50'!R134 | DB17: ='_Engine_R50'!R135 | DC17: ='_Engine_R50'!R136 | DD17: ='_Engine_R50'!R137 | DE17: ='_Engine_R50'!R138 | DF17: ='_Engine_R50'!R139 | DG17: ='_Engine_R50'!R140 | DH17: ='_Engine_R50'!R141 | DI17: ='_Engine_R50'!R142 | DJ17: ='_Engine_R50'!R143 | DK17: ='_Engine_R50'!R144 | DL17: ='_Engine_R50'!R145 | DM17: ='_Engine_R50'!R146 | DN17: ='_Engine_R50'!R147 | DO17: ='_Engine_R50'!R148 | DP17: ='_Engine_R50'!R149 | DQ17: ='_Engine_R50'!R150 | DR17: ='_Engine_R50'!R151 | DS17: ='_Engine_R50'!R152 | DT17: ='_Engine_R50'!R153 | DU17: ='_Engine_R50'!R154 | DV17: ='_Engine_R50'!R155 | DW17: ='_Engine_R50'!R156 | DX17: ='_Engine_R50'!R157 | DY17: ='_Engine_R50'!R158 | DZ17: ='_Engine_R50'!R159 | EA17: ='_Engine_R50'!R160 | EB17: ='_Engine_R50'!R161 | EC17: ='_Engine_R50'!R162 | ED17: ='_Engine_R50'!R163 | EE17: ='_Engine_R50'!R164 | EF17: ='_Engine_R50'!R165 | EG17: ='_Engine_R50'!R166 | EH17: ='_Engine_R50'!R167 | EI17: ='_Engine_R50'!R168 | EJ17: ='_Engine_R50'!R169 | EK17: ='_Engine_R50'!R170 | EL17: ='_Engine_R50'!R171 | EM17: ='_Engine_R50'!R172 | EN17: ='_Engine_R50'!R173 | EO17: ='_Engine_R50'!R174 | EP17: ='_Engine_R50'!R175 | EQ17: ='_Engine_R50'!R176 | ER17: ='_Engine_R50'!R177 | ES17: ='_Engine_R50'!R178 | ET17: ='_Engine_R50'!R179 | EU17: ='_Engine_R50'!R180 | EV17: ='_Engine_R50'!R181 | EW17: ='_Engine_R50'!R182 | EX17: ='_Engine_R50'!R183 | EY17: ='_Engine_R50'!R184 | EZ17: ='_Engine_R50'!R185 | FA17: ='_Engine_R50'!R186 | FB17: ='_Engine_R50'!R187 | FC17: ='_Engine_R50'!R188 | FD17: ='_Engine_R50'!R189 | FE17: ='_Engine_R50'!R190 | FF17: ='_Engine_R50'!R191 | FG17: ='_Engine_R50'!R192 | FH17: ='_Engine_R50'!R193 | FI17: ='_Engine_R50'!R194 | FJ17: ='_Engine_R50'!R195 | FK17: ='_Engine_R50'!R196 | FL17: ='_Engine_R50'!R197 | FM17: ='_Engine_R50'!R198 | FN17: ='_Engine_R50'!R199 | FO17: ='_Engine_R50'!R200 | FP17: ='_Engine_R50'!R201 | FQ17: ='_Engine_R50'!R202 | FR17: ='_Engine_R50'!R203 | FS17: ='_Engine_R50'!R204 | FT17: ='_Engine_R50'!R205 | FU17: ='_Engine_R50'!R206 | FV17: ='_Engine_R50'!R207 | FW17: ='_Engine_R50'!R208 | FX17: ='_Engine_R50'!R209 | FY17: ='_Engine_R50'!R210
A18: Gross Profit | B18: ='_Engine_R50'!S31 | C18: ='_Engine_R50'!S32 | D18: ='_Engine_R50'!S33 | E18: ='_Engine_R50'!S34 | F18: ='_Engine_R50'!S35 | G18: ='_Engine_R50'!S36 | H18: ='_Engine_R50'!S37 | I18: ='_Engine_R50'!S38 | J18: ='_Engine_R50'!S39 | K18: ='_Engine_R50'!S40 | L18: ='_Engine_R50'!S41 | M18: ='_Engine_R50'!S42 | N18: ='_Engine_R50'!S43 | O18: ='_Engine_R50'!S44 | P18: ='_Engine_R50'!S45 | Q18: ='_Engine_R50'!S46 | R18: ='_Engine_R50'!S47 | S18: ='_Engine_R50'!S48 | T18: ='_Engine_R50'!S49 | U18: ='_Engine_R50'!S50 | V18: ='_Engine_R50'!S51 | W18: ='_Engine_R50'!S52 | X18: ='_Engine_R50'!S53 | Y18: ='_Engine_R50'!S54 | Z18: ='_Engine_R50'!S55 | AA18: ='_Engine_R50'!S56 | AB18: ='_Engine_R50'!S57 | AC18: ='_Engine_R50'!S58 | AD18: ='_Engine_R50'!S59 | AE18: ='_Engine_R50'!S60 | AF18: ='_Engine_R50'!S61 | AG18: ='_Engine_R50'!S62 | AH18: ='_Engine_R50'!S63 | AI18: ='_Engine_R50'!S64 | AJ18: ='_Engine_R50'!S65 | AK18: ='_Engine_R50'!S66 | AL18: ='_Engine_R50'!S67 | AM18: ='_Engine_R50'!S68 | AN18: ='_Engine_R50'!S69 | AO18: ='_Engine_R50'!S70 | AP18: ='_Engine_R50'!S71 | AQ18: ='_Engine_R50'!S72 | AR18: ='_Engine_R50'!S73 | AS18: ='_Engine_R50'!S74 | AT18: ='_Engine_R50'!S75 | AU18: ='_Engine_R50'!S76 | AV18: ='_Engine_R50'!S77 | AW18: ='_Engine_R50'!S78 | AX18: ='_Engine_R50'!S79 | AY18: ='_Engine_R50'!S80 | AZ18: ='_Engine_R50'!S81 | BA18: ='_Engine_R50'!S82 | BB18: ='_Engine_R50'!S83 | BC18: ='_Engine_R50'!S84 | BD18: ='_Engine_R50'!S85 | BE18: ='_Engine_R50'!S86 | BF18: ='_Engine_R50'!S87 | BG18: ='_Engine_R50'!S88 | BH18: ='_Engine_R50'!S89 | BI18: ='_Engine_R50'!S90 | BJ18: ='_Engine_R50'!S91 | BK18: ='_Engine_R50'!S92 | BL18: ='_Engine_R50'!S93 | BM18: ='_Engine_R50'!S94 | BN18: ='_Engine_R50'!S95 | BO18: ='_Engine_R50'!S96 | BP18: ='_Engine_R50'!S97 | BQ18: ='_Engine_R50'!S98 | BR18: ='_Engine_R50'!S99 | BS18: ='_Engine_R50'!S100 | BT18: ='_Engine_R50'!S101 | BU18: ='_Engine_R50'!S102 | BV18: ='_Engine_R50'!S103 | BW18: ='_Engine_R50'!S104 | BX18: ='_Engine_R50'!S105 | BY18: ='_Engine_R50'!S106 | BZ18: ='_Engine_R50'!S107 | CA18: ='_Engine_R50'!S108 | CB18: ='_Engine_R50'!S109 | CC18: ='_Engine_R50'!S110 | CD18: ='_Engine_R50'!S111 | CE18: ='_Engine_R50'!S112 | CF18: ='_Engine_R50'!S113 | CG18: ='_Engine_R50'!S114 | CH18: ='_Engine_R50'!S115 | CI18: ='_Engine_R50'!S116 | CJ18: ='_Engine_R50'!S117 | CK18: ='_Engine_R50'!S118 | CL18: ='_Engine_R50'!S119 | CM18: ='_Engine_R50'!S120 | CN18: ='_Engine_R50'!S121 | CO18: ='_Engine_R50'!S122 | CP18: ='_Engine_R50'!S123 | CQ18: ='_Engine_R50'!S124 | CR18: ='_Engine_R50'!S125 | CS18: ='_Engine_R50'!S126 | CT18: ='_Engine_R50'!S127 | CU18: ='_Engine_R50'!S128 | CV18: ='_Engine_R50'!S129 | CW18: ='_Engine_R50'!S130 | CX18: ='_Engine_R50'!S131 | CY18: ='_Engine_R50'!S132 | CZ18: ='_Engine_R50'!S133 | DA18: ='_Engine_R50'!S134 | DB18: ='_Engine_R50'!S135 | DC18: ='_Engine_R50'!S136 | DD18: ='_Engine_R50'!S137 | DE18: ='_Engine_R50'!S138 | DF18: ='_Engine_R50'!S139 | DG18: ='_Engine_R50'!S140 | DH18: ='_Engine_R50'!S141 | DI18: ='_Engine_R50'!S142 | DJ18: ='_Engine_R50'!S143 | DK18: ='_Engine_R50'!S144 | DL18: ='_Engine_R50'!S145 | DM18: ='_Engine_R50'!S146 | DN18: ='_Engine_R50'!S147 | DO18: ='_Engine_R50'!S148 | DP18: ='_Engine_R50'!S149 | DQ18: ='_Engine_R50'!S150 | DR18: ='_Engine_R50'!S151 | DS18: ='_Engine_R50'!S152 | DT18: ='_Engine_R50'!S153 | DU18: ='_Engine_R50'!S154 | DV18: ='_Engine_R50'!S155 | DW18: ='_Engine_R50'!S156 | DX18: ='_Engine_R50'!S157 | DY18: ='_Engine_R50'!S158 | DZ18: ='_Engine_R50'!S159 | EA18: ='_Engine_R50'!S160 | EB18: ='_Engine_R50'!S161 | EC18: ='_Engine_R50'!S162 | ED18: ='_Engine_R50'!S163 | EE18: ='_Engine_R50'!S164 | EF18: ='_Engine_R50'!S165 | EG18: ='_Engine_R50'!S166 | EH18: ='_Engine_R50'!S167 | EI18: ='_Engine_R50'!S168 | EJ18: ='_Engine_R50'!S169 | EK18: ='_Engine_R50'!S170 | EL18: ='_Engine_R50'!S171 | EM18: ='_Engine_R50'!S172 | EN18: ='_Engine_R50'!S173 | EO18: ='_Engine_R50'!S174 | EP18: ='_Engine_R50'!S175 | EQ18: ='_Engine_R50'!S176 | ER18: ='_Engine_R50'!S177 | ES18: ='_Engine_R50'!S178 | ET18: ='_Engine_R50'!S179 | EU18: ='_Engine_R50'!S180 | EV18: ='_Engine_R50'!S181 | EW18: ='_Engine_R50'!S182 | EX18: ='_Engine_R50'!S183 | EY18: ='_Engine_R50'!S184 | EZ18: ='_Engine_R50'!S185 | FA18: ='_Engine_R50'!S186 | FB18: ='_Engine_R50'!S187 | FC18: ='_Engine_R50'!S188 | FD18: ='_Engine_R50'!S189 | FE18: ='_Engine_R50'!S190 | FF18: ='_Engine_R50'!S191 | FG18: ='_Engine_R50'!S192 | FH18: ='_Engine_R50'!S193 | FI18: ='_Engine_R50'!S194 | FJ18: ='_Engine_R50'!S195 | FK18: ='_Engine_R50'!S196 | FL18: ='_Engine_R50'!S197 | FM18: ='_Engine_R50'!S198 | FN18: ='_Engine_R50'!S199 | FO18: ='_Engine_R50'!S200 | FP18: ='_Engine_R50'!S201 | FQ18: ='_Engine_R50'!S202 | FR18: ='_Engine_R50'!S203 | FS18: ='_Engine_R50'!S204 | FT18: ='_Engine_R50'!S205 | FU18: ='_Engine_R50'!S206 | FV18: ='_Engine_R50'!S207 | FW18: ='_Engine_R50'!S208 | FX18: ='_Engine_R50'!S209 | FY18: ='_Engine_R50'!S210
B19: ='_Engine_R50'!D31 | C19: ='_Engine_R50'!D32 | D19: ='_Engine_R50'!D33 | E19: ='_Engine_R50'!D34 | F19: ='_Engine_R50'!D35 | G19: ='_Engine_R50'!D36 | H19: ='_Engine_R50'!D37 | I19: ='_Engine_R50'!D38 | J19: ='_Engine_R50'!D39 | K19: ='_Engine_R50'!D40 | L19: ='_Engine_R50'!D41 | M19: ='_Engine_R50'!D42 | N19: ='_Engine_R50'!D43 | O19: ='_Engine_R50'!D44 | P19: ='_Engine_R50'!D45 | Q19: ='_Engine_R50'!D46 | R19: ='_Engine_R50'!D47 | S19: ='_Engine_R50'!D48 | T19: ='_Engine_R50'!D49 | U19: ='_Engine_R50'!D50 | V19: ='_Engine_R50'!D51 | W19: ='_Engine_R50'!D52 | X19: ='_Engine_R50'!D53 | Y19: ='_Engine_R50'!D54 | Z19: ='_Engine_R50'!D55 | AA19: ='_Engine_R50'!D56 | AB19: ='_Engine_R50'!D57 | AC19: ='_Engine_R50'!D58 | AD19: ='_Engine_R50'!D59 | AE19: ='_Engine_R50'!D60 | AF19: ='_Engine_R50'!D61 | AG19: ='_Engine_R50'!D62 | AH19: ='_Engine_R50'!D63 | AI19: ='_Engine_R50'!D64 | AJ19: ='_Engine_R50'!D65 | AK19: ='_Engine_R50'!D66 | AL19: ='_Engine_R50'!D67 | AM19: ='_Engine_R50'!D68 | AN19: ='_Engine_R50'!D69 | AO19: ='_Engine_R50'!D70 | AP19: ='_Engine_R50'!D71 | AQ19: ='_Engine_R50'!D72 | AR19: ='_Engine_R50'!D73 | AS19: ='_Engine_R50'!D74 | AT19: ='_Engine_R50'!D75 | AU19: ='_Engine_R50'!D76 | AV19: ='_Engine_R50'!D77 | AW19: ='_Engine_R50'!D78 | AX19: ='_Engine_R50'!D79 | AY19: ='_Engine_R50'!D80 | AZ19: ='_Engine_R50'!D81 | BA19: ='_Engine_R50'!D82 | BB19: ='_Engine_R50'!D83 | BC19: ='_Engine_R50'!D84 | BD19: ='_Engine_R50'!D85 | BE19: ='_Engine_R50'!D86 | BF19: ='_Engine_R50'!D87 | BG19: ='_Engine_R50'!D88 | BH19: ='_Engine_R50'!D89 | BI19: ='_Engine_R50'!D90 | BJ19: ='_Engine_R50'!D91 | BK19: ='_Engine_R50'!D92 | BL19: ='_Engine_R50'!D93 | BM19: ='_Engine_R50'!D94 | BN19: ='_Engine_R50'!D95 | BO19: ='_Engine_R50'!D96 | BP19: ='_Engine_R50'!D97 | BQ19: ='_Engine_R50'!D98 | BR19: ='_Engine_R50'!D99 | BS19: ='_Engine_R50'!D100 | BT19: ='_Engine_R50'!D101 | BU19: ='_Engine_R50'!D102 | BV19: ='_Engine_R50'!D103 | BW19: ='_Engine_R50'!D104 | BX19: ='_Engine_R50'!D105 | BY19: ='_Engine_R50'!D106 | BZ19: ='_Engine_R50'!D107 | CA19: ='_Engine_R50'!D108 | CB19: ='_Engine_R50'!D109 | CC19: ='_Engine_R50'!D110 | CD19: ='_Engine_R50'!D111 | CE19: ='_Engine_R50'!D112 | CF19: ='_Engine_R50'!D113 | CG19: ='_Engine_R50'!D114 | CH19: ='_Engine_R50'!D115 | CI19: ='_Engine_R50'!D116 | CJ19: ='_Engine_R50'!D117 | CK19: ='_Engine_R50'!D118 | CL19: ='_Engine_R50'!D119 | CM19: ='_Engine_R50'!D120 | CN19: ='_Engine_R50'!D121 | CO19: ='_Engine_R50'!D122 | CP19: ='_Engine_R50'!D123 | CQ19: ='_Engine_R50'!D124 | CR19: ='_Engine_R50'!D125 | CS19: ='_Engine_R50'!D126 | CT19: ='_Engine_R50'!D127 | CU19: ='_Engine_R50'!D128 | CV19: ='_Engine_R50'!D129 | CW19: ='_Engine_R50'!D130 | CX19: ='_Engine_R50'!D131 | CY19: ='_Engine_R50'!D132 | CZ19: ='_Engine_R50'!D133 | DA19: ='_Engine_R50'!D134 | DB19: ='_Engine_R50'!D135 | DC19: ='_Engine_R50'!D136 | DD19: ='_Engine_R50'!D137 | DE19: ='_Engine_R50'!D138 | DF19: ='_Engine_R50'!D139 | DG19: ='_Engine_R50'!D140 | DH19: ='_Engine_R50'!D141 | DI19: ='_Engine_R50'!D142 | DJ19: ='_Engine_R50'!D143 | DK19: ='_Engine_R50'!D144 | DL19: ='_Engine_R50'!D145 | DM19: ='_Engine_R50'!D146 | DN19: ='_Engine_R50'!D147 | DO19: ='_Engine_R50'!D148 | DP19: ='_Engine_R50'!D149 | DQ19: ='_Engine_R50'!D150 | DR19: ='_Engine_R50'!D151 | DS19: ='_Engine_R50'!D152 | DT19: ='_Engine_R50'!D153 | DU19: ='_Engine_R50'!D154 | DV19: ='_Engine_R50'!D155 | DW19: ='_Engine_R50'!D156 | DX19: ='_Engine_R50'!D157 | DY19: ='_Engine_R50'!D158 | DZ19: ='_Engine_R50'!D159 | EA19: ='_Engine_R50'!D160 | EB19: ='_Engine_R50'!D161 | EC19: ='_Engine_R50'!D162 | ED19: ='_Engine_R50'!D163 | EE19: ='_Engine_R50'!D164 | EF19: ='_Engine_R50'!D165 | EG19: ='_Engine_R50'!D166 | EH19: ='_Engine_R50'!D167 | EI19: ='_Engine_R50'!D168 | EJ19: ='_Engine_R50'!D169 | EK19: ='_Engine_R50'!D170 | EL19: ='_Engine_R50'!D171 | EM19: ='_Engine_R50'!D172 | EN19: ='_Engine_R50'!D173 | EO19: ='_Engine_R50'!D174 | EP19: ='_Engine_R50'!D175 | EQ19: ='_Engine_R50'!D176 | ER19: ='_Engine_R50'!D177 | ES19: ='_Engine_R50'!D178 | ET19: ='_Engine_R50'!D179 | EU19: ='_Engine_R50'!D180 | EV19: ='_Engine_R50'!D181 | EW19: ='_Engine_R50'!D182 | EX19: ='_Engine_R50'!D183 | EY19: ='_Engine_R50'!D184 | EZ19: ='_Engine_R50'!D185 | FA19: ='_Engine_R50'!D186 | FB19: ='_Engine_R50'!D187 | FC19: ='_Engine_R50'!D188 | FD19: ='_Engine_R50'!D189 | FE19: ='_Engine_R50'!D190 | FF19: ='_Engine_R50'!D191 | FG19: ='_Engine_R50'!D192 | FH19: ='_Engine_R50'!D193 | FI19: ='_Engine_R50'!D194 | FJ19: ='_Engine_R50'!D195 | FK19: ='_Engine_R50'!D196 | FL19: ='_Engine_R50'!D197 | FM19: ='_Engine_R50'!D198 | FN19: ='_Engine_R50'!D199 | FO19: ='_Engine_R50'!D200 | FP19: ='_Engine_R50'!D201 | FQ19: ='_Engine_R50'!D202 | FR19: ='_Engine_R50'!D203 | FS19: ='_Engine_R50'!D204 | FT19: ='_Engine_R50'!D205 | FU19: ='_Engine_R50'!D206 | FV19: ='_Engine_R50'!D207 | FW19: ='_Engine_R50'!D208 | FX19: ='_Engine_R50'!D209 | FY19: ='_Engine_R50'!D210
A20: Vendor Costs | B20: ='_Engine_R50'!E31 | C20: ='_Engine_R50'!E32 | D20: ='_Engine_R50'!E33 | E20: ='_Engine_R50'!E34 | F20: ='_Engine_R50'!E35 | G20: ='_Engine_R50'!E36 | H20: ='_Engine_R50'!E37 | I20: ='_Engine_R50'!E38 | J20: ='_Engine_R50'!E39 | K20: ='_Engine_R50'!E40 | L20: ='_Engine_R50'!E41 | M20: ='_Engine_R50'!E42 | N20: ='_Engine_R50'!E43 | O20: ='_Engine_R50'!E44 | P20: ='_Engine_R50'!E45 | Q20: ='_Engine_R50'!E46 | R20: ='_Engine_R50'!E47 | S20: ='_Engine_R50'!E48 | T20: ='_Engine_R50'!E49 | U20: ='_Engine_R50'!E50 | V20: ='_Engine_R50'!E51 | W20: ='_Engine_R50'!E52 | X20: ='_Engine_R50'!E53 | Y20: ='_Engine_R50'!E54 | Z20: ='_Engine_R50'!E55 | AA20: ='_Engine_R50'!E56 | AB20: ='_Engine_R50'!E57 | AC20: ='_Engine_R50'!E58 | AD20: ='_Engine_R50'!E59 | AE20: ='_Engine_R50'!E60 | AF20: ='_Engine_R50'!E61 | AG20: ='_Engine_R50'!E62 | AH20: ='_Engine_R50'!E63 | AI20: ='_Engine_R50'!E64 | AJ20: ='_Engine_R50'!E65 | AK20: ='_Engine_R50'!E66 | AL20: ='_Engine_R50'!E67 | AM20: ='_Engine_R50'!E68 | AN20: ='_Engine_R50'!E69 | AO20: ='_Engine_R50'!E70 | AP20: ='_Engine_R50'!E71 | AQ20: ='_Engine_R50'!E72 | AR20: ='_Engine_R50'!E73 | AS20: ='_Engine_R50'!E74 | AT20: ='_Engine_R50'!E75 | AU20: ='_Engine_R50'!E76 | AV20: ='_Engine_R50'!E77 | AW20: ='_Engine_R50'!E78 | AX20: ='_Engine_R50'!E79 | AY20: ='_Engine_R50'!E80 | AZ20: ='_Engine_R50'!E81 | BA20: ='_Engine_R50'!E82 | BB20: ='_Engine_R50'!E83 | BC20: ='_Engine_R50'!E84 | BD20: ='_Engine_R50'!E85 | BE20: ='_Engine_R50'!E86 | BF20: ='_Engine_R50'!E87 | BG20: ='_Engine_R50'!E88 | BH20: ='_Engine_R50'!E89 | BI20: ='_Engine_R50'!E90 | BJ20: ='_Engine_R50'!E91 | BK20: ='_Engine_R50'!E92 | BL20: ='_Engine_R50'!E93 | BM20: ='_Engine_R50'!E94 | BN20: ='_Engine_R50'!E95 | BO20: ='_Engine_R50'!E96 | BP20: ='_Engine_R50'!E97 | BQ20: ='_Engine_R50'!E98 | BR20: ='_Engine_R50'!E99 | BS20: ='_Engine_R50'!E100 | BT20: ='_Engine_R50'!E101 | BU20: ='_Engine_R50'!E102 | BV20: ='_Engine_R50'!E103 | BW20: ='_Engine_R50'!E104 | BX20: ='_Engine_R50'!E105 | BY20: ='_Engine_R50'!E106 | BZ20: ='_Engine_R50'!E107 | CA20: ='_Engine_R50'!E108 | CB20: ='_Engine_R50'!E109 | CC20: ='_Engine_R50'!E110 | CD20: ='_Engine_R50'!E111 | CE20: ='_Engine_R50'!E112 | CF20: ='_Engine_R50'!E113 | CG20: ='_Engine_R50'!E114 | CH20: ='_Engine_R50'!E115 | CI20: ='_Engine_R50'!E116 | CJ20: ='_Engine_R50'!E117 | CK20: ='_Engine_R50'!E118 | CL20: ='_Engine_R50'!E119 | CM20: ='_Engine_R50'!E120 | CN20: ='_Engine_R50'!E121 | CO20: ='_Engine_R50'!E122 | CP20: ='_Engine_R50'!E123 | CQ20: ='_Engine_R50'!E124 | CR20: ='_Engine_R50'!E125 | CS20: ='_Engine_R50'!E126 | CT20: ='_Engine_R50'!E127 | CU20: ='_Engine_R50'!E128 | CV20: ='_Engine_R50'!E129 | CW20: ='_Engine_R50'!E130 | CX20: ='_Engine_R50'!E131 | CY20: ='_Engine_R50'!E132 | CZ20: ='_Engine_R50'!E133 | DA20: ='_Engine_R50'!E134 | DB20: ='_Engine_R50'!E135 | DC20: ='_Engine_R50'!E136 | DD20: ='_Engine_R50'!E137 | DE20: ='_Engine_R50'!E138 | DF20: ='_Engine_R50'!E139 | DG20: ='_Engine_R50'!E140 | DH20: ='_Engine_R50'!E141 | DI20: ='_Engine_R50'!E142 | DJ20: ='_Engine_R50'!E143 | DK20: ='_Engine_R50'!E144 | DL20: ='_Engine_R50'!E145 | DM20: ='_Engine_R50'!E146 | DN20: ='_Engine_R50'!E147 | DO20: ='_Engine_R50'!E148 | DP20: ='_Engine_R50'!E149 | DQ20: ='_Engine_R50'!E150 | DR20: ='_Engine_R50'!E151 | DS20: ='_Engine_R50'!E152 | DT20: ='_Engine_R50'!E153 | DU20: ='_Engine_R50'!E154 | DV20: ='_Engine_R50'!E155 | DW20: ='_Engine_R50'!E156 | DX20: ='_Engine_R50'!E157 | DY20: ='_Engine_R50'!E158 | DZ20: ='_Engine_R50'!E159 | EA20: ='_Engine_R50'!E160 | EB20: ='_Engine_R50'!E161 | EC20: ='_Engine_R50'!E162 | ED20: ='_Engine_R50'!E163 | EE20: ='_Engine_R50'!E164 | EF20: ='_Engine_R50'!E165 | EG20: ='_Engine_R50'!E166 | EH20: ='_Engine_R50'!E167 | EI20: ='_Engine_R50'!E168 | EJ20: ='_Engine_R50'!E169 | EK20: ='_Engine_R50'!E170 | EL20: ='_Engine_R50'!E171 | EM20: ='_Engine_R50'!E172 | EN20: ='_Engine_R50'!E173 | EO20: ='_Engine_R50'!E174 | EP20: ='_Engine_R50'!E175 | EQ20: ='_Engine_R50'!E176 | ER20: ='_Engine_R50'!E177 | ES20: ='_Engine_R50'!E178 | ET20: ='_Engine_R50'!E179 | EU20: ='_Engine_R50'!E180 | EV20: ='_Engine_R50'!E181 | EW20: ='_Engine_R50'!E182 | EX20: ='_Engine_R50'!E183 | EY20: ='_Engine_R50'!E184 | EZ20: ='_Engine_R50'!E185 | FA20: ='_Engine_R50'!E186 | FB20: ='_Engine_R50'!E187 | FC20: ='_Engine_R50'!E188 | FD20: ='_Engine_R50'!E189 | FE20: ='_Engine_R50'!E190 | FF20: ='_Engine_R50'!E191 | FG20: ='_Engine_R50'!E192 | FH20: ='_Engine_R50'!E193 | FI20: ='_Engine_R50'!E194 | FJ20: ='_Engine_R50'!E195 | FK20: ='_Engine_R50'!E196 | FL20: ='_Engine_R50'!E197 | FM20: ='_Engine_R50'!E198 | FN20: ='_Engine_R50'!E199 | FO20: ='_Engine_R50'!E200 | FP20: ='_Engine_R50'!E201 | FQ20: ='_Engine_R50'!E202 | FR20: ='_Engine_R50'!E203 | FS20: ='_Engine_R50'!E204 | FT20: ='_Engine_R50'!E205 | FU20: ='_Engine_R50'!E206 | FV20: ='_Engine_R50'!E207 | FW20: ='_Engine_R50'!E208 | FX20: ='_Engine_R50'!E209 | FY20: ='_Engine_R50'!E210
A21: Corporate Allocation | B21: ='_Engine_R50'!U31 | C21: ='_Engine_R50'!U32 | D21: ='_Engine_R50'!U33 | E21: ='_Engine_R50'!U34 | F21: ='_Engine_R50'!U35 | G21: ='_Engine_R50'!U36 | H21: ='_Engine_R50'!U37 | I21: ='_Engine_R50'!U38 | J21: ='_Engine_R50'!U39 | K21: ='_Engine_R50'!U40 | L21: ='_Engine_R50'!U41 | M21: ='_Engine_R50'!U42 | N21: ='_Engine_R50'!U43 | O21: ='_Engine_R50'!U44 | P21: ='_Engine_R50'!U45 | Q21: ='_Engine_R50'!U46 | R21: ='_Engine_R50'!U47 | S21: ='_Engine_R50'!U48 | T21: ='_Engine_R50'!U49 | U21: ='_Engine_R50'!U50 | V21: ='_Engine_R50'!U51 | W21: ='_Engine_R50'!U52 | X21: ='_Engine_R50'!U53 | Y21: ='_Engine_R50'!U54 | Z21: ='_Engine_R50'!U55 | AA21: ='_Engine_R50'!U56 | AB21: ='_Engine_R50'!U57 | AC21: ='_Engine_R50'!U58 | AD21: ='_Engine_R50'!U59 | AE21: ='_Engine_R50'!U60 | AF21: ='_Engine_R50'!U61 | AG21: ='_Engine_R50'!U62 | AH21: ='_Engine_R50'!U63 | AI21: ='_Engine_R50'!U64 | AJ21: ='_Engine_R50'!U65 | AK21: ='_Engine_R50'!U66 | AL21: ='_Engine_R50'!U67 | AM21: ='_Engine_R50'!U68 | AN21: ='_Engine_R50'!U69 | AO21: ='_Engine_R50'!U70 | AP21: ='_Engine_R50'!U71 | AQ21: ='_Engine_R50'!U72 | AR21: ='_Engine_R50'!U73 | AS21: ='_Engine_R50'!U74 | AT21: ='_Engine_R50'!U75 | AU21: ='_Engine_R50'!U76 | AV21: ='_Engine_R50'!U77 | AW21: ='_Engine_R50'!U78 | AX21: ='_Engine_R50'!U79 | AY21: ='_Engine_R50'!U80 | AZ21: ='_Engine_R50'!U81 | BA21: ='_Engine_R50'!U82 | BB21: ='_Engine_R50'!U83 | BC21: ='_Engine_R50'!U84 | BD21: ='_Engine_R50'!U85 | BE21: ='_Engine_R50'!U86 | BF21: ='_Engine_R50'!U87 | BG21: ='_Engine_R50'!U88 | BH21: ='_Engine_R50'!U89 | BI21: ='_Engine_R50'!U90 | BJ21: ='_Engine_R50'!U91 | BK21: ='_Engine_R50'!U92 | BL21: ='_Engine_R50'!U93 | BM21: ='_Engine_R50'!U94 | BN21: ='_Engine_R50'!U95 | BO21: ='_Engine_R50'!U96 | BP21: ='_Engine_R50'!U97 | BQ21: ='_Engine_R50'!U98 | BR21: ='_Engine_R50'!U99 | BS21: ='_Engine_R50'!U100 | BT21: ='_Engine_R50'!U101 | BU21: ='_Engine_R50'!U102 | BV21: ='_Engine_R50'!U103 | BW21: ='_Engine_R50'!U104 | BX21: ='_Engine_R50'!U105 | BY21: ='_Engine_R50'!U106 | BZ21: ='_Engine_R50'!U107 | CA21: ='_Engine_R50'!U108 | CB21: ='_Engine_R50'!U109 | CC21: ='_Engine_R50'!U110 | CD21: ='_Engine_R50'!U111 | CE21: ='_Engine_R50'!U112 | CF21: ='_Engine_R50'!U113 | CG21: ='_Engine_R50'!U114 | CH21: ='_Engine_R50'!U115 | CI21: ='_Engine_R50'!U116 | CJ21: ='_Engine_R50'!U117 | CK21: ='_Engine_R50'!U118 | CL21: ='_Engine_R50'!U119 | CM21: ='_Engine_R50'!U120 | CN21: ='_Engine_R50'!U121 | CO21: ='_Engine_R50'!U122 | CP21: ='_Engine_R50'!U123 | CQ21: ='_Engine_R50'!U124 | CR21: ='_Engine_R50'!U125 | CS21: ='_Engine_R50'!U126 | CT21: ='_Engine_R50'!U127 | CU21: ='_Engine_R50'!U128 | CV21: ='_Engine_R50'!U129 | CW21: ='_Engine_R50'!U130 | CX21: ='_Engine_R50'!U131 | CY21: ='_Engine_R50'!U132 | CZ21: ='_Engine_R50'!U133 | DA21: ='_Engine_R50'!U134 | DB21: ='_Engine_R50'!U135 | DC21: ='_Engine_R50'!U136 | DD21: ='_Engine_R50'!U137 | DE21: ='_Engine_R50'!U138 | DF21: ='_Engine_R50'!U139 | DG21: ='_Engine_R50'!U140 | DH21: ='_Engine_R50'!U141 | DI21: ='_Engine_R50'!U142 | DJ21: ='_Engine_R50'!U143 | DK21: ='_Engine_R50'!U144 | DL21: ='_Engine_R50'!U145 | DM21: ='_Engine_R50'!U146 | DN21: ='_Engine_R50'!U147 | DO21: ='_Engine_R50'!U148 | DP21: ='_Engine_R50'!U149 | DQ21: ='_Engine_R50'!U150 | DR21: ='_Engine_R50'!U151 | DS21: ='_Engine_R50'!U152 | DT21: ='_Engine_R50'!U153 | DU21: ='_Engine_R50'!U154 | DV21: ='_Engine_R50'!U155 | DW21: ='_Engine_R50'!U156 | DX21: ='_Engine_R50'!U157 | DY21: ='_Engine_R50'!U158 | DZ21: ='_Engine_R50'!U159 | EA21: ='_Engine_R50'!U160 | EB21: ='_Engine_R50'!U161 | EC21: ='_Engine_R50'!U162 | ED21: ='_Engine_R50'!U163 | EE21: ='_Engine_R50'!U164 | EF21: ='_Engine_R50'!U165 | EG21: ='_Engine_R50'!U166 | EH21: ='_Engine_R50'!U167 | EI21: ='_Engine_R50'!U168 | EJ21: ='_Engine_R50'!U169 | EK21: ='_Engine_R50'!U170 | EL21: ='_Engine_R50'!U171 | EM21: ='_Engine_R50'!U172 | EN21: ='_Engine_R50'!U173 | EO21: ='_Engine_R50'!U174 | EP21: ='_Engine_R50'!U175 | EQ21: ='_Engine_R50'!U176 | ER21: ='_Engine_R50'!U177 | ES21: ='_Engine_R50'!U178 | ET21: ='_Engine_R50'!U179 | EU21: ='_Engine_R50'!U180 | EV21: ='_Engine_R50'!U181 | EW21: ='_Engine_R50'!U182 | EX21: ='_Engine_R50'!U183 | EY21: ='_Engine_R50'!U184 | EZ21: ='_Engine_R50'!U185 | FA21: ='_Engine_R50'!U186 | FB21: ='_Engine_R50'!U187 | FC21: ='_Engine_R50'!U188 | FD21: ='_Engine_R50'!U189 | FE21: ='_Engine_R50'!U190 | FF21: ='_Engine_R50'!U191 | FG21: ='_Engine_R50'!U192 | FH21: ='_Engine_R50'!U193 | FI21: ='_Engine_R50'!U194 | FJ21: ='_Engine_R50'!U195 | FK21: ='_Engine_R50'!U196 | FL21: ='_Engine_R50'!U197 | FM21: ='_Engine_R50'!U198 | FN21: ='_Engine_R50'!U199 | FO21: ='_Engine_R50'!U200 | FP21: ='_Engine_R50'!U201 | FQ21: ='_Engine_R50'!U202 | FR21: ='_Engine_R50'!U203 | FS21: ='_Engine_R50'!U204 | FT21: ='_Engine_R50'!U205 | FU21: ='_Engine_R50'!U206 | FV21: ='_Engine_R50'!U207 | FW21: ='_Engine_R50'!U208 | FX21: ='_Engine_R50'!U209 | FY21: ='_Engine_R50'!U210
A22: Team Compensation | B22: =B17+B18+B19+B20+B21+B14 | C22: =C17+C18+C19+C20+C21+C14 | D22: =D17+D18+D19+D20+D21+D14 | E22: =E17+E18+E19+E20+E21+E14 | F22: =F17+F18+F19+F20+F21+F14 | G22: =G17+G18+G19+G20+G21+G14 | H22: =H17+H18+H19+H20+H21+H14 | I22: =I17+I18+I19+I20+I21+I14 | ... FY22: =FY17+FY18+FY19+FY20+FY21+FY14
A23: Legacy Headcount Expenses | B23: 0 | C23: 0 | D23: 0 | E23: 1.2587 | F23: 1.0927 | G23: 0.9309 | H23: 2.1106 | I23: 1.7807 | J23: 1.4592 | K23: 2.626 | L23: 2.21 | M23: 3.083 | N23: 2.5195 | O23: 2.06 | P23: 1.6124 | Q23: 2.4254 | R23: 1.9842 | S23: 1.5545 | T23: 1.2214 | U23: 0.9492 | V23: 0.6842 | W23: 0.4261 | X23: 0.3161 | Y23: 1.3889 | Z23: 1.179 | AA23: 0.9744 | AB23: 0.7751 | AC23: 0.581 | AD23: 0.4408 | AE23: 1.4842 | AF23: 1.2745 | AG23: 1.0701 | AH23: 0.871 | AI23: 0.6771 | AJ23: 0.4882 | AK23: 1.4842 | AL23: 1.2745 | AM23: 1.0701 | AN23: 0.871 | AO23: 0.6771 | AP23: 0.4882 | AQ23: 0.3042 | AR23: 0.2501 | AS23: 0.1974 | AT23: 0.1461 | AU23: 0.0961 | AV23: 0.0474 | AW23: 0 | AX23: 0 | AY23: 0 | AZ23: 0 | BA23: 0 | BB23: 0 | BC23: 0 | BD23: 0 | BE23: 0 | BF23: 0 | BG23: 0 | BH23: 0 | BI23: 0 | BJ23: 0 | BK23: 0 | BL23: 0 | BM23: 0 | BN23: 0 | BO23: 0 | BP23: 0 | BQ23: 0 | BR23: 0 | BS23: 0 | BT23: 0 | BU23: 0 | BV23: 0 | BW23: 0 | BX23: 0 | BY23: 0 | BZ23: 0 | CA23: 0 | CB23: 0 | CC23: 0 | CD23: 0 | CE23: 0 | CF23: 0 | CG23: 0 | CH23: 0 | CI23: 0 | CJ23: 0 | CK23: 0 | CL23: 0 | CM23: 0 | CN23: 0 | CO23: 0 | CP23: 0 | CQ23: 0 | CR23: 0 | CS23: 0 | CT23: 0 | CU23: 0 | CV23: 0 | CW23: 0 | CX23: 0 | CY23: 0 | CZ23: 0 | DA23: 0 | DB23: 0 | DC23: 0 | DD23: 0 | DE23: 0 | DF23: 0 | DG23: 0 | DH23: 0 | DI23: 0 | DJ23: 0 | DK23: 0 | DL23: 0 | DM23: 0 | DN23: 0 | DO23: 0 | DP23: 0 | DQ23: 0 | DR23: 0 | DS23: 0 | DT23: 0 | DU23: 0 | DV23: 0 | DW23: 0 | DX23: 0 | DY23: 0 | DZ23: 0 | EA23: 0 | EB23: 0 | EC23: 0 | ED23: 0 | EE23: 0 | EF23: 0 | EG23: 0 | EH23: 0 | EI23: 0 | EJ23: 0 | EK23: 0 | EL23: 0 | EM23: 0 | EN23: 0 | EO23: 0 | EP23: 0 | EQ23: 0 | ER23: 0 | ES23: 0 | ET23: 0 | EU23: 0 | EV23: 0 | EW23: 0 | EX23: 0 | EY23: 0 | EZ23: 0 | FA23: 0 | FB23: 0 | FC23: 0 | FD23: 0 | FE23: 0 | FF23: 0 | FG23: 0 | FH23: 0 | FI23: 0 | FJ23: 0 | FK23: 0 | FL23: 0 | FM23: 0 | FN23: 0 | FO23: 0 | FP23: 0 | FQ23: 0 | FR23: 0 | FS23: 0 | FT23: 0 | FU23: 0 | FV23: 0 | FW23: 0 | FX23: 0 | FY23: 0
